Workbook
Name lista: OFFSET([1]DinamicValidation!$B$4,0,0,COUNTA([1]DinamicValidation!$B$4:$B$1048576),1)

Sheet OpeningPage

Sheet Admin
C9: Business Valuation
C12: Date | D12: 44896
C13: Student name | D13: Sam Sample | I13: Master in Finance
C14: Neptun code | D14: ABCD1234 | I14: Master in Accounting
C16: Study program | D16: Master in Accounting
C17: Instructor | D17: Péter Juhász, PhD, CFA
C20: Total points achieved | D20: =+'Task 3'!C9+'Task 4'!C9+'Task 5'!C9+'Task 1'!C9+'Task 2'!C9 -> 0

Sheet Task 1
B2: =+Admin!C12 -> Date | C2: =+Admin!D12 -> 44896
B3: =+Admin!C13 -> Student name | C3: =+Admin!D13 -> Sam Sample
B4: =+Admin!C14 -> Neptun code | C4: =+Admin!D14 -> ABCD1234
B6: =+Admin!C16 -> Study program | C6: =+Admin!D16 -> Master in Accounting
B7: =+Admin!C17 -> Instructor | C7: =+Admin!D17 -> Péter Juhász, PhD, CFA
B9: Points achived:
D23: 2020 | E23: 2021 | F23: 2022 | G23: 2023 | H23: 2024 | I23: 2025 | J23: 2026
C24: IC boy | D24: 10000
C25: dIC | D25: 1500 | E25: 2000 | F25: 1600 | G25: 3500 | H25: 1200 | I25: 4000 | J25: 1500
C26: Sales | D26: 10000 | E26: 12000 | F26: 14000 | G26: 16000 | H26: 18000 | I26: 20000 | J26: 22000
C27: EBIT/Sales | D27: 0.01 | E27: 0.05 | F27: 0.1 | G27: 0.03 | H27: 0.09 | I27: 0.1 | J27: 0.12
C28: Corporate tax rate | D28: 0.1 | E28: 0.1 | F28: 0.1 | G28: 0.09 | H28: 0.09 | I28: 0.09 | J28: 0.09
C29: rD | D29: 0.04 | E29: 0.04 | F29: 0.04 | G29: 0.05 | H29: 0.05 | I29: 0.05 | J29: 0.05
C30: Debt boy | D30: 5000 | E30: 4500 | F30: 4000 | G30: 7000 | H30: 6500 | I30: 6000 | J30: 7000
C33: ROIC
C34: RONIC
C35: K
C36: g
C37: t (effective)

Sheet Task 2
B2: =+Admin!C12 -> Date | C2: =+Admin!D12 -> 44896
B3: =+Admin!C13 -> Student name | C3: =+Admin!D13 -> Sam Sample
B4: =+Admin!C14 -> Neptun code | C4: =+Admin!D14 -> ABCD1234
B6: =+Admin!C16 -> Study program | C6: =+Admin!D16 -> Master in Accounting
B7: =+Admin!C17 -> Instructor | C7: =+Admin!D17 -> Péter Juhász, PhD, CFA
B9: Points achived:
D24: 2021 | E24: 2022 | F24: 2023 | G24: 2024 | H24: 2025 | I24: TV
C25: ROIC | D25: 0.11
C26: RONIC | E26: 0.16 | F26: 0.18 | G26: 0.2 | H26: 0.22
C27: K | D27: 0.6 | E27: 0.5 | F27: 0.4 | G27: 0.3 | H27: 0.25
C28: rA | D28: 0.12 | E28: 0.12 | F28: 0.12 | G28: 0.12 | H28: 0.12 | I28: 0.12
C29: rD | D29: 0.06 | E29: 0.07 | F29: 0.072 | G29: 0.073 | H29: 0.073 | I29: 0.073
C30: t | D30: 0.1 | E30: 0.1 | F30: 0.1 | G30: 0.1 | H30: 0.1 | I30: 0.1
C31: g TV period | I31: 0.05
D33: =+D24 -> 2021 | E33: =+E24 -> 2022 | F33: =+F24 -> 2023 | G33: =+G24 -> 2024 | H33: =+H24 -> 2025 | I33: =+I24 -> TV
C34: D/V boy | I34: 0.5
C35: D/IC boy | D35: 0 | E35: 0.2 | F35: 0.4 | G35: 0.5 | H35: 0.5
C36: IC boy | D36: 20000

Sheet Task 3
B2: =+Admin!C12 -> Date | C2: =+Admin!D12 -> 44896
B3: =+Admin!C13 -> Student name | C3: =+Admin!D13 -> Sam Sample
B4: =+Admin!C14 -> Neptun code | C4: =+Admin!D14 -> ABCD1234
B6: =+Admin!C16 -> Study program | C6: =+Admin!D16 -> Master in Accounting
B7: =+Admin!C17 -> Instructor | C7: =+Admin!D17 -> Péter Juhász, PhD, CFA
B9: Points achived:
D18: 2017 | E18: 2018 | F18: 2019
C19: Sales | D19: 12000 | E19: 13200 | F19: 14256
C20: Other income | D20: 0 | E20: 396 | F20: 712.8
C21: Material expenses | D21: 7680 | E21: 8580 | F21: 9408.96
C22: Labour expenses | D22: 3840 | E22: 3960 | F22: 4419.36
C23: D&A | D23: 250 | E23: 150 | F23: 180
C24: EBIT | D24: =+D19+D20-D21-D22-D23 -> 230 | E24: =+E19+E20-E21-E22-E23 -> 906 | F24: =+F19+F20-F21-F22-F23 -> 960.48
C25: Dividend received | D25: 100 | E25: 0 | F25: 120
C26: Interests received | D26: 10 | E26: 0 | F26: 50
C27: Interests paid | D27: 80 | E27: 85 | F27: 40
C28: Financial profit | D28: =+D25+D26-D27 -> 30 | E28: =+E25+E26-E27 -> -85 | F28: =+F25+F26-F27 -> 130
C29: Profit before tax | D29: =+D28+D24 -> 260 | E29: =+E28+E24 -> 821 | F29: =+F28+F24 -> 1090.48
C30: Corporate tax | D30: 23 | E30: 74 | F30: 98
C31: Profit after tax | D31: =+D29-D30 -> 237 | E31: =+E29-E30 -> 747 | F31: =+F29-F30 -> 992.48
C32: Dividend | D32: 30 | E32: 164.2 | F32: 297.71
C33: Retained earnings | D33: =+D31-D32 -> 207 | E33: =+E31-E32 -> 582.8 | F33: =+F31-F32 -> 694.77
C35: Cash | D35: 779.6 | E35: 254.77 | F35: 182.54
C36: Marketable securities | D36: 48.4 | E36: 50 | F36: 0
C37: Receivables | D37: 300 | E37: 733.33 | F37: 1108.8
C38: Inventory | D38: 250 | E38: 870.83 | F38: 768.24
C39: Current assets | D39: =SUM(D35:D38) -> 1378 | E39: =SUM(E35:E38) -> 1908.93 | F39: =SUM(F35:F38) -> 2059.58
C40: Invested assets | D40: 1000 | E40: 1200 | F40: 1500
C41: Total of assests | D41: =+D40+D39 -> 2378 | E41: =+E40+E39 -> 3108.93 | F41: =+F40+F39 -> 3559.58
C42: Short term loans | D42: 300 | E42: 250 | F42: 100
C43: Payables | D43: 300 | E43: 238.33 | F43: 444.31
C44: Short term liabilities | D44: =+D42+D43 -> 600 | E44: =+E42+E43 -> 488.33 | F44: =+F42+F43 -> 544.31
C45: Long term debt | D45: 500 | E45: 600 | F45: 300
C46: Equity | D46: 1278 | E46: 2020.6 | F46: 2715.27
C47: Total of Liabilities and Equity | D47: =+D44+D45+D46 -> 2378 | E47: =+E44+E45+E46 -> 3108.93 | F47: =+F44+F45+F46 -> 3559.58

Sheet Task 4
B2: =+Admin!C12 -> Date | C2: =+Admin!D12 -> 44896
B3: =+Admin!C13 -> Student name | C3: =+Admin!D13 -> Sam Sample
B4: =+Admin!C14 -> Neptun code | C4: =+Admin!D14 -> ABCD1234
B6: =+Admin!C16 -> Study program | C6: =+Admin!D16 -> Master in Accounting
B7: =+Admin!C17 -> Instructor | C7: =+Admin!D17 -> Péter Juhász, PhD, CFA
B9: Points achived:
D19: 2021 | E19: 2022 | F19: 2023 | G19: 2024 | H19: 2025 | I19: TV
C20: RONIC | D20: 0.15 | E20: 0.2 | F20: 0.22 | G20: 0.22 | H20: 0.22
C21: K | D21: 0.5 | E21: 0.4 | F21: 0.3 | G21: 0.3 | H21: 0.25
C22: rA | D22: 0.12 | E22: 0.12 | F22: 0.12 | G22: 0.12 | H22: 0.12 | I22: 0.12
C23: rD | D23: 0.06 | E23: 0.07 | F23: 0.072 | G23: 0.073 | H23: 0.073 | I23: 0.073
C24: t | D24: 0.1 | E24: 0.1 | F24: 0.1 | G24: 0.1 | H24: 0.1 | I24: 0.1
C25: g TV period | I25: 0.05
D27: =+D19 -> 2021 | E27: =+E19 -> 2022 | F27: =+F19 -> 2023 | G27: =+G19 -> 2024 | H27: =+H19 -> 2025 | I27: =+I19 -> TV
C28: D/V boy | I28: 0.5
C29: D/IC boy | D29: 0.3 | E29: 0.4 | F29: 0.45 | G29: 0.45 | H29: 0.45
C30: IC boy | D30: 10000

Sheet Task 5
B2: =+Admin!C12 -> Date | C2: =+Admin!D12 -> 44896
B3: =+Admin!C13 -> Student name | C3: =+Admin!D13 -> Sam Sample
B4: =+Admin!C14 -> Neptun code | C4: =+Admin!D14 -> ABCD1234
B6: =+Admin!C16 -> Study program | C6: =+Admin!D16 -> Master in Accounting
B7: =+Admin!C17 -> Instructor | C7: =+Admin!D17 -> Péter Juhász, PhD, CFA
B9: Points achived:

Sheet Sample theoretical questions
B3: Sample theoretical questions. Not all possibilities are listed here.
B5: Compare the accounting and the business cash flow statements.
B6: List any correction types you may need to use before analysing the historical statements of a firm.
B7: List and contrast the DCF models learned. When are those most appropriate to use?
B8: What are the most important requirements to consider when estimating the terminal value in a DCF model?
B9: Present the possible methods of estimating the cost of debt.
B10: What are value drivers? List them and show the calculation formulas.
B11: How do you have to select the peers for a multiple-based valuation?
B12: What kind of asset valuation methods do you know?
B13: Describe how the bargaining range for an M&A transaction is set.
