Workbook

Sheet Assumptions
A1: Macro assumptions
A3: General | B3: 2024 | C3: =+B3+1 -> 2025 | D3: =+C3+1 -> 2026 | E3: =+D3+1 -> 2027 | F3: =+E3+1 -> 2028 | G3: TV
A4: Inflation (Hungary) | B4: 0.044 | C4: 0.029 | D4: 0.03 | E4: 0.03 | F4: 0.03 | G4: 0.03
A5: Inflation (Slovakia) | B5: 0.034 | C5: 0.033 | D5: 0.02 | E5: 0.02 | F5: 0.02 | G5: 0.02
A6: Corporate Tax | B6: 0.09 | C6: 0.09 | D6: 0.09 | E6: 0.09 | F6: 0.09 | G6: 0.09
A7: Wage contribution | B7: 0.13 | C7: 0.13 | D7: 0.13 | E7: 0.13 | F7: 0.13 | G7: 0.13
A8: Number of months | B8: 12 | C8: 12 | D8: 12 | E8: 12 | F8: 12 | G8: 12
A10: Assumptions for the balance sheet & income statement
A12: Number of days | B12: =B3 -> 2024 | C12: =+C3 -> 2025 | D12: =+D3 -> 2026 | E12: =+E3 -> 2027 | F12: =+F3 -> 2028 | G12: =+G3 -> TV
A13: Accounts receivables days | B13: 30 | C13: 30 | D13: 30 | E13: 30 | F13: 30
A14: Accounts receivables
A16: Accounts payables days | B16: 30 | C16: 30 | D16: 30 | E16: 30 | F16: 30
A17: Accounts payables
A19: Inventory days | B19: 45 | C19: 45 | D19: 45 | E19: 45 | F19: 45
A20: Inventory
A23: Debt | B23: =+B12 -> 2024 | C23: =+C12 -> 2025 | D23: =+D12 -> 2026 | E23: =+E12 -> 2027 | F23: =+F12 -> 2028 | G23: =+G12 -> TV
A24: Cost of debt | B24: 0.15 | C24: 0.12 | D24: 0.09 | E24: =+D24 -> 0.09 | F24: =+E24 -> 0.09 | G24: =+F24 -> 0.09
A27: Debit | B27: =B3 -> 2024 | C27: =+C23 -> 2025 | D27: =+D23 -> 2026 | E27: =+E23 -> 2027 | F27: =+F23 -> 2028 | G27: =G23 -> TV
A28: debit interest rate | B28: 0.0025 | C28: =+B28 -> 0.0025 | D28: =+C28 -> 0.0025 | E28: =+D28 -> 0.0025 | F28: =+E28 -> 0.0025 | G28: =+F28 -> 0.0025
A31: Costs | B31: =B3 -> 2024 | I31: 3200
A32: Monthly operating costs | B32: 700
A33: Monthly rent | B33: 6000
A35: Growth | B35: =B3 -> 2024 | C35: =C3 -> 2025 | D35: =D3 -> 2026 | E35: =E3 -> 2027 | F35: =F3 -> 2028
A36: paprika | C36: 0.25 | D36: 0.2 | E36: 0.12 | F36: 0.05
A37: pepper | C37: 0.25 | D37: 0.15 | E37: 0.08 | F37: 0.05
A38: herbs | C38: 0.2 | D38: 0.1 | E38: 0.05 | F38: 0.03
A39: export | C39: 0.1 | D39: 0.08 | E39: 0.06 | F39: 0.04
A41: net investment in the ratio of the sales | C41: 0.02 | D41: 0.02 | E41: 0.02 | F41: 0.02
A43: Depreciation & amortization | B43: =B3 -> 2024 | C43: =C3 -> 2025 | D43: =D3 -> 2026 | E43: =E3 -> 2027 | F43: =F3 -> 2028
A44: DD&A | B44: 0.05 | C44: 0.05 | D44: 0.05 | E44: 0.05 | F44: 0.05
A46: Wages | B46: =B3 -> 2024 | C46: =C3 -> 2025 | D46: =D3 -> 2026 | E46: =E3 -> 2027 | F46: =F3 -> 2028 | G46: =G3 -> TV
A47: one month wage | B47: 3200
A48: New employees gross wage per month | B48: 232 | C48: =B48*(1+B4) -> 242.208 | D48: =C48*(1+C4) -> 249.23203 | E48: =D48*(1+D4) -> 256.70899 | F48: =E48*(1+E4) -> 264.41026 | G48: =F48*(1+F4) -> 272.34257
A49: new employers capacity in sales | B49: 45000 | C49: =B49*(1+B4) -> 46980 | D49: =C49*(1+C4) -> 48342.42 | E49: =D49*(1+D4) -> 49792.693 | F49: =E49*(1+E4) -> 51286.473 | G49: =F49*(1+F4) -> 52825.068
A51: Premium over COGS (per ton) | B51: =B46 -> 2024
A52: paprika | B52: 525
A53: pepper | B53: 500
A54: herbs | B54: 450
A55: export (paprika) | B55: =B52*1.2 -> 630
A57: Sales (ton) | B57: =B51 -> 2024
A58: paprika | B58: 180
A59: pepper | B59: 55
A60: herbs | B60: 37
A61: export (paprika) | B61: 110
A63: Cost of sales (per ton) | B63: =B57 -> 2024
A64: paprika | B64: 1352
A65: pepper | B65: 1361
A66: herbs | B66: 1487
A67: export (paprika) | B67: =B64 -> 1352
A69: D/IC | B69: =B35 -> 2024 | C69: =C35 -> 2025 | D69: =D35 -> 2026 | E69: =E35 -> 2027 | F69: =F35 -> 2028
A70: D/IC | B70: 0.4 | C70: 0.4 | D70: 0.4 | E70: 0.4 | F70: 0.4

Sheet Business plan
B2: Income Statement | C2: eFT
C3: =Assumptions!B3 -> 2024 | D3: =Assumptions!C3 -> 2025 | E3: =Assumptions!D3 -> 2026 | F3: =Assumptions!E3 -> 2027 | G3: =Assumptions!F3 -> 2028
B4: Net sales | C4: =K29+K30 -> 729904 | D4: =L29+L30 -> 902459.55 | E4: =M29+M30 -> 1066248.9 | F4: =N29+N30 -> 1196612.2 | G4: =O29+O30 -> 1285794.4
B5: Cost of sales | C5: =K31+K32 -> 521954 | D5: =L31+L32 -> 646232.04 | E5: =M31+M32 -> 764074.38 | F5: =N31+N32 -> 857709.75 | G5: =O31+O32 -> 921731.8
B6: Gross profit | C6: =C4-C5 -> 207950 | D6: =D4-D5 -> 256227.51 | E6: =E4-E5 -> 302174.52 | F6: =F4-F5 -> 338902.43 | G6: =G4-G5 -> 364062.56
B7: Selling, general and administrative | C7: =SUM(C8:C10) -> 123792 | D7: =SUM(D8:D10) -> 142376.21 | E7: =SUM(E8:E10) -> 156643.88 | F7: =SUM(F8:F10) -> 171786.12 | G7: =SUM(G8:G10) -> 180525.1
B8: operating costs | C8: =(Assumptions!B32+Assumptions!B33)*Assumptions!B8 -> 80400 | D8: =C8*(1+Assumptions!B4) -> 83937.6 | E8: =D8*(1+Assumptions!C4) -> 86371.79 | F8: =E8*(1+Assumptions!D4) -> 88962.944 | G8: =F8*(1+Assumptions!E4) -> 91631.832
B9: wages | C9: =Assumptions!B47*12 -> 38400 | D9: =C9*(1+Assumptions!B4)+(D11-C11)*Assumptions!C48*12 -> 51715.584 | E9: =D9*(1+Assumptions!C4)+(E11-D11)*Assumptions!D48*12 -> 62187.689 | F9: =E9*(1+Assumptions!D4)+(F11-E11)*Assumptions!E48*12 -> 73294.844 | G9: =F9*(1+Assumptions!E4)+(G11-F11)*Assumptions!F48*12 -> 78666.612
B10: wage contribution | C10: =C9*Assumptions!B7 -> 4992 | D10: =D9*Assumptions!C7 -> 6723.0259 | E10: =E9*Assumptions!D7 -> 8084.3996 | F10: =F9*Assumptions!E7 -> 9528.3297 | G10: =G9*Assumptions!F7 -> 10226.66
B11: Increase in the number of employees compared to 2023 | D11: =ROUNDUP((D4-$C$4)/Assumptions!C49,0) -> 4 | E11: =ROUNDUP((E4-$C$4)/Assumptions!D49,0) -> 7 | F11: =ROUNDUP((F4-$C$4)/Assumptions!E49,0) -> 10 | G11: =ROUNDUP((G4-$C$4)/Assumptions!F49,0) -> 11 | J11: Sales (ton)
B12: Research and development | C12: 0 | D12: 0 | E12: 0 | F12: 0 | G12: 0 | J12: Sales (ton) | K12: =C3 -> 2024 | L12: =D3 -> 2025 | M12: =E3 -> 2026 | N12: =F3 -> 2027 | O12: =G3 -> 2028
B13: Depreciation & Amortization | C13: 33000 | D13: =D36*Assumptions!C44 -> 38075.86 | E13: =E36*Assumptions!D44 -> 39142.108 | F13: =F36*Assumptions!E44 -> 40338.721 | G13: =G36*Assumptions!F44 -> 40338.721 | J13: paprika | K13: =Assumptions!B58 -> 180 | L13: =K13*(1+Assumptions!C36) -> 225 | M13: =L13*(1+Assumptions!D36) -> 270 | N13: =M13*(1+Assumptions!E36) -> 302.4 | O13: =N13*(1+Assumptions!F36) -> 317.52
B14: Operating income | C14: =C6-C7-C13 -> 51158 | D14: =D6-D7-D13 -> 75775.441 | E14: =E6-E7-E13 -> 106388.54 | F14: =F6-F7-F13 -> 126777.59 | G14: =G6-G7-G13 -> 143198.74 | J14: pepper | K14: =Assumptions!B59 -> 55 | L14: =K14*(1+Assumptions!C37) -> 68.75 | M14: =L14*(1+Assumptions!D37) -> 79.0625 | N14: =M14*(1+Assumptions!E37) -> 85.3875 | O14: =N14*(1+Assumptions!F37) -> 89.656875
B15: Other income/expenses | J15: herbs | K15: =Assumptions!B60 -> 37 | L15: =K15*(1+Assumptions!C38) -> 44.4 | M15: =L15*(1+Assumptions!D38) -> 48.84 | N15: =M15*(1+Assumptions!E38) -> 51.282 | O15: =N15*(1+Assumptions!F38) -> 52.82046
B16: Earning before interest and taxes | C16: =C14+C15 -> 51158 | D16: =D14+D15 -> 75775.441 | E16: =E14+E15 -> 106388.54 | F16: =F14+F15 -> 126777.59 | G16: =G14+G15 -> 143198.74 | J16: export paprika | K16: =Assumptions!B61 -> 110 | L16: =K16*(1+Assumptions!C39) -> 121 | M16: =L16*(1+Assumptions!D39) -> 130.68 | N16: =M16*(1+Assumptions!E39) -> 138.5208 | O16: =N16*(1+Assumptions!F39) -> 144.06163
B17: Interest income | C17: 3000 | D17: =D33*Assumptions!C28 -> 298.92506 | E17: =E33*Assumptions!D28 -> 350.99847 | F17: =F33*Assumptions!E28 -> 393.16784 | G17: =G33*Assumptions!F28 -> 421.66431
B18: interest expense | C18: 40000 | D18: =C44*Assumptions!C24 -> 44999.07 | E18: =D44*Assumptions!D24 -> 35977.417 | F18: =E44*Assumptions!E24 -> 38217.277 | G18: =F44*Assumptions!F24 -> 40277.545 | J18: Cost of sales/ton
B19: Pretax income | C19: =C16+C17-C18 -> 14158 | D19: =D16+D17-D18 -> 31075.295 | E19: =E16+E17-E18 -> 70762.118 | F19: =F16+F17-F18 -> 88953.481 | G19: =G16+G17-G18 -> 103342.86 | J19: paprika | K19: =Assumptions!B64 -> 1352 | L19: =K19*(1+Assumptions!C$4) -> 1391.208 | M19: =L19*(1+Assumptions!D$4) -> 1432.9442 | N19: =M19*(1+Assumptions!E$4) -> 1475.9326 | O19: =N19*(1+Assumptions!F$4) -> 1520.2105
B20: Taxes | C20: =C19*Assumptions!B6 -> 1274.22 | D20: =D19*Assumptions!C6 -> 2796.7766 | E20: =E19*Assumptions!D6 -> 6368.5906 | F20: =F19*Assumptions!E6 -> 8005.8133 | G20: =G19*Assumptions!F6 -> 9300.8572 | J20: pepper | K20: =Assumptions!B65 -> 1361 | L20: =K20*(1+Assumptions!C$4) -> 1400.469 | M20: =L20*(1+Assumptions!D$4) -> 1442.4831 | N20: =M20*(1+Assumptions!E$4) -> 1485.7576 | O20: =N20*(1+Assumptions!F$4) -> 1530.3303
B21: Net income | C21: =C19-C20 -> 12883.78 | D21: =D19-D20 -> 28278.519 | E21: =E19-E20 -> 64393.527 | F21: =F19-F20 -> 80947.667 | G21: =G19-G20 -> 94042.001 | J21: herbs | K21: =Assumptions!B66 -> 1487 | L21: =K21*(1+Assumptions!C$4) -> 1530.123 | M21: =L21*(1+Assumptions!D$4) -> 1576.0267 | N21: =M21*(1+Assumptions!E$4) -> 1623.3075 | O21: =N21*(1+Assumptions!F$4) -> 1672.0067
J22: export paprika | K22: =Assumptions!B67 -> 1352 | L22: =K22*(1+Assumptions!C$5) -> 1396.616 | M22: =L22*(1+Assumptions!D$5) -> 1424.5483 | N22: =M22*(1+Assumptions!E$5) -> 1453.0393 | O22: =N22*(1+Assumptions!F$5) -> 1482.1001
B24: Dividend | C24: =C21-C25 -> 10395.399 | D24: =D21-D25 -> 0 | E24: =E21-E25 -> 27062.521 | F24: =F21-F25 -> 46609.87 | G24: =G21-G25 -> 80579.749 | J24: Net sales/ton
B25: Retained earning | C25: =IF(C21<0,C21,MAX(0,MIN(C27,C21))) -> 2488.3808 | D25: =IF(D21<0,D21,MAX(0,MIN(D27,D21))) -> 28278.519 | E25: =IF(E21<0,E21,MAX(0,MIN(E27,E21))) -> 37331.006 | F25: =IF(F21<0,F21,MAX(0,MIN(F27,F21))) -> 34337.797 | G25: =IF(G21<0,G21,MAX(0,MIN(G27,G21))) -> 13462.252 | J25: paprika | K25: =K19+Assumptions!B52 -> 1877 | L25: =K25*(1+Assumptions!C4) -> 1931.433 | M25: =L25*(1+Assumptions!D4) -> 1989.376 | N25: =M25*(1+Assumptions!E4) -> 2049.0573 | O25: =N25*(1+Assumptions!F4) -> 2110.529
J26: pepper | K26: =K20+Assumptions!B53 -> 1861 | L26: =K26*(1+Assumptions!C4) -> 1914.969 | M26: =L26*(1+Assumptions!D4) -> 1972.4181 | N26: =M26*(1+Assumptions!E4) -> 2031.5906 | O26: =N26*(1+Assumptions!F4) -> 2092.5383
B27: Stockholders' equity change needed | C27: =C45-C46-C49 -> 2488.3808 | D27: =D45-C45 -> 37135.23 | E27: =E45-D45 -> 37331.006 | F27: =F45-E45 -> 34337.797 | G27: =G45-F45 -> 13462.252 | J27: herbs | K27: =K21+Assumptions!B54 -> 1937 | L27: =K27*(1+Assumptions!C4) -> 1993.173 | M27: =L27*(1+Assumptions!D4) -> 2052.9682 | N27: =M27*(1+Assumptions!E4) -> 2114.5572 | O27: =N27*(1+Assumptions!F4) -> 2177.994
B28: Common stock repurchase/issue | C28: =C27-C25 -> 0 | D28: =D27-D25 -> 8856.7119 | E28: =E27-E25 -> 0 | F28: =F27-F25 -> 0 | G28: =G27-G25 -> 0 | J28: export paprika | K28: =K22+Assumptions!B55 -> 1982 | L28: =K28*(1+Assumptions!C5) -> 2047.406 | M28: =L28*(1+Assumptions!D5) -> 2088.3541 | N28: =M28*(1+Assumptions!E5) -> 2130.1212 | O28: =N28*(1+Assumptions!F5) -> 2172.7236
J29: Net sales - Hungary | K29: =SUMPRODUCT(K25:K27,K13:K15) -> 511884 | L29: =SUMPRODUCT(L25:L27,L13:L15) -> 654723.42 | M29: =SUMPRODUCT(M25:M27,M13:M15) -> 793342.79 | N29: =SUMPRODUCT(N25:N27,N13:N15) -> 901546.09 | O29: =SUMPRODUCT(O25:O27,O13:O15) -> 972788.25
B30: Balance sheet | C30: eFt | E30: eFt | J30: Net sales - Slovakia | K30: =K16*K28 -> 218020 | L30: =L16*L28 -> 247736.13 | M30: =M16*M28 -> 272906.12 | N30: =N16*N28 -> 295066.09 | O30: =O16*O28 -> 313006.11
C31: =+C3 -> 2024 | D31: =+D3 -> 2025 | E31: =+E3 -> 2026 | F31: =+F3 -> 2027 | G31: =+G3 -> 2028 | J31: Cost of sales - Hungary | K31: =SUMPRODUCT(K13:K15,K19:K21) -> 373234 | L31: =SUMPRODUCT(L13:L15,L19:L21) -> 477241.5 | M31: =SUMPRODUCT(M13:M15,M19:M21) -> 577914.41 | N31: =SUMPRODUCT(N13:N15,N19:N21) -> 656433.59 | O31: =SUMPRODUCT(O13:O15,O19:O21) -> 708218.05
B32: Current assets | C32: =SUM(C33:C35) -> 236912.96 | D32: =SUM(D33:D35) -> 290970.46 | E32: =SUM(E33:E35) -> 341549.49 | F32: =SUM(F33:F35) -> 382542.97 | G32: =SUM(G33:G35) -> 410242.14 | J32: Cost of sales - Slovakia | K32: =K16*K22 -> 148720 | L32: =L16*L22 -> 168990.54 | M32: =M16*M22 -> 186159.97 | N32: =N16*N22 -> 201276.16 | O32: =O16*O22 -> 213513.76
B33: Cash (operation) | C33: =C5/6+C7/12 -> 97308.333 | D33: =D5/6+D7/12 -> 119570.02 | E33: =E5/6+E7/12 -> 140399.39 | F33: =F5/6+F7/12 -> 157267.13 | G33: =G5/6+G7/12 -> 168665.73
B34: Accounts receivables | C34: =C4*Assumptions!B13/365 -> 59992.11 | D34: =D4*Assumptions!C13/365 -> 74174.758 | E34: =E4*Assumptions!D13/365 -> 87636.896 | F34: =F4*Assumptions!E13/365 -> 98351.686 | G34: =G4*Assumptions!F13/365 -> 105681.73
B35: Inventories | C35: =(C5+C7)*Assumptions!B19/365 -> 79612.521 | D35: =(D5+D7)*Assumptions!C19/365 -> 97225.675 | E35: =(E5+E7)*Assumptions!D19/365 -> 113513.21 | F35: =(F5+F7)*Assumptions!E19/365 -> 126924.15 | G35: =(G5+G7)*Assumptions!F19/365 -> 135894.69
B36: Long-term assets | C36: =C37+C38 -> 743468 | D36: =C36+D4*Assumptions!D41 -> 761517.19 | E36: =D36+E4*Assumptions!E41 -> 782842.17 | F36: =E36+F4*Assumptions!F41 -> 806774.41 | G36: =F36+G4*Assumptions!G41 -> 806774.41
B37: Intangible assets | C37: 80000
B38: Net property land and equipement | C38: 663468
B39: Total assets | C39: =+C32+C36 -> 980380.96 | D39: =+D32+D36 -> 1052487.6 | E39: =+E32+E36 -> 1124391.7 | F39: =+F32+F36 -> 1189317.4 | G39: =+G32+G36 -> 1217016.6
B40: Current liablities | C40: =C41+C42 -> 42900.329 | D40: =D41+D42 -> 53114.962 | E40: =E41+E42 -> 62800.634 | F40: =F41+F42 -> 70496.692 | G40: =G41+G42 -> 75758.778
B41: Accounts payables | C41: =C5*Assumptions!B16/365 -> 42900.329 | D41: =D5*Assumptions!C16/365 -> 53114.962 | E41: =E5*Assumptions!D16/365 -> 62800.634 | F41: =F5*Assumptions!E16/365 -> 70496.692 | G41: =G5*Assumptions!F16/365 -> 75758.778
B42: Notes payable/short-term debt | C42: 0 | D42: 0 | E42: 0 | F42: 0 | G42: 0
B43: Long-term liabilities | C43: =C44 -> 374992.25 | D43: =D44 -> 399749.07 | E43: =E44 -> 424636.41 | F43: =F44 -> 447528.28 | G43: =G44 -> 456503.11
B44: Long-term debt | C44: =C57*Assumptions!B70 -> 374992.25 | D44: =D57*Assumptions!C70 -> 399749.07 | E44: =E57*Assumptions!D70 -> 424636.41 | F44: =F57*Assumptions!E70 -> 447528.28 | G44: =G57*Assumptions!F70 -> 456503.11
B45: Stockholder's equity | C45: =C39-C43-C40 -> 562488.38 | D45: =D39-D43-D40 -> 599623.61 | E45: =E39-E43-E40 -> 636954.62 | F45: =F39-F43-F40 -> 671292.41 | G45: =G39-G43-G40 -> 684754.67
B46: Common stocks | C46: 500000 | D46: =C46+C48 -> 500000 | E46: =D46+D48 -> 508856.71 | F46: =E46+E48 -> 508856.71 | G46: =F46+F48 -> 508856.71
B47: Net income | C47: =C21 -> 12883.78 | D47: =D21 -> 28278.519 | E47: =E21 -> 64393.527 | F47: =F21 -> 80947.667 | G47: =G21 -> 94042.001
B48: Common stocks repurchase/issue | C48: =C28 -> 0 | D48: =D28 -> 8856.7119 | E48: =E28 -> 0 | F48: =F28 -> 0 | G48: =G28 -> 0
B49: Accumulated retained earnings | C49: 60000 | D49: =C49+C25 -> 62488.381 | E49: =D49+D25 -> 90766.899 | F49: =E49+E25 -> 128097.9 | G49: =F49+F25 -> 162435.7
B50: Retained earnings | C50: =C25 -> 2488.3808 | D50: =D25 -> 28278.519 | E50: =E25 -> 37331.006 | F50: =F25 -> 34337.797 | G50: =G25 -> 13462.252
B51: Total liabilities and Stockholders' Equity | C51: =C45+C43+C40 -> 980380.96 | D51: =D45+D43+D40 -> 1052487.6 | E51: =E45+E43+E40 -> 1124391.7 | F51: =F45+F43+F40 -> 1189317.4 | G51: =G45+G43+G40 -> 1217016.6
B52: Check | C52: =C51-C39 -> 0 | D52: =D51-D39 -> 0 | E52: =E51-E39 -> 0 | F52: =F51-F39 -> 0 | G52: =G51-G39 -> 0
B54: CF | C54: =C31 -> 2024 | D54: =D31 -> 2025 | E54: =E31 -> 2026 | F54: =F31 -> 2027 | G54: =G31 -> 2028 | H54: 2029 (TV cash flow) | I54: TV2
B55: EBIT | C55: =C16 -> 51158 | D55: =D16 -> 75775.441 | E55: =E16 -> 106388.54 | F55: =F16 -> 126777.59 | G55: =G16 -> 143198.74 | H55: =H56/(1-H60) -> 349515.6
B56: NOPLAT | C56: =C55*(1-C60) -> 46553.78 | D56: =D55*(1-D60) -> 68955.651 | E56: =E55*(1-E60) -> 96813.568 | F56: =F55*(1-F60) -> 115367.61 | G56: =G55*(1-G60) -> 130310.85 | H56: =G56+G57*I71 -> 318059.2
B57: IC | C57: =C32-C40+C36 -> 937480.63 | D57: =D32-D40+D36 -> 999372.69 | E57: =E32-E40+E36 -> 1061591 | F57: =F32-F40+F36 -> 1118820.7 | G57: =G32-G40+G36 -> 1141257.8 | H57: =G57+H58 -> 1199259
B58: DIC | D58: =D57-C57 -> 61892.051 | E58: =E57-D57 -> 62218.343 | F58: =F57-E57 -> 57229.662 | G58: =G57-F57 -> 22437.086 | H58: =(I62/I71)*H56 -> 58001.182
B59: FCFF | D59: =D56-D58 -> 7063.6001 | E59: =E56-E58 -> 34595.225 | F59: =F56-F58 -> 58137.945 | G59: =G56-G58 -> 107873.77 | H59: =H56-H58 -> 260058.02
B60: effective taxrate | C60: =C20/C19 -> 0.09 | D60: =D20/D19 -> 0.09 | E60: =E20/E19 -> 0.09 | F60: =F20/F19 -> 0.09 | G60: =G20/G19 -> 0.09 | H60: =G60 -> 0.09
B62: g | I62: 0.03 | J62: g(t+1)=DNOPLAT(at time t+1)/NOPLAT(at time t)
B63: rA | D63: =D68+D65*D66+D67 -> 0.12872051 | E63: =E68+E65*E66+E67 -> 0.13363328 | F63: =F68+F65*F66+F67 -> 0.12873765 | G63: =G68+G65*G66+G67 -> 0.12903774 | H63: =H68+H65*H66+H67 -> 0.16775003
B64: rf | C64: 0.0546 | D64: =AVERAGE(C64,E64) -> 0.05705 | E64: 0.0595 | F64: =AVERAGE(E64,G64) -> 0.05965 | G64: 0.0598 | H64: 0.066 | I64: http://www.worldgovernmentbonds.com/country/hungary/ | O64: IC=NWC+LTA
B65: unlevered beta (food processing) | C65: 0.48 | D65: =+C65 -> 0.48 | E65: =+D65 -> 0.48 | F65: =+E65 -> 0.48 | G65: =+F65 -> 0.48 | H65: =+G65 -> 0.48 | I65: https://pages.stern.nyu.edu/~adamodar/New_Home_Page/datafile/Betas.html | O65: Equity= Debt-IC
B66: MRP | C66: 0.085 | D66: 0.085 | E66: 0.085 | F66: 0.085 | G66: 0.085 | H66: 0.085 | I66: https://papers.ssrn.com/sol3/papers.cfm?abstract_id=4754347 | O66: rA=rg+βA*MRP
B67: CRP | C67: 0.0278 | D67: 0.0278 | E67: 0.0278 | F67: 0.0278 | G67: 0.0278 | H67: 0.0278 | I67: https://pages.stern.nyu.edu/~adamodar/New_Home_Page/datafile/ctryprem.html | O67: ROA = (Net Income / Total Assets)
B68: forward rate | D68: =((1+D64)^2.25)/((1+C64)^1.25)-1 -> 0.060120506 | E68: =((1+E64)^3.25)/((1+D64)^2.25)-1 -> 0.065033282 | F68: =((1+F64)^4.25)/((1+E64)^3.25)-1 -> 0.060137647 | G68: =((1+G64)^5.25)/((1+F64)^4.25)-1 -> 0.060437737 | H68: =((1+H64)^6.25)/((1+G64)^5.25)-1 -> 0.099150026 | O68: MRP = E(Rm) - Rf
B69: WACC | D69: =D63-D60*D86*D70 -> 0.12568929 | E69: =E63-E60*E86*E70 -> 0.13147022 | F69: =F63-F60*F86*F70 -> 0.12666456 | G69: =G63-G60*G86*G70 -> 0.12703627 | H69: =H63-H60*(H86)*H70 -> 0.16451003 | I69: =H69 -> 0.16451003 | O69: CRP country risk premuim
B70: D/V | D70: =D88/C93 -> 0.28066768 | E70: =E88/D93 -> 0.26704443 | F70: =F88/E93 -> 0.25593673 | G70: =G88/F93 -> 0.24709441 | H70: 0.4
B71: RONIC | H71: =H69 -> 0.16451003 | I71: =H71 -> 0.16451003 | J71: Return on Newly Invested Capital
D72: =((1+D64)^2)/((1+C64)^1)-1 -> 0.059505692 | J72: RONIC(t+1)=DNOPLAT(t+1)/DIC(t)
J73: RONIC(2029)=(NOPLAT(2029)-NOPLAT(2028))/DIC(2028)
J74: g(t+1)/RONIC(t+1)=
B75: Value of unlevered firm
B76: FCFF | C76: =C54 -> 2024 | D76: =D54 -> 2025 | E76: =E54 -> 2026 | F76: =F54 -> 2027 | G76: =G54 -> 2028 | H76: 2029 (TV cash flow)
B77: FCFF | C77: =C59 -> 0 | D77: =D59 -> 7063.6001 | E77: =E59 -> 34595.225 | F77: =F59 -> 58137.945 | G77: =G59 -> 107873.77 | H77: =H59 -> 260058.02
B78: TV | G78: =H77/(H69-I62) -> 1933372.7
B79: PV(FCFF) = V | C79: =(D77+D79)/(1+D69) -> 1336072.1 | D79: =(E77+E79)/(1+E69) -> 1496938.4 | E79: =(F77+F79)/(1+F69) -> 1659146 | F79: =(G77+G78)/(1+G69) -> 1811163.1
B81: APV (Adjusted Present Value) | C81: =C76 -> 2024 | D81: =D76 -> 2025 | E81: =E76 -> 2026 | F81: =F76 -> 2027 | G81: =G76 -> 2028 | H81: 2029 (TV cash flow)
B82: FCFF | C82: =C77 -> 0 | D82: =D77 -> 7063.6001 | E82: =E77 -> 34595.225 | F82: =F77 -> 58137.945 | G82: =G77 -> 107873.77 | H82: =H77 -> 260058.02
B83: TV | G83: =H82/(H63-I62) -> 1887898.1
B84: PV(FCFF) - value of the operation | C84: =(D82+D84)/(1+D63) -> 1297461.5 | D84: =(E82+E84)/(1+E63) -> 1457407.8 | E84: =(F82+F84)/(1+F63) -> 1617570.8 | F84: =(G82+G83)/(1+G63) -> 1767675.1
B85: t | C85: =Assumptions!B6 -> 0.09 | D85: =Assumptions!C6 -> 0.09 | E85: =Assumptions!D6 -> 0.09 | F85: =Assumptions!E6 -> 0.09 | G85: =Assumptions!F6 -> 0.09 | H85: =Assumptions!G6 -> 0.09
B86: rD | C86: =Assumptions!B24 -> 0.15 | D86: =Assumptions!C24 -> 0.12 | E86: =Assumptions!D24 -> 0.09 | F86: =Assumptions!E24 -> 0.09 | G86: =Assumptions!F24 -> 0.09 | H86: =Assumptions!G24 -> 0.09
B87: D | C87: =C43 -> 374992.25 | D87: =D43 -> 399749.07 | E87: =E43 -> 424636.41 | F87: =F43 -> 447528.28 | G87: =G43 -> 456503.11
B88: D (beginning of the year) | D88: =C87 -> 374992.25 | E88: =D87 -> 399749.07 | F88: =E87 -> 424636.41 | G88: =F87 -> 447528.28 | H88: =G78*H70 -> 773349.09 | I88: !!!!!
B89: Interest (rD*D) | D89: =D88*D86 -> 44999.07 | E89: =E88*E86 -> 35977.417 | F89: =F88*F86 -> 38217.277 | G89: =G88*G86 -> 40277.545 | H89: =H88*H86 -> 69601.418
B90: TS = tax shield (t*rD*D) | D90: =D89*D85 -> 4049.9163 | E90: =E89*E85 -> 3237.9675 | F90: =F89*F85 -> 3439.5549 | G90: =G89*G85 -> 3624.979 | H90: =H89*H85 -> 6264.1277
B91: TV of TS | G91: =H90/(H63-I62) -> 45474.602
B92: PV(TS) | C92: =(D90+D92)/(1+D63) -> 38610.554 | D92: =(E90+E92)/(1+E63) -> 39530.608 | E92: =(F90+F92)/(1+F63) -> 41575.245 | F92: =(G90+G91)/(1+G63) -> 43487.989
B93: V | C93: =C92+C84 -> 1336072.1 | D93: =D92+D84 -> 1496938.4 | E93: =E92+E84 -> 1659146 | F93: =F92+F84 -> 1811163.1 | G93: =G91+G83 -> 1933372.7
B94: E | C94: =C93-D88 -> 961079.82
B96: EVA (Economic Value Added) | C96: =C81 -> 2024 | D96: =D81 -> 2025 | E96: =E81 -> 2026 | F96: =F81 -> 2027 | G96: =G81 -> 2028 | H96: 2029 (TV cash flow)
B97: ROIC | D97: =D56/C57 -> 0.073554214 | E97: =E56/D57 -> 0.096874338 | F97: =F56/E57 -> 0.10867425 | G97: =G56/F57 -> 0.11647161 | H97: =H56/G57 -> 0.27869181
B98: WACC | D98: =D69 -> 0.12568929 | E98: =E69 -> 0.13147022 | F98: =F69 -> 0.12666456 | G98: =G69 -> 0.12703627 | H98: =H69 -> 0.16451003
B99: EVA | D99: =C100*(D97-D98) -> -48875.629 | E99: =D100*(E97-E98) -> -34574.182 | F99: =E100*(F97-F98) -> -19098.353 | G99: =F100*(G97-G98) -> -11819.958 | H99: =G100*(H97-H98) -> 130310.85
B100: IC | C100: =C57 -> 937480.63 | D100: =D57 -> 999372.69 | E100: =E57 -> 1061591 | F100: =F57 -> 1118820.7 | G100: =G57 -> 1141257.8
B101: PV(EVA) | C101: =(D99+D101)/(1+D98) -> 398591.44 | D101: =(E99+E101)/(1+E98) -> 497565.75 | E101: =(F99+F101)/(1+F98) -> 597555.01 | F101: =(G99+G101)/(1+G98) -> 692342.4 | G101: =H99/H98 -> 792114.96 | I101: if RONIC=WACC --> EVA/WACC
B102: V | C102: =C101+C100 -> 1336072.1 | D102: =D101+D100 -> 1496938.4 | E102: =E101+E100 -> 1659146 | F102: =F101+F100 -> 1811163.1 | G102: =G101+G100 -> 1933372.7
