Workbook

Sheet Task1
A1: Date | B1: 45404
C4: Bond name | D4: 2028/A | E4: 2030/A | F4: 2032/A
C5: ISIN | D5: HU0000402532 | E5: HU0000403696 | F5: HU0000405550
C6: Expiration date | D6: 47048 | E6: 47716 | F6: 48542 | I6: Portfolio | J6: Market Value | K6: =SUM(D14:F14) -> 99995519 | L6: HUF
C7: Principal repayment | D7: at maturity | E7: at maturity | F7: at maturity | J7: Duration | K7: =SUMPRODUCT(D14:F14,D15:F15)/K6 -> 5.3219392 | L7: =ROUND(K7*365,0) -> 1943
C8: Interest type | D8: Fix | E8: Fix | F8: Fix
C9: Interest rate | D9: 0.0675 | E9: 0.03 | F9: 0.0475
C10: Interest payment frequency | D10: 1 year | E10: 1 year | F10: 1 year
C11: Next payment | D11: 45587 | E11: 45525 | F11: 45620
C12: Nominal value | D12: 10000 | E12: 10000 | F12: =E12 -> 10000
C13: Piece | D13: 4152 | E13: 3323 | F13: 3548 | G13: solver
C14: Market price | D14: =D13*H25 -> 42187479 | E14: =E13*H34 -> 27012926 | F14: =F13*H45 -> 30795115
C15: Duration | D15: =J25 -> 3.9034058 | E15: =J34 -> 5.6555852 | F15: =J45 -> 6.9725775
C18: Price and Duration Calculation
E19: t | F19: CF | G19: r | H19: PV | I19: w | J19: D
C20: 2028/A | D20: =D11 -> 45587 | E20: =D20-$B$1 -> 183 | F20: =$D$12*$D$9 -> 675 | G20: =_xlfn.XLOOKUP(E20,'zero-coupon-yields_202405171536'!$B$2:$B$1411,'zero-coupon-yields_202405171536'!D2:D1411,1,1)/100 -> 0.070976 | H20: =F20/(1+G20)^(E20/365) -> 652.18846 | I20: =H20/$H$25 -> 0.064186971 | J20: =I20*E20/365 -> 0.032181413
D21: =D20+365 -> 45952 | E21: =D21-$B$1 -> 548 | F21: =$D$12*$D$9 -> 675 | G21: =_xlfn.XLOOKUP(E21,'zero-coupon-yields_202405171536'!$B$2:$B$1411,'zero-coupon-yields_202405171536'!D3:D1412,1,1)/100 -> 0.071681 | H21: =F21/(1+G21)^(E21/365) -> 608.3651 | I21: =H21/$H$25 -> 0.059873971 | J21: =I21*E21/365 -> 0.089892976
D22: =D21+365 -> 46317 | E22: =D22-$B$1 -> 913 | F22: =$D$12*$D$9 -> 675 | G22: =_xlfn.XLOOKUP(E22,'zero-coupon-yields_202405171536'!$B$2:$B$1411,'zero-coupon-yields_202405171536'!D4:D1413,1,1)/100 -> 0.072059 | H22: =F22/(1+G22)^(E22/365) -> 567.17315 | I22: =H22/$H$25 -> 0.055819949 | J22: =I22*E22/365 -> 0.13962634
D23: =D22+365 -> 46682 | E23: =D23-$B$1 -> 1278 | F23: =$D$12*$D$9 -> 675 | G23: =_xlfn.XLOOKUP(E23,'zero-coupon-yields_202405171536'!$B$2:$B$1411,'zero-coupon-yields_202405171536'!D5:D1414,1,1)/100 -> 0.072114 | H23: =F23/(1+G23)^(E23/365) -> 528.95529 | I23: =H23/$H$25 -> 0.05205863 | J23: =I23*E23/365 -> 0.18227652
D24: =D6 -> 47048 | E24: =D24-$B$1 -> 1644 | F24: =$D$12*(1+$D$9) -> 10675 | G24: =_xlfn.XLOOKUP(E24,'zero-coupon-yields_202405171536'!$B$2:$B$1411,'zero-coupon-yields_202405171536'!D6:D1415,1,1)/100 -> 0.072025 | H24: =F24/(1+G24)^(E24/365) -> 7804.0788 | I24: =H24/$H$25 -> 0.76806048 | J24: =I24*E24/365 -> 3.4594286
H25: =SUM(H20:H24) -> 10160.761 | I25: =SUM(I20:I24) -> 1 | J25: =SUM(J20:J24) -> 3.9034058
C27: =E4 -> 2030/A | D27: =E11 -> 45525 | E27: =D27-$B$1 -> 121 | F27: =$E$12*$E$9 -> 300 | G27: =_xlfn.XLOOKUP(E27,'zero-coupon-yields_202405171536'!$B$2:$B$1411,'zero-coupon-yields_202405171536'!D2:D1411,1,1)/100 -> 0.070828 | H27: =F27/(1+G27)^(E27/365) -> 293.27089 | I27: =H27/$H$34 -> 0.036076772 | J27: =I27*E27/365 -> 0.011959697
D28: =D27+365 -> 45890 | E28: =D28-$B$1 -> 486 | F28: =$E$12*$E$9 -> 300 | G28: =_xlfn.XLOOKUP(E28,'zero-coupon-yields_202405171536'!$B$2:$B$1411,'zero-coupon-yields_202405171536'!D3:D1412,1,1)/100 -> 0.071582 | H28: =F28/(1+G28)^(E28/365) -> 273.61646 | I28: =H28/$H$34 -> 0.033658978 | J28: =I28*E28/365 -> 0.04481716
D29: =D28+365 -> 46255 | E29: =D29-$B$1 -> 851 | F29: =$E$12*$E$9 -> 300 | G29: =_xlfn.XLOOKUP(E29,'zero-coupon-yields_202405171536'!$B$2:$B$1411,'zero-coupon-yields_202405171536'!D4:D1413,1,1)/100 -> 0.072021 | H29: =F29/(1+G29)^(E29/365) -> 255.09507 | I29: =H29/$H$34 -> 0.031380567 | J29: =I29*E29/365 -> 0.073164006
D30: =D29+365 -> 46620 | E30: =D30-$B$1 -> 1216 | F30: =$E$12*$E$9 -> 300 | G30: =_xlfn.XLOOKUP(E30,'zero-coupon-yields_202405171536'!$B$2:$B$1411,'zero-coupon-yields_202405171536'!D5:D1414,1,1)/100 -> 0.072119 | H30: =F30/(1+G30)^(E30/365) -> 237.8847 | I30: =H30/$H$34 -> 0.02926343 | J30: =I30*E30/365 -> 0.097491317
D31: =D30+365 -> 46985 | E31: =D31-$B$1 -> 1581 | F31: =$E$12*$E$9 -> 300 | G31: =_xlfn.XLOOKUP(E31,'zero-coupon-yields_202405171536'!$B$2:$B$1411,'zero-coupon-yields_202405171536'!D6:D1415,1,1)/100 -> 0.072045 | H31: =F31/(1+G31)^(E31/365) -> 221.94909 | I31: =H31/$H$34 -> 0.027303108 | J31: =I31*E31/365 -> 0.1182636
D32: =D31+365 -> 47350 | E32: =D32-$B$1 -> 1946 | F32: =$E$12*$E$9 -> 300 | G32: =_xlfn.XLOOKUP(E32,'zero-coupon-yields_202405171536'!$B$2:$B$1411,'zero-coupon-yields_202405171536'!D7:D1416,1,1)/100 -> 0.071911 | H32: =F32/(1+G32)^(E32/365) -> 207.1714 | I32: =H32/$H$34 -> 0.025485227 | J32: =I32*E32/365 -> 0.13587466
D33: =E6 -> 47716 | E33: =D33-$B$1 -> 2312 | F33: =E12*(1+E9) -> 10300 | G33: =_xlfn.XLOOKUP(E33,'zero-coupon-yields_202405171536'!$B$2:$B$1411,'zero-coupon-yields_202405171536'!D8:D1417,1,1)/100 -> 0.071767 | H33: =F33/(1+G33)^(E33/365) -> 6640.0904 | I33: =H33/$H$34 -> 0.81683192 | J33: =I33*E33/365 -> 5.1740148
H34: =SUM(H27:H33) -> 8129.078 | I34: =SUM(I27:I33) -> 1 | J34: =SUM(J27:J33) -> 5.6555852
C36: =F4 -> 2032/A | D36: =F11 -> 45620 | E36: =D36-$B$1 -> 216 | F36: =$F$12*$F$9 -> 475 | G36: =_xlfn.XLOOKUP(E36,'zero-coupon-yields_202405171536'!$B$2:$B$1411,'zero-coupon-yields_202405171536'!D2:D1411,1,1)/100 -> 0.071039 | H36: =F36/(1+G36)^(E36/365) -> 456.09511 | I36: =H36/$H$45 -> 0.052548122 | J36: =I36*E36/365 -> 0.031096971
D37: =D36+365 -> 45985 | E37: =D37-$B$1 -> 581 | F37: =$F$12*$F$9 -> 475 | G37: =_xlfn.XLOOKUP(E37,'zero-coupon-yields_202405171536'!$B$2:$B$1411,'zero-coupon-yields_202405171536'!D3:D1412,1,1)/100 -> 0.071721 | H37: =F37/(1+G37)^(E37/365) -> 425.41233 | I37: =H37/$H$45 -> 0.049013064 | J37: =I37*E37/365 -> 0.078018056
D38: =D37+365 -> 46350 | E38: =D38-$B$1 -> 946 | F38: =$F$12*$F$9 -> 475 | G38: =_xlfn.XLOOKUP(E38,'zero-coupon-yields_202405171536'!$B$2:$B$1411,'zero-coupon-yields_202405171536'!D4:D1413,1,1)/100 -> 0.072075 | H38: =F38/(1+G38)^(E38/365) -> 396.60355 | I38: =H38/$H$45 -> 0.045693916 | J38: =I38*E38/365 -> 0.11842862
D39: =D38+365 -> 46715 | E39: =D39-$B$1 -> 1311 | F39: =$F$12*$F$9 -> 475 | G39: =_xlfn.XLOOKUP(E39,'zero-coupon-yields_202405171536'!$B$2:$B$1411,'zero-coupon-yields_202405171536'!D5:D1414,1,1)/100 -> 0.07211 | H39: =F39/(1+G39)^(E39/365) -> 369.89674 | I39: =H39/$H$45 -> 0.042616942 | J39: =I39*E39/365 -> 0.15307072
D40: =D39+365 -> 47080 | E40: =D40-$B$1 -> 1676 | F40: =$F$12*$F$9 -> 475 | G40: =_xlfn.XLOOKUP(E40,'zero-coupon-yields_202405171536'!$B$2:$B$1411,'zero-coupon-yields_202405171536'!D6:D1415,1,1)/100 -> 0.072013 | H40: =F40/(1+G40)^(E40/365) -> 345.1609 | I40: =H40/$H$45 -> 0.03976705 | J40: =I40*E40/365 -> 0.18260158
D41: =D40+365 -> 47445 | E41: =D41-$B$1 -> 2041 | F41: =$F$12*$F$9 -> 475 | G41: =_xlfn.XLOOKUP(E41,'zero-coupon-yields_202405171536'!$B$2:$B$1411,'zero-coupon-yields_202405171536'!D7:D1416,1,1)/100 -> 0.071873 | H41: =F41/(1+G41)^(E41/365) -> 322.20977 | I41: =H41/$H$45 -> 0.03712278 | J41: =I41*E41/365 -> 0.20758245
D42: =D41+365 -> 47810 | E42: =D42-$B$1 -> 2406 | F42: =$F$12*$F$9 -> 475 | G42: =_xlfn.XLOOKUP(E42,'zero-coupon-yields_202405171536'!$B$2:$B$1411,'zero-coupon-yields_202405171536'!D8:D1417,1,1)/100 -> 0.071735 | H42: =F42/(1+G42)^(E42/365) -> 300.85967 | I42: =H42/$H$45 -> 0.034662969 | J42: =I42*E42/365 -> 0.22849069
D43: =D42+365 -> 48175 | E43: =D43-$B$1 -> 2771 | F43: =$F$12*$F$9 -> 475 | G43: =_xlfn.XLOOKUP(E43,'zero-coupon-yields_202405171536'!$B$2:$B$1411,'zero-coupon-yields_202405171536'!D9:D1418,1,1)/100 -> 0.071631 | H43: =F43/(1+G43)^(E43/365) -> 280.92896 | I43: =H43/$H$45 -> 0.032366691 | J43: =I43*E43/365 -> 0.24572082
D44: =F6 -> 48542 | E44: =D44-$B$1 -> 3138 | F44: =F12*(1+F9) -> 10475 | G44: =_xlfn.XLOOKUP(E44,'zero-coupon-yields_202405171536'!$B$2:$B$1411,'zero-coupon-yields_202405171536'!D10:D1419,1,1)/100 -> 0.071556 | H44: =F44/(1+G44)^(E44/365) -> 5782.4031 | I44: =H44/$H$45 -> 0.66620846 | J44: =I44*E44/365 -> 5.7275676
H45: =SUM(H36:H44) -> 8679.5701 | I45: =SUM(I36:I44) -> 1 | J45: =SUM(J36:J44) -> 6.9725775
C48: Portfolio Cash Flow | D48: 45587 | E48: 45952 | F48: 46317 | G48: 46682 | H48: 47048 | I48: 45525 | J48: 45890 | K48: 46255 | L48: 46620 | M48: 46985 | N48: 47350 | O48: 47716 | P48: 45620 | Q48: 45985 | R48: 46350 | S48: 46715 | T48: 47080 | U48: 47445 | V48: 47810 | W48: 48175 | X48: 48542
C49: Cash Flow | D49: 675 | E49: 675 | F49: 675 | G49: 675 | H49: 10675 | I49: 300 | J49: 300 | K49: 300 | L49: 300 | M49: 300 | N49: 300 | O49: 10300 | P49: 475 | Q49: 475 | R49: 475 | S49: 475 | T49: 475 | U49: 475 | V49: 475 | W49: 475 | X49: 10475

Sheet Task2
B4: day | C4: year | F4: Mapped cash flow dates (years) | P4: Portfolio | T4: Correlation Matrix
A5: =Task1!D4 -> 2028/A | B5: =Task1!E20 -> 183 | C5: =B5/365 -> 0.50136986 | R5: 1 day
B6: =Task1!E21 -> 548 | C6: =B6/365 -> 1.5013699 | F6: t | G6: r(t) | H6: DF(t) | I6: CF' | J6: PV | K6: w(t) | L6: DUR | M6: w(t)*bond price volatility | T6: t | U6: 0.25 | V6: 0.5 | W6: 1 | X6: 3 | Y6: 5 | Z6: 10
B7: =Task1!E22 -> 913 | C7: =B7/365 -> 2.5013699 | F7: 0.25 | G7: {=_xlfn.XLOOKUP(Task1!$B$1,'Benchmark yields table'!$A$3:$A$599,_xlfn.XLOOKUP(Task2!F7,'Benchmark yields table'!$B$2:$I$2,'Benchmark yields table'!$B$3:$I$599))/100} -> 0.0668 | H7: =1/(1+G7)^F7 -> 0.98396409 | I7: =L45*M44 -> 358865.5 | J7: =H7*I7 -> 353110.76 | K7: =J7/$J$13 -> 0.0035200348 | L7: =K7*F7 -> 0.00088000871 | M7: =K7*U15 -> 1.7180811e-06 | Q7: Volatility | R7: {=SQRT(MMULT(TRANSPOSE(M7:M12),MMULT(U7:Z12,M7:M12)))} -> 0.0051693086 | T7: 0.25 | U7: =CORREL(_xlfn.XLOOKUP($T7,'Benchmark yields table'!$J$2:$Q$2,'Benchmark yields table'!$J$20:$Q$599),_xlfn.XLOOKUP(U$6,'Benchmark yields table'!$J$2:$Q$2,'Benchmark yields table'!$J$20:$Q$599)) -> 1 | V7: =CORREL(_xlfn.XLOOKUP($T7,'Benchmark yields table'!$J$2:$Q$2,'Benchmark yields table'!$J$20:$Q$599),_xlfn.XLOOKUP(V$6,'Benchmark yields table'!$J$2:$Q$2,'Benchmark yields table'!$J$20:$Q$599)) -> 0.60501119 | W7: =CORREL(_xlfn.XLOOKUP($T7,'Benchmark yields table'!$J$2:$Q$2,'Benchmark yields table'!$J$20:$Q$599),_xlfn.XLOOKUP(W$6,'Benchmark yields table'!$J$2:$Q$2,'Benchmark yields table'!$J$20:$Q$599)) -> 0.51525983 | X7: =CORREL(_xlfn.XLOOKUP($T7,'Benchmark yields table'!$J$2:$Q$2,'Benchmark yields table'!$J$20:$Q$599),_xlfn.XLOOKUP(X$6,'Benchmark yields table'!$J$2:$Q$2,'Benchmark yields table'!$J$20:$Q$599)) -> 0.38125654 | Y7: =CORREL(_xlfn.XLOOKUP($T7,'Benchmark yields table'!$J$2:$Q$2,'Benchmark yields table'!$J$20:$Q$599),_xlfn.XLOOKUP(Y$6,'Benchmark yields table'!$J$2:$Q$2,'Benchmark yields table'!$J$20:$Q$599)) -> 0.36677534 | Z7: =CORREL(_xlfn.XLOOKUP($T7,'Benchmark yields table'!$J$2:$Q$2,'Benchmark yields table'!$J$20:$Q$599),_xlfn.XLOOKUP(Z$6,'Benchmark yields table'!$J$2:$Q$2,'Benchmark yields table'!$J$20:$Q$599)) -> 0.3658849
B8: =Task1!E23 -> 1278 | C8: =B8/365 -> 3.5013699 | F8: 0.5 | G8: {=_xlfn.XLOOKUP(Task1!$B$1,'Benchmark yields table'!$A$3:$A$599,_xlfn.XLOOKUP(Task2!F8,'Benchmark yields table'!$B$2:$I$2,'Benchmark yields table'!$B$3:$I$599))/100} -> 0.0692 | H8: =1/(1+G8)^F8 -> 0.96709809 | I8: =M23*SUM(L24)+M44*SUM(L47)+M73*SUM(L74) -> 4631897.6 | J8: =H8*I8 -> 4479499.3 | K8: =J8/$J$13 -> 0.044654526 | L8: =K8*F8 -> 0.022327263 | M8: =K8*V15 -> 2.9048412e-05 | Q8: Multiplier for 99% confidence | R8: =NORMSINV(1-R13) -> -2.3263479 | T8: 0.5 | U8: =CORREL(_xlfn.XLOOKUP($T8,'Benchmark yields table'!$J$2:$Q$2,'Benchmark yields table'!$J$20:$Q$599),_xlfn.XLOOKUP(U$6,'Benchmark yields table'!$J$2:$Q$2,'Benchmark yields table'!$J$20:$Q$599)) -> 0.60501119 | V8: =CORREL(_xlfn.XLOOKUP($T8,'Benchmark yields table'!$J$2:$Q$2,'Benchmark yields table'!$J$20:$Q$599),_xlfn.XLOOKUP(V$6,'Benchmark yields table'!$J$2:$Q$2,'Benchmark yields table'!$J$20:$Q$599)) -> 1 | W8: =CORREL(_xlfn.XLOOKUP($T8,'Benchmark yields table'!$J$2:$Q$2,'Benchmark yields table'!$J$20:$Q$599),_xlfn.XLOOKUP(W$6,'Benchmark yields table'!$J$2:$Q$2,'Benchmark yields table'!$J$20:$Q$599)) -> 0.73079441 | X8: =CORREL(_xlfn.XLOOKUP($T8,'Benchmark yields table'!$J$2:$Q$2,'Benchmark yields table'!$J$20:$Q$599),_xlfn.XLOOKUP(X$6,'Benchmark yields table'!$J$2:$Q$2,'Benchmark yields table'!$J$20:$Q$599)) -> 0.53728582 | Y8: =CORREL(_xlfn.XLOOKUP($T8,'Benchmark yields table'!$J$2:$Q$2,'Benchmark yields table'!$J$20:$Q$599),_xlfn.XLOOKUP(Y$6,'Benchmark yields table'!$J$2:$Q$2,'Benchmark yields table'!$J$20:$Q$599)) -> 0.5331356 | Z8: =CORREL(_xlfn.XLOOKUP($T8,'Benchmark yields table'!$J$2:$Q$2,'Benchmark yields table'!$J$20:$Q$599),_xlfn.XLOOKUP(Z$6,'Benchmark yields table'!$J$2:$Q$2,'Benchmark yields table'!$J$20:$Q$599)) -> 0.55077977
B9: =Task1!E24 -> 1644 | C9: =B9/365 -> 4.5041096 | F9: 1 | G9: {=_xlfn.XLOOKUP(Task1!$B$1,'Benchmark yields table'!$A$3:$A$599,_xlfn.XLOOKUP(Task2!F9,'Benchmark yields table'!$B$2:$I$2,'Benchmark yields table'!$B$3:$I$599))/100} -> 0.0688 | H9: =1/(1+G9)^F9 -> 0.93562874 | I9: =M23*SUM(L26,L28,L32)+M44*SUM(L49,L53)+M73*SUM(L76,L78,L82) -> 5226346.3 | J9: =H9*I9 -> 4889919.8 | K9: =J9/$J$13 -> 0.048745862 | L9: =K9*F9 -> 0.048745862 | M9: =K9*W15 -> 5.8787736e-05 | Q9: VaR (1 day, 99%) | R9: =-R7*R8 -> 0.01202561 | T9: 1 | U9: =CORREL(_xlfn.XLOOKUP($T9,'Benchmark yields table'!$J$2:$Q$2,'Benchmark yields table'!$J$20:$Q$599),_xlfn.XLOOKUP(U$6,'Benchmark yields table'!$J$2:$Q$2,'Benchmark yields table'!$J$20:$Q$599)) -> 0.51525983 | V9: =CORREL(_xlfn.XLOOKUP($T9,'Benchmark yields table'!$J$2:$Q$2,'Benchmark yields table'!$J$20:$Q$599),_xlfn.XLOOKUP(V$6,'Benchmark yields table'!$J$2:$Q$2,'Benchmark yields table'!$J$20:$Q$599)) -> 0.73079441 | W9: =CORREL(_xlfn.XLOOKUP($T9,'Benchmark yields table'!$J$2:$Q$2,'Benchmark yields table'!$J$20:$Q$599),_xlfn.XLOOKUP(W$6,'Benchmark yields table'!$J$2:$Q$2,'Benchmark yields table'!$J$20:$Q$599)) -> 1 | X9: =CORREL(_xlfn.XLOOKUP($T9,'Benchmark yields table'!$J$2:$Q$2,'Benchmark yields table'!$J$20:$Q$599),_xlfn.XLOOKUP(X$6,'Benchmark yields table'!$J$2:$Q$2,'Benchmark yields table'!$J$20:$Q$599)) -> 0.66514828 | Y9: =CORREL(_xlfn.XLOOKUP($T9,'Benchmark yields table'!$J$2:$Q$2,'Benchmark yields table'!$J$20:$Q$599),_xlfn.XLOOKUP(Y$6,'Benchmark yields table'!$J$2:$Q$2,'Benchmark yields table'!$J$20:$Q$599)) -> 0.66363795 | Z9: =CORREL(_xlfn.XLOOKUP($T9,'Benchmark yields table'!$J$2:$Q$2,'Benchmark yields table'!$J$20:$Q$599),_xlfn.XLOOKUP(Z$6,'Benchmark yields table'!$J$2:$Q$2,'Benchmark yields table'!$J$20:$Q$599)) -> 0.67559884
A10: =Task1!E4 -> 2030/A | B10: =Task1!E27 -> 121 | C10: =B10/365 -> 0.33150685 | F10: 3 | G10: {=_xlfn.XLOOKUP(Task1!$B$1,'Benchmark yields table'!$A$3:$A$599,_xlfn.XLOOKUP(Task2!F10,'Benchmark yields table'!$B$2:$I$2,'Benchmark yields table'!$B$3:$I$599))/100} -> 0.0725 | H10: =1/(1+G10)^F10 -> 0.8106028 | I10: =M23*SUM(L30,L34,L36,L40)+M44*SUM(L51,L55,L57,L61)+M73*SUM(L80,L84,L86,L90) -> 21391831 | J10: =H10*I10 -> 17340278 | K10: =J10/$J$13 -> 0.17285903 | L10: =K10*F10 -> 0.51857708 | M10: =K10*X15 -> 0.00048992242 | Q10: VaR (HUF, 1 day, 99%) | R10: =R9*Task1!K6 -> 1202507.1 | T10: 3 | U10: =CORREL(_xlfn.XLOOKUP($T10,'Benchmark yields table'!$J$2:$Q$2,'Benchmark yields table'!$J$20:$Q$599),_xlfn.XLOOKUP(U$6,'Benchmark yields table'!$J$2:$Q$2,'Benchmark yields table'!$J$20:$Q$599)) -> 0.38125654 | V10: =CORREL(_xlfn.XLOOKUP($T10,'Benchmark yields table'!$J$2:$Q$2,'Benchmark yields table'!$J$20:$Q$599),_xlfn.XLOOKUP(V$6,'Benchmark yields table'!$J$2:$Q$2,'Benchmark yields table'!$J$20:$Q$599)) -> 0.53728582 | W10: =CORREL(_xlfn.XLOOKUP($T10,'Benchmark yields table'!$J$2:$Q$2,'Benchmark yields table'!$J$20:$Q$599),_xlfn.XLOOKUP(W$6,'Benchmark yields table'!$J$2:$Q$2,'Benchmark yields table'!$J$20:$Q$599)) -> 0.66514828 | X10: =CORREL(_xlfn.XLOOKUP($T10,'Benchmark yields table'!$J$2:$Q$2,'Benchmark yields table'!$J$20:$Q$599),_xlfn.XLOOKUP(X$6,'Benchmark yields table'!$J$2:$Q$2,'Benchmark yields table'!$J$20:$Q$599)) -> 1 | Y10: =CORREL(_xlfn.XLOOKUP($T10,'Benchmark yields table'!$J$2:$Q$2,'Benchmark yields table'!$J$20:$Q$599),_xlfn.XLOOKUP(Y$6,'Benchmark yields table'!$J$2:$Q$2,'Benchmark yields table'!$J$20:$Q$599)) -> 0.95541409 | Z10: =CORREL(_xlfn.XLOOKUP($T10,'Benchmark yields table'!$J$2:$Q$2,'Benchmark yields table'!$J$20:$Q$599),_xlfn.XLOOKUP(Z$6,'Benchmark yields table'!$J$2:$Q$2,'Benchmark yields table'!$J$20:$Q$599)) -> 0.91480363
B11: =Task1!E28 -> 486 | C11: =B11/365 -> 1.3315068 | F11: 5 | G11: {=_xlfn.XLOOKUP(Task1!$B$1,'Benchmark yields table'!$A$3:$A$599,_xlfn.XLOOKUP(Task2!F11,'Benchmark yields table'!$B$2:$I$2,'Benchmark yields table'!$B$3:$I$599))/100} -> 0.0721 | H11: =1/(1+G11)^F11 -> 0.70603059 | I11: =M23*SUM(L38,L42)+M44*SUM(L59,L63,L65,L69)+M73*SUM(L88,L92,L94,L98,L102,L106) -> 76488558 | J11: =H11*I11 -> 54003262 | K11: =J11/$J$13 -> 0.5383392 | L11: =K11*F11 -> 2.691696 | M11: =K11*Y15 -> 0.002719078 | Q11: VaR (10 days, 99%) | R11: =R9*SQRT(10) -> 0.038028318 | T11: 5 | U11: =CORREL(_xlfn.XLOOKUP($T11,'Benchmark yields table'!$J$2:$Q$2,'Benchmark yields table'!$J$20:$Q$599),_xlfn.XLOOKUP(U$6,'Benchmark yields table'!$J$2:$Q$2,'Benchmark yields table'!$J$20:$Q$599)) -> 0.36677534 | V11: =CORREL(_xlfn.XLOOKUP($T11,'Benchmark yields table'!$J$2:$Q$2,'Benchmark yields table'!$J$20:$Q$599),_xlfn.XLOOKUP(V$6,'Benchmark yields table'!$J$2:$Q$2,'Benchmark yields table'!$J$20:$Q$599)) -> 0.5331356 | W11: =CORREL(_xlfn.XLOOKUP($T11,'Benchmark yields table'!$J$2:$Q$2,'Benchmark yields table'!$J$20:$Q$599),_xlfn.XLOOKUP(W$6,'Benchmark yields table'!$J$2:$Q$2,'Benchmark yields table'!$J$20:$Q$599)) -> 0.66363795 | X11: =CORREL(_xlfn.XLOOKUP($T11,'Benchmark yields table'!$J$2:$Q$2,'Benchmark yields table'!$J$20:$Q$599),_xlfn.XLOOKUP(X$6,'Benchmark yields table'!$J$2:$Q$2,'Benchmark yields table'!$J$20:$Q$599)) -> 0.95541409 | Y11: =CORREL(_xlfn.XLOOKUP($T11,'Benchmark yields table'!$J$2:$Q$2,'Benchmark yields table'!$J$20:$Q$599),_xlfn.XLOOKUP(Y$6,'Benchmark yields table'!$J$2:$Q$2,'Benchmark yields table'!$J$20:$Q$599)) -> 1 | Z11: =CORREL(_xlfn.XLOOKUP($T11,'Benchmark yields table'!$J$2:$Q$2,'Benchmark yields table'!$J$20:$Q$599),_xlfn.XLOOKUP(Z$6,'Benchmark yields table'!$J$2:$Q$2,'Benchmark yields table'!$J$20:$Q$599)) -> 0.96353862
B12: =Task1!E29 -> 851 | C12: =B12/365 -> 2.3315068 | F12: 10 | G12: {=_xlfn.XLOOKUP(Task1!$B$1,'Benchmark yields table'!$A$3:$A$599,_xlfn.XLOOKUP(Task2!F12,'Benchmark yields table'!$B$2:$I$2,'Benchmark yields table'!$B$3:$I$599))/100} -> 0.0712 | H12: =1/(1+G12)^F12 -> 0.50268319 | I12: =M44*SUM(L67,L71)+M73*SUM(L96,L104,L100,L108) -> 38291502 | J12: =H12*I12 -> 19248494 | K12: =J12/$J$13 -> 0.19188135 | L12: =K12*F12 -> 1.9188135 | M12: =K12*Z15 -> 0.001969072 | T12: 10 | U12: =CORREL(_xlfn.XLOOKUP($T12,'Benchmark yields table'!$J$2:$Q$2,'Benchmark yields table'!$J$20:$Q$599),_xlfn.XLOOKUP(U$6,'Benchmark yields table'!$J$2:$Q$2,'Benchmark yields table'!$J$20:$Q$599)) -> 0.3658849 | V12: =CORREL(_xlfn.XLOOKUP($T12,'Benchmark yields table'!$J$2:$Q$2,'Benchmark yields table'!$J$20:$Q$599),_xlfn.XLOOKUP(V$6,'Benchmark yields table'!$J$2:$Q$2,'Benchmark yields table'!$J$20:$Q$599)) -> 0.55077977 | W12: =CORREL(_xlfn.XLOOKUP($T12,'Benchmark yields table'!$J$2:$Q$2,'Benchmark yields table'!$J$20:$Q$599),_xlfn.XLOOKUP(W$6,'Benchmark yields table'!$J$2:$Q$2,'Benchmark yields table'!$J$20:$Q$599)) -> 0.67559884 | X12: =CORREL(_xlfn.XLOOKUP($T12,'Benchmark yields table'!$J$2:$Q$2,'Benchmark yields table'!$J$20:$Q$599),_xlfn.XLOOKUP(X$6,'Benchmark yields table'!$J$2:$Q$2,'Benchmark yields table'!$J$20:$Q$599)) -> 0.91480363 | Y12: =CORREL(_xlfn.XLOOKUP($T12,'Benchmark yields table'!$J$2:$Q$2,'Benchmark yields table'!$J$20:$Q$599),_xlfn.XLOOKUP(Y$6,'Benchmark yields table'!$J$2:$Q$2,'Benchmark yields table'!$J$20:$Q$599)) -> 0.96353862 | Z12: =CORREL(_xlfn.XLOOKUP($T12,'Benchmark yields table'!$J$2:$Q$2,'Benchmark yields table'!$J$20:$Q$599),_xlfn.XLOOKUP(Z$6,'Benchmark yields table'!$J$2:$Q$2,'Benchmark yields table'!$J$20:$Q$599)) -> 1
B13: =Task1!E30 -> 1216 | C13: =B13/365 -> 3.3315068 | J13: =SUM(J7:J12) -> 1.0031456e+08 | K13: =J13/$J$13 -> 1 | L13: =SUM(L7:L12) -> 5.2010397 | Q13: Significance | R13: 0.99
B14: =Task1!E31 -> 1581 | C14: =B14/365 -> 4.3315068 | T14: "bond price volatilities" for Bechmark yield curve points
B15: =Task1!E32 -> 1946 | C15: =B15/365 -> 5.3315068 | U15: {=_xlfn.XLOOKUP(Task1!$B$1,'Benchmark yields table'!$A$3:$A$20,_xlfn.XLOOKUP(U6,'Benchmark yields table'!$BF$2:$BM$2,'Benchmark yields table'!$BF$3:$BM$20))} -> 0.0004880864 | V15: {=_xlfn.XLOOKUP(Task1!$B$1,'Benchmark yields table'!$A$3:$A$20,_xlfn.XLOOKUP(V6,'Benchmark yields table'!$BF$2:$BM$2,'Benchmark yields table'!$BF$3:$BM$20))} -> 0.00065051439 | W15: {=_xlfn.XLOOKUP(Task1!$B$1,'Benchmark yields table'!$A$3:$A$20,_xlfn.XLOOKUP(W6,'Benchmark yields table'!$BF$2:$BM$2,'Benchmark yields table'!$BF$3:$BM$20))} -> 0.0012060047 | X15: {=_xlfn.XLOOKUP(Task1!$B$1,'Benchmark yields table'!$A$3:$A$20,_xlfn.XLOOKUP(X6,'Benchmark yields table'!$BF$2:$BM$2,'Benchmark yields table'!$BF$3:$BM$20))} -> 0.002834231 | Y15: {=_xlfn.XLOOKUP(Task1!$B$1,'Benchmark yields table'!$A$3:$A$20,_xlfn.XLOOKUP(Y6,'Benchmark yields table'!$BF$2:$BM$2,'Benchmark yields table'!$BF$3:$BM$20))} -> 0.0050508639 | Z15: {=_xlfn.XLOOKUP(Task1!$B$1,'Benchmark yields table'!$A$3:$A$20,_xlfn.XLOOKUP(Z6,'Benchmark yields table'!$BF$2:$BM$2,'Benchmark yields table'!$BF$3:$BM$20))} -> 0.010261925
B16: =Task1!E33 -> 2312 | C16: =B16/365 -> 6.3342466
A17: =Task1!F4 -> 2032/A | B17: =Task1!E36 -> 216 | C17: =B17/365 -> 0.59178082
B18: =Task1!E37 -> 581 | C18: =B18/365 -> 1.5917808
B19: =Task1!E38 -> 946 | C19: =B19/365 -> 2.5917808
B20: =Task1!E39 -> 1311 | C20: =B20/365 -> 3.5917808 | F20: Cash Flow Mapping
B21: =Task1!E40 -> 1676 | C21: =B21/365 -> 4.5917808 | G21: t | H21: r(t) | I21: stddev(t) | J21: DF(t) | K21: CF | L21: CF' | M21: number of securities
B22: =Task1!E41 -> 2041 | C22: =B22/365 -> 5.5917808
B23: =Task1!E42 -> 2406 | C23: =B23/365 -> 6.5917808 | F23: =Task1!D4 -> 2028/A | M23: =Task1!D13 -> 4152
B24: =Task1!E43 -> 2771 | C24: =B24/365 -> 7.5917808 | F24: =1-((G25-G24)/(G26-G24)) -> 0.99726027 | G24: 0.5 | H24: {=_xlfn.XLOOKUP(Task1!$B$1,'Benchmark yields table'!$A$3:$A$599,_xlfn.XLOOKUP(Task2!G24,'Benchmark yields table'!$B$2:$I$2,'Benchmark yields table'!$B$3:$I$599))/100} -> 0.0692 | I24: {=_xlfn.XLOOKUP(Task1!$B$1,'Benchmark yields table'!$A$3:$A$599,_xlfn.XLOOKUP(Task2!G24,'Benchmark yields table'!$BF$2:$BM$2,'Benchmark yields table'!$BF$3:$BM$599))} -> 0.00065051439 | J24: =1/(1+H24)^G24 -> 0.96709809 | L24: =K25*M25 -> 670.61375 | M24: alfa | N24: PV= | P24: =K25*J25 -> 652.73171 | Q24: Korrel | R24: Vol | S24: =I25 -> 0.00065203628 | T24: a | V24: =I24^2+I26^2-2*Q25*I24*I26 -> 7.3096559e-07 | W24: =(-V25+SQRT(V25^2-4*V24*V26))/(2*V24) -> 1.4173419
B25: =Task1!E44 -> 3138 | C25: =B25/365 -> 8.5972603 | G25: =C5 -> 0.50136986 | H25: =F24*H24+(1-F24)*H26 -> 0.069198904 | I25: =F24*I24+(1-F24)*I26 -> 0.00065203628 | J25: =1/(1+H25)^G25 -> 0.96700995 | K25: =Task1!F20 -> 675 | M25: =MIN(W24:W25) -> 0.99350186 | N25: PV'= | P25: =L24*J24+L26*J26 -> 652.65318 | Q25: {=_xlfn.XLOOKUP(G24,$T$7:$T$12,_xlfn.XLOOKUP(G26,$U$6:$Z$6,$U$7:$Z$12))} -> 0.73079441 | R25: Vol' | S25: =SQRT((M25*I24)^2+((1-M25)*I26)^2+2*M25*(1-M25)*Q25*I24*I26) -> 0.00065203628 | T25: b | V25: =2*Q25*I24*I26-2*I26^2 -> -1.7622438e-06 | W25: =(-V25-SQRT(V25^2-4*V24*V26))/(2*V24) -> 0.99350186
G26: 1 | H26: {=_xlfn.XLOOKUP(Task1!$B$1,'Benchmark yields table'!$A$3:$A$599,_xlfn.XLOOKUP(Task2!G26,'Benchmark yields table'!$B$2:$I$2,'Benchmark yields table'!$B$3:$I$599))/100} -> 0.0688 | I26: {=_xlfn.XLOOKUP(Task1!$B$1,'Benchmark yields table'!$A$3:$A$599,_xlfn.XLOOKUP(Task2!G26,'Benchmark yields table'!$BF$2:$BM$2,'Benchmark yields table'!$BF$3:$BM$599))} -> 0.0012060047 | J26: =1/(1+H26)^G26 -> 0.93562874 | L26: =(1-M25)*K25 -> 4.3862466 | N26: Pvdiff | P26: =ABS(P24-P25) -> 0.078536621 | R26: Voldiff | S26: =ABS(S24-S25) -> 0 | T26: c | V26: =I26^2-I25^2 -> 1.0292959e-06
F28: =1-((G29-G28)/(G30-G28)) -> 0.74931507 | G28: 1 | H28: {=_xlfn.XLOOKUP(Task1!$B$1,'Benchmark yields table'!$A$3:$A$599,_xlfn.XLOOKUP(G28,'Benchmark yields table'!$B$2:$I$2,'Benchmark yields table'!$B$3:$I$599))/100} -> 0.0688 | I28: {=_xlfn.XLOOKUP(Task1!$B$1,'Benchmark yields table'!$A$3:$A$599,_xlfn.XLOOKUP(G28,'Benchmark yields table'!$BF$2:$BM$2,'Benchmark yields table'!$BF$3:$BM$599))} -> 0.0012060047 | J28: =1/(1+H28)^G28 -> 0.93562874 | L28: =K29*M29 -> 442.40156 | M28: alfa | N28: PV= | P28: =K29*J29 -> 610.03382 | Q28: Korrel | R28: Vol | S28: =I29 -> 0.0016141765 | T28: a | V28: =I28^2+I30^2-2*Q29*I28*I30 -> 4.9402317e-06 | W28: =(-V29+SQRT(V29^2-4*V28*V30))/(2*V28) -> 1.6761915
G29: =C6 -> 1.5013699 | H29: =H28*F28+(1-F28)*H30 -> 0.069727534 | I29: =I28*F28+(1-F28)*I30 -> 0.0016141765 | J29: =1/(1+H29)^G29 -> 0.9037538 | K29: =Task1!F21 -> 675 | M29: =MIN(W28:W29) -> 0.65540972 | N29: PV'= | P29: =L28*J28+L30*J30 -> 602.46856 | Q29: {=_xlfn.XLOOKUP(G28,$T$7:$T$12,_xlfn.XLOOKUP(G30,$U$6:$Z$6,$U$7:$Z$12))} -> 0.66514828 | R29: Vol' | S29: =SQRT((M29*I28)^2+((1-M29)*I30)^2+2*M29*(1-M29)*Q29*I28*I30) -> 0.0016141765 | T29: b | V29: =2*Q29*I28*I30-2*I30^2 -> -1.151865e-05 | W29: =(-V29-SQRT(V29^2-4*V28*V30))/(2*V28) -> 0.65540972
G30: 3 | H30: {=_xlfn.XLOOKUP(Task1!$B$1,'Benchmark yields table'!$A$3:$A$599,_xlfn.XLOOKUP(G30,'Benchmark yields table'!$B$2:$I$2,'Benchmark yields table'!$B$3:$I$599))/100} -> 0.0725 | I30: {=_xlfn.XLOOKUP(Task1!$B$1,'Benchmark yields table'!$A$3:$A$599,_xlfn.XLOOKUP(G30,'Benchmark yields table'!$BF$2:$BM$2,'Benchmark yields table'!$BF$3:$BM$599))} -> 0.002834231 | J30: =1/(1+H30)^G30 -> 0.8106028 | L30: =(1-M29)*K29 -> 232.59844 | N30: Pvdiff | P30: =ABS(P28-P29) -> 7.5652561 | R30: Voldiff | S30: =ABS(S28-S29) -> 0 | T30: c | V30: =I30^2-I29^2 -> 5.4272999e-06
F32: =1-((G33-G32)/(G34-G32)) -> 0.24931507 | G32: 1 | H32: {=_xlfn.XLOOKUP(Task1!$B$1,'Benchmark yields table'!$A$3:$A$599,_xlfn.XLOOKUP(G32,'Benchmark yields table'!$B$2:$I$2,'Benchmark yields table'!$B$3:$I$599))/100} -> 0.0688 | I32: {=_xlfn.XLOOKUP(Task1!$B$1,'Benchmark yields table'!$A$3:$A$599,_xlfn.XLOOKUP(G32,'Benchmark yields table'!$BF$2:$BM$2,'Benchmark yields table'!$BF$3:$BM$599))} -> 0.0012060047 | J32: =1/(1+H32)^G32 -> 0.93562874 | L32: =K33*M33 -> 137.13648 | M32: alfa | N32: PV= | P32: =K33*J33 -> 567.81079 | Q32: Korrel | R32: Vol | S32: =I33 -> 0.0024282897 | T32: a | V32: =I32^2+I34^2-2*Q33*I32*I34 -> 4.9402317e-06 | W32: =(-V33+SQRT(V33^2-4*V32*V34))/(2*V32) -> 2.128436
G33: =C7 -> 2.5013699 | H33: =H32*F32+(1-F32)*H34 -> 0.071577534 | I33: =I32*F32+(1-F32)*I34 -> 0.0024282897 | J33: =1/(1+H33)^G33 -> 0.84120118 | K33: =Task1!F22 -> 675 | M33: =MIN(W32:W33) -> 0.20316515 | N33: PV'= | P33: =L32*J32+L34*J34 -> 564.30251 | Q33: {=_xlfn.XLOOKUP(G32,$T$7:$T$12,_xlfn.XLOOKUP(G34,$U$6:$Z$6,$U$7:$Z$12))} -> 0.66514828 | R33: Vol' | S33: =SQRT((M33*I32)^2+((1-M33)*I34)^2+2*M33*(1-M33)*Q33*I32*I34) -> 0.0024282897 | T33: b | V33: =2*Q33*I32*I34-2*I34^2 -> -1.151865e-05 | W33: =(-V33-SQRT(V33^2-4*V32*V34))/(2*V32) -> 0.20316515
G34: 3 | H34: {=_xlfn.XLOOKUP(Task1!$B$1,'Benchmark yields table'!$A$3:$A$599,_xlfn.XLOOKUP(G34,'Benchmark yields table'!$B$2:$I$2,'Benchmark yields table'!$B$3:$I$599))/100} -> 0.0725 | I34: {=_xlfn.XLOOKUP(Task1!$B$1,'Benchmark yields table'!$A$3:$A$599,_xlfn.XLOOKUP(G34,'Benchmark yields table'!$BF$2:$BM$2,'Benchmark yields table'!$BF$3:$BM$599))} -> 0.002834231 | J34: =1/(1+H34)^G34 -> 0.8106028 | L34: =(1-M33)*K33 -> 537.86352 | N34: Pvdiff | P34: =ABS(P32-P33) -> 3.5082896 | R34: Voldiff | S34: =ABS(S32-S33) -> 4.3368087e-19 | T34: c | V34: =I34^2-I33^2 -> 2.1362749e-06
F36: =1-((G37-G36)/(G38-G36)) -> 0.74931507 | G36: 3 | H36: {=_xlfn.XLOOKUP(Task1!$B$1,'Benchmark yields table'!$A$3:$A$599,_xlfn.XLOOKUP(G36,'Benchmark yields table'!$B$2:$I$2,'Benchmark yields table'!$B$3:$I$599))/100} -> 0.0725 | I36: {=_xlfn.XLOOKUP(Task1!$B$1,'Benchmark yields table'!$A$3:$A$599,_xlfn.XLOOKUP(G36,'Benchmark yields table'!$BF$2:$BM$2,'Benchmark yields table'!$BF$3:$BM$599))} -> 0.002834231 | J36: =1/(1+H36)^G36 -> 0.8106028 | L36: =K37*M37 -> 494.62086 | M36: alfa | N36: PV= | P36: =K37*J37 -> 528.46199 | Q36: Korrel | R36: Vol | S36: =I37 -> 0.0033899075 | T36: a | V36: =I36^2+I38^2-2*Q37*I36*I38 -> 6.189984e-06 | W36: =(-V37+SQRT(V37^2-4*V36*V38))/(2*V36) -> 3.0908804
G37: =C8 -> 3.5013699 | H37: =F36*H36+(1-F36)*H38 -> 0.072399726 | I37: =I36*F36+(1-F36)*I38 -> 0.0033899075 | J37: =1/(1+H37)^G37 -> 0.78290666 | K37: =Task1!F23 -> 675 | M37: =MIN(W36:W37) -> 0.73277164 | N37: PV'= | P37: =L36*J36+L38*J38 -> 528.29424 | Q37: {=_xlfn.XLOOKUP(G36,$T$7:$T$12,_xlfn.XLOOKUP(G38,$U$6:$Z$6,$U$7:$Z$12))} -> 0.95541409 | R37: Vol' | S37: =SQRT((M37*I36)^2+((1-M37)*I38)^2+2*M37*(1-M37)*Q37*I36*I38) -> 0.0033899075 | T37: b | V37: =2*Q37*I36*I38-2*I38^2 -> -2.3668345e-05 | W37: =(-V37-SQRT(V37^2-4*V36*V38))/(2*V36) -> 0.73277164
G38: 5 | H38: {=_xlfn.XLOOKUP(Task1!$B$1,'Benchmark yields table'!$A$3:$A$599,_xlfn.XLOOKUP(G38,'Benchmark yields table'!$B$2:$I$2,'Benchmark yields table'!$B$3:$I$599))/100} -> 0.0721 | I38: {=_xlfn.XLOOKUP(Task1!$B$1,'Benchmark yields table'!$A$3:$A$599,_xlfn.XLOOKUP(G38,'Benchmark yields table'!$BF$2:$BM$2,'Benchmark yields table'!$BF$3:$BM$599))} -> 0.0050508639 | J38: =1/(1+H38)^G38 -> 0.70603059 | L38: =(1-M37)*K37 -> 180.37914 | N38: Pvdiff | P38: =ABS(P36-P37) -> 0.16774951 | R38: Voldiff | S38: =ABS(S36-S37) -> 4.3368087e-19 | T38: c | V38: =I38^2-I37^2 -> 1.4019753e-05
F40: =1-((G41-G40)/(G42-G40)) -> 0.24794521 | G40: 3 | H40: {=_xlfn.XLOOKUP(Task1!$B$1,'Benchmark yields table'!$A$3:$A$599,_xlfn.XLOOKUP(G40,'Benchmark yields table'!$B$2:$I$2,'Benchmark yields table'!$B$3:$I$599))/100} -> 0.0725 | I40: {=_xlfn.XLOOKUP(Task1!$B$1,'Benchmark yields table'!$A$3:$A$599,_xlfn.XLOOKUP(G40,'Benchmark yields table'!$BF$2:$BM$2,'Benchmark yields table'!$BF$3:$BM$599))} -> 0.002834231 | J40: =1/(1+H40)^G40 -> 0.8106028 | L40: =K41*M41 -> 2523.8846 | M40: alfa | N40: PV= | P40: =K41*J41 -> 7798.3702 | Q40: Korrel | R40: Vol | S40: =I41 -> 0.0045012604 | T40: a | V40: =I40^2+I42^2-2*Q41*I40*I42 -> 6.189984e-06 | W40: =(-V41+SQRT(V41^2-4*V40*V42))/(2*V40) -> 3.5872225
G41: =C9 -> 4.5041096 | H41: =F40*H40+(1-F40)*H42 -> 0.072199178 | I41: =I40*F40+(1-F40)*I42 -> 0.0045012604 | J41: =1/(1+H41)^G41 -> 0.73052648 | K41: =Task1!F24 -> 10675 | M41: =MIN(W40:W41) -> 0.23642947 | N41: PV'= | P41: =L40*J40+L42*J42 -> 7800.8048 | Q41: {=_xlfn.XLOOKUP(G40,$T$7:$T$12,_xlfn.XLOOKUP(G42,$U$6:$Z$6,$U$7:$Z$12))} -> 0.95541409 | R41: Vol' | S41: =SQRT((M41*I40)^2+((1-M41)*I42)^2+2*M41*(1-M41)*Q41*I40*I42) -> 0.0045012604 | T41: b | V41: =2*Q41*I40*I42-2*I42^2 -> -2.3668345e-05 | W41: =(-V41-SQRT(V41^2-4*V40*V42))/(2*V40) -> 0.23642947
G42: 5 | H42: {=_xlfn.XLOOKUP(Task1!$B$1,'Benchmark yields table'!$A$3:$A$599,_xlfn.XLOOKUP(G42,'Benchmark yields table'!$B$2:$I$2,'Benchmark yields table'!$B$3:$I$599))/100} -> 0.0721 | I42: {=_xlfn.XLOOKUP(Task1!$B$1,'Benchmark yields table'!$A$3:$A$599,_xlfn.XLOOKUP(G42,'Benchmark yields table'!$BF$2:$BM$2,'Benchmark yields table'!$BF$3:$BM$599))} -> 0.0050508639 | J42: =1/(1+H42)^G42 -> 0.70603059 | L42: =(1-M41)*K41 -> 8151.1154 | N42: Pvdiff | P42: =ABS(P40-P41) -> 2.4345313 | R42: Voldiff | S42: =ABS(S40-S41) -> 0 | T42: c | V42: =I42^2-I41^2 -> 5.2498809e-06
F44: =Task1!E4 -> 2030/A | M44: =Task1!E13 -> 3323
F45: =1-((G46-G45)/(G47-G45)) -> 0.6739726 | G45: 0.25 | H45: {=_xlfn.XLOOKUP(Task1!$B$1,'Benchmark yields table'!$A$3:$A$599,_xlfn.XLOOKUP(Task2!G45,'Benchmark yields table'!$B$2:$I$2,'Benchmark yields table'!$B$3:$I$599))/100} -> 0.0668 | I45: {=_xlfn.XLOOKUP(Task1!$B$1,'Benchmark yields table'!$A$3:$A$599,_xlfn.XLOOKUP(Task2!G45,'Benchmark yields table'!$BF$2:$BM$2,'Benchmark yields table'!$BF$3:$BM$599))} -> 0.0004880864 | J45: =1/(1+H45)^G45 -> 0.98396409 | L45: =K46*M46 -> 107.99443 | M45: alfa | N45: PV= | P45: =K46*J46 -> 293.56616 | Q45: Korrel | R45: Vol | S45: =I46 -> 0.00054104237 | T45: a | V45: =I45^2+I47^2-2*Q46*I45*I47 -> 2.7720646e-07 | W45: =(-V46+SQRT(V46^2-4*V45*V47))/(2*V45) -> 1.3071771
G46: =C10 -> 0.33150685 | H46: =F45*H45+(1-F45)*H47 -> 0.067582466 | I46: =F45*I45+(1-F45)*I47 -> 0.00054104237 | J46: =1/(1+H46)^G46 -> 0.97855385 | K46: =Task1!F27 -> 300 | M46: =MIN(W45:W46) -> 0.35998144 | N46: PV'= | P46: =L45*J45+L47*J47 -> 291.95086 | Q46: {=_xlfn.XLOOKUP(G45,$T$7:$T$12,_xlfn.XLOOKUP(G47,$U$6:$Z$6,$U$7:$Z$12))} -> 0.60501119 | R46: Vol' | S46: =SQRT((M46*I45)^2+((1-M46)*I47)^2+2*M46*(1-M46)*Q46*I45*I47) -> 0.00054104237 | T46: b | V46: =2*Q46*I45*I47-2*I47^2 -> -4.621471e-07 | W46: =(-V46-SQRT(V46^2-4*V45*V47))/(2*V45) -> 0.35998144
G47: 0.5 | H47: {=_xlfn.XLOOKUP(Task1!$B$1,'Benchmark yields table'!$A$3:$A$599,_xlfn.XLOOKUP(Task2!G47,'Benchmark yields table'!$B$2:$I$2,'Benchmark yields table'!$B$3:$I$599))/100} -> 0.0692 | I47: {=_xlfn.XLOOKUP(Task1!$B$1,'Benchmark yields table'!$A$3:$A$599,_xlfn.XLOOKUP(Task2!G47,'Benchmark yields table'!$BF$2:$BM$2,'Benchmark yields table'!$BF$3:$BM$599))} -> 0.00065051439 | J47: =1/(1+H47)^G47 -> 0.96709809 | L47: =(1-M46)*K46 -> 192.00557 | N47: Pvdiff | P47: =ABS(P45-P46) -> 1.6152949 | R47: Voldiff | S47: =ABS(S45-S46) -> 0 | T47: c | V47: =I47^2-I46^2 -> 1.3044213e-07
F49: =1-((G50-G49)/(G51-G49)) -> 0.83424658 | G49: 1 | H49: {=_xlfn.XLOOKUP(Task1!$B$1,'Benchmark yields table'!$A$3:$A$599,_xlfn.XLOOKUP(G49,'Benchmark yields table'!$B$2:$I$2,'Benchmark yields table'!$B$3:$I$599))/100} -> 0.0688 | I49: {=_xlfn.XLOOKUP(Task1!$B$1,'Benchmark yields table'!$A$3:$A$599,_xlfn.XLOOKUP(G49,'Benchmark yields table'!$BF$2:$BM$2,'Benchmark yields table'!$BF$3:$BM$599))} -> 0.0012060047 | J49: =1/(1+H49)^G49 -> 0.93562874 | L49: =K50*M50 -> 224.5998 | M49: alfa | N49: PV= | P49: =K50*J50 -> 274.35553 | Q49: Korrel | R49: Vol | S49: =I50 -> 0.0014758888 | T49: a | V49: =I49^2+I51^2-2*Q50*I49*I51 -> 4.9402317e-06 | W49: =(-V50+SQRT(V50^2-4*V49*V51))/(2*V49) -> 1.5829352
G50: =C11 -> 1.3315068 | H50: =H49*F49+(1-F49)*H51 -> 0.069413288 | I50: =I49*F49+(1-F49)*I51 -> 0.0014758888 | J50: =1/(1+H50)^G50 -> 0.91451844 | K50: =Task1!F28 -> 300 | M50: =MIN(W49:W50) -> 0.74866601 | N50: PV'= | P50: =L49*J49+L51*J51 -> 271.26164 | Q50: {=_xlfn.XLOOKUP(G49,$T$7:$T$12,_xlfn.XLOOKUP(G51,$U$6:$Z$6,$U$7:$Z$12))} -> 0.66514828 | R50: Vol' | S50: =SQRT((M50*I49)^2+((1-M50)*I51)^2+2*M50*(1-M50)*Q50*I49*I51) -> 0.0014758888 | T50: b | V50: =2*Q50*I49*I51-2*I51^2 -> -1.151865e-05 | W50: =(-V50-SQRT(V50^2-4*V49*V51))/(2*V49) -> 0.74866601
G51: 3 | H51: {=_xlfn.XLOOKUP(Task1!$B$1,'Benchmark yields table'!$A$3:$A$599,_xlfn.XLOOKUP(G51,'Benchmark yields table'!$B$2:$I$2,'Benchmark yields table'!$B$3:$I$599))/100} -> 0.0725 | I51: {=_xlfn.XLOOKUP(Task1!$B$1,'Benchmark yields table'!$A$3:$A$599,_xlfn.XLOOKUP(G51,'Benchmark yields table'!$BF$2:$BM$2,'Benchmark yields table'!$BF$3:$BM$599))} -> 0.002834231 | J51: =1/(1+H51)^G51 -> 0.8106028 | L51: =(1-M50)*K50 -> 75.400198 | N51: Pvdiff | P51: =ABS(P49-P50) -> 3.0938898 | R51: Voldiff | S51: =ABS(S49-S50) -> 0 | T51: c | V51: =I51^2-I50^2 -> 5.854618e-06
F53: =1-((G54-G53)/(G55-G53)) -> 0.33424658 | G53: 1 | H53: {=_xlfn.XLOOKUP(Task1!$B$1,'Benchmark yields table'!$A$3:$A$599,_xlfn.XLOOKUP(G53,'Benchmark yields table'!$B$2:$I$2,'Benchmark yields table'!$B$3:$I$599))/100} -> 0.0688 | I53: {=_xlfn.XLOOKUP(Task1!$B$1,'Benchmark yields table'!$A$3:$A$599,_xlfn.XLOOKUP(G53,'Benchmark yields table'!$BF$2:$BM$2,'Benchmark yields table'!$BF$3:$BM$599))} -> 0.0012060047 | J53: =1/(1+H53)^G53 -> 0.93562874 | L53: =K54*M54 -> 82.320532 | M53: alfa | N53: PV= | P53: =K54*J54 -> 255.51595 | Q53: Korrel | R53: Vol | S53: =I54 -> 0.0022900019 | T53: a | V53: =I53^2+I55^2-2*Q54*I53*I55 -> 4.9402317e-06 | W53: =(-V54+SQRT(V54^2-4*V53*V55))/(2*V53) -> 2.0571994
G54: =C12 -> 2.3315068 | H54: =H53*F53+(1-F53)*H55 -> 0.071263288 | I54: =I53*F53+(1-F53)*I55 -> 0.0022900019 | J54: =1/(1+H54)^G54 -> 0.85171982 | K54: =Task1!F29 -> 300 | M54: =MIN(W53:W54) -> 0.27440177 | N54: PV'= | P54: =L53*J53+L55*J55 -> 253.47304 | Q54: {=_xlfn.XLOOKUP(G53,$T$7:$T$12,_xlfn.XLOOKUP(G55,$U$6:$Z$6,$U$7:$Z$12))} -> 0.66514828 | R54: Vol' | S54: =SQRT((M54*I53)^2+((1-M54)*I55)^2+2*M54*(1-M54)*Q54*I53*I55) -> 0.0022900019 | T54: b | V54: =2*Q54*I53*I55-2*I55^2 -> -1.151865e-05 | W54: =(-V54-SQRT(V54^2-4*V53*V55))/(2*V53) -> 0.27440177
G55: 3 | H55: {=_xlfn.XLOOKUP(Task1!$B$1,'Benchmark yields table'!$A$3:$A$599,_xlfn.XLOOKUP(G55,'Benchmark yields table'!$B$2:$I$2,'Benchmark yields table'!$B$3:$I$599))/100} -> 0.0725 | I55: {=_xlfn.XLOOKUP(Task1!$B$1,'Benchmark yields table'!$A$3:$A$599,_xlfn.XLOOKUP(G55,'Benchmark yields table'!$BF$2:$BM$2,'Benchmark yields table'!$BF$3:$BM$599))} -> 0.002834231 | J55: =1/(1+H55)^G55 -> 0.8106028 | L55: =(1-M54)*K54 -> 217.67947 | N55: Pvdiff | P55: =ABS(P53-P54) -> 2.042905 | R55: Voldiff | S55: =ABS(S53-S54) -> 4.3368087e-19 | T55: c | V55: =I55^2-I54^2 -> 2.7887567e-06
F57: =1-((G58-G57)/(G59-G57)) -> 0.83424658 | G57: 3 | H57: {=_xlfn.XLOOKUP(Task1!$B$1,'Benchmark yields table'!$A$3:$A$599,_xlfn.XLOOKUP(G57,'Benchmark yields table'!$B$2:$I$2,'Benchmark yields table'!$B$3:$I$599))/100} -> 0.0725 | I57: {=_xlfn.XLOOKUP(Task1!$B$1,'Benchmark yields table'!$A$3:$A$599,_xlfn.XLOOKUP(G57,'Benchmark yields table'!$BF$2:$BM$2,'Benchmark yields table'!$BF$3:$BM$599))} -> 0.002834231 | J57: =1/(1+H57)^G57 -> 0.8106028 | L57: =K58*M58 -> 246.32853 | M57: alfa | N57: PV= | P57: =K58*J58 -> 237.65223 | Q57: Korrel | R57: Vol | S57: =I58 -> 0.0032016455 | T57: a | V57: =I57^2+I59^2-2*Q58*I57*I59 -> 6.189984e-06 | W57: =(-V58+SQRT(V58^2-4*V57*V59))/(2*V57) -> 3.0025569
G58: =C13 -> 3.3315068 | H58: =F57*H57+(1-F57)*H59 -> 0.072433699 | I58: =I57*F57+(1-F57)*I59 -> 0.0032016455 | J58: =1/(1+H58)^G58 -> 0.79217408 | K58: =Task1!F30 -> 300 | M58: =MIN(W57:W58) -> 0.8210951 | N58: PV'= | P58: =L57*J57+L59*J59 -> 237.56829 | Q58: {=_xlfn.XLOOKUP(G57,$T$7:$T$12,_xlfn.XLOOKUP(G59,$U$6:$Z$6,$U$7:$Z$12))} -> 0.95541409 | R58: Vol' | S58: =SQRT((M58*I57)^2+((1-M58)*I59)^2+2*M58*(1-M58)*Q58*I57*I59) -> 0.0032016455 | T58: b | V58: =2*Q58*I57*I59-2*I59^2 -> -2.3668345e-05 | W58: =(-V58-SQRT(V58^2-4*V57*V59))/(2*V57) -> 0.8210951
G59: 5 | H59: {=_xlfn.XLOOKUP(Task1!$B$1,'Benchmark yields table'!$A$3:$A$599,_xlfn.XLOOKUP(G59,'Benchmark yields table'!$B$2:$I$2,'Benchmark yields table'!$B$3:$I$599))/100} -> 0.0721 | I59: {=_xlfn.XLOOKUP(Task1!$B$1,'Benchmark yields table'!$A$3:$A$599,_xlfn.XLOOKUP(G59,'Benchmark yields table'!$BF$2:$BM$2,'Benchmark yields table'!$BF$3:$BM$599))} -> 0.0050508639 | J59: =1/(1+H59)^G59 -> 0.70603059 | L59: =(1-M58)*K58 -> 53.67147 | N59: Pvdiff | P59: =ABS(P57-P58) -> 0.083930397 | R59: Voldiff | S59: =ABS(S57-S58) -> 4.3368087e-19 | T59: c | V59: =I59^2-I58^2 -> 1.5260692e-05
F61: =1-((G62-G61)/(G63-G61)) -> 0.33424658 | G61: 3 | H61: {=_xlfn.XLOOKUP(Task1!$B$1,'Benchmark yields table'!$A$3:$A$599,_xlfn.XLOOKUP(G61,'Benchmark yields table'!$B$2:$I$2,'Benchmark yields table'!$B$3:$I$599))/100} -> 0.0725 | I61: {=_xlfn.XLOOKUP(Task1!$B$1,'Benchmark yields table'!$A$3:$A$599,_xlfn.XLOOKUP(G61,'Benchmark yields table'!$BF$2:$BM$2,'Benchmark yields table'!$BF$3:$BM$599))} -> 0.002834231 | J61: =1/(1+H61)^G61 -> 0.8106028 | L61: =K62*M62 -> 95.93056 | M61: alfa | N61: PV= | P61: =K62*J62 -> 221.77995 | Q61: Korrel | R61: Vol | S61: =I62 -> 0.004309962 | T61: a | V61: =I61^2+I63^2-2*Q62*I61*I63 -> 6.189984e-06 | W61: =(-V62+SQRT(V62^2-4*V61*V63))/(2*V61) -> 3.5038835
G62: =C14 -> 4.3315068 | H62: =F61*H61+(1-F61)*H63 -> 0.072233699 | I62: =I61*F61+(1-F61)*I63 -> 0.004309962 | J62: =1/(1+H62)^G62 -> 0.73926651 | K62: =Task1!F31 -> 300 | M62: =MIN(W61:W62) -> 0.31976853 | N62: PV'= | P62: =L61*J61+L63*J63 -> 221.84085 | Q62: {=_xlfn.XLOOKUP(G61,$T$7:$T$12,_xlfn.XLOOKUP(G63,$U$6:$Z$6,$U$7:$Z$12))} -> 0.95541409 | R62: Vol' | S62: =SQRT((M62*I61)^2+((1-M62)*I63)^2+2*M62*(1-M62)*Q62*I61*I63) -> 0.004309962 | T62: b | V62: =2*Q62*I61*I63-2*I63^2 -> -2.3668345e-05 | W62: =(-V62-SQRT(V62^2-4*V61*V63))/(2*V61) -> 0.31976853
G63: 5 | H63: {=_xlfn.XLOOKUP(Task1!$B$1,'Benchmark yields table'!$A$3:$A$599,_xlfn.XLOOKUP(G63,'Benchmark yields table'!$B$2:$I$2,'Benchmark yields table'!$B$3:$I$599))/100} -> 0.0721 | I63: {=_xlfn.XLOOKUP(Task1!$B$1,'Benchmark yields table'!$A$3:$A$599,_xlfn.XLOOKUP(G63,'Benchmark yields table'!$BF$2:$BM$2,'Benchmark yields table'!$BF$3:$BM$599))} -> 0.0050508639 | J63: =1/(1+H63)^G63 -> 0.70603059 | L63: =(1-M62)*K62 -> 204.06944 | N63: Pvdiff | P63: =ABS(P61-P62) -> 0.060896148 | R63: Voldiff | S63: =ABS(S61-S62) -> 0 | T63: c | V63: =I63^2-I62^2 -> 6.9354541e-06
F65: =1-((G66-G65)/(G67-G65)) -> 0.93369863 | G65: 5 | H65: {=_xlfn.XLOOKUP(Task1!$B$1,'Benchmark yields table'!$A$3:$A$599,_xlfn.XLOOKUP(G65,'Benchmark yields table'!$B$2:$I$2,'Benchmark yields table'!$B$3:$I$599))/100} -> 0.0721 | I65: {=_xlfn.XLOOKUP(Task1!$B$1,'Benchmark yields table'!$A$3:$A$599,_xlfn.XLOOKUP(G65,'Benchmark yields table'!$BF$2:$BM$2,'Benchmark yields table'!$BF$3:$BM$599))} -> 0.0050508639 | J65: =1/(1+H65)^G65 -> 0.70603059 | L65: =K66*M66 -> 278.78763 | M65: alfa | N65: PV= | P65: =K66*J66 -> 207.03818 | Q65: Korrel | R65: Vol | S65: =I66 -> 0.0053963644 | T65: a | V65: =I65^2+I67^2-2*Q66*I65*I67 -> 3.0934857e-05 | W65: =(-V66+SQRT(V66^2-4*V65*V67))/(2*V65) -> 2.6501888
G66: =C15 -> 5.3315068 | H66: =F65*H65+(1-F65)*H67 -> 0.072040329 | I66: =I65*F65+(1-F65)*I67 -> 0.0053963644 | J66: =1/(1+H66)^G66 -> 0.69012727 | K66: =Task1!F32 -> 300 | M66: =MIN(W65:W66) -> 0.92929209 | N66: PV'= | P66: =L65*J65+L67*J67 -> 207.4957 | Q66: {=_xlfn.XLOOKUP(G65,$T$7:$T$12,_xlfn.XLOOKUP(G67,$U$6:$Z$6,$U$7:$Z$12))} -> 0.96353862 | R66: Vol' | S66: =SQRT((M66*I65)^2+((1-M66)*I67)^2+2*M66*(1-M66)*Q66*I65*I67) -> 0.0053963644 | T66: b | V66: =2*Q66*I65*I67-2*I67^2 -> -0.00011073073 | W66: =(-V66-SQRT(V66^2-4*V65*V67))/(2*V65) -> 0.92929209
G67: 10 | H67: {=_xlfn.XLOOKUP(Task1!$B$1,'Benchmark yields table'!$A$3:$A$599,_xlfn.XLOOKUP(G67,'Benchmark yields table'!$B$2:$I$2,'Benchmark yields table'!$B$3:$I$599))/100} -> 0.0712 | I67: {=_xlfn.XLOOKUP(Task1!$B$1,'Benchmark yields table'!$A$3:$A$599,_xlfn.XLOOKUP(G67,'Benchmark yields table'!$BF$2:$BM$2,'Benchmark yields table'!$BF$3:$BM$599))} -> 0.010261925 | J67: =1/(1+H67)^G67 -> 0.50268319 | L67: =(1-M66)*K66 -> 21.212372 | N67: Pvdiff | P67: =ABS(P65-P66) -> 0.45751575 | R67: Voldiff | S67: =ABS(S65-S66) -> 2.6020852e-18 | T67: c | V67: =I67^2-I66^2 -> 7.6186351e-05
F69: =1-((G70-G69)/(G71-G69)) -> 0.73315068 | G69: 5 | H69: {=_xlfn.XLOOKUP(Task1!$B$1,'Benchmark yields table'!$A$3:$A$599,_xlfn.XLOOKUP(G69,'Benchmark yields table'!$B$2:$I$2,'Benchmark yields table'!$B$3:$I$599))/100} -> 0.0721 | I69: {=_xlfn.XLOOKUP(Task1!$B$1,'Benchmark yields table'!$A$3:$A$599,_xlfn.XLOOKUP(G69,'Benchmark yields table'!$BF$2:$BM$2,'Benchmark yields table'!$BF$3:$BM$599))} -> 0.0050508639 | J69: =1/(1+H69)^G69 -> 0.70603059 | L69: =K70*M70 -> 7435.5574 | M69: alfa | N69: PV= | P69: =K70*J70 -> 6636.4483 | Q69: Korrel | R69: Vol | S69: =I70 -> 0.0064414319 | T69: a | V69: =I69^2+I71^2-2*Q70*I69*I71 -> 3.0934857e-05 | W69: =(-V70+SQRT(V70^2-4*V69*V71))/(2*V69) -> 2.8575821
G70: =C16 -> 6.3342466 | H70: =F69*H69+(1-F69)*H71 -> 0.071859836 | I70: =I69*F69+(1-F69)*I71 -> 0.0064414319 | J70: =1/(1+H70)^G70 -> 0.64431537 | K70: =Task1!F33 -> 10300 | M70: =MIN(W69:W70) -> 0.72189878 | N70: PV'= | P70: =L69*J69+L71*J71 -> 6689.6381 | Q70: {=_xlfn.XLOOKUP(G69,$T$7:$T$12,_xlfn.XLOOKUP(G71,$U$6:$Z$6,$U$7:$Z$12))} -> 0.96353862 | R70: Vol' | S70: =SQRT((M70*I69)^2+((1-M70)*I71)^2+2*M70*(1-M70)*Q70*I69*I71) -> 0.0064414319 | T70: b | V70: =2*Q70*I69*I71-2*I71^2 -> -0.00011073073 | W70: =(-V70-SQRT(V70^2-4*V69*V71))/(2*V69) -> 0.72189878
G71: 10 | H71: {=_xlfn.XLOOKUP(Task1!$B$1,'Benchmark yields table'!$A$3:$A$599,_xlfn.XLOOKUP(G71,'Benchmark yields table'!$B$2:$I$2,'Benchmark yields table'!$B$3:$I$599))/100} -> 0.0712 | I71: {=_xlfn.XLOOKUP(Task1!$B$1,'Benchmark yields table'!$A$3:$A$599,_xlfn.XLOOKUP(G71,'Benchmark yields table'!$BF$2:$BM$2,'Benchmark yields table'!$BF$3:$BM$599))} -> 0.010261925 | J71: =1/(1+H71)^G71 -> 0.50268319 | L71: =(1-M70)*K70 -> 2864.4426 | N71: Pvdiff | P71: =ABS(P69-P70) -> 53.189811 | R71: Voldiff | S71: =ABS(S69-S70) -> 1.7347235e-18 | T71: c | V71: =I71^2-I70^2 -> 6.3815054e-05
F73: =Task1!F4 -> 2032/A | M73: =Task1!F13 -> 3548
F74: =1-((G75-G74)/(G76-G74)) -> 0.81643836 | G74: 0.5 | H74: {=_xlfn.XLOOKUP(Task1!$B$1,'Benchmark yields table'!$A$3:$A$599,_xlfn.XLOOKUP(Task2!G74,'Benchmark yields table'!$B$2:$I$2,'Benchmark yields table'!$B$3:$I$599))/100} -> 0.0692 | I74: {=_xlfn.XLOOKUP(Task1!$B$1,'Benchmark yields table'!$A$3:$A$599,_xlfn.XLOOKUP(Task2!G74,'Benchmark yields table'!$BF$2:$BM$2,'Benchmark yields table'!$BF$3:$BM$599))} -> 0.00065051439 | J74: =1/(1+H74)^G74 -> 0.96709809 | L74: =K75*M75 -> 340.88917 | M74: alfa | N74: PV= | P74: =K75*J75 -> 456.57774 | Q74: Korrel | R74: Vol | S74: =I75 -> 0.0007524811 | T74: a | V74: =I74^2+I76^2-2*Q75*I74*I76 -> 7.3096559e-07 | W74: =(-V75+SQRT(V75^2-4*V74*V76))/(2*V74) -> 1.6931824
G75: =C17 -> 0.59178082 | H75: =F74*H74+(1-F74)*H76 -> 0.069126575 | I75: =F74*I74+(1-F74)*I76 -> 0.0007524811 | J75: =1/(1+H75)^G75 -> 0.96121629 | K75: =Task1!F36 -> 475 | M75: =MIN(W74:W75) -> 0.71766142 | N75: PV'= | P75: =L74*J74+L76*J76 -> 455.15121 | Q75: {=_xlfn.XLOOKUP(G74,$T$7:$T$12,_xlfn.XLOOKUP(G76,$U$6:$Z$6,$U$7:$Z$12))} -> 0.73079441 | R75: Vol' | S75: =SQRT((M75*I74)^2+((1-M75)*I76)^2+2*M75*(1-M75)*Q75*I74*I76) -> 0.0007524811 | T75: b | V75: =2*Q75*I74*I76-2*I76^2 -> -1.7622438e-06 | W75: =(-V75-SQRT(V75^2-4*V74*V76))/(2*V74) -> 0.71766142
G76: 1 | H76: {=_xlfn.XLOOKUP(Task1!$B$1,'Benchmark yields table'!$A$3:$A$599,_xlfn.XLOOKUP(Task2!G76,'Benchmark yields table'!$B$2:$I$2,'Benchmark yields table'!$B$3:$I$599))/100} -> 0.0688 | I76: {=_xlfn.XLOOKUP(Task1!$B$1,'Benchmark yields table'!$A$3:$A$599,_xlfn.XLOOKUP(Task2!G76,'Benchmark yields table'!$BF$2:$BM$2,'Benchmark yields table'!$BF$3:$BM$599))} -> 0.0012060047 | J76: =1/(1+H76)^G76 -> 0.93562874 | L76: =(1-M75)*K75 -> 134.11083 | N76: Pvdiff | P76: =ABS(P74-P75) -> 1.4265238 | R76: Voldiff | S76: =ABS(S74-S75) -> 0 | T76: c | V76: =I76^2-I75^2 -> 8.8821942e-07
F78: =1-((G79-G78)/(G80-G78)) -> 0.70410959 | G78: 1 | H78: {=_xlfn.XLOOKUP(Task1!$B$1,'Benchmark yields table'!$A$3:$A$599,_xlfn.XLOOKUP(G78,'Benchmark yields table'!$B$2:$I$2,'Benchmark yields table'!$B$3:$I$599))/100} -> 0.0688 | I78: {=_xlfn.XLOOKUP(Task1!$B$1,'Benchmark yields table'!$A$3:$A$599,_xlfn.XLOOKUP(G78,'Benchmark yields table'!$BF$2:$BM$2,'Benchmark yields table'!$BF$3:$BM$599))} -> 0.0012060047 | J78: =1/(1+H78)^G78 -> 0.93562874 | L78: =K79*M79 -> 289.41666 | M78: alfa | N78: PV= | P78: =K79*J79 -> 426.56876 | Q78: Korrel | R78: Vol | S78: =I79 -> 0.0016877812 | T78: a | V78: =I78^2+I80^2-2*Q79*I78*I80 -> 4.9402317e-06 | W78: =(-V79+SQRT(V79^2-4*V78*V80))/(2*V78) -> 1.7223029
G79: =C18 -> 1.5917808 | H79: =H78*F78+(1-F78)*H80 -> 0.069894795 | I79: =I78*F78+(1-F78)*I80 -> 0.0016877812 | J79: =1/(1+H79)^G79 -> 0.8980395 | K79: =Task1!F37 -> 475 | M79: =MIN(W78:W79) -> 0.60929824 | N79: PV'= | P79: =L78*J78+L80*J80 -> 421.22092 | Q79: {=_xlfn.XLOOKUP(G78,$T$7:$T$12,_xlfn.XLOOKUP(G80,$U$6:$Z$6,$U$7:$Z$12))} -> 0.66514828 | R79: Vol' | S79: =SQRT((M79*I78)^2+((1-M79)*I80)^2+2*M79*(1-M79)*Q79*I78*I80) -> 0.0016877812 | T79: b | V79: =2*Q79*I78*I80-2*I80^2 -> -1.151865e-05 | W79: =(-V79-SQRT(V79^2-4*V78*V80))/(2*V78) -> 0.60929824
G80: 3 | H80: {=_xlfn.XLOOKUP(Task1!$B$1,'Benchmark yields table'!$A$3:$A$599,_xlfn.XLOOKUP(G80,'Benchmark yields table'!$B$2:$I$2,'Benchmark yields table'!$B$3:$I$599))/100} -> 0.0725 | I80: {=_xlfn.XLOOKUP(Task1!$B$1,'Benchmark yields table'!$A$3:$A$599,_xlfn.XLOOKUP(G80,'Benchmark yields table'!$BF$2:$BM$2,'Benchmark yields table'!$BF$3:$BM$599))} -> 0.002834231 | J80: =1/(1+H80)^G80 -> 0.8106028 | L80: =(1-M79)*K79 -> 185.58334 | N80: Pvdiff | P80: =ABS(P78-P79) -> 5.3478432 | R80: Voldiff | S80: =ABS(S78-S79) -> 2.1684043e-19 | T80: c | V80: =I80^2-I79^2 -> 5.1842601e-06
F82: =1-((G83-G82)/(G84-G82)) -> 0.20410959 | G82: 1 | H82: {=_xlfn.XLOOKUP(Task1!$B$1,'Benchmark yields table'!$A$3:$A$599,_xlfn.XLOOKUP(G82,'Benchmark yields table'!$B$2:$I$2,'Benchmark yields table'!$B$3:$I$599))/100} -> 0.0688 | I82: {=_xlfn.XLOOKUP(Task1!$B$1,'Benchmark yields table'!$A$3:$A$599,_xlfn.XLOOKUP(G82,'Benchmark yields table'!$BF$2:$BM$2,'Benchmark yields table'!$BF$3:$BM$599))} -> 0.0012060047 | J82: =1/(1+H82)^G82 -> 0.93562874 | L82: =K83*M83 -> 78.726295 | M82: alfa | N82: PV= | P82: =K83*J83 -> 396.92033 | Q82: Korrel | R82: Vol | S82: =I83 -> 0.0025018944 | T82: a | V82: =I82^2+I84^2-2*Q83*I82*I84 -> 4.9402317e-06 | W82: =(-V83+SQRT(V83^2-4*V82*V84))/(2*V82) -> 2.1658616
G83: =C19 -> 2.5917808 | H83: =H82*F82+(1-F82)*H84 -> 0.071744795 | I83: =I82*F82+(1-F82)*I84 -> 0.0025018944 | J83: =1/(1+H83)^G83 -> 0.83562174 | K83: =Task1!F38 -> 475 | M83: =MIN(W82:W83) -> 0.16573957 | N83: PV'= | P83: =L82*J82+L84*J84 -> 394.87916 | Q83: {=_xlfn.XLOOKUP(G82,$T$7:$T$12,_xlfn.XLOOKUP(G84,$U$6:$Z$6,$U$7:$Z$12))} -> 0.66514828 | R83: Vol' | S83: =SQRT((M83*I82)^2+((1-M83)*I84)^2+2*M83*(1-M83)*Q83*I82*I84) -> 0.0025018944 | T83: b | V83: =2*Q83*I82*I84-2*I84^2 -> -1.151865e-05 | W83: =(-V83-SQRT(V83^2-4*V82*V84))/(2*V82) -> 0.16573957
G84: 3 | H84: {=_xlfn.XLOOKUP(Task1!$B$1,'Benchmark yields table'!$A$3:$A$599,_xlfn.XLOOKUP(G84,'Benchmark yields table'!$B$2:$I$2,'Benchmark yields table'!$B$3:$I$599))/100} -> 0.0725 | I84: {=_xlfn.XLOOKUP(Task1!$B$1,'Benchmark yields table'!$A$3:$A$599,_xlfn.XLOOKUP(G84,'Benchmark yields table'!$BF$2:$BM$2,'Benchmark yields table'!$BF$3:$BM$599))} -> 0.002834231 | J84: =1/(1+H84)^G84 -> 0.8106028 | L84: =(1-M83)*K83 -> 396.2737 | N84: Pvdiff | P84: =ABS(P82-P83) -> 2.0411695 | R84: Voldiff | S84: =ABS(S82-S83) -> 0 | T84: c | V84: =I84^2-I83^2 -> 1.7733899e-06
F86: =1-((G87-G86)/(G88-G86)) -> 0.70410959 | G86: 3 | H86: {=_xlfn.XLOOKUP(Task1!$B$1,'Benchmark yields table'!$A$3:$A$599,_xlfn.XLOOKUP(G86,'Benchmark yields table'!$B$2:$I$2,'Benchmark yields table'!$B$3:$I$599))/100} -> 0.0725 | I86: {=_xlfn.XLOOKUP(Task1!$B$1,'Benchmark yields table'!$A$3:$A$599,_xlfn.XLOOKUP(G86,'Benchmark yields table'!$BF$2:$BM$2,'Benchmark yields table'!$BF$3:$BM$599))} -> 0.002834231 | J86: =1/(1+H86)^G86 -> 0.8106028 | L86: =K87*M87 -> 326.06431 | M86: alfa | N86: PV= | P86: =K87*J87 -> 369.56031 | Q86: Korrel | R86: Vol | S86: =I87 -> 0.0034901115 | T86: a | V86: =I86^2+I88^2-2*Q87*I86*I88 -> 6.189984e-06 | W86: =(-V87+SQRT(V87^2-4*V86*V88))/(2*V86) -> 3.1372008
G87: =C20 -> 3.5917808 | H87: =F86*H86+(1-F86)*H88 -> 0.072381644 | I87: =I86*F86+(1-F86)*I88 -> 0.0034901115 | J87: =1/(1+H87)^G87 -> 0.7780217 | K87: =Task1!F39 -> 475 | M87: =MIN(W86:W87) -> 0.68645117 | N87: PV'= | P87: =L86*J86+L88*J88 -> 369.46179 | Q87: {=_xlfn.XLOOKUP(G86,$T$7:$T$12,_xlfn.XLOOKUP(G88,$U$6:$Z$6,$U$7:$Z$12))} -> 0.95541409 | R87: Vol' | S87: =SQRT((M87*I86)^2+((1-M87)*I88)^2+2*M87*(1-M87)*Q87*I86*I88) -> 0.0034901115 | T87: b | V87: =2*Q87*I86*I88-2*I88^2 -> -2.3668345e-05 | W87: =(-V87-SQRT(V87^2-4*V86*V88))/(2*V86) -> 0.68645117
G88: 5 | H88: {=_xlfn.XLOOKUP(Task1!$B$1,'Benchmark yields table'!$A$3:$A$599,_xlfn.XLOOKUP(G88,'Benchmark yields table'!$B$2:$I$2,'Benchmark yields table'!$B$3:$I$599))/100} -> 0.0721 | I88: {=_xlfn.XLOOKUP(Task1!$B$1,'Benchmark yields table'!$A$3:$A$599,_xlfn.XLOOKUP(G88,'Benchmark yields table'!$BF$2:$BM$2,'Benchmark yields table'!$BF$3:$BM$599))} -> 0.0050508639 | J88: =1/(1+H88)^G88 -> 0.70603059 | L88: =(1-M87)*K87 -> 148.93569 | N88: Pvdiff | P88: =ABS(P86-P87) -> 0.09851242 | R88: Voldiff | S88: =ABS(S86-S87) -> 4.3368087e-19 | T88: c | V88: =I88^2-I87^2 -> 1.3330348e-05
F90: =1-((G91-G90)/(G92-G90)) -> 0.20410959 | G90: 3 | H90: {=_xlfn.XLOOKUP(Task1!$B$1,'Benchmark yields table'!$A$3:$A$599,_xlfn.XLOOKUP(G90,'Benchmark yields table'!$B$2:$I$2,'Benchmark yields table'!$B$3:$I$599))/100} -> 0.0725 | I90: {=_xlfn.XLOOKUP(Task1!$B$1,'Benchmark yields table'!$A$3:$A$599,_xlfn.XLOOKUP(G90,'Benchmark yields table'!$BF$2:$BM$2,'Benchmark yields table'!$BF$3:$BM$599))} -> 0.002834231 | J90: =1/(1+H90)^G90 -> 0.8106028 | L90: =K91*M91 -> 92.306243 | M90: alfa | N90: PV= | P90: =K91*J91 -> 344.91168 | Q90: Korrel | R90: Vol | S90: =I91 -> 0.0045984279 | T90: a | V90: =I90^2+I92^2-2*Q91*I90*I92 -> 6.189984e-06 | W90: =(-V91+SQRT(V91^2-4*V90*V92))/(2*V90) -> 3.6293231
G91: =C21 -> 4.5917808 | H91: =F90*H90+(1-F90)*H92 -> 0.072181644 | I91: =I90*F90+(1-F90)*I92 -> 0.0045984279 | J91: =1/(1+H91)^G91 -> 0.72612985 | K91: =Task1!F40 -> 475 | M91: =MIN(W90:W91) -> 0.19432893 | N91: PV'= | P91: =L90*J90+L92*J92 -> 345.0172 | Q91: {=_xlfn.XLOOKUP(G90,$T$7:$T$12,_xlfn.XLOOKUP(G92,$U$6:$Z$6,$U$7:$Z$12))} -> 0.95541409 | R91: Vol' | S91: =SQRT((M91*I90)^2+((1-M91)*I92)^2+2*M91*(1-M91)*Q91*I90*I92) -> 0.0045984279 | T91: b | V91: =2*Q91*I90*I92-2*I92^2 -> -2.3668345e-05 | W91: =(-V91-SQRT(V91^2-4*V90*V92))/(2*V90) -> 0.19432893
G92: 5 | H92: {=_xlfn.XLOOKUP(Task1!$B$1,'Benchmark yields table'!$A$3:$A$599,_xlfn.XLOOKUP(G92,'Benchmark yields table'!$B$2:$I$2,'Benchmark yields table'!$B$3:$I$599))/100} -> 0.0721 | I92: {=_xlfn.XLOOKUP(Task1!$B$1,'Benchmark yields table'!$A$3:$A$599,_xlfn.XLOOKUP(G92,'Benchmark yields table'!$BF$2:$BM$2,'Benchmark yields table'!$BF$3:$BM$599))} -> 0.0050508639 | J92: =1/(1+H92)^G92 -> 0.70603059 | L92: =(1-M91)*K91 -> 382.69376 | N92: Pvdiff | P92: =ABS(P90-P91) -> 0.10552042 | R92: Voldiff | S92: =ABS(S90-S91) -> 0 | T92: c | V92: =I92^2-I91^2 -> 4.3656872e-06
F94: =1-((G95-G94)/(G96-G94)) -> 0.88164384 | G94: 5 | H94: {=_xlfn.XLOOKUP(Task1!$B$1,'Benchmark yields table'!$A$3:$A$599,_xlfn.XLOOKUP(G94,'Benchmark yields table'!$B$2:$I$2,'Benchmark yields table'!$B$3:$I$599))/100} -> 0.0721 | I94: {=_xlfn.XLOOKUP(Task1!$B$1,'Benchmark yields table'!$A$3:$A$599,_xlfn.XLOOKUP(G94,'Benchmark yields table'!$BF$2:$BM$2,'Benchmark yields table'!$BF$3:$BM$599))} -> 0.0050508639 | J94: =1/(1+H94)^G94 -> 0.70603059 | L94: =K95*M95 -> 415.45915 | M94: alfa | N94: PV= | P94: =K95*J95 -> 322.00733 | Q94: Korrel | R94: Vol | S94: =I95 -> 0.0056676251 | T94: a | V94: =I94^2+I96^2-2*Q95*I94*I96 -> 3.0934857e-05 | W94: =(-V95+SQRT(V95^2-4*V94*V96))/(2*V94) -> 2.70483
G95: =C22 -> 5.5917808 | H95: =F94*H94+(1-F94)*H96 -> 0.071993479 | I95: =I94*F94+(1-F94)*I96 -> 0.0056676251 | J95: =1/(1+H95)^G95 -> 0.67791017 | K95: =Task1!F41 -> 475 | M95: =MIN(W94:W95) -> 0.87465085 | N95: PV'= | P95: =L94*J94+L96*J96 -> 323.25706 | Q95: {=_xlfn.XLOOKUP(G94,$T$7:$T$12,_xlfn.XLOOKUP(G96,$U$6:$Z$6,$U$7:$Z$12))} -> 0.96353862 | R95: Vol' | S95: =SQRT((M95*I94)^2+((1-M95)*I96)^2+2*M95*(1-M95)*Q95*I94*I96) -> 0.0056676251 | T95: b | V95: =2*Q95*I94*I96-2*I96^2 -> -0.00011073073 | W95: =(-V95-SQRT(V95^2-4*V94*V96))/(2*V94) -> 0.87465085
G96: 10 | H96: {=_xlfn.XLOOKUP(Task1!$B$1,'Benchmark yields table'!$A$3:$A$599,_xlfn.XLOOKUP(G96,'Benchmark yields table'!$B$2:$I$2,'Benchmark yields table'!$B$3:$I$599))/100} -> 0.0712 | I96: {=_xlfn.XLOOKUP(Task1!$B$1,'Benchmark yields table'!$A$3:$A$599,_xlfn.XLOOKUP(G96,'Benchmark yields table'!$BF$2:$BM$2,'Benchmark yields table'!$BF$3:$BM$599))} -> 0.010261925 | J96: =1/(1+H96)^G96 -> 0.50268319 | L96: =(1-M95)*K95 -> 59.540845 | N96: Pvdiff | P96: =ABS(P94-P95) -> 1.2497241 | R96: Voldiff | S96: =ABS(S94-S95) -> 8.6736174e-19 | T96: c | V96: =I96^2-I95^2 -> 7.3185125e-05
F98: =1-((G99-G98)/(G100-G98)) -> 0.68164384 | G98: 5 | H98: {=_xlfn.XLOOKUP(Task1!$B$1,'Benchmark yields table'!$A$3:$A$599,_xlfn.XLOOKUP(G98,'Benchmark yields table'!$B$2:$I$2,'Benchmark yields table'!$B$3:$I$599))/100} -> 0.0721 | I98: {=_xlfn.XLOOKUP(Task1!$B$1,'Benchmark yields table'!$A$3:$A$599,_xlfn.XLOOKUP(G98,'Benchmark yields table'!$BF$2:$BM$2,'Benchmark yields table'!$BF$3:$BM$599))} -> 0.0050508639 | J98: =1/(1+H98)^G98 -> 0.70603059 | L98: =K99*M99 -> 318.12832 | M98: alfa | N98: PV= | P98: =K99*J99 -> 300.71449 | Q98: Korrel | R98: Vol | S98: =I99 -> 0.0067098373 | T98: a | V98: =I98^2+I100^2-2*Q99*I98*I100 -> 3.0934857e-05 | W98: =(-V99+SQRT(V99^2-4*V98*V100))/(2*V98) -> 2.909737
G99: =C23 -> 6.5917808 | H99: =F98*H98+(1-F98)*H100 -> 0.071813479 | I99: =I98*F98+(1-F98)*I100 -> 0.0067098373 | J99: =1/(1+H99)^G99 -> 0.63308313 | K99: =Task1!F42 -> 475 | M99: =MIN(W98:W99) -> 0.66974384 | N99: PV'= | P99: =L98*J98+L100*J100 -> 303.46508 | Q99: {=_xlfn.XLOOKUP(G98,$T$7:$T$12,_xlfn.XLOOKUP(G100,$U$6:$Z$6,$U$7:$Z$12))} -> 0.96353862 | R99: Vol' | S99: =SQRT((M99*I98)^2+((1-M99)*I100)^2+2*M99*(1-M99)*Q99*I98*I100) -> 0.0067098373 | T99: b | V99: =2*Q99*I98*I100-2*I100^2 -> -0.00011073073 | W99: =(-V99-SQRT(V99^2-4*V98*V100))/(2*V98) -> 0.66974384
G100: 10 | H100: {=_xlfn.XLOOKUP(Task1!$B$1,'Benchmark yields table'!$A$3:$A$599,_xlfn.XLOOKUP(G100,'Benchmark yields table'!$B$2:$I$2,'Benchmark yields table'!$B$3:$I$599))/100} -> 0.0712 | I100: {=_xlfn.XLOOKUP(Task1!$B$1,'Benchmark yields table'!$A$3:$A$599,_xlfn.XLOOKUP(G100,'Benchmark yields table'!$BF$2:$BM$2,'Benchmark yields table'!$BF$3:$BM$599))} -> 0.010261925 | J100: =1/(1+H100)^G100 -> 0.50268319 | L100: =(1-M99)*K99 -> 156.87168 | N100: Pvdiff | P100: =ABS(P98-P99) -> 2.7505975 | R100: Voldiff | S100: =ABS(S98-S99) -> 0 | T100: c | V100: =I100^2-I99^2 -> 6.0285184e-05
F102: =1-((G103-G102)/(G104-G102)) -> 0.48164384 | G102: 5 | H102: {=_xlfn.XLOOKUP(Task1!$B$1,'Benchmark yields table'!$A$3:$A$599,_xlfn.XLOOKUP(G102,'Benchmark yields table'!$B$2:$I$2,'Benchmark yields table'!$B$3:$I$599))/100} -> 0.0721 | I102: {=_xlfn.XLOOKUP(Task1!$B$1,'Benchmark yields table'!$A$3:$A$599,_xlfn.XLOOKUP(G102,'Benchmark yields table'!$BF$2:$BM$2,'Benchmark yields table'!$BF$3:$BM$599))} -> 0.0050508639 | J102: =1/(1+H102)^G102 -> 0.70603059 | L102: =K103*M103 -> 223.26685 | M102: alfa | N102: PV= | P102: =K103*J103 -> 280.92403 | Q102: Korrel | R102: Vol | S102: =I103 -> 0.0077520494 | T102: a | V102: =I102^2+I104^2-2*Q103*I102*I104 -> 3.0934857e-05 | W102: =(-V103+SQRT(V103^2-4*V102*V104))/(2*V102) -> 3.1094454
G103: =C24 -> 7.5917808 | H103: =F102*H102+(1-F102)*H104 -> 0.071633479 | I103: =I102*F102+(1-F102)*I104 -> 0.0077520494 | J103: =1/(1+H103)^G103 -> 0.59141901 | K103: =Task1!F43 -> 475 | M103: =MIN(W102:W103) -> 0.47003547 | N103: PV'= | P103: =L102*J102+L104*J104 -> 284.17525 | Q103: {=_xlfn.XLOOKUP(G102,$T$7:$T$12,_xlfn.XLOOKUP(G104,$U$6:$Z$6,$U$7:$Z$12))} -> 0.96353862 | R103: Vol' | S103: =SQRT((M103*I102)^2+((1-M103)*I104)^2+2*M103*(1-M103)*Q103*I102*I104) -> 0.0077520494 | T103: b | V103: =2*Q103*I102*I104-2*I104^2 -> -0.00011073073 | W103: =(-V103-SQRT(V103^2-4*V102*V104))/(2*V102) -> 0.47003547
G104: 10 | H104: {=_xlfn.XLOOKUP(Task1!$B$1,'Benchmark yields table'!$A$3:$A$599,_xlfn.XLOOKUP(G104,'Benchmark yields table'!$B$2:$I$2,'Benchmark yields table'!$B$3:$I$599))/100} -> 0.0712 | I104: {=_xlfn.XLOOKUP(Task1!$B$1,'Benchmark yields table'!$A$3:$A$599,_xlfn.XLOOKUP(G104,'Benchmark yields table'!$BF$2:$BM$2,'Benchmark yields table'!$BF$3:$BM$599))} -> 0.010261925 | J104: =1/(1+H104)^G104 -> 0.50268319 | L104: =(1-M103)*K103 -> 251.73315 | N104: Pvdiff | P104: =ABS(P102-P103) -> 3.2512185 | R104: Voldiff | S104: =ABS(S102-S103) -> 1.7347235e-18 | T104: c | V104: =I104^2-I103^2 -> 4.5212829e-05
F106: =1-((G107-G106)/(G108-G106)) -> 0.28054795 | G106: 5 | H106: {=_xlfn.XLOOKUP(Task1!$B$1,'Benchmark yields table'!$A$3:$A$599,_xlfn.XLOOKUP(G106,'Benchmark yields table'!$B$2:$I$2,'Benchmark yields table'!$B$3:$I$599))/100} -> 0.0721 | I106: {=_xlfn.XLOOKUP(Task1!$B$1,'Benchmark yields table'!$A$3:$A$599,_xlfn.XLOOKUP(G106,'Benchmark yields table'!$BF$2:$BM$2,'Benchmark yields table'!$BF$3:$BM$599))} -> 0.0050508639 | J106: =1/(1+H106)^G106 -> 0.70603059 | L106: =K107*M107 -> 2853.3851 | M106: alfa | N106: PV= | P106: =K107*J107 -> 5787.2073 | Q106: Korrel | R106: Vol | S106: =I107 -> 0.0087999723 | T106: a | V106: =I106^2+I108^2-2*Q107*I106*I108 -> 3.0934857e-05 | W106: =(-V107+SQRT(V107^2-4*V106*V108))/(2*V106) -> 3.3070813
G107: =C25 -> 8.5972603 | H107: =F106*H106+(1-F106)*H108 -> 0.071452493 | I107: =I106*F106+(1-F106)*I108 -> 0.0087999723 | J107: =1/(1+H107)^G107 -> 0.55247802 | K107: =Task1!F44 -> 10475 | M107: =MIN(W106:W107) -> 0.27239953 | N107: PV'= | P107: =L106*J106+L108*J108 -> 5845.8348 | Q107: {=_xlfn.XLOOKUP(G106,$T$7:$T$12,_xlfn.XLOOKUP(G108,$U$6:$Z$6,$U$7:$Z$12))} -> 0.96353862 | R107: Vol' | S107: =SQRT((M107*I106)^2+((1-M107)*I108)^2+2*M107*(1-M107)*Q107*I106*I108) -> 0.0087999723 | T107: b | V107: =2*Q107*I106*I108-2*I108^2 -> -0.00011073073 | W107: =(-V107-SQRT(V107^2-4*V106*V108))/(2*V106) -> 0.27239953
G108: 10 | H108: {=_xlfn.XLOOKUP(Task1!$B$1,'Benchmark yields table'!$A$3:$A$599,_xlfn.XLOOKUP(G108,'Benchmark yields table'!$B$2:$I$2,'Benchmark yields table'!$B$3:$I$599))/100} -> 0.0712 | I108: {=_xlfn.XLOOKUP(Task1!$B$1,'Benchmark yields table'!$A$3:$A$599,_xlfn.XLOOKUP(G108,'Benchmark yields table'!$BF$2:$BM$2,'Benchmark yields table'!$BF$3:$BM$599))} -> 0.010261925 | J108: =1/(1+H108)^G108 -> 0.50268319 | L108: =(1-M107)*K107 -> 7621.6149 | N108: Pvdiff | P108: =ABS(P106-P107) -> 58.627543 | R108: Voldiff | S108: =ABS(S106-S107) -> 1.7347235e-18 | T108: c | V108: =I108^2-I107^2 -> 2.7867586e-05

Sheet Task3
C4: date | D4: 44851
E5: t | F5: CF | G5: r | H5: PV | I5: w | J5: D
C6: 2028/A | D6: 45587 | E6: 183 | F6: 675 | G6: =_xlfn.XLOOKUP(E6,'zero-coupon-yields_202405172251'!$B$2:$B$1490,'zero-coupon-yields_202405172251'!$D$2:$D$1490,,1,1)/100 -> 0.136458 | H6: =F6/(1+G6)^(E6/365) -> 633.0689 | I6: =H6/$H$11 -> 0.077169335 | J6: =I6*E6/365 -> 0.038690379
D7: 45952 | E7: 548 | F7: 675 | G7: =_xlfn.XLOOKUP(E7,'zero-coupon-yields_202405172251'!$B$2:$B$1490,'zero-coupon-yields_202405172251'!$D$2:$D$1490,,1,1)/100 -> 0.1418 | H7: =F7/(1+G7)^(E7/365) -> 553.14606 | I7: =H7/$H$11 -> 0.067426964 | J7: =I7*E7/365 -> 0.10123281
D8: 46317 | E8: 913 | F8: 675 | G8: =_xlfn.XLOOKUP(E8,'zero-coupon-yields_202405172251'!$B$2:$B$1490,'zero-coupon-yields_202405172251'!$D$2:$D$1490,,1,1)/100 -> 0.143124 | H8: =F8/(1+G8)^(E8/365) -> 483.04861 | I8: =H8/$H$11 -> 0.058882279 | J8: =I8*E8/365 -> 0.14728636
D9: 46682 | E9: 1278 | F9: 675 | G9: =_xlfn.XLOOKUP(E9,'zero-coupon-yields_202405172251'!$B$2:$B$1490,'zero-coupon-yields_202405172251'!$D$2:$D$1490,,1,1)/100 -> 0.139158 | H9: =F9/(1+G9)^(E9/365) -> 427.74248 | I9: =H9/$H$11 -> 0.052140617 | J9: =I9*E9/365 -> 0.18256358
D10: 47048 | E10: 1644 | F10: 10675 | G10: =_xlfn.XLOOKUP(E10,'zero-coupon-yields_202405172251'!$B$2:$B$1490,'zero-coupon-yields_202405172251'!$D$2:$D$1490,,1,1)/100 -> 0.132021 | H10: =F10/(1+G10)^(E10/365) -> 6106.6269 | I10: =H10/$H$11 -> 0.74438081 | J10: =I10*E10/365 -> 3.3527727
H11: =SUM(H6:H10) -> 8203.633 | I11: =SUM(I6:I10) -> 1 | J11: =SUM(J6:J10) -> 3.8225459
C13: 2030/A | D13: 45525 | E13: 121 | F13: 300 | G13: =_xlfn.XLOOKUP(E13,'zero-coupon-yields_202405172251'!$B$2:$B$1490,'zero-coupon-yields_202405172251'!$D$2:$D$1490,,1,1)/100 -> 0.135242 | H13: =F13/(1+G13)^(E13/365) -> 287.64647 | I13: =H13/$H$20 -> 0.044955572 | J13: =I13*E13/365 -> 0.01490308
D14: 45890 | E14: 486 | F14: 300 | G14: =_xlfn.XLOOKUP(E14,'zero-coupon-yields_202405172251'!$B$2:$B$1490,'zero-coupon-yields_202405172251'!$D$2:$D$1490,,1,1)/100 -> 0.141115 | H14: =F14/(1+G14)^(E14/365) -> 251.6441 | I14: =H14/$H$20 -> 0.039328848 | J14: =I14*E14/365 -> 0.05236663 | N14: =C6 -> 2028/A | O14: =C13 -> 2030/A | P14: =C22 -> 2032/A
D15: 46255 | E15: 851 | F15: 300 | G15: =_xlfn.XLOOKUP(E15,'zero-coupon-yields_202405172251'!$B$2:$B$1490,'zero-coupon-yields_202405172251'!$D$2:$D$1490,,1,1)/100 -> 0.143263 | H15: =F15/(1+G15)^(E15/365) -> 219.55994 | I15: =H15/$H$20 -> 0.034314493 | J15: =I15*E15/365 -> 0.080004476 | M15: piece | N15: =Task1!D13 -> 4152 | O15: =Task1!E13 -> 3323 | P15: =Task1!F13 -> 3548
D16: 46620 | E16: 1216 | F16: 300 | G16: =_xlfn.XLOOKUP(E16,'zero-coupon-yields_202405172251'!$B$2:$B$1490,'zero-coupon-yields_202405172251'!$D$2:$D$1490,,1,1)/100 -> 0.140151 | H16: =F16/(1+G16)^(E16/365) -> 193.79864 | I16: =H16/$H$20 -> 0.030288321 | J16: =I16*E16/365 -> 0.10090575 | M16: price | N16: =H11 -> 8203.633 | O16: =H20 -> 6398.461 | P16: =H31 -> 8663.7269
D17: 46985 | E17: 1581 | F17: 300 | G17: =_xlfn.XLOOKUP(E17,'zero-coupon-yields_202405172251'!$B$2:$B$1490,'zero-coupon-yields_202405172251'!$D$2:$D$1490,,1,1)/100 -> 0.133378 | H17: =F17/(1+G17)^(E17/365) -> 174.4201 | I17: =H17/$H$20 -> 0.027259696 | J17: =I17*E17/365 -> 0.11807556 | M17: Market value | N17: =N15*N16 -> 34061484 | O17: =O15*O16 -> 21262086 | P17: =P15*P16 -> 30738903
D18: 47350 | E18: 1946 | F18: 300 | G18: =_xlfn.XLOOKUP(E18,'zero-coupon-yields_202405172251'!$B$2:$B$1490,'zero-coupon-yields_202405172251'!$D$2:$D$1490,,1,1)/100 -> 0.125231 | H18: =F18/(1+G18)^(E18/365) -> 159.92849 | I18: =H18/$H$20 -> 0.024994838 | J18: =I18*E18/365 -> 0.13326015
D19: 47716 | E19: 2312 | F19: 10300 | G19: =_xlfn.XLOOKUP(E19,'zero-coupon-yields_202405172251'!$B$2:$B$1490,'zero-coupon-yields_202405172251'!$D$2:$D$1490,,1,1)/100 -> 0.116964 | H19: =F19/(1+G19)^(E19/365) -> 5111.4632 | I19: =H19/$H$20 -> 0.79885823 | J19: =I19*E19/365 -> 5.060165 | M19: Portfolio Value
H20: =SUM(H13:H19) -> 6398.461 | I20: =SUM(I13:I19) -> 1 | J20: =SUM(J13:J19) -> 5.5596807 | M20: Yield 2024.04.22 | N20: =Task1!K6 -> 99995519
M21: Yield 2022.10.17 | N21: =SUM(N17:P17) -> 86062473
C22: 2032/A | D22: 45620 | E22: 216 | F22: 475 | G22: =_xlfn.XLOOKUP(E22,'zero-coupon-yields_202405172251'!$B$2:$B$1490,'zero-coupon-yields_202405172251'!$D$2:$D$1490,,1,1)/100 -> 0.136975 | H22: =F22/(1+G22)^(E22/365) -> 440.25195 | I22: =H22/$H$31 -> 0.050815538 | J22: =I22*E22/365 -> 0.030071661 | M22: Change (%) in value | N22: =(N21-N20)/N20 -> -0.13933671
D23: 45985 | E23: 581 | F23: 475 | G23: =_xlfn.XLOOKUP(E23,'zero-coupon-yields_202405172251'!$B$2:$B$1490,'zero-coupon-yields_202405172251'!$D$2:$D$1490,,1,1)/100 -> 0.142067 | H23: 425.41233 | I23: =H23/$H$31 -> 0.049102694 | J23: =I23*E23/365 -> 0.078160726 | M23: Day | N23: =Task1!B1-Task3!D4 -> 553
D24: 46350 | E24: 946 | F24: 475 | G24: =_xlfn.XLOOKUP(E24,'zero-coupon-yields_202405172251'!$B$2:$B$1490,'zero-coupon-yields_202405172251'!$D$2:$D$1490,,1,1)/100 -> 0.142971 | H24: 396.60355 | I24: =H24/$H$31 -> 0.045777476 | J24: =I24*E24/365 -> 0.11864518 | M24: VaR | N24: =Task2!R9*SQRT(Task3!N23) -> 0.28279367
D25: 46715 | E25: 1311 | F25: 475 | G25: =_xlfn.XLOOKUP(E25,'zero-coupon-yields_202405172251'!$B$2:$B$1490,'zero-coupon-yields_202405172251'!$D$2:$D$1490,,1,1)/100 -> 0.138566 | H25: 369.89674 | I25: =H25/$H$31 -> 0.042694875 | J25: =I25*E25/365 -> 0.15335063
D26: 47080 | E26: 1676 | F26: 475 | G26: =_xlfn.XLOOKUP(E26,'zero-coupon-yields_202405172251'!$B$2:$B$1490,'zero-coupon-yields_202405172251'!$D$2:$D$1490,,1,1)/100 -> 0.131253 | H26: 345.1609 | I26: =H26/$H$31 -> 0.039839771 | J26: =I26*E26/365 -> 0.1829355
D27: 47445 | E27: 2041 | F27: 475 | G27: =_xlfn.XLOOKUP(E27,'zero-coupon-yields_202405172251'!$B$2:$B$1490,'zero-coupon-yields_202405172251'!$D$2:$D$1490,,1,1)/100 -> 0.122994 | H27: 322.20977 | I27: =H27/$H$31 -> 0.037190666 | J27: =I27*E27/365 -> 0.20796205 | M27: The value of the portfolio will be 86,065,601.96, if the yields at day 2022.10.17 was used, which means a 13,93% decrease compared to the value calculated in task1.
D28: 47810 | E28: 2406 | F28: 475 | G28: =_xlfn.XLOOKUP(E28,'zero-coupon-yields_202405172251'!$B$2:$B$1490,'zero-coupon-yields_202405172251'!$D$2:$D$1490,,1,1)/100 -> 0.115075 | H28: 300.85967 | I28: =H28/$H$31 -> 0.034726356 | J28: =I28*E28/365 -> 0.22890853 | M28: Daily VaR as calculated in task 2 is about 1,2%. For 553 days it is 28.28% which indicates substantial yield driven changes.
D29: 48175 | E29: 2771 | F29: 475 | G29: =_xlfn.XLOOKUP(E29,'zero-coupon-yields_202405172251'!$B$2:$B$1490,'zero-coupon-yields_202405172251'!$D$2:$D$1490,,1,1)/100 -> 0.108503 | H29: 280.92896 | I29: =H29/$H$31 -> 0.032425879 | J29: =I29*E29/365 -> 0.24617017 | M29: This movement is because of the high inflation in year 2022, it was measured at 14.5% in 2022, compared to the EU average of approximately 9.32%. In addition to the impact of the Russia-Ukraine war on energy prices, the depreciation of the national currency and iefficiencies in the domestic food manfacturing industry have contributed to Hungary recording way higher inflation rates in recent years than the EU average.
D30: 48542 | E30: 3138 | F30: 10475 | G30: =_xlfn.XLOOKUP(E30,'zero-coupon-yields_202405172251'!$B$2:$B$1490,'zero-coupon-yields_202405172251'!$D$2:$D$1490,,1,1)/100 -> 0.103754 | H30: 5782.4031 | I30: =H30/$H$31 -> 0.66742675 | J30: =I30*E30/365 -> 5.7380414
H31: =SUM(H22:H30) -> 8663.7269 | I31: =SUM(I22:I30) -> 1 | J31: =SUM(J22:J30) -> 6.9842459

Sheet Task4
B4: day | C4: year | F4: Mapped cash flow dates (years) | P4: Portfolio | T4: Correlation Matrix
A5: =Task1!D4 -> 2028/A | B5: =Task1!E20 -> 183 | C5: =B5/365 -> 0.50136986 | R5: 1 day
B6: =Task1!E21 -> 548 | C6: =B6/365 -> 1.5013699 | F6: t | G6: r(t) | H6: DF(t) | I6: CF' | J6: PV | K6: w(t) | L6: DUR | M6: w(t)*bond price volatility | T6: t | U6: 0.25 | V6: 0.5 | W6: 1 | X6: 3 | Y6: 5 | Z6: 10
B7: =Task1!E22 -> 913 | C7: =B7/365 -> 2.5013699 | F7: 0.25 | G7: {=_xlfn.XLOOKUP(Task1!$B$1,'Benchmark yields table'!$A$3:$A$599,_xlfn.XLOOKUP(Task4!F7,'Benchmark yields table'!$B$2:$I$2,'Benchmark yields table'!$B$3:$I$599))/100} -> 0.0668 | H7: =1/(1+G7)^F7 -> 0.98396409 | I7: =L45*M44 -> 317503.63 | J7: =H7*I7 -> 312412.17 | K7: =J7/$J$13 -> 0.002968203 | L7: =K7*F7 -> 0.00074205075 | M7: =K7*U15 -> 1.4487395e-06 | Q7: Volatility | R7: {=SQRT(MMULT(TRANSPOSE(M7:M12),MMULT(U7:Z12,M7:M12)))} -> 0.0043072983 | T7: 0.25 | U7: =CORREL(_xlfn.XLOOKUP($T7,'Benchmark yields table'!$J$2:$Q$2,'Benchmark yields table'!$J$20:$Q$599),_xlfn.XLOOKUP(U$6,'Benchmark yields table'!$J$2:$Q$2,'Benchmark yields table'!$J$20:$Q$599)) -> 1 | V7: =CORREL(_xlfn.XLOOKUP($T7,'Benchmark yields table'!$J$2:$Q$2,'Benchmark yields table'!$J$20:$Q$599),_xlfn.XLOOKUP(V$6,'Benchmark yields table'!$J$2:$Q$2,'Benchmark yields table'!$J$20:$Q$599)) -> 0.60501119 | W7: =CORREL(_xlfn.XLOOKUP($T7,'Benchmark yields table'!$J$2:$Q$2,'Benchmark yields table'!$J$20:$Q$599),_xlfn.XLOOKUP(W$6,'Benchmark yields table'!$J$2:$Q$2,'Benchmark yields table'!$J$20:$Q$599)) -> 0.51525983 | X7: =CORREL(_xlfn.XLOOKUP($T7,'Benchmark yields table'!$J$2:$Q$2,'Benchmark yields table'!$J$20:$Q$599),_xlfn.XLOOKUP(X$6,'Benchmark yields table'!$J$2:$Q$2,'Benchmark yields table'!$J$20:$Q$599)) -> 0.38125654 | Y7: =CORREL(_xlfn.XLOOKUP($T7,'Benchmark yields table'!$J$2:$Q$2,'Benchmark yields table'!$J$20:$Q$599),_xlfn.XLOOKUP(Y$6,'Benchmark yields table'!$J$2:$Q$2,'Benchmark yields table'!$J$20:$Q$599)) -> 0.36677534 | Z7: =CORREL(_xlfn.XLOOKUP($T7,'Benchmark yields table'!$J$2:$Q$2,'Benchmark yields table'!$J$20:$Q$599),_xlfn.XLOOKUP(Z$6,'Benchmark yields table'!$J$2:$Q$2,'Benchmark yields table'!$J$20:$Q$599)) -> 0.3658849
B8: =Task1!E23 -> 1278 | C8: =B8/365 -> 3.5013699 | F8: 0.5 | G8: {=_xlfn.XLOOKUP(Task1!$B$1,'Benchmark yields table'!$A$3:$A$599,_xlfn.XLOOKUP(Task4!F8,'Benchmark yields table'!$B$2:$I$2,'Benchmark yields table'!$B$3:$I$599))/100} -> 0.0692 | H8: =1/(1+G8)^F8 -> 0.96709809 | I8: =M23*SUM(L24)+M44*SUM(L47)+M73*SUM(L74) -> 5818081.6 | J8: =H8*I8 -> 5626655.6 | K8: =J8/$J$13 -> 0.053458404 | L8: =K8*F8 -> 0.026729202 | M8: =K8*V15 -> 3.4775461e-05 | Q8: Multiplier for 99% confidence | R8: =NORMSINV(1-R13) -> -2.3263479 | T8: 0.5 | U8: =CORREL(_xlfn.XLOOKUP($T8,'Benchmark yields table'!$J$2:$Q$2,'Benchmark yields table'!$J$20:$Q$599),_xlfn.XLOOKUP(U$6,'Benchmark yields table'!$J$2:$Q$2,'Benchmark yields table'!$J$20:$Q$599)) -> 0.60501119 | V8: =CORREL(_xlfn.XLOOKUP($T8,'Benchmark yields table'!$J$2:$Q$2,'Benchmark yields table'!$J$20:$Q$599),_xlfn.XLOOKUP(V$6,'Benchmark yields table'!$J$2:$Q$2,'Benchmark yields table'!$J$20:$Q$599)) -> 1 | W8: =CORREL(_xlfn.XLOOKUP($T8,'Benchmark yields table'!$J$2:$Q$2,'Benchmark yields table'!$J$20:$Q$599),_xlfn.XLOOKUP(W$6,'Benchmark yields table'!$J$2:$Q$2,'Benchmark yields table'!$J$20:$Q$599)) -> 0.73079441 | X8: =CORREL(_xlfn.XLOOKUP($T8,'Benchmark yields table'!$J$2:$Q$2,'Benchmark yields table'!$J$20:$Q$599),_xlfn.XLOOKUP(X$6,'Benchmark yields table'!$J$2:$Q$2,'Benchmark yields table'!$J$20:$Q$599)) -> 0.53728582 | Y8: =CORREL(_xlfn.XLOOKUP($T8,'Benchmark yields table'!$J$2:$Q$2,'Benchmark yields table'!$J$20:$Q$599),_xlfn.XLOOKUP(Y$6,'Benchmark yields table'!$J$2:$Q$2,'Benchmark yields table'!$J$20:$Q$599)) -> 0.5331356 | Z8: =CORREL(_xlfn.XLOOKUP($T8,'Benchmark yields table'!$J$2:$Q$2,'Benchmark yields table'!$J$20:$Q$599),_xlfn.XLOOKUP(Z$6,'Benchmark yields table'!$J$2:$Q$2,'Benchmark yields table'!$J$20:$Q$599)) -> 0.55077977
B9: =Task1!E24 -> 1644 | C9: =B9/365 -> 4.5041096 | F9: 1 | G9: {=_xlfn.XLOOKUP(Task1!$B$1,'Benchmark yields table'!$A$3:$A$599,_xlfn.XLOOKUP(Task4!F9,'Benchmark yields table'!$B$2:$I$2,'Benchmark yields table'!$B$3:$I$599))/100} -> 0.0688 | H9: =1/(1+G9)^F9 -> 0.93562874 | I9: =M23*SUM(L26,L28,L32)+M44*SUM(L49,L53)+M73*SUM(L76,L78,L82) -> 5575412.9 | J9: =H9*I9 -> 5216516.6 | K9: =J9/$J$13 -> 0.049561707 | L9: =K9*F9 -> 0.049561707 | M9: =K9*W15 -> 5.9771649e-05 | Q9: VaR (1 day, 99%) | R9: =-R7*R8 -> 0.010020274 | T9: 1 | U9: =CORREL(_xlfn.XLOOKUP($T9,'Benchmark yields table'!$J$2:$Q$2,'Benchmark yields table'!$J$20:$Q$599),_xlfn.XLOOKUP(U$6,'Benchmark yields table'!$J$2:$Q$2,'Benchmark yields table'!$J$20:$Q$599)) -> 0.51525983 | V9: =CORREL(_xlfn.XLOOKUP($T9,'Benchmark yields table'!$J$2:$Q$2,'Benchmark yields table'!$J$20:$Q$599),_xlfn.XLOOKUP(V$6,'Benchmark yields table'!$J$2:$Q$2,'Benchmark yields table'!$J$20:$Q$599)) -> 0.73079441 | W9: =CORREL(_xlfn.XLOOKUP($T9,'Benchmark yields table'!$J$2:$Q$2,'Benchmark yields table'!$J$20:$Q$599),_xlfn.XLOOKUP(W$6,'Benchmark yields table'!$J$2:$Q$2,'Benchmark yields table'!$J$20:$Q$599)) -> 1 | X9: =CORREL(_xlfn.XLOOKUP($T9,'Benchmark yields table'!$J$2:$Q$2,'Benchmark yields table'!$J$20:$Q$599),_xlfn.XLOOKUP(X$6,'Benchmark yields table'!$J$2:$Q$2,'Benchmark yields table'!$J$20:$Q$599)) -> 0.66514828 | Y9: =CORREL(_xlfn.XLOOKUP($T9,'Benchmark yields table'!$J$2:$Q$2,'Benchmark yields table'!$J$20:$Q$599),_xlfn.XLOOKUP(Y$6,'Benchmark yields table'!$J$2:$Q$2,'Benchmark yields table'!$J$20:$Q$599)) -> 0.66363795 | Z9: =CORREL(_xlfn.XLOOKUP($T9,'Benchmark yields table'!$J$2:$Q$2,'Benchmark yields table'!$J$20:$Q$599),_xlfn.XLOOKUP(Z$6,'Benchmark yields table'!$J$2:$Q$2,'Benchmark yields table'!$J$20:$Q$599)) -> 0.67559884
A10: =Task1!E4 -> 2030/A | B10: =Task1!E27 -> 121 | C10: =B10/365 -> 0.33150685 | F10: 3 | G10: {=_xlfn.XLOOKUP(Task1!$B$1,'Benchmark yields table'!$A$3:$A$599,_xlfn.XLOOKUP(Task4!F10,'Benchmark yields table'!$B$2:$I$2,'Benchmark yields table'!$B$3:$I$599))/100} -> 0.0725 | H10: =1/(1+G10)^F10 -> 0.8106028 | I10: =M23*SUM(L30,L34,L36,L40)+M44*SUM(L51,L55,L57,L61)+M73*SUM(L80,L84,L86,L90) -> 31106268 | J10: =H10*I10 -> 25214828 | K10: =J10/$J$13 -> 0.23956406 | L10: =K10*F10 -> 0.71869218 | M10: =K10*X15 -> 0.00067897989 | Q10: VaR (HUF, 1 day, 99%) | R10: =R9*Task1!K6 -> 1001982.5 | T10: 3 | U10: =CORREL(_xlfn.XLOOKUP($T10,'Benchmark yields table'!$J$2:$Q$2,'Benchmark yields table'!$J$20:$Q$599),_xlfn.XLOOKUP(U$6,'Benchmark yields table'!$J$2:$Q$2,'Benchmark yields table'!$J$20:$Q$599)) -> 0.38125654 | V10: =CORREL(_xlfn.XLOOKUP($T10,'Benchmark yields table'!$J$2:$Q$2,'Benchmark yields table'!$J$20:$Q$599),_xlfn.XLOOKUP(V$6,'Benchmark yields table'!$J$2:$Q$2,'Benchmark yields table'!$J$20:$Q$599)) -> 0.53728582 | W10: =CORREL(_xlfn.XLOOKUP($T10,'Benchmark yields table'!$J$2:$Q$2,'Benchmark yields table'!$J$20:$Q$599),_xlfn.XLOOKUP(W$6,'Benchmark yields table'!$J$2:$Q$2,'Benchmark yields table'!$J$20:$Q$599)) -> 0.66514828 | X10: =CORREL(_xlfn.XLOOKUP($T10,'Benchmark yields table'!$J$2:$Q$2,'Benchmark yields table'!$J$20:$Q$599),_xlfn.XLOOKUP(X$6,'Benchmark yields table'!$J$2:$Q$2,'Benchmark yields table'!$J$20:$Q$599)) -> 1 | Y10: =CORREL(_xlfn.XLOOKUP($T10,'Benchmark yields table'!$J$2:$Q$2,'Benchmark yields table'!$J$20:$Q$599),_xlfn.XLOOKUP(Y$6,'Benchmark yields table'!$J$2:$Q$2,'Benchmark yields table'!$J$20:$Q$599)) -> 0.95541409 | Z10: =CORREL(_xlfn.XLOOKUP($T10,'Benchmark yields table'!$J$2:$Q$2,'Benchmark yields table'!$J$20:$Q$599),_xlfn.XLOOKUP(Z$6,'Benchmark yields table'!$J$2:$Q$2,'Benchmark yields table'!$J$20:$Q$599)) -> 0.91480363
B11: =Task1!E28 -> 486 | C11: =B11/365 -> 1.3315068 | F11: 5 | G11: {=_xlfn.XLOOKUP(Task1!$B$1,'Benchmark yields table'!$A$3:$A$599,_xlfn.XLOOKUP(Task4!F11,'Benchmark yields table'!$B$2:$I$2,'Benchmark yields table'!$B$3:$I$599))/100} -> 0.0721 | H11: =1/(1+G11)^F11 -> 0.70603059 | I11: =M23*SUM(L38,L42)+M44*SUM(L59,L63,L65,L69)+M73*SUM(L88,L92,L94,L98,L102,L106) -> 88758073 | J11: =H11*I11 -> 62665915 | K11: =J11/$J$13 -> 0.59538385 | L11: =K11*F11 -> 2.9769192 | M11: =K11*Y15 -> 0.0030072028 | Q11: VaR (10 days, 99%) | R11: =R9*SQRT(10) -> 0.031686889 | T11: 5 | U11: =CORREL(_xlfn.XLOOKUP($T11,'Benchmark yields table'!$J$2:$Q$2,'Benchmark yields table'!$J$20:$Q$599),_xlfn.XLOOKUP(U$6,'Benchmark yields table'!$J$2:$Q$2,'Benchmark yields table'!$J$20:$Q$599)) -> 0.36677534 | V11: =CORREL(_xlfn.XLOOKUP($T11,'Benchmark yields table'!$J$2:$Q$2,'Benchmark yields table'!$J$20:$Q$599),_xlfn.XLOOKUP(V$6,'Benchmark yields table'!$J$2:$Q$2,'Benchmark yields table'!$J$20:$Q$599)) -> 0.5331356 | W11: =CORREL(_xlfn.XLOOKUP($T11,'Benchmark yields table'!$J$2:$Q$2,'Benchmark yields table'!$J$20:$Q$599),_xlfn.XLOOKUP(W$6,'Benchmark yields table'!$J$2:$Q$2,'Benchmark yields table'!$J$20:$Q$599)) -> 0.66363795 | X11: =CORREL(_xlfn.XLOOKUP($T11,'Benchmark yields table'!$J$2:$Q$2,'Benchmark yields table'!$J$20:$Q$599),_xlfn.XLOOKUP(X$6,'Benchmark yields table'!$J$2:$Q$2,'Benchmark yields table'!$J$20:$Q$599)) -> 0.95541409 | Y11: =CORREL(_xlfn.XLOOKUP($T11,'Benchmark yields table'!$J$2:$Q$2,'Benchmark yields table'!$J$20:$Q$599),_xlfn.XLOOKUP(Y$6,'Benchmark yields table'!$J$2:$Q$2,'Benchmark yields table'!$J$20:$Q$599)) -> 1 | Z11: =CORREL(_xlfn.XLOOKUP($T11,'Benchmark yields table'!$J$2:$Q$2,'Benchmark yields table'!$J$20:$Q$599),_xlfn.XLOOKUP(Z$6,'Benchmark yields table'!$J$2:$Q$2,'Benchmark yields table'!$J$20:$Q$599)) -> 0.96353862
B12: =Task1!E29 -> 851 | C12: =B12/365 -> 2.3315068 | F12: 10 | G12: {=_xlfn.XLOOKUP(Task1!$B$1,'Benchmark yields table'!$A$3:$A$599,_xlfn.XLOOKUP(Task4!F12,'Benchmark yields table'!$B$2:$I$2,'Benchmark yields table'!$B$3:$I$599))/100} -> 0.0712 | H12: =1/(1+G12)^F12 -> 0.50268319 | I12: =M44*SUM(L67,L71)+M73*SUM(L96,L104,L100,L108) -> 12366911 | J12: =H12*I12 -> 6216638.1 | K12: =J12/$J$13 -> 0.059063781 | L12: =K12*F12 -> 0.59063781 | M12: =K12*Z15 -> 0.00060610807 | T12: 10 | U12: =CORREL(_xlfn.XLOOKUP($T12,'Benchmark yields table'!$J$2:$Q$2,'Benchmark yields table'!$J$20:$Q$599),_xlfn.XLOOKUP(U$6,'Benchmark yields table'!$J$2:$Q$2,'Benchmark yields table'!$J$20:$Q$599)) -> 0.3658849 | V12: =CORREL(_xlfn.XLOOKUP($T12,'Benchmark yields table'!$J$2:$Q$2,'Benchmark yields table'!$J$20:$Q$599),_xlfn.XLOOKUP(V$6,'Benchmark yields table'!$J$2:$Q$2,'Benchmark yields table'!$J$20:$Q$599)) -> 0.55077977 | W12: =CORREL(_xlfn.XLOOKUP($T12,'Benchmark yields table'!$J$2:$Q$2,'Benchmark yields table'!$J$20:$Q$599),_xlfn.XLOOKUP(W$6,'Benchmark yields table'!$J$2:$Q$2,'Benchmark yields table'!$J$20:$Q$599)) -> 0.67559884 | X12: =CORREL(_xlfn.XLOOKUP($T12,'Benchmark yields table'!$J$2:$Q$2,'Benchmark yields table'!$J$20:$Q$599),_xlfn.XLOOKUP(X$6,'Benchmark yields table'!$J$2:$Q$2,'Benchmark yields table'!$J$20:$Q$599)) -> 0.91480363 | Y12: =CORREL(_xlfn.XLOOKUP($T12,'Benchmark yields table'!$J$2:$Q$2,'Benchmark yields table'!$J$20:$Q$599),_xlfn.XLOOKUP(Y$6,'Benchmark yields table'!$J$2:$Q$2,'Benchmark yields table'!$J$20:$Q$599)) -> 0.96353862 | Z12: =CORREL(_xlfn.XLOOKUP($T12,'Benchmark yields table'!$J$2:$Q$2,'Benchmark yields table'!$J$20:$Q$599),_xlfn.XLOOKUP(Z$6,'Benchmark yields table'!$J$2:$Q$2,'Benchmark yields table'!$J$20:$Q$599)) -> 1
B13: =Task1!E30 -> 1216 | C13: =B13/365 -> 3.3315068 | J13: =SUM(J7:J12) -> 1.0525297e+08 | K13: =J13/$J$13 -> 1 | L13: =SUM(L7:L12) -> 4.3632822 | Q13: Significance | R13: 0.99
B14: =Task1!E31 -> 1581 | C14: =B14/365 -> 4.3315068 | T14: "bond price volatilities" for Bechmark yield curve points
B15: =Task1!E32 -> 1946 | C15: =B15/365 -> 5.3315068 | U15: {=_xlfn.XLOOKUP(Task1!$B$1,'Benchmark yields table'!$A$3:$A$20,_xlfn.XLOOKUP(U6,'Benchmark yields table'!$BF$2:$BM$2,'Benchmark yields table'!$BF$3:$BM$20))} -> 0.0004880864 | V15: {=_xlfn.XLOOKUP(Task1!$B$1,'Benchmark yields table'!$A$3:$A$20,_xlfn.XLOOKUP(V6,'Benchmark yields table'!$BF$2:$BM$2,'Benchmark yields table'!$BF$3:$BM$20))} -> 0.00065051439 | W15: {=_xlfn.XLOOKUP(Task1!$B$1,'Benchmark yields table'!$A$3:$A$20,_xlfn.XLOOKUP(W6,'Benchmark yields table'!$BF$2:$BM$2,'Benchmark yields table'!$BF$3:$BM$20))} -> 0.0012060047 | X15: {=_xlfn.XLOOKUP(Task1!$B$1,'Benchmark yields table'!$A$3:$A$20,_xlfn.XLOOKUP(X6,'Benchmark yields table'!$BF$2:$BM$2,'Benchmark yields table'!$BF$3:$BM$20))} -> 0.002834231 | Y15: {=_xlfn.XLOOKUP(Task1!$B$1,'Benchmark yields table'!$A$3:$A$20,_xlfn.XLOOKUP(Y6,'Benchmark yields table'!$BF$2:$BM$2,'Benchmark yields table'!$BF$3:$BM$20))} -> 0.0050508639 | Z15: {=_xlfn.XLOOKUP(Task1!$B$1,'Benchmark yields table'!$A$3:$A$20,_xlfn.XLOOKUP(Z6,'Benchmark yields table'!$BF$2:$BM$2,'Benchmark yields table'!$BF$3:$BM$20))} -> 0.010261925
B16: =Task1!E33 -> 2312 | C16: =B16/365 -> 6.3342466
A17: =Task1!F4 -> 2032/A | B17: =Task1!E36 -> 216 | C17: =B17/365 -> 0.59178082
B18: =Task1!E37 -> 581 | C18: =B18/365 -> 1.5917808
B19: =Task1!E38 -> 946 | C19: =B19/365 -> 2.5917808
B20: =Task1!E39 -> 1311 | C20: =B20/365 -> 3.5917808 | F20: Cash Flow Mapping
B21: =Task1!E40 -> 1676 | C21: =B21/365 -> 4.5917808 | G21: t | H21: r(t) | I21: stddev(t) | J21: DF(t) | K21: CF | L21: CF' | M21: number of securities
B22: =Task1!E41 -> 2041 | C22: =B22/365 -> 5.5917808
B23: =Task1!E42 -> 2406 | C23: =B23/365 -> 6.5917808 | F23: =Task1!D4 -> 2028/A | M23: 7590
B24: =Task1!E43 -> 2771 | C24: =B24/365 -> 7.5917808 | F24: =1-((G25-G24)/(G26-G24)) -> 0.99726027 | G24: 0.5 | H24: {=_xlfn.XLOOKUP(Task1!$B$1,'Benchmark yields table'!$A$3:$A$599,_xlfn.XLOOKUP(Task4!G24,'Benchmark yields table'!$B$2:$I$2,'Benchmark yields table'!$B$3:$I$599))/100} -> 0.0692 | I24: {=_xlfn.XLOOKUP(Task1!$B$1,'Benchmark yields table'!$A$3:$A$599,_xlfn.XLOOKUP(Task4!G24,'Benchmark yields table'!$BF$2:$BM$2,'Benchmark yields table'!$BF$3:$BM$599))} -> 0.00065051439 | J24: =1/(1+H24)^G24 -> 0.96709809 | L24: =K25*M25 -> 670.61375 | M24: alfa | N24: PV= | P24: =K25*J25 -> 652.73171 | Q24: Korrel | R24: Vol | S24: =I25 -> 0.00065203628 | T24: a | V24: =I24^2+I26^2-2*Q25*I24*I26 -> 7.3096559e-07 | W24: =(-V25+SQRT(V25^2-4*V24*V26))/(2*V24) -> 1.4173419
B25: =Task1!E44 -> 3138 | C25: =B25/365 -> 8.5972603 | G25: =C5 -> 0.50136986 | H25: =F24*H24+(1-F24)*H26 -> 0.069198904 | I25: =F24*I24+(1-F24)*I26 -> 0.00065203628 | J25: =1/(1+H25)^G25 -> 0.96700995 | K25: =Task1!F20 -> 675 | M25: =MIN(W24:W25) -> 0.99350186 | N25: PV'= | P25: =L24*J24+L26*J26 -> 652.65318 | Q25: {=_xlfn.XLOOKUP(G24,$T$7:$T$12,_xlfn.XLOOKUP(G26,$U$6:$Z$6,$U$7:$Z$12))} -> 0.73079441 | R25: Vol' | S25: =SQRT((M25*I24)^2+((1-M25)*I26)^2+2*M25*(1-M25)*Q25*I24*I26) -> 0.00065203628 | T25: b | V25: =2*Q25*I24*I26-2*I26^2 -> -1.7622438e-06 | W25: =(-V25-SQRT(V25^2-4*V24*V26))/(2*V24) -> 0.99350186
G26: 1 | H26: {=_xlfn.XLOOKUP(Task1!$B$1,'Benchmark yields table'!$A$3:$A$599,_xlfn.XLOOKUP(Task4!G26,'Benchmark yields table'!$B$2:$I$2,'Benchmark yields table'!$B$3:$I$599))/100} -> 0.0688 | I26: {=_xlfn.XLOOKUP(Task1!$B$1,'Benchmark yields table'!$A$3:$A$599,_xlfn.XLOOKUP(Task4!G26,'Benchmark yields table'!$BF$2:$BM$2,'Benchmark yields table'!$BF$3:$BM$599))} -> 0.0012060047 | J26: =1/(1+H26)^G26 -> 0.93562874 | L26: =(1-M25)*K25 -> 4.3862466 | N26: Pvdiff | P26: =ABS(P24-P25) -> 0.078536621 | R26: Voldiff | S26: =ABS(S24-S25) -> 0 | T26: c | V26: =I26^2-I25^2 -> 1.0292959e-06 | Z26: Target VaR | AB26: =Task2!R9/1.2 -> 0.010021342
F28: =1-((G29-G28)/(G30-G28)) -> 0.74931507 | G28: 1 | H28: {=_xlfn.XLOOKUP(Task1!$B$1,'Benchmark yields table'!$A$3:$A$599,_xlfn.XLOOKUP(G28,'Benchmark yields table'!$B$2:$I$2,'Benchmark yields table'!$B$3:$I$599))/100} -> 0.0688 | I28: {=_xlfn.XLOOKUP(Task1!$B$1,'Benchmark yields table'!$A$3:$A$599,_xlfn.XLOOKUP(G28,'Benchmark yields table'!$BF$2:$BM$2,'Benchmark yields table'!$BF$3:$BM$599))} -> 0.0012060047 | J28: =1/(1+H28)^G28 -> 0.93562874 | L28: =K29*M29 -> 442.40156 | M28: alfa | N28: PV= | P28: =K29*J29 -> 610.03382 | Q28: Korrel | R28: Vol | S28: =I29 -> 0.0016141765 | T28: a | V28: =I28^2+I30^2-2*Q29*I28*I30 -> 4.9402317e-06 | W28: =(-V29+SQRT(V29^2-4*V28*V30))/(2*V28) -> 1.6761915
G29: =C6 -> 1.5013699 | H29: =H28*F28+(1-F28)*H30 -> 0.069727534 | I29: =I28*F28+(1-F28)*I30 -> 0.0016141765 | J29: =1/(1+H29)^G29 -> 0.9037538 | K29: =Task1!F21 -> 675 | M29: =MIN(W28:W29) -> 0.65540972 | N29: PV'= | P29: =L28*J28+L30*J30 -> 602.46856 | Q29: {=_xlfn.XLOOKUP(G28,$T$7:$T$12,_xlfn.XLOOKUP(G30,$U$6:$Z$6,$U$7:$Z$12))} -> 0.66514828 | R29: Vol' | S29: =SQRT((M29*I28)^2+((1-M29)*I30)^2+2*M29*(1-M29)*Q29*I28*I30) -> 0.0016141765 | T29: b | V29: =2*Q29*I28*I30-2*I30^2 -> -1.151865e-05 | W29: =(-V29-SQRT(V29^2-4*V28*V30))/(2*V28) -> 0.65540972 | Z29: Portfolio | AA29: Before | AB29: Adjust Var | AC29: Movement | AD29: Transaction
G30: 3 | H30: {=_xlfn.XLOOKUP(Task1!$B$1,'Benchmark yields table'!$A$3:$A$599,_xlfn.XLOOKUP(G30,'Benchmark yields table'!$B$2:$I$2,'Benchmark yields table'!$B$3:$I$599))/100} -> 0.0725 | I30: {=_xlfn.XLOOKUP(Task1!$B$1,'Benchmark yields table'!$A$3:$A$599,_xlfn.XLOOKUP(G30,'Benchmark yields table'!$BF$2:$BM$2,'Benchmark yields table'!$BF$3:$BM$599))} -> 0.002834231 | J30: =1/(1+H30)^G30 -> 0.8106028 | L30: =(1-M29)*K29 -> 232.59844 | N30: Pvdiff | P30: =ABS(P28-P29) -> 7.5652561 | R30: Voldiff | S30: =ABS(S28-S29) -> 0 | T30: c | V30: =I30^2-I29^2 -> 5.4272999e-06 | Z30: =Task1!D4 -> 2028/A | AA30: =Task1!D13 -> 4152 | AB30: =M23 -> 7590 | AC30: =AB30-AA30 -> 3438 | AD30: =IF(AC30>=1,"buy","sell") -> buy
Z31: =Task1!E4 -> 2030/A | AA31: =Task1!E13 -> 3323 | AB31: =M44 -> 2940 | AC31: =AB31-AA31 -> -383 | AD31: =IF(AC31>=1,"buy","sell") -> sell
F32: =1-((G33-G32)/(G34-G32)) -> 0.24931507 | G32: 1 | H32: {=_xlfn.XLOOKUP(Task1!$B$1,'Benchmark yields table'!$A$3:$A$599,_xlfn.XLOOKUP(G32,'Benchmark yields table'!$B$2:$I$2,'Benchmark yields table'!$B$3:$I$599))/100} -> 0.0688 | I32: {=_xlfn.XLOOKUP(Task1!$B$1,'Benchmark yields table'!$A$3:$A$599,_xlfn.XLOOKUP(G32,'Benchmark yields table'!$BF$2:$BM$2,'Benchmark yields table'!$BF$3:$BM$599))} -> 0.0012060047 | J32: =1/(1+H32)^G32 -> 0.93562874 | L32: =K33*M33 -> 137.13648 | M32: alfa | N32: PV= | P32: =K33*J33 -> 567.81079 | Q32: Korrel | R32: Vol | S32: =I33 -> 0.0024282897 | T32: a | V32: =I32^2+I34^2-2*Q33*I32*I34 -> 4.9402317e-06 | W32: =(-V33+SQRT(V33^2-4*V32*V34))/(2*V32) -> 2.128436 | Z32: =Task1!F4 -> 2032/A | AA32: =Task1!F13 -> 3548 | AB32: =M73 -> 480 | AC32: =AB32-AA32 -> -3068 | AD32: =IF(AC32>=1,"buy","sell") -> sell
G33: =C7 -> 2.5013699 | H33: =H32*F32+(1-F32)*H34 -> 0.071577534 | I33: =I32*F32+(1-F32)*I34 -> 0.0024282897 | J33: =1/(1+H33)^G33 -> 0.84120118 | K33: =Task1!F22 -> 675 | M33: =MIN(W32:W33) -> 0.20316515 | N33: PV'= | P33: =L32*J32+L34*J34 -> 564.30251 | Q33: {=_xlfn.XLOOKUP(G32,$T$7:$T$12,_xlfn.XLOOKUP(G34,$U$6:$Z$6,$U$7:$Z$12))} -> 0.66514828 | R33: Vol' | S33: =SQRT((M33*I32)^2+((1-M33)*I34)^2+2*M33*(1-M33)*Q33*I32*I34) -> 0.0024282897 | T33: b | V33: =2*Q33*I32*I34-2*I34^2 -> -1.151865e-05 | W33: =(-V33-SQRT(V33^2-4*V32*V34))/(2*V32) -> 0.20316515
G34: 3 | H34: {=_xlfn.XLOOKUP(Task1!$B$1,'Benchmark yields table'!$A$3:$A$599,_xlfn.XLOOKUP(G34,'Benchmark yields table'!$B$2:$I$2,'Benchmark yields table'!$B$3:$I$599))/100} -> 0.0725 | I34: {=_xlfn.XLOOKUP(Task1!$B$1,'Benchmark yields table'!$A$3:$A$599,_xlfn.XLOOKUP(G34,'Benchmark yields table'!$BF$2:$BM$2,'Benchmark yields table'!$BF$3:$BM$599))} -> 0.002834231 | J34: =1/(1+H34)^G34 -> 0.8106028 | L34: =(1-M33)*K33 -> 537.86352 | N34: Pvdiff | P34: =ABS(P32-P33) -> 3.5082896 | R34: Voldiff | S34: =ABS(S32-S33) -> 4.3368087e-19 | T34: c | V34: =I34^2-I33^2 -> 2.1362749e-06
F36: =1-((G37-G36)/(G38-G36)) -> 0.74931507 | G36: 3 | H36: {=_xlfn.XLOOKUP(Task1!$B$1,'Benchmark yields table'!$A$3:$A$599,_xlfn.XLOOKUP(G36,'Benchmark yields table'!$B$2:$I$2,'Benchmark yields table'!$B$3:$I$599))/100} -> 0.0725 | I36: {=_xlfn.XLOOKUP(Task1!$B$1,'Benchmark yields table'!$A$3:$A$599,_xlfn.XLOOKUP(G36,'Benchmark yields table'!$BF$2:$BM$2,'Benchmark yields table'!$BF$3:$BM$599))} -> 0.002834231 | J36: =1/(1+H36)^G36 -> 0.8106028 | L36: =K37*M37 -> 494.62086 | M36: alfa | N36: PV= | P36: =K37*J37 -> 528.46199 | Q36: Korrel | R36: Vol | S36: =I37 -> 0.0033899075 | T36: a | V36: =I36^2+I38^2-2*Q37*I36*I38 -> 6.189984e-06 | W36: =(-V37+SQRT(V37^2-4*V36*V38))/(2*V36) -> 3.0908804
G37: =C8 -> 3.5013699 | H37: =F36*H36+(1-F36)*H38 -> 0.072399726 | I37: =I36*F36+(1-F36)*I38 -> 0.0033899075 | J37: =1/(1+H37)^G37 -> 0.78290666 | K37: =Task1!F23 -> 675 | M37: =MIN(W36:W37) -> 0.73277164 | N37: PV'= | P37: =L36*J36+L38*J38 -> 528.29424 | Q37: {=_xlfn.XLOOKUP(G36,$T$7:$T$12,_xlfn.XLOOKUP(G38,$U$6:$Z$6,$U$7:$Z$12))} -> 0.95541409 | R37: Vol' | S37: =SQRT((M37*I36)^2+((1-M37)*I38)^2+2*M37*(1-M37)*Q37*I36*I38) -> 0.0033899075 | T37: b | V37: =2*Q37*I36*I38-2*I38^2 -> -2.3668345e-05 | W37: =(-V37-SQRT(V37^2-4*V36*V38))/(2*V36) -> 0.73277164
G38: 5 | H38: {=_xlfn.XLOOKUP(Task1!$B$1,'Benchmark yields table'!$A$3:$A$599,_xlfn.XLOOKUP(G38,'Benchmark yields table'!$B$2:$I$2,'Benchmark yields table'!$B$3:$I$599))/100} -> 0.0721 | I38: {=_xlfn.XLOOKUP(Task1!$B$1,'Benchmark yields table'!$A$3:$A$599,_xlfn.XLOOKUP(G38,'Benchmark yields table'!$BF$2:$BM$2,'Benchmark yields table'!$BF$3:$BM$599))} -> 0.0050508639 | J38: =1/(1+H38)^G38 -> 0.70603059 | L38: =(1-M37)*K37 -> 180.37914 | N38: Pvdiff | P38: =ABS(P36-P37) -> 0.16774951 | R38: Voldiff | S38: =ABS(S36-S37) -> 4.3368087e-19 | T38: c | V38: =I38^2-I37^2 -> 1.4019753e-05
F40: =1-((G41-G40)/(G42-G40)) -> 0.24794521 | G40: 3 | H40: {=_xlfn.XLOOKUP(Task1!$B$1,'Benchmark yields table'!$A$3:$A$599,_xlfn.XLOOKUP(G40,'Benchmark yields table'!$B$2:$I$2,'Benchmark yields table'!$B$3:$I$599))/100} -> 0.0725 | I40: {=_xlfn.XLOOKUP(Task1!$B$1,'Benchmark yields table'!$A$3:$A$599,_xlfn.XLOOKUP(G40,'Benchmark yields table'!$BF$2:$BM$2,'Benchmark yields table'!$BF$3:$BM$599))} -> 0.002834231 | J40: =1/(1+H40)^G40 -> 0.8106028 | L40: =K41*M41 -> 2523.8846 | M40: alfa | N40: PV= | P40: =K41*J41 -> 7798.3702 | Q40: Korrel | R40: Vol | S40: =I41 -> 0.0045012604 | T40: a | V40: =I40^2+I42^2-2*Q41*I40*I42 -> 6.189984e-06 | W40: =(-V41+SQRT(V41^2-4*V40*V42))/(2*V40) -> 3.5872225
G41: =C9 -> 4.5041096 | H41: =F40*H40+(1-F40)*H42 -> 0.072199178 | I41: =I40*F40+(1-F40)*I42 -> 0.0045012604 | J41: =1/(1+H41)^G41 -> 0.73052648 | K41: =Task1!F24 -> 10675 | M41: =MIN(W40:W41) -> 0.23642947 | N41: PV'= | P41: =L40*J40+L42*J42 -> 7800.8048 | Q41: {=_xlfn.XLOOKUP(G40,$T$7:$T$12,_xlfn.XLOOKUP(G42,$U$6:$Z$6,$U$7:$Z$12))} -> 0.95541409 | R41: Vol' | S41: =SQRT((M41*I40)^2+((1-M41)*I42)^2+2*M41*(1-M41)*Q41*I40*I42) -> 0.0045012604 | T41: b | V41: =2*Q41*I40*I42-2*I42^2 -> -2.3668345e-05 | W41: =(-V41-SQRT(V41^2-4*V40*V42))/(2*V40) -> 0.23642947
G42: 5 | H42: {=_xlfn.XLOOKUP(Task1!$B$1,'Benchmark yields table'!$A$3:$A$599,_xlfn.XLOOKUP(G42,'Benchmark yields table'!$B$2:$I$2,'Benchmark yields table'!$B$3:$I$599))/100} -> 0.0721 | I42: {=_xlfn.XLOOKUP(Task1!$B$1,'Benchmark yields table'!$A$3:$A$599,_xlfn.XLOOKUP(G42,'Benchmark yields table'!$BF$2:$BM$2,'Benchmark yields table'!$BF$3:$BM$599))} -> 0.0050508639 | J42: =1/(1+H42)^G42 -> 0.70603059 | L42: =(1-M41)*K41 -> 8151.1154 | N42: Pvdiff | P42: =ABS(P40-P41) -> 2.4345313 | R42: Voldiff | S42: =ABS(S40-S41) -> 0 | T42: c | V42: =I42^2-I41^2 -> 5.2498809e-06
F44: =Task1!E4 -> 2030/A | M44: 2940
F45: =1-((G46-G45)/(G47-G45)) -> 0.6739726 | G45: 0.25 | H45: {=_xlfn.XLOOKUP(Task1!$B$1,'Benchmark yields table'!$A$3:$A$599,_xlfn.XLOOKUP(Task4!G45,'Benchmark yields table'!$B$2:$I$2,'Benchmark yields table'!$B$3:$I$599))/100} -> 0.0668 | I45: {=_xlfn.XLOOKUP(Task1!$B$1,'Benchmark yields table'!$A$3:$A$599,_xlfn.XLOOKUP(Task4!G45,'Benchmark yields table'!$BF$2:$BM$2,'Benchmark yields table'!$BF$3:$BM$599))} -> 0.0004880864 | J45: =1/(1+H45)^G45 -> 0.98396409 | L45: =K46*M46 -> 107.99443 | M45: alfa | N45: PV= | P45: =K46*J46 -> 293.56616 | Q45: Korrel | R45: Vol | S45: =I46 -> 0.00054104237 | T45: a | V45: =I45^2+I47^2-2*Q46*I45*I47 -> 2.7720646e-07 | W45: =(-V46+SQRT(V46^2-4*V45*V47))/(2*V45) -> 1.3071771
G46: =C10 -> 0.33150685 | H46: =F45*H45+(1-F45)*H47 -> 0.067582466 | I46: =F45*I45+(1-F45)*I47 -> 0.00054104237 | J46: =1/(1+H46)^G46 -> 0.97855385 | K46: =Task1!F27 -> 300 | M46: =MIN(W45:W46) -> 0.35998144 | N46: PV'= | P46: =L45*J45+L47*J47 -> 291.95086 | Q46: {=_xlfn.XLOOKUP(G45,$T$7:$T$12,_xlfn.XLOOKUP(G47,$U$6:$Z$6,$U$7:$Z$12))} -> 0.60501119 | R46: Vol' | S46: =SQRT((M46*I45)^2+((1-M46)*I47)^2+2*M46*(1-M46)*Q46*I45*I47) -> 0.00054104237 | T46: b | V46: =2*Q46*I45*I47-2*I47^2 -> -4.621471e-07 | W46: =(-V46-SQRT(V46^2-4*V45*V47))/(2*V45) -> 0.35998144
G47: 0.5 | H47: {=_xlfn.XLOOKUP(Task1!$B$1,'Benchmark yields table'!$A$3:$A$599,_xlfn.XLOOKUP(Task4!G47,'Benchmark yields table'!$B$2:$I$2,'Benchmark yields table'!$B$3:$I$599))/100} -> 0.0692 | I47: {=_xlfn.XLOOKUP(Task1!$B$1,'Benchmark yields table'!$A$3:$A$599,_xlfn.XLOOKUP(Task4!G47,'Benchmark yields table'!$BF$2:$BM$2,'Benchmark yields table'!$BF$3:$BM$599))} -> 0.00065051439 | J47: =1/(1+H47)^G47 -> 0.96709809 | L47: =(1-M46)*K46 -> 192.00557 | N47: Pvdiff | P47: =ABS(P45-P46) -> 1.6152949 | R47: Voldiff | S47: =ABS(S45-S46) -> 0 | T47: c | V47: =I47^2-I46^2 -> 1.3044213e-07
F49: =1-((G50-G49)/(G51-G49)) -> 0.83424658 | G49: 1 | H49: {=_xlfn.XLOOKUP(Task1!$B$1,'Benchmark yields table'!$A$3:$A$599,_xlfn.XLOOKUP(G49,'Benchmark yields table'!$B$2:$I$2,'Benchmark yields table'!$B$3:$I$599))/100} -> 0.0688 | I49: {=_xlfn.XLOOKUP(Task1!$B$1,'Benchmark yields table'!$A$3:$A$599,_xlfn.XLOOKUP(G49,'Benchmark yields table'!$BF$2:$BM$2,'Benchmark yields table'!$BF$3:$BM$599))} -> 0.0012060047 | J49: =1/(1+H49)^G49 -> 0.93562874 | L49: =K50*M50 -> 224.5998 | M49: alfa | N49: PV= | P49: =K50*J50 -> 274.35553 | Q49: Korrel | R49: Vol | S49: =I50 -> 0.0014758888 | T49: a | V49: =I49^2+I51^2-2*Q50*I49*I51 -> 4.9402317e-06 | W49: =(-V50+SQRT(V50^2-4*V49*V51))/(2*V49) -> 1.5829352
G50: =C11 -> 1.3315068 | H50: =H49*F49+(1-F49)*H51 -> 0.069413288 | I50: =I49*F49+(1-F49)*I51 -> 0.0014758888 | J50: =1/(1+H50)^G50 -> 0.91451844 | K50: =Task1!F28 -> 300 | M50: =MIN(W49:W50) -> 0.74866601 | N50: PV'= | P50: =L49*J49+L51*J51 -> 271.26164 | Q50: {=_xlfn.XLOOKUP(G49,$T$7:$T$12,_xlfn.XLOOKUP(G51,$U$6:$Z$6,$U$7:$Z$12))} -> 0.66514828 | R50: Vol' | S50: =SQRT((M50*I49)^2+((1-M50)*I51)^2+2*M50*(1-M50)*Q50*I49*I51) -> 0.0014758888 | T50: b | V50: =2*Q50*I49*I51-2*I51^2 -> -1.151865e-05 | W50: =(-V50-SQRT(V50^2-4*V49*V51))/(2*V49) -> 0.74866601
G51: 3 | H51: {=_xlfn.XLOOKUP(Task1!$B$1,'Benchmark yields table'!$A$3:$A$599,_xlfn.XLOOKUP(G51,'Benchmark yields table'!$B$2:$I$2,'Benchmark yields table'!$B$3:$I$599))/100} -> 0.0725 | I51: {=_xlfn.XLOOKUP(Task1!$B$1,'Benchmark yields table'!$A$3:$A$599,_xlfn.XLOOKUP(G51,'Benchmark yields table'!$BF$2:$BM$2,'Benchmark yields table'!$BF$3:$BM$599))} -> 0.002834231 | J51: =1/(1+H51)^G51 -> 0.8106028 | L51: =(1-M50)*K50 -> 75.400198 | N51: Pvdiff | P51: =ABS(P49-P50) -> 3.0938898 | R51: Voldiff | S51: =ABS(S49-S50) -> 0 | T51: c | V51: =I51^2-I50^2 -> 5.854618e-06
F53: =1-((G54-G53)/(G55-G53)) -> 0.33424658 | G53: 1 | H53: {=_xlfn.XLOOKUP(Task1!$B$1,'Benchmark yields table'!$A$3:$A$599,_xlfn.XLOOKUP(G53,'Benchmark yields table'!$B$2:$I$2,'Benchmark yields table'!$B$3:$I$599))/100} -> 0.0688 | I53: {=_xlfn.XLOOKUP(Task1!$B$1,'Benchmark yields table'!$A$3:$A$599,_xlfn.XLOOKUP(G53,'Benchmark yields table'!$BF$2:$BM$2,'Benchmark yields table'!$BF$3:$BM$599))} -> 0.0012060047 | J53: =1/(1+H53)^G53 -> 0.93562874 | L53: =K54*M54 -> 82.320532 | M53: alfa | N53: PV= | P53: =K54*J54 -> 255.51595 | Q53: Korrel | R53: Vol | S53: =I54 -> 0.0022900019 | T53: a | V53: =I53^2+I55^2-2*Q54*I53*I55 -> 4.9402317e-06 | W53: =(-V54+SQRT(V54^2-4*V53*V55))/(2*V53) -> 2.0571994
G54: =C12 -> 2.3315068 | H54: =H53*F53+(1-F53)*H55 -> 0.071263288 | I54: =I53*F53+(1-F53)*I55 -> 0.0022900019 | J54: =1/(1+H54)^G54 -> 0.85171982 | K54: =Task1!F29 -> 300 | M54: =MIN(W53:W54) -> 0.27440177 | N54: PV'= | P54: =L53*J53+L55*J55 -> 253.47304 | Q54: {=_xlfn.XLOOKUP(G53,$T$7:$T$12,_xlfn.XLOOKUP(G55,$U$6:$Z$6,$U$7:$Z$12))} -> 0.66514828 | R54: Vol' | S54: =SQRT((M54*I53)^2+((1-M54)*I55)^2+2*M54*(1-M54)*Q54*I53*I55) -> 0.0022900019 | T54: b | V54: =2*Q54*I53*I55-2*I55^2 -> -1.151865e-05 | W54: =(-V54-SQRT(V54^2-4*V53*V55))/(2*V53) -> 0.27440177
G55: 3 | H55: {=_xlfn.XLOOKUP(Task1!$B$1,'Benchmark yields table'!$A$3:$A$599,_xlfn.XLOOKUP(G55,'Benchmark yields table'!$B$2:$I$2,'Benchmark yields table'!$B$3:$I$599))/100} -> 0.0725 | I55: {=_xlfn.XLOOKUP(Task1!$B$1,'Benchmark yields table'!$A$3:$A$599,_xlfn.XLOOKUP(G55,'Benchmark yields table'!$BF$2:$BM$2,'Benchmark yields table'!$BF$3:$BM$599))} -> 0.002834231 | J55: =1/(1+H55)^G55 -> 0.8106028 | L55: =(1-M54)*K54 -> 217.67947 | N55: Pvdiff | P55: =ABS(P53-P54) -> 2.042905 | R55: Voldiff | S55: =ABS(S53-S54) -> 4.3368087e-19 | T55: c | V55: =I55^2-I54^2 -> 2.7887567e-06
F57: =1-((G58-G57)/(G59-G57)) -> 0.83424658 | G57: 3 | H57: {=_xlfn.XLOOKUP(Task1!$B$1,'Benchmark yields table'!$A$3:$A$599,_xlfn.XLOOKUP(G57,'Benchmark yields table'!$B$2:$I$2,'Benchmark yields table'!$B$3:$I$599))/100} -> 0.0725 | I57: {=_xlfn.XLOOKUP(Task1!$B$1,'Benchmark yields table'!$A$3:$A$599,_xlfn.XLOOKUP(G57,'Benchmark yields table'!$BF$2:$BM$2,'Benchmark yields table'!$BF$3:$BM$599))} -> 0.002834231 | J57: =1/(1+H57)^G57 -> 0.8106028 | L57: =K58*M58 -> 246.32853 | M57: alfa | N57: PV= | P57: =K58*J58 -> 237.65223 | Q57: Korrel | R57: Vol | S57: =I58 -> 0.0032016455 | T57: a | V57: =I57^2+I59^2-2*Q58*I57*I59 -> 6.189984e-06 | W57: =(-V58+SQRT(V58^2-4*V57*V59))/(2*V57) -> 3.0025569
G58: =C13 -> 3.3315068 | H58: =F57*H57+(1-F57)*H59 -> 0.072433699 | I58: =I57*F57+(1-F57)*I59 -> 0.0032016455 | J58: =1/(1+H58)^G58 -> 0.79217408 | K58: =Task1!F30 -> 300 | M58: =MIN(W57:W58) -> 0.8210951 | N58: PV'= | P58: =L57*J57+L59*J59 -> 237.56829 | Q58: {=_xlfn.XLOOKUP(G57,$T$7:$T$12,_xlfn.XLOOKUP(G59,$U$6:$Z$6,$U$7:$Z$12))} -> 0.95541409 | R58: Vol' | S58: =SQRT((M58*I57)^2+((1-M58)*I59)^2+2*M58*(1-M58)*Q58*I57*I59) -> 0.0032016455 | T58: b | V58: =2*Q58*I57*I59-2*I59^2 -> -2.3668345e-05 | W58: =(-V58-SQRT(V58^2-4*V57*V59))/(2*V57) -> 0.8210951
G59: 5 | H59: {=_xlfn.XLOOKUP(Task1!$B$1,'Benchmark yields table'!$A$3:$A$599,_xlfn.XLOOKUP(G59,'Benchmark yields table'!$B$2:$I$2,'Benchmark yields table'!$B$3:$I$599))/100} -> 0.0721 | I59: {=_xlfn.XLOOKUP(Task1!$B$1,'Benchmark yields table'!$A$3:$A$599,_xlfn.XLOOKUP(G59,'Benchmark yields table'!$BF$2:$BM$2,'Benchmark yields table'!$BF$3:$BM$599))} -> 0.0050508639 | J59: =1/(1+H59)^G59 -> 0.70603059 | L59: =(1-M58)*K58 -> 53.67147 | N59: Pvdiff | P59: =ABS(P57-P58) -> 0.083930397 | R59: Voldiff | S59: =ABS(S57-S58) -> 4.3368087e-19 | T59: c | V59: =I59^2-I58^2 -> 1.5260692e-05
F61: =1-((G62-G61)/(G63-G61)) -> 0.33424658 | G61: 3 | H61: {=_xlfn.XLOOKUP(Task1!$B$1,'Benchmark yields table'!$A$3:$A$599,_xlfn.XLOOKUP(G61,'Benchmark yields table'!$B$2:$I$2,'Benchmark yields table'!$B$3:$I$599))/100} -> 0.0725 | I61: {=_xlfn.XLOOKUP(Task1!$B$1,'Benchmark yields table'!$A$3:$A$599,_xlfn.XLOOKUP(G61,'Benchmark yields table'!$BF$2:$BM$2,'Benchmark yields table'!$BF$3:$BM$599))} -> 0.002834231 | J61: =1/(1+H61)^G61 -> 0.8106028 | L61: =K62*M62 -> 95.93056 | M61: alfa | N61: PV= | P61: =K62*J62 -> 221.77995 | Q61: Korrel | R61: Vol | S61: =I62 -> 0.004309962 | T61: a | V61: =I61^2+I63^2-2*Q62*I61*I63 -> 6.189984e-06 | W61: =(-V62+SQRT(V62^2-4*V61*V63))/(2*V61) -> 3.5038835
G62: =C14 -> 4.3315068 | H62: =F61*H61+(1-F61)*H63 -> 0.072233699 | I62: =I61*F61+(1-F61)*I63 -> 0.004309962 | J62: =1/(1+H62)^G62 -> 0.73926651 | K62: =Task1!F31 -> 300 | M62: =MIN(W61:W62) -> 0.31976853 | N62: PV'= | P62: =L61*J61+L63*J63 -> 221.84085 | Q62: {=_xlfn.XLOOKUP(G61,$T$7:$T$12,_xlfn.XLOOKUP(G63,$U$6:$Z$6,$U$7:$Z$12))} -> 0.95541409 | R62: Vol' | S62: =SQRT((M62*I61)^2+((1-M62)*I63)^2+2*M62*(1-M62)*Q62*I61*I63) -> 0.004309962 | T62: b | V62: =2*Q62*I61*I63-2*I63^2 -> -2.3668345e-05 | W62: =(-V62-SQRT(V62^2-4*V61*V63))/(2*V61) -> 0.31976853
G63: 5 | H63: {=_xlfn.XLOOKUP(Task1!$B$1,'Benchmark yields table'!$A$3:$A$599,_xlfn.XLOOKUP(G63,'Benchmark yields table'!$B$2:$I$2,'Benchmark yields table'!$B$3:$I$599))/100} -> 0.0721 | I63: {=_xlfn.XLOOKUP(Task1!$B$1,'Benchmark yields table'!$A$3:$A$599,_xlfn.XLOOKUP(G63,'Benchmark yields table'!$BF$2:$BM$2,'Benchmark yields table'!$BF$3:$BM$599))} -> 0.0050508639 | J63: =1/(1+H63)^G63 -> 0.70603059 | L63: =(1-M62)*K62 -> 204.06944 | N63: Pvdiff | P63: =ABS(P61-P62) -> 0.060896148 | R63: Voldiff | S63: =ABS(S61-S62) -> 0 | T63: c | V63: =I63^2-I62^2 -> 6.9354541e-06
F65: =1-((G66-G65)/(G67-G65)) -> 0.93369863 | G65: 5 | H65: {=_xlfn.XLOOKUP(Task1!$B$1,'Benchmark yields table'!$A$3:$A$599,_xlfn.XLOOKUP(G65,'Benchmark yields table'!$B$2:$I$2,'Benchmark yields table'!$B$3:$I$599))/100} -> 0.0721 | I65: {=_xlfn.XLOOKUP(Task1!$B$1,'Benchmark yields table'!$A$3:$A$599,_xlfn.XLOOKUP(G65,'Benchmark yields table'!$BF$2:$BM$2,'Benchmark yields table'!$BF$3:$BM$599))} -> 0.0050508639 | J65: =1/(1+H65)^G65 -> 0.70603059 | L65: =K66*M66 -> 278.78763 | M65: alfa | N65: PV= | P65: =K66*J66 -> 207.03818 | Q65: Korrel | R65: Vol | S65: =I66 -> 0.0053963644 | T65: a | V65: =I65^2+I67^2-2*Q66*I65*I67 -> 3.0934857e-05 | W65: =(-V66+SQRT(V66^2-4*V65*V67))/(2*V65) -> 2.6501888
G66: =C15 -> 5.3315068 | H66: =F65*H65+(1-F65)*H67 -> 0.072040329 | I66: =I65*F65+(1-F65)*I67 -> 0.0053963644 | J66: =1/(1+H66)^G66 -> 0.69012727 | K66: =Task1!F32 -> 300 | M66: =MIN(W65:W66) -> 0.92929209 | N66: PV'= | P66: =L65*J65+L67*J67 -> 207.4957 | Q66: {=_xlfn.XLOOKUP(G65,$T$7:$T$12,_xlfn.XLOOKUP(G67,$U$6:$Z$6,$U$7:$Z$12))} -> 0.96353862 | R66: Vol' | S66: =SQRT((M66*I65)^2+((1-M66)*I67)^2+2*M66*(1-M66)*Q66*I65*I67) -> 0.0053963644 | T66: b | V66: =2*Q66*I65*I67-2*I67^2 -> -0.00011073073 | W66: =(-V66-SQRT(V66^2-4*V65*V67))/(2*V65) -> 0.92929209
G67: 10 | H67: {=_xlfn.XLOOKUP(Task1!$B$1,'Benchmark yields table'!$A$3:$A$599,_xlfn.XLOOKUP(G67,'Benchmark yields table'!$B$2:$I$2,'Benchmark yields table'!$B$3:$I$599))/100} -> 0.0712 | I67: {=_xlfn.XLOOKUP(Task1!$B$1,'Benchmark yields table'!$A$3:$A$599,_xlfn.XLOOKUP(G67,'Benchmark yields table'!$BF$2:$BM$2,'Benchmark yields table'!$BF$3:$BM$599))} -> 0.010261925 | J67: =1/(1+H67)^G67 -> 0.50268319 | L67: =(1-M66)*K66 -> 21.212372 | N67: Pvdiff | P67: =ABS(P65-P66) -> 0.45751575 | R67: Voldiff | S67: =ABS(S65-S66) -> 2.6020852e-18 | T67: c | V67: =I67^2-I66^2 -> 7.6186351e-05
F69: =1-((G70-G69)/(G71-G69)) -> 0.73315068 | G69: 5 | H69: {=_xlfn.XLOOKUP(Task1!$B$1,'Benchmark yields table'!$A$3:$A$599,_xlfn.XLOOKUP(G69,'Benchmark yields table'!$B$2:$I$2,'Benchmark yields table'!$B$3:$I$599))/100} -> 0.0721 | I69: {=_xlfn.XLOOKUP(Task1!$B$1,'Benchmark yields table'!$A$3:$A$599,_xlfn.XLOOKUP(G69,'Benchmark yields table'!$BF$2:$BM$2,'Benchmark yields table'!$BF$3:$BM$599))} -> 0.0050508639 | J69: =1/(1+H69)^G69 -> 0.70603059 | L69: =K70*M70 -> 7435.5574 | M69: alfa | N69: PV= | P69: =K70*J70 -> 6636.4483 | Q69: Korrel | R69: Vol | S69: =I70 -> 0.0064414319 | T69: a | V69: =I69^2+I71^2-2*Q70*I69*I71 -> 3.0934857e-05 | W69: =(-V70+SQRT(V70^2-4*V69*V71))/(2*V69) -> 2.8575821
G70: =C16 -> 6.3342466 | H70: =F69*H69+(1-F69)*H71 -> 0.071859836 | I70: =I69*F69+(1-F69)*I71 -> 0.0064414319 | J70: =1/(1+H70)^G70 -> 0.64431537 | K70: =Task1!F33 -> 10300 | M70: =MIN(W69:W70) -> 0.72189878 | N70: PV'= | P70: =L69*J69+L71*J71 -> 6689.6381 | Q70: {=_xlfn.XLOOKUP(G69,$T$7:$T$12,_xlfn.XLOOKUP(G71,$U$6:$Z$6,$U$7:$Z$12))} -> 0.96353862 | R70: Vol' | S70: =SQRT((M70*I69)^2+((1-M70)*I71)^2+2*M70*(1-M70)*Q70*I69*I71) -> 0.0064414319 | T70: b | V70: =2*Q70*I69*I71-2*I71^2 -> -0.00011073073 | W70: =(-V70-SQRT(V70^2-4*V69*V71))/(2*V69) -> 0.72189878
G71: 10 | H71: {=_xlfn.XLOOKUP(Task1!$B$1,'Benchmark yields table'!$A$3:$A$599,_xlfn.XLOOKUP(G71,'Benchmark yields table'!$B$2:$I$2,'Benchmark yields table'!$B$3:$I$599))/100} -> 0.0712 | I71: {=_xlfn.XLOOKUP(Task1!$B$1,'Benchmark yields table'!$A$3:$A$599,_xlfn.XLOOKUP(G71,'Benchmark yields table'!$BF$2:$BM$2,'Benchmark yields table'!$BF$3:$BM$599))} -> 0.010261925 | J71: =1/(1+H71)^G71 -> 0.50268319 | L71: =(1-M70)*K70 -> 2864.4426 | N71: Pvdiff | P71: =ABS(P69-P70) -> 53.189811 | R71: Voldiff | S71: =ABS(S69-S70) -> 1.7347235e-18 | T71: c | V71: =I71^2-I70^2 -> 6.3815054e-05
F73: =Task1!F4 -> 2032/A | M73: 480
F74: =1-((G75-G74)/(G76-G74)) -> 0.81643836 | G74: 0.5 | H74: {=_xlfn.XLOOKUP(Task1!$B$1,'Benchmark yields table'!$A$3:$A$599,_xlfn.XLOOKUP(Task4!G74,'Benchmark yields table'!$B$2:$I$2,'Benchmark yields table'!$B$3:$I$599))/100} -> 0.0692 | I74: {=_xlfn.XLOOKUP(Task1!$B$1,'Benchmark yields table'!$A$3:$A$599,_xlfn.XLOOKUP(Task4!G74,'Benchmark yields table'!$BF$2:$BM$2,'Benchmark yields table'!$BF$3:$BM$599))} -> 0.00065051439 | J74: =1/(1+H74)^G74 -> 0.96709809 | L74: =K75*M75 -> 340.88917 | M74: alfa | N74: PV= | P74: =K75*J75 -> 456.57774 | Q74: Korrel | R74: Vol | S74: =I75 -> 0.0007524811 | T74: a | V74: =I74^2+I76^2-2*Q75*I74*I76 -> 7.3096559e-07 | W74: =(-V75+SQRT(V75^2-4*V74*V76))/(2*V74) -> 1.6931824
G75: =C17 -> 0.59178082 | H75: =F74*H74+(1-F74)*H76 -> 0.069126575 | I75: =F74*I74+(1-F74)*I76 -> 0.0007524811 | J75: =1/(1+H75)^G75 -> 0.96121629 | K75: =Task1!F36 -> 475 | M75: =MIN(W74:W75) -> 0.71766142 | N75: PV'= | P75: =L74*J74+L76*J76 -> 455.15121 | Q75: {=_xlfn.XLOOKUP(G74,$T$7:$T$12,_xlfn.XLOOKUP(G76,$U$6:$Z$6,$U$7:$Z$12))} -> 0.73079441 | R75: Vol' | S75: =SQRT((M75*I74)^2+((1-M75)*I76)^2+2*M75*(1-M75)*Q75*I74*I76) -> 0.0007524811 | T75: b | V75: =2*Q75*I74*I76-2*I76^2 -> -1.7622438e-06 | W75: =(-V75-SQRT(V75^2-4*V74*V76))/(2*V74) -> 0.71766142
G76: 1 | H76: {=_xlfn.XLOOKUP(Task1!$B$1,'Benchmark yields table'!$A$3:$A$599,_xlfn.XLOOKUP(Task4!G76,'Benchmark yields table'!$B$2:$I$2,'Benchmark yields table'!$B$3:$I$599))/100} -> 0.0688 | I76: {=_xlfn.XLOOKUP(Task1!$B$1,'Benchmark yields table'!$A$3:$A$599,_xlfn.XLOOKUP(Task4!G76,'Benchmark yields table'!$BF$2:$BM$2,'Benchmark yields table'!$BF$3:$BM$599))} -> 0.0012060047 | J76: =1/(1+H76)^G76 -> 0.93562874 | L76: =(1-M75)*K75 -> 134.11083 | N76: Pvdiff | P76: =ABS(P74-P75) -> 1.4265238 | R76: Voldiff | S76: =ABS(S74-S75) -> 0 | T76: c | V76: =I76^2-I75^2 -> 8.8821942e-07
F78: =1-((G79-G78)/(G80-G78)) -> 0.70410959 | G78: 1 | H78: {=_xlfn.XLOOKUP(Task1!$B$1,'Benchmark yields table'!$A$3:$A$599,_xlfn.XLOOKUP(G78,'Benchmark yields table'!$B$2:$I$2,'Benchmark yields table'!$B$3:$I$599))/100} -> 0.0688 | I78: {=_xlfn.XLOOKUP(Task1!$B$1,'Benchmark yields table'!$A$3:$A$599,_xlfn.XLOOKUP(G78,'Benchmark yields table'!$BF$2:$BM$2,'Benchmark yields table'!$BF$3:$BM$599))} -> 0.0012060047 | J78: =1/(1+H78)^G78 -> 0.93562874 | L78: =K79*M79 -> 289.41666 | M78: alfa | N78: PV= | P78: =K79*J79 -> 426.56876 | Q78: Korrel | R78: Vol | S78: =I79 -> 0.0016877812 | T78: a | V78: =I78^2+I80^2-2*Q79*I78*I80 -> 4.9402317e-06 | W78: =(-V79+SQRT(V79^2-4*V78*V80))/(2*V78) -> 1.7223029
G79: =C18 -> 1.5917808 | H79: =H78*F78+(1-F78)*H80 -> 0.069894795 | I79: =I78*F78+(1-F78)*I80 -> 0.0016877812 | J79: =1/(1+H79)^G79 -> 0.8980395 | K79: =Task1!F37 -> 475 | M79: =MIN(W78:W79) -> 0.60929824 | N79: PV'= | P79: =L78*J78+L80*J80 -> 421.22092 | Q79: {=_xlfn.XLOOKUP(G78,$T$7:$T$12,_xlfn.XLOOKUP(G80,$U$6:$Z$6,$U$7:$Z$12))} -> 0.66514828 | R79: Vol' | S79: =SQRT((M79*I78)^2+((1-M79)*I80)^2+2*M79*(1-M79)*Q79*I78*I80) -> 0.0016877812 | T79: b | V79: =2*Q79*I78*I80-2*I80^2 -> -1.151865e-05 | W79: =(-V79-SQRT(V79^2-4*V78*V80))/(2*V78) -> 0.60929824
G80: 3 | H80: {=_xlfn.XLOOKUP(Task1!$B$1,'Benchmark yields table'!$A$3:$A$599,_xlfn.XLOOKUP(G80,'Benchmark yields table'!$B$2:$I$2,'Benchmark yields table'!$B$3:$I$599))/100} -> 0.0725 | I80: {=_xlfn.XLOOKUP(Task1!$B$1,'Benchmark yields table'!$A$3:$A$599,_xlfn.XLOOKUP(G80,'Benchmark yields table'!$BF$2:$BM$2,'Benchmark yields table'!$BF$3:$BM$599))} -> 0.002834231 | J80: =1/(1+H80)^G80 -> 0.8106028 | L80: =(1-M79)*K79 -> 185.58334 | N80: Pvdiff | P80: =ABS(P78-P79) -> 5.3478432 | R80: Voldiff | S80: =ABS(S78-S79) -> 2.1684043e-19 | T80: c | V80: =I80^2-I79^2 -> 5.1842601e-06
F82: =1-((G83-G82)/(G84-G82)) -> 0.20410959 | G82: 1 | H82: {=_xlfn.XLOOKUP(Task1!$B$1,'Benchmark yields table'!$A$3:$A$599,_xlfn.XLOOKUP(G82,'Benchmark yields table'!$B$2:$I$2,'Benchmark yields table'!$B$3:$I$599))/100} -> 0.0688 | I82: {=_xlfn.XLOOKUP(Task1!$B$1,'Benchmark yields table'!$A$3:$A$599,_xlfn.XLOOKUP(G82,'Benchmark yields table'!$BF$2:$BM$2,'Benchmark yields table'!$BF$3:$BM$599))} -> 0.0012060047 | J82: =1/(1+H82)^G82 -> 0.93562874 | L82: =K83*M83 -> 78.726295 | M82: alfa | N82: PV= | P82: =K83*J83 -> 396.92033 | Q82: Korrel | R82: Vol | S82: =I83 -> 0.0025018944 | T82: a | V82: =I82^2+I84^2-2*Q83*I82*I84 -> 4.9402317e-06 | W82: =(-V83+SQRT(V83^2-4*V82*V84))/(2*V82) -> 2.1658616
G83: =C19 -> 2.5917808 | H83: =H82*F82+(1-F82)*H84 -> 0.071744795 | I83: =I82*F82+(1-F82)*I84 -> 0.0025018944 | J83: =1/(1+H83)^G83 -> 0.83562174 | K83: =Task1!F38 -> 475 | M83: =MIN(W82:W83) -> 0.16573957 | N83: PV'= | P83: =L82*J82+L84*J84 -> 394.87916 | Q83: {=_xlfn.XLOOKUP(G82,$T$7:$T$12,_xlfn.XLOOKUP(G84,$U$6:$Z$6,$U$7:$Z$12))} -> 0.66514828 | R83: Vol' | S83: =SQRT((M83*I82)^2+((1-M83)*I84)^2+2*M83*(1-M83)*Q83*I82*I84) -> 0.0025018944 | T83: b | V83: =2*Q83*I82*I84-2*I84^2 -> -1.151865e-05 | W83: =(-V83-SQRT(V83^2-4*V82*V84))/(2*V82) -> 0.16573957
G84: 3 | H84: {=_xlfn.XLOOKUP(Task1!$B$1,'Benchmark yields table'!$A$3:$A$599,_xlfn.XLOOKUP(G84,'Benchmark yields table'!$B$2:$I$2,'Benchmark yields table'!$B$3:$I$599))/100} -> 0.0725 | I84: {=_xlfn.XLOOKUP(Task1!$B$1,'Benchmark yields table'!$A$3:$A$599,_xlfn.XLOOKUP(G84,'Benchmark yields table'!$BF$2:$BM$2,'Benchmark yields table'!$BF$3:$BM$599))} -> 0.002834231 | J84: =1/(1+H84)^G84 -> 0.8106028 | L84: =(1-M83)*K83 -> 396.2737 | N84: Pvdiff | P84: =ABS(P82-P83) -> 2.0411695 | R84: Voldiff | S84: =ABS(S82-S83) -> 0 | T84: c | V84: =I84^2-I83^2 -> 1.7733899e-06
F86: =1-((G87-G86)/(G88-G86)) -> 0.70410959 | G86: 3 | H86: {=_xlfn.XLOOKUP(Task1!$B$1,'Benchmark yields table'!$A$3:$A$599,_xlfn.XLOOKUP(G86,'Benchmark yields table'!$B$2:$I$2,'Benchmark yields table'!$B$3:$I$599))/100} -> 0.0725 | I86: {=_xlfn.XLOOKUP(Task1!$B$1,'Benchmark yields table'!$A$3:$A$599,_xlfn.XLOOKUP(G86,'Benchmark yields table'!$BF$2:$BM$2,'Benchmark yields table'!$BF$3:$BM$599))} -> 0.002834231 | J86: =1/(1+H86)^G86 -> 0.8106028 | L86: =K87*M87 -> 326.06431 | M86: alfa | N86: PV= | P86: =K87*J87 -> 369.56031 | Q86: Korrel | R86: Vol | S86: =I87 -> 0.0034901115 | T86: a | V86: =I86^2+I88^2-2*Q87*I86*I88 -> 6.189984e-06 | W86: =(-V87+SQRT(V87^2-4*V86*V88))/(2*V86) -> 3.1372008
G87: =C20 -> 3.5917808 | H87: =F86*H86+(1-F86)*H88 -> 0.072381644 | I87: =I86*F86+(1-F86)*I88 -> 0.0034901115 | J87: =1/(1+H87)^G87 -> 0.7780217 | K87: =Task1!F39 -> 475 | M87: =MIN(W86:W87) -> 0.68645117 | N87: PV'= | P87: =L86*J86+L88*J88 -> 369.46179 | Q87: {=_xlfn.XLOOKUP(G86,$T$7:$T$12,_xlfn.XLOOKUP(G88,$U$6:$Z$6,$U$7:$Z$12))} -> 0.95541409 | R87: Vol' | S87: =SQRT((M87*I86)^2+((1-M87)*I88)^2+2*M87*(1-M87)*Q87*I86*I88) -> 0.0034901115 | T87: b | V87: =2*Q87*I86*I88-2*I88^2 -> -2.3668345e-05 | W87: =(-V87-SQRT(V87^2-4*V86*V88))/(2*V86) -> 0.68645117
G88: 5 | H88: {=_xlfn.XLOOKUP(Task1!$B$1,'Benchmark yields table'!$A$3:$A$599,_xlfn.XLOOKUP(G88,'Benchmark yields table'!$B$2:$I$2,'Benchmark yields table'!$B$3:$I$599))/100} -> 0.0721 | I88: {=_xlfn.XLOOKUP(Task1!$B$1,'Benchmark yields table'!$A$3:$A$599,_xlfn.XLOOKUP(G88,'Benchmark yields table'!$BF$2:$BM$2,'Benchmark yields table'!$BF$3:$BM$599))} -> 0.0050508639 | J88: =1/(1+H88)^G88 -> 0.70603059 | L88: =(1-M87)*K87 -> 148.93569 | N88: Pvdiff | P88: =ABS(P86-P87) -> 0.09851242 | R88: Voldiff | S88: =ABS(S86-S87) -> 4.3368087e-19 | T88: c | V88: =I88^2-I87^2 -> 1.3330348e-05
F90: =1-((G91-G90)/(G92-G90)) -> 0.20410959 | G90: 3 | H90: {=_xlfn.XLOOKUP(Task1!$B$1,'Benchmark yields table'!$A$3:$A$599,_xlfn.XLOOKUP(G90,'Benchmark yields table'!$B$2:$I$2,'Benchmark yields table'!$B$3:$I$599))/100} -> 0.0725 | I90: {=_xlfn.XLOOKUP(Task1!$B$1,'Benchmark yields table'!$A$3:$A$599,_xlfn.XLOOKUP(G90,'Benchmark yields table'!$BF$2:$BM$2,'Benchmark yields table'!$BF$3:$BM$599))} -> 0.002834231 | J90: =1/(1+H90)^G90 -> 0.8106028 | L90: =K91*M91 -> 92.306243 | M90: alfa | N90: PV= | P90: =K91*J91 -> 344.91168 | Q90: Korrel | R90: Vol | S90: =I91 -> 0.0045984279 | T90: a | V90: =I90^2+I92^2-2*Q91*I90*I92 -> 6.189984e-06 | W90: =(-V91+SQRT(V91^2-4*V90*V92))/(2*V90) -> 3.6293231
G91: =C21 -> 4.5917808 | H91: =F90*H90+(1-F90)*H92 -> 0.072181644 | I91: =I90*F90+(1-F90)*I92 -> 0.0045984279 | J91: =1/(1+H91)^G91 -> 0.72612985 | K91: =Task1!F40 -> 475 | M91: =MIN(W90:W91) -> 0.19432893 | N91: PV'= | P91: =L90*J90+L92*J92 -> 345.0172 | Q91: {=_xlfn.XLOOKUP(G90,$T$7:$T$12,_xlfn.XLOOKUP(G92,$U$6:$Z$6,$U$7:$Z$12))} -> 0.95541409 | R91: Vol' | S91: =SQRT((M91*I90)^2+((1-M91)*I92)^2+2*M91*(1-M91)*Q91*I90*I92) -> 0.0045984279 | T91: b | V91: =2*Q91*I90*I92-2*I92^2 -> -2.3668345e-05 | W91: =(-V91-SQRT(V91^2-4*V90*V92))/(2*V90) -> 0.19432893
G92: 5 | H92: {=_xlfn.XLOOKUP(Task1!$B$1,'Benchmark yields table'!$A$3:$A$599,_xlfn.XLOOKUP(G92,'Benchmark yields table'!$B$2:$I$2,'Benchmark yields table'!$B$3:$I$599))/100} -> 0.0721 | I92: {=_xlfn.XLOOKUP(Task1!$B$1,'Benchmark yields table'!$A$3:$A$599,_xlfn.XLOOKUP(G92,'Benchmark yields table'!$BF$2:$BM$2,'Benchmark yields table'!$BF$3:$BM$599))} -> 0.0050508639 | J92: =1/(1+H92)^G92 -> 0.70603059 | L92: =(1-M91)*K91 -> 382.69376 | N92: Pvdiff | P92: =ABS(P90-P91) -> 0.10552042 | R92: Voldiff | S92: =ABS(S90-S91) -> 0 | T92: c | V92: =I92^2-I91^2 -> 4.3656872e-06
F94: =1-((G95-G94)/(G96-G94)) -> 0.88164384 | G94: 5 | H94: {=_xlfn.XLOOKUP(Task1!$B$1,'Benchmark yields table'!$A$3:$A$599,_xlfn.XLOOKUP(G94,'Benchmark yields table'!$B$2:$I$2,'Benchmark yields table'!$B$3:$I$599))/100} -> 0.0721 | I94: {=_xlfn.XLOOKUP(Task1!$B$1,'Benchmark yields table'!$A$3:$A$599,_xlfn.XLOOKUP(G94,'Benchmark yields table'!$BF$2:$BM$2,'Benchmark yields table'!$BF$3:$BM$599))} -> 0.0050508639 | J94: =1/(1+H94)^G94 -> 0.70603059 | L94: =K95*M95 -> 415.45915 | M94: alfa | N94: PV= | P94: =K95*J95 -> 322.00733 | Q94: Korrel | R94: Vol | S94: =I95 -> 0.0056676251 | T94: a | V94: =I94^2+I96^2-2*Q95*I94*I96 -> 3.0934857e-05 | W94: =(-V95+SQRT(V95^2-4*V94*V96))/(2*V94) -> 2.70483
G95: =C22 -> 5.5917808 | H95: =F94*H94+(1-F94)*H96 -> 0.071993479 | I95: =I94*F94+(1-F94)*I96 -> 0.0056676251 | J95: =1/(1+H95)^G95 -> 0.67791017 | K95: =Task1!F41 -> 475 | M95: =MIN(W94:W95) -> 0.87465085 | N95: PV'= | P95: =L94*J94+L96*J96 -> 323.25706 | Q95: {=_xlfn.XLOOKUP(G94,$T$7:$T$12,_xlfn.XLOOKUP(G96,$U$6:$Z$6,$U$7:$Z$12))} -> 0.96353862 | R95: Vol' | S95: =SQRT((M95*I94)^2+((1-M95)*I96)^2+2*M95*(1-M95)*Q95*I94*I96) -> 0.0056676251 | T95: b | V95: =2*Q95*I94*I96-2*I96^2 -> -0.00011073073 | W95: =(-V95-SQRT(V95^2-4*V94*V96))/(2*V94) -> 0.87465085
G96: 10 | H96: {=_xlfn.XLOOKUP(Task1!$B$1,'Benchmark yields table'!$A$3:$A$599,_xlfn.XLOOKUP(G96,'Benchmark yields table'!$B$2:$I$2,'Benchmark yields table'!$B$3:$I$599))/100} -> 0.0712 | I96: {=_xlfn.XLOOKUP(Task1!$B$1,'Benchmark yields table'!$A$3:$A$599,_xlfn.XLOOKUP(G96,'Benchmark yields table'!$BF$2:$BM$2,'Benchmark yields table'!$BF$3:$BM$599))} -> 0.010261925 | J96: =1/(1+H96)^G96 -> 0.50268319 | L96: =(1-M95)*K95 -> 59.540845 | N96: Pvdiff | P96: =ABS(P94-P95) -> 1.2497241 | R96: Voldiff | S96: =ABS(S94-S95) -> 8.6736174e-19 | T96: c | V96: =I96^2-I95^2 -> 7.3185125e-05
F98: =1-((G99-G98)/(G100-G98)) -> 0.68164384 | G98: 5 | H98: {=_xlfn.XLOOKUP(Task1!$B$1,'Benchmark yields table'!$A$3:$A$599,_xlfn.XLOOKUP(G98,'Benchmark yields table'!$B$2:$I$2,'Benchmark yields table'!$B$3:$I$599))/100} -> 0.0721 | I98: {=_xlfn.XLOOKUP(Task1!$B$1,'Benchmark yields table'!$A$3:$A$599,_xlfn.XLOOKUP(G98,'Benchmark yields table'!$BF$2:$BM$2,'Benchmark yields table'!$BF$3:$BM$599))} -> 0.0050508639 | J98: =1/(1+H98)^G98 -> 0.70603059 | L98: =K99*M99 -> 318.12832 | M98: alfa | N98: PV= | P98: =K99*J99 -> 300.71449 | Q98: Korrel | R98: Vol | S98: =I99 -> 0.0067098373 | T98: a | V98: =I98^2+I100^2-2*Q99*I98*I100 -> 3.0934857e-05 | W98: =(-V99+SQRT(V99^2-4*V98*V100))/(2*V98) -> 2.909737
G99: =C23 -> 6.5917808 | H99: =F98*H98+(1-F98)*H100 -> 0.071813479 | I99: =I98*F98+(1-F98)*I100 -> 0.0067098373 | J99: =1/(1+H99)^G99 -> 0.63308313 | K99: =Task1!F42 -> 475 | M99: =MIN(W98:W99) -> 0.66974384 | N99: PV'= | P99: =L98*J98+L100*J100 -> 303.46508 | Q99: {=_xlfn.XLOOKUP(G98,$T$7:$T$12,_xlfn.XLOOKUP(G100,$U$6:$Z$6,$U$7:$Z$12))} -> 0.96353862 | R99: Vol' | S99: =SQRT((M99*I98)^2+((1-M99)*I100)^2+2*M99*(1-M99)*Q99*I98*I100) -> 0.0067098373 | T99: b | V99: =2*Q99*I98*I100-2*I100^2 -> -0.00011073073 | W99: =(-V99-SQRT(V99^2-4*V98*V100))/(2*V98) -> 0.66974384
G100: 10 | H100: {=_xlfn.XLOOKUP(Task1!$B$1,'Benchmark yields table'!$A$3:$A$599,_xlfn.XLOOKUP(G100,'Benchmark yields table'!$B$2:$I$2,'Benchmark yields table'!$B$3:$I$599))/100} -> 0.0712 | I100: {=_xlfn.XLOOKUP(Task1!$B$1,'Benchmark yields table'!$A$3:$A$599,_xlfn.XLOOKUP(G100,'Benchmark yields table'!$BF$2:$BM$2,'Benchmark yields table'!$BF$3:$BM$599))} -> 0.010261925 | J100: =1/(1+H100)^G100 -> 0.50268319 | L100: =(1-M99)*K99 -> 156.87168 | N100: Pvdiff | P100: =ABS(P98-P99) -> 2.7505975 | R100: Voldiff | S100: =ABS(S98-S99) -> 0 | T100: c | V100: =I100^2-I99^2 -> 6.0285184e-05
F102: =1-((G103-G102)/(G104-G102)) -> 0.48164384 | G102: 5 | H102: {=_xlfn.XLOOKUP(Task1!$B$1,'Benchmark yields table'!$A$3:$A$599,_xlfn.XLOOKUP(G102,'Benchmark yields table'!$B$2:$I$2,'Benchmark yields table'!$B$3:$I$599))/100} -> 0.0721 | I102: {=_xlfn.XLOOKUP(Task1!$B$1,'Benchmark yields table'!$A$3:$A$599,_xlfn.XLOOKUP(G102,'Benchmark yields table'!$BF$2:$BM$2,'Benchmark yields table'!$BF$3:$BM$599))} -> 0.0050508639 | J102: =1/(1+H102)^G102 -> 0.70603059 | L102: =K103*M103 -> 223.26685 | M102: alfa | N102: PV= | P102: =K103*J103 -> 280.92403 | Q102: Korrel | R102: Vol | S102: =I103 -> 0.0077520494 | T102: a | V102: =I102^2+I104^2-2*Q103*I102*I104 -> 3.0934857e-05 | W102: =(-V103+SQRT(V103^2-4*V102*V104))/(2*V102) -> 3.1094454
G103: =C24 -> 7.5917808 | H103: =F102*H102+(1-F102)*H104 -> 0.071633479 | I103: =I102*F102+(1-F102)*I104 -> 0.0077520494 | J103: =1/(1+H103)^G103 -> 0.59141901 | K103: =Task1!F43 -> 475 | M103: =MIN(W102:W103) -> 0.47003547 | N103: PV'= | P103: =L102*J102+L104*J104 -> 284.17525 | Q103: {=_xlfn.XLOOKUP(G102,$T$7:$T$12,_xlfn.XLOOKUP(G104,$U$6:$Z$6,$U$7:$Z$12))} -> 0.96353862 | R103: Vol' | S103: =SQRT((M103*I102)^2+((1-M103)*I104)^2+2*M103*(1-M103)*Q103*I102*I104) -> 0.0077520494 | T103: b | V103: =2*Q103*I102*I104-2*I104^2 -> -0.00011073073 | W103: =(-V103-SQRT(V103^2-4*V102*V104))/(2*V102) -> 0.47003547
G104: 10 | H104: {=_xlfn.XLOOKUP(Task1!$B$1,'Benchmark yields table'!$A$3:$A$599,_xlfn.XLOOKUP(G104,'Benchmark yields table'!$B$2:$I$2,'Benchmark yields table'!$B$3:$I$599))/100} -> 0.0712 | I104: {=_xlfn.XLOOKUP(Task1!$B$1,'Benchmark yields table'!$A$3:$A$599,_xlfn.XLOOKUP(G104,'Benchmark yields table'!$BF$2:$BM$2,'Benchmark yields table'!$BF$3:$BM$599))} -> 0.010261925 | J104: =1/(1+H104)^G104 -> 0.50268319 | L104: =(1-M103)*K103 -> 251.73315 | N104: Pvdiff | P104: =ABS(P102-P103) -> 3.2512185 | R104: Voldiff | S104: =ABS(S102-S103) -> 1.7347235e-18 | T104: c | V104: =I104^2-I103^2 -> 4.5212829e-05
F106: =1-((G107-G106)/(G108-G106)) -> 0.28054795 | G106: 5 | H106: {=_xlfn.XLOOKUP(Task1!$B$1,'Benchmark yields table'!$A$3:$A$599,_xlfn.XLOOKUP(G106,'Benchmark yields table'!$B$2:$I$2,'Benchmark yields table'!$B$3:$I$599))/100} -> 0.0721 | I106: {=_xlfn.XLOOKUP(Task1!$B$1,'Benchmark yields table'!$A$3:$A$599,_xlfn.XLOOKUP(G106,'Benchmark yields table'!$BF$2:$BM$2,'Benchmark yields table'!$BF$3:$BM$599))} -> 0.0050508639 | J106: =1/(1+H106)^G106 -> 0.70603059 | L106: =K107*M107 -> 2853.3851 | M106: alfa | N106: PV= | P106: =K107*J107 -> 5787.2073 | Q106: Korrel | R106: Vol | S106: =I107 -> 0.0087999723 | T106: a | V106: =I106^2+I108^2-2*Q107*I106*I108 -> 3.0934857e-05 | W106: =(-V107+SQRT(V107^2-4*V106*V108))/(2*V106) -> 3.3070813
G107: =C25 -> 8.5972603 | H107: =F106*H106+(1-F106)*H108 -> 0.071452493 | I107: =I106*F106+(1-F106)*I108 -> 0.0087999723 | J107: =1/(1+H107)^G107 -> 0.55247802 | K107: =Task1!F44 -> 10475 | M107: =MIN(W106:W107) -> 0.27239953 | N107: PV'= | P107: =L106*J106+L108*J108 -> 5845.8348 | Q107: {=_xlfn.XLOOKUP(G106,$T$7:$T$12,_xlfn.XLOOKUP(G108,$U$6:$Z$6,$U$7:$Z$12))} -> 0.96353862 | R107: Vol' | S107: =SQRT((M107*I106)^2+((1-M107)*I108)^2+2*M107*(1-M107)*Q107*I106*I108) -> 0.0087999723 | T107: b | V107: =2*Q107*I106*I108-2*I108^2 -> -0.00011073073 | W107: =(-V107-SQRT(V107^2-4*V106*V108))/(2*V106) -> 0.27239953
G108: 10 | H108: {=_xlfn.XLOOKUP(Task1!$B$1,'Benchmark yields table'!$A$3:$A$599,_xlfn.XLOOKUP(G108,'Benchmark yields table'!$B$2:$I$2,'Benchmark yields table'!$B$3:$I$599))/100} -> 0.0712 | I108: {=_xlfn.XLOOKUP(Task1!$B$1,'Benchmark yields table'!$A$3:$A$599,_xlfn.XLOOKUP(G108,'Benchmark yields table'!$BF$2:$BM$2,'Benchmark yields table'!$BF$3:$BM$599))} -> 0.010261925 | J108: =1/(1+H108)^G108 -> 0.50268319 | L108: =(1-M107)*K107 -> 7621.6149 | N108: Pvdiff | P108: =ABS(P106-P107) -> 58.627543 | R108: Voldiff | S108: =ABS(S106-S107) -> 1.7347235e-18 | T108: c | V108: =I108^2-I107^2 -> 2.7867586e-05

Sheet Extra Question
E6: To determine how much of our bond portfolio's VaR is attributable to market risk versus credit risk, we need to use separate models for each type of risk. However, these market and credit risk are in some cases correlated, therefore, it would be better if our risk models incorporate a measure of this correlation as well.
E7: Since all assets are bonds, market risk would be primarity driven by changes in interest rates. We can allocate a proportional amount of total VaR to each bond based on its sensitivity to interest rate movement.
E8: On the other hand, the Credit Risk Model should incorporate changes in credit spreads, issuer-specific credit events, changes in the creditworthiness of the bond issuers. For this, we need to assess the probability of default of the bond issuer, the exposure at the time of default, and the loss given default.

Sheet Benchmark yields table
A1: Date | B1: 3 month | C1: 6 month | D1: 12 month | E1: 3 year | F1: 5 year | G1: 10 year | H1: 15 year | I1: 20 year | J1: Yield change with continuous compounding | R1: Yield change with discrete compounding | Z1: Volatility of yields | AH1: Volatility of | AI1: =J1 -> Yield change with continuous compounding | AP1: Volatility of | AQ1: =R1 -> Yield change with discrete compounding | AX1: Bond price volatility using | AY1: =AI1 -> Yield change with continuous compounding | BF1: Bond price volatility using | BG1: =AQ1 -> Yield change with discrete compounding
B2: =3/12 -> 0.25 | C2: =6/12 -> 0.5 | D2: 1 | E2: 3 | F2: 5 | G2: 10 | H2: 15 | I2: 20 | J2: =3/12 -> 0.25 | K2: =6/12 -> 0.5 | L2: 1 | M2: 3 | N2: 5 | O2: 10 | P2: 15 | Q2: 20 | R2: =3/12 -> 0.25 | S2: =6/12 -> 0.5 | T2: 1 | U2: 3 | V2: 5 | W2: 10 | X2: 15 | Y2: 20 | Z2: =B2 -> 0.25 | AA2: =C2 -> 0.5 | AB2: =D2 -> 1 | AC2: =E2 -> 3 | AD2: =F2 -> 5 | AE2: =G2 -> 10 | AF2: =H2 -> 15 | AG2: =I2 -> 20 | AH2: =Z2 -> 0.25 | AI2: =AA2 -> 0.5 | AJ2: =AB2 -> 1 | AK2: =AC2 -> 3 | AL2: =AD2 -> 5 | AM2: =AE2 -> 10 | AN2: =AF2 -> 15 | AO2: =AG2 -> 20 | ... BM2: =BE2 -> 20 | BN2: Korrel(0,5;1) | BO2: korrel1,3 | BP2: korrel3,5
A3: 45428 | B3: 6.71 | C3: 6.75 | D3: 6.78 | E3: 6.71 | F3: 6.6 | G3: 6.59 | H3: 6.6 | I3: 6.62 | J3: =B4/100-B3/100 -> -0.0001 | K3: =C4/100-C3/100 -> 0 | L3: =D4/100-D3/100 -> -0.0002 | M3: =E4/100-E3/100 -> 0 | N3: =F4/100-F3/100 -> 0.0001 | O3: =G4/100-G3/100 -> 0.0004 | P3: =H4/100-H3/100 -> 0.0004 | Q3: =I4/100-I3/100 -> 0.0004 | R3: =LN((1+B4/100)/(1+B3/100)) -> -9.3716321e-05 | S3: =LN((1+C4/100)/(1+C3/100)) -> 0 | T3: =LN((1+D4/100)/(1+D3/100)) -> -0.00018731854 | U3: =LN((1+E4/100)/(1+E3/100)) -> 0 | V3: =LN((1+F4/100)/(1+F3/100)) -> 9.3804231e-05 | W3: =LN((1+G4/100)/(1+G3/100)) -> 0.00037519933 | X3: =LN((1+H4/100)/(1+H3/100)) -> 0.00037516414 | Y3: =LN((1+I4/100)/(1+I3/100)) -> 0.00037509378 | Z3: =STDEVA(B3:B255)/100 -> 0.020387058 | AA3: =STDEVA(C3:C255)/100 -> 0.020410836 | AB3: =STDEVA(D3:D255)/100 -> 0.019163291 | AC3: =STDEVA(E3:E255)/100 -> 0.011899573 | AD3: =STDEVA(F3:F255)/100 -> 0.0083390973 | AE3: =STDEVA(G3:G255)/100 -> 0.0055505911 | AF3: =STDEVA(H3:H255)/100 -> 0.0046010196 | AG3: =STDEVA(I3:I255)/100 -> 0.0045302255 | AH3: =STDEVA(J3:J255) -> 0.0020427959 | AI3: =STDEVA(K3:K255) -> 0.0014376399 | AJ3: =STDEVA(L3:L255) -> 0.001315699 | AK3: =STDEVA(M3:M255) -> 0.00098136617 | AL3: =STDEVA(N3:N255) -> 0.0010525911 | AM3: =STDEVA(O3:O255) -> 0.001077413 | AN3: =STDEVA(P3:P255) -> 0.0010224163 | AO3: =STDEVA(Q3:Q255) -> 0.0010191182 | ... AW3: =STDEVA(Y3:Y255) -> 0.00095374455 | AX3: =AX$2*AH3 -> 0.00051069898 | AY3: =AY$2*AI3 -> 0.00071881995 | AZ3: =AZ$2*AJ3 -> 0.001315699 | BA3: =BA$2*AK3 -> 0.0029440985 | BB3: =BB$2*AL3 -> 0.0052629557 | BC3: =BC$2*AM3 -> 0.01077413 | BD3: =BD$2*AN3 -> 0.015336244 | BE3: =BE$2*AO3 -> 0.020382364 | ... BM3: =BM$2*AW3 -> 0.019074891 | BN3: =CORREL(S3:S255,T3:T255) -> 0.56287467 | BO3: =CORREL(T3:T255,U3:U255) -> 0.2135193 | BP3: =CORREL(U3:U255,V3:V255) -> 0.93431817
A4: 45427 | B4: 6.7 | C4: 6.75 | D4: 6.76 | E4: 6.71 | F4: 6.61 | G4: 6.63 | H4: 6.64 | I4: 6.66 | J4: =B5/100-B4/100 -> 0.0001 | K4: =C5/100-C4/100 -> -0.0019 | L4: =D5/100-D4/100 -> 0.0002 | M4: =E5/100-E4/100 -> 0.001 | N4: =F5/100-F4/100 -> 0.0009 | O4: =G5/100-G4/100 -> 0.001 | P4: =H5/100-H4/100 -> 0.0009 | Q4: =I5/100-I4/100 -> 0.001 | R4: =LN((1+B5/100)/(1+B4/100)) -> 9.3716321e-05 | S4: =LN((1+C5/100)/(1+C4/100)) -> -0.0017814453 | T4: =LN((1+D5/100)/(1+D4/100)) -> 0.00018731854 | U4: =LN((1+E5/100)/(1+E4/100)) -> 0.00093668047 | V4: =LN((1+F5/100)/(1+F4/100)) -> 0.00084384235 | W4: =LN((1+G5/100)/(1+G4/100)) -> 0.0009373829 | X4: =LN((1+H5/100)/(1+H4/100)) -> 0.00084360506 | Y4: =LN((1+I5/100)/(1+I4/100)) -> 0.00093711936 | Z4: =STDEVA(B4:B256)/100 -> 0.020697977 | AA4: =STDEVA(C4:C256)/100 -> 0.020726297 | AB4: =STDEVA(D4:D256)/100 -> 0.019481151 | AC4: =STDEVA(E4:E256)/100 -> 0.011963209 | AD4: =STDEVA(F4:F256)/100 -> 0.0083885336 | AE4: =STDEVA(G4:G256)/100 -> 0.0055730407 | AF4: =STDEVA(H4:H256)/100 -> 0.0046136505 | AG4: =STDEVA(I4:I256)/100 -> 0.004539792 | AH4: =STDEVA(J4:J256) -> 0.00204265 | AI4: =STDEVA(K4:K256) -> 0.0014375592 | AJ4: =STDEVA(L4:L256) -> 0.0013154605 | AK4: =STDEVA(M4:M256) -> 0.00098149082 | AL4: =STDEVA(N4:N256) -> 0.0010525911 | AM4: =STDEVA(O4:O256) -> 0.0010772179 | AN4: =STDEVA(P4:P256) -> 0.0010221636 | AO4: =STDEVA(Q4:Q256) -> 0.0010188516 | ... AW4: =STDEVA(Y4:Y256) -> 0.0009534939 | AX4: =AX$2*AH4 -> 0.00051066251 | AY4: =AY$2*AI4 -> 0.00071877958 | AZ4: =AZ$2*AJ4 -> 0.0013154605 | BA4: =BA$2*AK4 -> 0.0029444725 | BB4: =BB$2*AL4 -> 0.0052629557 | BC4: =BC$2*AM4 -> 0.010772179 | BD4: =BD$2*AN4 -> 0.015332454 | BE4: =BE$2*AO4 -> 0.020377032 | ... BM4: =BM$2*AW4 -> 0.019069878 | BN4: =CORREL(S4:S256,T4:T256) -> 0.56279982 | BO4: =CORREL(T4:T256,U4:U256) -> 0.21357853 | BP4: =CORREL(U4:U256,V4:V256) -> 0.93424272
A5: 45426 | B5: 6.71 | C5: 6.56 | D5: 6.78 | E5: 6.81 | F5: 6.7 | G5: 6.73 | H5: 6.73 | I5: 6.76 | J5: =B6/100-B5/100 -> 0.0001 | K5: =C6/100-C5/100 -> 0.0001 | L5: =D6/100-D5/100 -> 0.0002 | M5: =E6/100-E5/100 -> 0.0005 | N5: =F6/100-F5/100 -> 0.0008 | O5: =G6/100-G5/100 -> 0.0009 | P5: =H6/100-H5/100 -> 0.0011 | Q5: =I6/100-I5/100 -> 0.001 | R5: =LN((1+B6/100)/(1+B5/100)) -> 9.3707539e-05 | S5: =LN((1+C6/100)/(1+C5/100)) -> 9.3839441e-05 | T5: =LN((1+D6/100)/(1+D5/100)) -> 0.00018728345 | U5: =LN((1+E6/100)/(1+E5/100)) -> 0.00046801143 | V5: =LN((1+F6/100)/(1+F5/100)) -> 0.00074948476 | W5: =LN((1+G6/100)/(1+G5/100)) -> 0.00084289399 | X5: =LN((1+H6/100)/(1+H5/100)) -> 0.0010301073 | Y5: =LN((1+I6/100)/(1+I5/100)) -> 0.00093624199 | Z5: =STDEVA(B5:B257)/100 -> 0.02100414 | AA5: =STDEVA(C5:C257)/100 -> 0.021038146 | AB5: =STDEVA(D5:D257)/100 -> 0.019795702 | AC5: =STDEVA(E5:E257)/100 -> 0.012028122 | AD5: =STDEVA(F5:F257)/100 -> 0.008437898 | AE5: =STDEVA(G5:G257)/100 -> 0.0055952404 | AF5: =STDEVA(H5:H257)/100 -> 0.004627329 | AG5: =STDEVA(I5:I257)/100 -> 0.0045498896 | AH5: =STDEVA(J5:J257) -> 0.0020426988 | AI5: =STDEVA(K5:K257) -> 0.0014307877 | AJ5: =STDEVA(L5:L257) -> 0.0013155049 | AK5: =STDEVA(M5:M257) -> 0.00098022194 | AL5: =STDEVA(N5:N257) -> 0.0010513065 | AM5: =STDEVA(O5:O257) -> 0.00107553 | AN5: =STDEVA(P5:P257) -> 0.0010211251 | AO5: =STDEVA(Q5:Q257) -> 0.0010174428 | ... AW5: =STDEVA(Y5:Y257) -> 0.00095216623 | AX5: =AX$2*AH5 -> 0.0005106747 | AY5: =AY$2*AI5 -> 0.00071539386 | AZ5: =AZ$2*AJ5 -> 0.0013155049 | BA5: =BA$2*AK5 -> 0.0029406658 | BB5: =BB$2*AL5 -> 0.0052565324 | BC5: =BC$2*AM5 -> 0.0107553 | BD5: =BD$2*AN5 -> 0.015316877 | BE5: =BE$2*AO5 -> 0.020348855 | ... BM5: =BM$2*AW5 -> 0.019043325 | BN5: =CORREL(S5:S257,T5:T257) -> 0.56517987 | BO5: =CORREL(T5:T257,U5:U257) -> 0.21431458 | BP5: =CORREL(U5:U257,V5:V257) -> 0.93385435
A6: 45425 | B6: 6.72 | C6: 6.57 | D6: 6.8 | E6: 6.86 | F6: 6.78 | G6: 6.82 | H6: 6.84 | I6: 6.86 | J6: =B7/100-B6/100 -> 0.0004 | K6: =C7/100-C6/100 -> -0.0001 | L6: =D7/100-D6/100 -> -0.0001 | M6: =E7/100-E6/100 -> -0.0002 | N6: =F7/100-F6/100 -> -0.0003 | O6: =G7/100-G6/100 -> -0.0004 | P6: =H7/100-H6/100 -> -0.0005 | Q6: =I7/100-I6/100 -> -0.0005 | R6: =LN((1+B7/100)/(1+B6/100)) -> 0.00037474237 | S6: =LN((1+C7/100)/(1+C6/100)) -> -9.3839441e-05 | T6: =LN((1+D7/100)/(1+D6/100)) -> -9.3637343e-05 | U6: =LN((1+E7/100)/(1+E6/100)) -> -0.00018717829 | V6: =LN((1+F7/100)/(1+F6/100)) -> -0.00028099096 | W6: =LN((1+G7/100)/(1+G6/100)) -> -0.00037453184 | X6: =LN((1+H7/100)/(1+H6/100)) -> -0.00046809906 | Y6: =LN((1+I7/100)/(1+I6/100)) -> -0.00046801143 | Z6: =STDEVA(B6:B258)/100 -> 0.021301953 | AA6: =STDEVA(C6:C258)/100 -> 0.021338457 | AB6: =STDEVA(D6:D258)/100 -> 0.020107284 | AC6: =STDEVA(E6:E258)/100 -> 0.012097996 | AD6: =STDEVA(F6:F258)/100 -> 0.0084885985 | AE6: =STDEVA(G6:G258)/100 -> 0.0056191235 | AF6: =STDEVA(H6:H258)/100 -> 0.0046447591 | AG6: =STDEVA(I6:I258)/100 -> 0.0045634071 | AH6: =STDEVA(J6:J258) -> 0.0020426695 | AI6: =STDEVA(K6:K258) -> 0.0014309642 | AJ6: =STDEVA(L6:L258) -> 0.0013155037 | AK6: =STDEVA(M6:M258) -> 0.00098022194 | AL6: =STDEVA(N6:N258) -> 0.0010505089 | AM6: =STDEVA(O6:O258) -> 0.0010744014 | AN6: =STDEVA(P6:P258) -> 0.0010195303 | AO6: =STDEVA(Q6:Q258) -> 0.0010162334 | ... AW6: =STDEVA(Y6:Y258) -> 0.00095102592 | AX6: =AX$2*AH6 -> 0.00051066737 | AY6: =AY$2*AI6 -> 0.00071548211 | AZ6: =AZ$2*AJ6 -> 0.0013155037 | BA6: =BA$2*AK6 -> 0.0029406658 | BB6: =BB$2*AL6 -> 0.0052525444 | BC6: =BC$2*AM6 -> 0.010744014 | BD6: =BD$2*AN6 -> 0.015292954 | BE6: =BE$2*AO6 -> 0.020324669 | ... BM6: =BM$2*AW6 -> 0.019020518 | BN6: =CORREL(S6:S258,T6:T258) -> 0.56499787 | BO6: =CORREL(T6:T258,U6:U258) -> 0.21452437 | BP6: =CORREL(U6:U258,V6:V258) -> 0.93397711
A7: 45422 | B7: 6.76 | C7: 6.56 | D7: 6.79 | E7: 6.84 | F7: 6.75 | G7: 6.78 | H7: 6.79 | I7: 6.81 | J7: =B8/100-B7/100 -> -0.0001 | K7: =C8/100-C7/100 -> 0 | L7: =D8/100-D7/100 -> 0.0001 | M7: =E8/100-E7/100 -> 0.0001 | N7: =F8/100-F7/100 -> -0.0001 | O7: =G8/100-G7/100 -> -0.0001 | P7: =H8/100-H7/100 -> 0 | Q7: =I8/100-I7/100 -> -0.0001 | R7: =LN((1+B8/100)/(1+B7/100)) -> -9.3672428e-05 | S7: =LN((1+C8/100)/(1+C7/100)) -> 0 | T7: =LN((1+D8/100)/(1+D7/100)) -> 9.3637343e-05 | U7: =LN((1+E8/100)/(1+E7/100)) -> 9.3593523e-05 | V7: =LN((1+F8/100)/(1+F7/100)) -> -9.3681203e-05 | W7: =LN((1+G8/100)/(1+G7/100)) -> -9.3654882e-05 | X7: =LN((1+H8/100)/(1+H7/100)) -> 0 | Y7: =LN((1+I8/100)/(1+I7/100)) -> -9.3628576e-05 | Z7: =STDEVA(B7:B259)/100 -> 0.021593928 | AA7: =STDEVA(C7:C259)/100 -> 0.021629177 | AB7: =STDEVA(D7:D259)/100 -> 0.020414879 | AC7: =STDEVA(E7:E259)/100 -> 0.012171268 | AD7: =STDEVA(F7:F259)/100 -> 0.0085423222 | AE7: =STDEVA(G7:G259)/100 -> 0.0056458031 | AF7: =STDEVA(H7:H259)/100 -> 0.0046661073 | AG7: =STDEVA(I7:I259)/100 -> 0.0045802322 | AH7: =STDEVA(J7:J259) -> 0.0020428154 | AI7: =STDEVA(K7:K259) -> 0.0014307409 | AJ7: =STDEVA(L7:L259) -> 0.0013152747 | AK7: =STDEVA(M7:M259) -> 0.00098093534 | AL7: =STDEVA(N7:N259) -> 0.0010507709 | AM7: =STDEVA(O7:O259) -> 0.0010740532 | AN7: =STDEVA(P7:P259) -> 0.0010189855 | AO7: =STDEVA(Q7:Q259) -> 0.0010156954 | ... AW7: =STDEVA(Y7:Y259) -> 0.00095052236 | AX7: =AX$2*AH7 -> 0.00051070384 | AY7: =AY$2*AI7 -> 0.00071537046 | AZ7: =AZ$2*AJ7 -> 0.0013152747 | BA7: =BA$2*AK7 -> 0.002942806 | BB7: =BB$2*AL7 -> 0.0052538544 | BC7: =BC$2*AM7 -> 0.010740532 | BD7: =BD$2*AN7 -> 0.015284783 | BE7: =BE$2*AO7 -> 0.020313908 | ... BM7: =BM$2*AW7 -> 0.019010447 | BN7: =CORREL(S7:S259,T7:T259) -> 0.56485578 | BO7: =CORREL(T7:T259,U7:U259) -> 0.21379592 | BP7: =CORREL(U7:U259,V7:V259) -> 0.93397519
A8: 45421 | B8: 6.75 | C8: 6.56 | D8: 6.8 | E8: 6.85 | F8: 6.74 | G8: 6.77 | H8: 6.79 | I8: 6.8 | J8: =B9/100-B8/100 -> 0 | K8: =C9/100-C8/100 -> -0.0001 | L8: =D9/100-D8/100 -> -0.0009 | M8: =E9/100-E8/100 -> -0.0007 | N8: =F9/100-F8/100 -> -0.0008 | O8: =G9/100-G8/100 -> -0.0015 | P8: =H9/100-H8/100 -> -0.0015 | Q8: =I9/100-I8/100 -> -0.0014 | R8: =LN((1+B9/100)/(1+B8/100)) -> 0 | S8: =LN((1+C9/100)/(1+C8/100)) -> -9.3848247e-05 | T8: =LN((1+D9/100)/(1+D8/100)) -> -0.0008430519 | U8: =LN((1+E9/100)/(1+E8/100)) -> -0.00065533869 | V8: =LN((1+F9/100)/(1+F8/100)) -> -0.00074976573 | W8: =LN((1+G9/100)/(1+G8/100)) -> -0.0014058768 | X8: =LN((1+H9/100)/(1+H8/100)) -> -0.0014056133 | Y8: =LN((1+I9/100)/(1+I8/100)) -> -0.0013117214 | Z8: =STDEVA(B8:B260)/100 -> 0.021878068 | AA8: =STDEVA(C8:C260)/100 -> 0.021913182 | AB8: =STDEVA(D8:D260)/100 -> 0.020715366 | AC8: =STDEVA(E8:E260)/100 -> 0.012248276 | AD8: =STDEVA(F8:F260)/100 -> 0.008599043 | AE8: =STDEVA(G8:G260)/100 -> 0.0056724327 | AF8: =STDEVA(H8:H260)/100 -> 0.0046869626 | AG8: =STDEVA(I8:I260)/100 -> 0.0045967518 | AH8: =STDEVA(J8:J260) -> 0.0020426698 | AI8: =STDEVA(K8:K260) -> 0.0014309731 | AJ8: =STDEVA(L8:L260) -> 0.0013154576 | AK8: =STDEVA(M8:M260) -> 0.00098108547 | AL8: =STDEVA(N8:N260) -> 0.0010507709 | AM8: =STDEVA(O8:O260) -> 0.0010741231 | AN8: =STDEVA(P8:P260) -> 0.0010190871 | AO8: =STDEVA(Q8:Q260) -> 0.0010156655 | ... AW8: =STDEVA(Y8:Y260) -> 0.00095049432 | AX8: =AX$2*AH8 -> 0.00051066745 | AY8: =AY$2*AI8 -> 0.00071548654 | AZ8: =AZ$2*AJ8 -> 0.0013154576 | BA8: =BA$2*AK8 -> 0.0029432564 | BB8: =BB$2*AL8 -> 0.0052538544 | BC8: =BC$2*AM8 -> 0.010741231 | BD8: =BD$2*AN8 -> 0.015286306 | BE8: =BE$2*AO8 -> 0.020313309 | ... BM8: =BM$2*AW8 -> 0.019009886 | BN8: =CORREL(S8:S260,T8:T260) -> 0.56498498 | BO8: =CORREL(T8:T260,U8:U260) -> 0.21339958 | BP8: =CORREL(U8:U260,V8:V260) -> 0.93364816
A9: 45420 | B9: 6.75 | C9: 6.55 | D9: 6.71 | E9: 6.78 | F9: 6.66 | G9: 6.62 | H9: 6.64 | I9: 6.66 | J9: =B10/100-B9/100 -> 0.0001 | K9: =C10/100-C9/100 -> 0 | L9: =D10/100-D9/100 -> 0.0001 | M9: =E10/100-E9/100 -> 0.0007 | N9: =F10/100-F9/100 -> 0.0006 | O9: =G10/100-G9/100 -> 0.0003 | P9: =H10/100-H9/100 -> 0.0002 | Q9: =I10/100-I9/100 -> 0.0001 | R9: =LN((1+B10/100)/(1+B9/100)) -> 9.3672428e-05 | S9: =LN((1+C10/100)/(1+C9/100)) -> 0 | T9: =LN((1+D10/100)/(1+D9/100)) -> 9.3707539e-05 | U9: =LN((1+E10/100)/(1+E9/100)) -> 0.00065533869 | V9: =LN((1+F10/100)/(1+F9/100)) -> 0.00056237699 | W9: =LN((1+G10/100)/(1+G9/100)) -> 0.00028133352 | X9: =LN((1+H10/100)/(1+H9/100)) -> 0.0001875293 | Y9: =LN((1+I10/100)/(1+I9/100)) -> 9.3751465e-05 | Z9: =STDEVA(B9:B261)/100 -> 0.022156269 | AA9: =STDEVA(C9:C261)/100 -> 0.022186837 | AB9: =STDEVA(D9:D261)/100 -> 0.021006405 | AC9: =STDEVA(E9:E261)/100 -> 0.0123268 | AD9: =STDEVA(F9:F261)/100 -> 0.0086538782 | AE9: =STDEVA(G9:G261)/100 -> 0.005697368 | AF9: =STDEVA(H9:H261)/100 -> 0.0047063585 | AG9: =STDEVA(I9:I261)/100 -> 0.004613009 | AH9: =STDEVA(J9:J261) -> 0.0020428252 | AI9: =STDEVA(K9:K261) -> 0.0014307302 | AJ9: =STDEVA(L9:L261) -> 0.001313278 | AK9: =STDEVA(M9:M261) -> 0.00098006944 | AL9: =STDEVA(N9:N261) -> 0.0010493792 | AM9: =STDEVA(O9:O261) -> 0.0010704897 | AN9: =STDEVA(P9:P261) -> 0.0010148712 | AO9: =STDEVA(Q9:Q261) -> 0.0010117701 | ... AW9: =STDEVA(Y9:Y261) -> 0.00094683952 | AX9: =AX$2*AH9 -> 0.0005107063 | AY9: =AY$2*AI9 -> 0.00071536509 | AZ9: =AZ$2*AJ9 -> 0.001313278 | BA9: =BA$2*AK9 -> 0.0029402083 | BB9: =BB$2*AL9 -> 0.0052468961 | BC9: =BC$2*AM9 -> 0.010704897 | BD9: =BD$2*AN9 -> 0.015223068 | BE9: =BE$2*AO9 -> 0.020235402 | ... BM9: =BM$2*AW9 -> 0.01893679 | BN9: =CORREL(S9:S261,T9:T261) -> 0.56495424 | BO9: =CORREL(T9:T261,U9:U261) -> 0.21075877 | BP9: =CORREL(U9:U261,V9:V261) -> 0.93335254
A10: 45419 | B10: 6.76 | C10: 6.55 | D10: 6.72 | E10: 6.85 | F10: 6.72 | G10: 6.65 | H10: 6.66 | I10: 6.67 | J10: =B11/100-B10/100 -> -0.0002 | K10: =C11/100-C10/100 -> 0 | L10: =D11/100-D10/100 -> 0.0001 | M10: =E11/100-E10/100 -> 0.0013 | N10: =F11/100-F10/100 -> 0.0012 | O10: =G11/100-G10/100 -> 0.0005 | P10: =H11/100-H10/100 -> 0.0006 | Q10: =I11/100-I10/100 -> 0.0006 | R10: =LN((1+B11/100)/(1+B10/100)) -> -0.00018735363 | S10: =LN((1+C11/100)/(1+C10/100)) -> 0 | T10: =LN((1+D11/100)/(1+D10/100)) -> 9.3698759e-05 | U10: =LN((1+E11/100)/(1+E10/100)) -> 0.0012159193 | V10: =LN((1+F11/100)/(1+F10/100)) -> 0.0011238061 | W10: =LN((1+G11/100)/(1+G10/100)) -> 0.00046871339 | X10: =LN((1+H11/100)/(1+H10/100)) -> 0.00056237699 | Y10: =LN((1+I11/100)/(1+I10/100)) -> 0.00056232429 | Z10: =STDEVA(B10:B262)/100 -> 0.022424937 | AA10: =STDEVA(C10:C262)/100 -> 0.022455362 | AB10: =STDEVA(D10:D262)/100 -> 0.021290242 | AC10: =STDEVA(E10:E262)/100 -> 0.01239927 | AD10: =STDEVA(F10:F262)/100 -> 0.0087056808 | AE10: =STDEVA(G10:G262)/100 -> 0.0057162731 | AF10: =STDEVA(H10:H262)/100 -> 0.0047212872 | AG10: =STDEVA(I10:I262)/100 -> 0.0046263752 | AH10: =STDEVA(J10:J262) -> 0.0020427961 | AI10: =STDEVA(K10:K262) -> 0.0014320273 | AJ10: =STDEVA(L10:L262) -> 0.00131377 | AK10: =STDEVA(M10:M262) -> 0.00098019618 | AL10: =STDEVA(N10:N262) -> 0.0010491263 | AM10: =STDEVA(O10:O262) -> 0.0010707266 | AN10: =STDEVA(P10:P262) -> 0.0010150343 | AO10: =STDEVA(Q10:Q262) -> 0.0010121243 | ... AW10: =STDEVA(Y10:Y262) -> 0.00094716739 | AX10: =AX$2*AH10 -> 0.00051069902 | AY10: =AY$2*AI10 -> 0.00071601363 | AZ10: =AZ$2*AJ10 -> 0.00131377 | BA10: =BA$2*AK10 -> 0.0029405885 | BB10: =BB$2*AL10 -> 0.0052456315 | BC10: =BC$2*AM10 -> 0.010707266 | BD10: =BD$2*AN10 -> 0.015225514 | BE10: =BE$2*AO10 -> 0.020242485 | ... BM10: =BM$2*AW10 -> 0.018943348 | BN10: =CORREL(S10:S262,T10:T262) -> 0.56536935 | BO10: =CORREL(T10:T262,U10:U262) -> 0.21213916 | BP10: =CORREL(U10:U262,V10:V262) -> 0.93320944
A11: 45418 | B11: 6.74 | C11: 6.55 | D11: 6.73 | E11: 6.98 | F11: 6.84 | G11: 6.7 | H11: 6.72 | I11: 6.73 | J11: =B12/100-B11/100 -> 0.0002 | K11: =C12/100-C11/100 -> 0.0015 | L11: =D12/100-D11/100 -> 0.0004 | M11: =E12/100-E11/100 -> 0.001 | N11: =F12/100-F11/100 -> 0.0011 | O11: =G12/100-G11/100 -> 0.0009 | P11: =H12/100-H11/100 -> 0.0009 | Q11: =I12/100-I11/100 -> 0.0008 | R11: =LN((1+B12/100)/(1+B11/100)) -> 0.00018735363 | S11: =LN((1+C12/100)/(1+C11/100)) -> 0.0014067998 | T11: =LN((1+D12/100)/(1+D11/100)) -> 0.00037470726 | U11: =LN((1+E12/100)/(1+E11/100)) -> 0.00093431755 | V11: =LN((1+F12/100)/(1+F11/100)) -> 0.0010290473 | W11: =LN((1+G12/100)/(1+G11/100)) -> 0.00084313088 | X11: =LN((1+H12/100)/(1+H11/100)) -> 0.00084297293 | Y11: =LN((1+I12/100)/(1+I11/100)) -> 0.00074927418 | Z11: =STDEVA(B11:B263)/100 -> 0.022688784 | AA11: =STDEVA(C11:C263)/100 -> 0.022709066 | AB11: =STDEVA(D11:D263)/100 -> 0.02156311 | AC11: =STDEVA(E11:E263)/100 -> 0.012468406 | AD11: =STDEVA(F11:F263)/100 -> 0.0087554489 | AE11: =STDEVA(G11:G263)/100 -> 0.0057332582 | AF11: =STDEVA(H11:H263)/100 -> 0.0047347417 | AG11: =STDEVA(I11:I263)/100 -> 0.004637712 | AH11: =STDEVA(J11:J263) -> 0.0020437269 | AI11: =STDEVA(K11:K263) -> 0.0014319068 | AJ11: =STDEVA(L11:L263) -> 0.0013138474 | AK11: =STDEVA(M11:M263) -> 0.00097758603 | AL11: =STDEVA(N11:N263) -> 0.0010467249 | AM11: =STDEVA(O11:O263) -> 0.0010707266 | AN11: =STDEVA(P11:P263) -> 0.0010148318 | AO11: =STDEVA(Q11:Q263) -> 0.0010117551 | ... AW11: =STDEVA(Y11:Y263) -> 0.00094681704 | AX11: =AX$2*AH11 -> 0.00051093173 | AY11: =AY$2*AI11 -> 0.00071595338 | AZ11: =AZ$2*AJ11 -> 0.0013138474 | BA11: =BA$2*AK11 -> 0.0029327581 | BB11: =BB$2*AL11 -> 0.0052336246 | BC11: =BC$2*AM11 -> 0.010707266 | BD11: =BD$2*AN11 -> 0.015222477 | BE11: =BE$2*AO11 -> 0.020235101 | ... BM11: =BM$2*AW11 -> 0.018936341 | BN11: =CORREL(S11:S263,T11:T263) -> 0.56532809 | BO11: =CORREL(T11:T263,U11:U263) -> 0.21373144 | BP11: =CORREL(U11:U263,V11:V263) -> 0.93278004
A12: 45415 | B12: 6.76 | C12: 6.7 | D12: 6.77 | E12: 7.08 | F12: 6.95 | G12: 6.79 | H12: 6.81 | I12: 6.81 | J12: =B13/100-B12/100 -> 0.0008 | K12: =C13/100-C12/100 -> 0.001 | L12: =D13/100-D12/100 -> 0.001 | M12: =E13/100-E12/100 -> 0.0009 | N12: =F13/100-F12/100 -> 0.0013 | O12: =G13/100-G12/100 -> 0.0014 | P12: =H13/100-H12/100 -> 0.0013 | Q12: =I13/100-I12/100 -> 0.0012 | R12: =LN((1+B13/100)/(1+B12/100)) -> 0.00074906371 | S12: =LN((1+C13/100)/(1+C12/100)) -> 0.00093676822 | T12: =LN((1+D13/100)/(1+D12/100)) -> 0.00093615435 | U12: =LN((1+E13/100)/(1+E12/100)) -> 0.00084014007 | V12: =LN((1+F13/100)/(1+F12/100)) -> 0.0012147831 | W12: =LN((1+G13/100)/(1+G12/100)) -> 0.0013101256 | X12: =LN((1+H13/100)/(1+H12/100)) -> 0.0012163744 | Y12: =LN((1+I13/100)/(1+I12/100)) -> 0.0011228597 | Z12: =STDEVA(B12:B264)/100 -> 0.022937143 | AA12: =STDEVA(C12:C264)/100 -> 0.022957568 | AB12: =STDEVA(D12:D264)/100 -> 0.021828619 | AC12: =STDEVA(E12:E264)/100 -> 0.012537924 | AD12: =STDEVA(F12:F264)/100 -> 0.0088059368 | AE12: =STDEVA(G12:G264)/100 -> 0.0057533991 | AF12: =STDEVA(H12:H264)/100 -> 0.0047514988 | AG12: =STDEVA(I12:I264)/100 -> 0.0046516525 | AH12: =STDEVA(J12:J264) -> 0.0020438035 | AI12: =STDEVA(K12:K264) -> 0.0014304805 | AJ12: =STDEVA(L12:L264) -> 0.0013150669 | AK12: =STDEVA(M12:M264) -> 0.00097619881 | AL12: =STDEVA(N12:N264) -> 0.0010448336 | AM12: =STDEVA(O12:O264) -> 0.0010695588 | AN12: =STDEVA(P12:P264) -> 0.0010137101 | AO12: =STDEVA(Q12:Q264) -> 0.0010113491 | ... AW12: =STDEVA(Y12:Y264) -> 0.00094642765 | AX12: =AX$2*AH12 -> 0.00051095088 | AY12: =AY$2*AI12 -> 0.00071524027 | AZ12: =AZ$2*AJ12 -> 0.0013150669 | BA12: =BA$2*AK12 -> 0.0029285964 | BB12: =BB$2*AL12 -> 0.0052241682 | BC12: =BC$2*AM12 -> 0.010695588 | BD12: =BD$2*AN12 -> 0.015205651 | BE12: =BE$2*AO12 -> 0.020226982 | ... BM12: =BM$2*AW12 -> 0.018928553 | BN12: =CORREL(S12:S264,T12:T264) -> 0.56630395 | BO12: =CORREL(T12:T264,U12:U264) -> 0.21439374 | BP12: =CORREL(U12:U264,V12:V264) -> 0.93256359
A13: 45414 | B13: 6.84 | C13: 6.8 | D13: 6.87 | E13: 7.17 | F13: 7.08 | G13: 6.93 | H13: 6.94 | I13: 6.93 | J13: =B14/100-B13/100 -> 0.0001 | K13: =C14/100-C13/100 -> 0.0005 | L13: =D14/100-D13/100 -> 0 | M13: =E14/100-E13/100 -> 0.0007 | N13: =F14/100-F13/100 -> 0.0009 | O13: =G14/100-G13/100 -> 0.001 | P13: =H14/100-H13/100 -> 0.001 | Q13: =I14/100-I13/100 -> 0.0012 | R13: =LN((1+B14/100)/(1+B13/100)) -> 9.3593523e-05 | S13: =LN((1+C14/100)/(1+C13/100)) -> 0.00046805524 | T13: =LN((1+D14/100)/(1+D13/100)) -> 0 | U13: =LN((1+E14/100)/(1+E13/100)) -> 0.00065295464 | V13: =LN((1+F14/100)/(1+F13/100)) -> 0.00084014007 | W13: =LN((1+G14/100)/(1+G13/100)) -> 0.00093475423 | X13: =LN((1+H14/100)/(1+H13/100)) -> 0.00093466686 | Y13: =LN((1+I14/100)/(1+I13/100)) -> 0.0011216003 | Z13: =STDEVA(B13:B265)/100 -> 0.023179656 | AA13: =STDEVA(C13:C265)/100 -> 0.023201776 | AB13: =STDEVA(D13:D265)/100 -> 0.022082022 | AC13: =STDEVA(E13:E265)/100 -> 0.012606843 | AD13: =STDEVA(F13:F265)/100 -> 0.0088552013 | AE13: =STDEVA(G13:G265)/100 -> 0.0057726947 | AF13: =STDEVA(H13:H265)/100 -> 0.0047667696 | AG13: =STDEVA(I13:I265)/100 -> 0.0046632602 | AH13: =STDEVA(J13:J265) -> 0.0020436408 | AI13: =STDEVA(K13:K265) -> 0.0014299497 | AJ13: =STDEVA(L13:L265) -> 0.0013150635 | AK13: =STDEVA(M13:M265) -> 0.00097510482 | AL13: =STDEVA(N13:N265) -> 0.001044383 | AM13: =STDEVA(O13:O265) -> 0.0010678275 | AN13: =STDEVA(P13:P265) -> 0.0010117036 | AO13: =STDEVA(Q13:Q265) -> 0.0010118302 | ... AW13: =STDEVA(Y13:Y265) -> 0.0009468442 | AX13: =AX$2*AH13 -> 0.0005109102 | AY13: =AY$2*AI13 -> 0.00071497487 | AZ13: =AZ$2*AJ13 -> 0.0013150635 | BA13: =BA$2*AK13 -> 0.0029253145 | BB13: =BB$2*AL13 -> 0.0052219152 | BC13: =BC$2*AM13 -> 0.010678275 | BD13: =BD$2*AN13 -> 0.015175554 | BE13: =BE$2*AO13 -> 0.020236605 | ... BM13: =BM$2*AW13 -> 0.018936884 | BN13: =CORREL(S13:S265,T13:T265) -> 0.56591465 | BO13: =CORREL(T13:T265,U13:U265) -> 0.21228958 | BP13: =CORREL(U13:U265,V13:V265) -> 0.93150567
A14: 45412 | B14: 6.85 | C14: 6.85 | D14: 6.87 | E14: 7.24 | F14: 7.17 | G14: 7.03 | H14: 7.04 | I14: 7.05 | J14: =B15/100-B14/100 -> -0.0001 | K14: =C15/100-C14/100 -> 0 | L14: =D15/100-D14/100 -> 0.0001 | M14: =E15/100-E14/100 -> 0.0001 | N14: =F15/100-F14/100 -> 0 | O14: =G15/100-G14/100 -> 0.0001 | P14: =H15/100-H14/100 -> 0.0001 | Q14: =I15/100-I14/100 -> 0 | R14: =LN((1+B15/100)/(1+B14/100)) -> -9.3593523e-05 | S14: =LN((1+C15/100)/(1+C14/100)) -> 0 | T14: =LN((1+D15/100)/(1+D14/100)) -> 9.3567252e-05 | U14: =LN((1+E15/100)/(1+E14/100)) -> 9.324444e-05 | V14: =LN((1+F15/100)/(1+F14/100)) -> 0 | W14: =LN((1+G15/100)/(1+G14/100)) -> 9.3427384e-05 | X14: =LN((1+H15/100)/(1+H14/100)) -> 9.3418656e-05 | Y14: =LN((1+I15/100)/(1+I14/100)) -> 0 | Z14: =STDEVA(B14:B266)/100 -> 0.023418434 | AA14: =STDEVA(C14:C266)/100 -> 0.023442894 | AB14: =STDEVA(D14:D266)/100 -> 0.022327996 | AC14: =STDEVA(E14:E266)/100 -> 0.012678925 | AD14: =STDEVA(F14:F266)/100 -> 0.0089123989 | AE14: =STDEVA(G14:G266)/100 -> 0.0057978481 | AF14: =STDEVA(H14:H266)/100 -> 0.0047862262 | AG14: =STDEVA(I14:I266)/100 -> 0.0046812772 | AH14: =STDEVA(J14:J266) -> 0.0020436881 | AI14: =STDEVA(K14:K266) -> 0.0014299099 | AJ14: =STDEVA(L14:L266) -> 0.0013149304 | AK14: =STDEVA(M14:M266) -> 0.00099744922 | AL14: =STDEVA(N14:N266) -> 0.0010571738 | AM14: =STDEVA(O14:O266) -> 0.0010773364 | AN14: =STDEVA(P14:P266) -> 0.0010167156 | AO14: =STDEVA(Q14:Q266) -> 0.001012311 | ... AW14: =STDEVA(Y14:Y266) -> 0.00094725899 | AX14: =AX$2*AH14 -> 0.00051092202 | AY14: =AY$2*AI14 -> 0.00071495496 | AZ14: =AZ$2*AJ14 -> 0.0013149304 | BA14: =BA$2*AK14 -> 0.0029923477 | BB14: =BB$2*AL14 -> 0.0052858692 | BC14: =BC$2*AM14 -> 0.010773364 | BD14: =BD$2*AN14 -> 0.015250735 | BE14: =BE$2*AO14 -> 0.02024622 | ... BM14: =BM$2*AW14 -> 0.01894518 | BN14: =CORREL(S14:S266,T14:T266) -> 0.56612014 | BO14: =CORREL(T14:T266,U14:U266) -> 0.20823108 | BP14: =CORREL(U14:U266,V14:V266) -> 0.93259921
... A599: 44564 | B599: 2.18 | C599: 2.62 | D599: 3.58 | E599: 4.17 | F599: 4.35 | G599: 4.46 | H599: 4.68 | I599: 4.69 | J599: =B600/100-B599/100 -> -0.0218 | K599: =C600/100-C599/100 -> -0.0262 | L599: =D600/100-D599/100 -> -0.0358 | M599: =E600/100-E599/100 -> -0.0417 | N599: =F600/100-F599/100 -> -0.0435 | O599: =G600/100-G599/100 -> -0.0446 | P599: =H600/100-H599/100 -> -0.0468 | Q599: =I600/100-I599/100 -> -0.0469 | R599: =LN((1+B600/100)/(1+B599/100)) -> -0.021565778 | S599: =LN((1+C600/100)/(1+C599/100)) -> -0.02586266 | T599: =LN((1+D600/100)/(1+D599/100)) -> -0.035174075 | U599: =LN((1+E600/100)/(1+E599/100)) -> -0.040853994 | V599: =LN((1+F600/100)/(1+F599/100)) -> -0.042580448 | W599: =LN((1+G600/100)/(1+G599/100)) -> -0.043634037 | X599: =LN((1+H600/100)/(1+H599/100)) -> -0.045737892 | Y599: =LN((1+I600/100)/(1+I599/100)) -> -0.045833416 | Z599: =STDEVA(B599:B851)/100 -> #DIV/0! | AA599: =STDEVA(C599:C851)/100 -> #DIV/0! | AB599: =STDEVA(D599:D851)/100 -> #DIV/0! | AC599: =STDEVA(E599:E851)/100 -> #DIV/0! | AD599: =STDEVA(F599:F851)/100 -> #DIV/0! | AE599: =STDEVA(G599:G851)/100 -> #DIV/0! | AF599: =STDEVA(H599:H851)/100 -> #DIV/0! | AG599: =STDEVA(I599:I851)/100 -> #DIV/0! | AH599: =STDEVA(J599:J851) -> #DIV/0! | AI599: =STDEVA(K599:K851) -> #DIV/0! | AJ599: =STDEVA(L599:L851) -> #DIV/0! | AK599: =STDEVA(M599:M851) -> #DIV/0! | AL599: =STDEVA(N599:N851) -> #DIV/0! | AM599: =STDEVA(O599:O851) -> #DIV/0! | AN599: =STDEVA(P599:P851) -> #DIV/0! | AO599: =STDEVA(Q599:Q851) -> #DIV/0! | ... AW599: =STDEVA(Y599:Y851) -> #DIV/0! | AX599: =AX$2*AH599 -> #DIV/0! | AY599: =AY$2*AI599 -> #DIV/0! | AZ599: =AZ$2*AJ599 -> #DIV/0! | BA599: =BA$2*AK599 -> #DIV/0! | BB599: =BB$2*AL599 -> #DIV/0! | BC599: =BC$2*AM599 -> #DIV/0! | BD599: =BD$2*AN599 -> #DIV/0! | BE599: =BE$2*AO599 -> #DIV/0! | ... BM599: =BM$2*AW599 -> #DIV/0! | BN599: =CORREL(S599:S851,T599:T851) -> #DIV/0! | BO599: =CORREL(T599:T851,U599:U851) -> #DIV/0! | BP599: =CORREL(U599:U851,V599:V851) -> #DIV/0!

Sheet BENCHMARK_240517172308
A1: Date | B1: Settle Date | C1: Tenor | D1: Name | E1: Isin | F1: Maturity Date | G1: Yield | H1: Change | I1: Avg Bid | J1: Avg Ask | K1: Net Price | L1: Accrued Interest
A2: 45428 | B2: 45433 | C2: 15Y | D2: 2038/A | E2: HU0000403555 | F2: 50705 | G2: 6.6 | H2: -0.04 | I2: 6.68 | J2: 6.53 | K2: 67.113 | L2: 1.6967
A3: 45428 | B3: 45433 | C3: 20Y | D3: 2041/A | E3: HU0000404165 | F3: 51616 | G3: 6.62 | H3: -0.04 | I3: 6.7 | J3: 6.55 | K3: 63.7856 | L3: 0.2137
A4: 45428 | B4: 45433 | C4: 5Y | D4: 2029/A | E4: HU0000404603 | F4: 47261 | G4: 6.6 | H4: -0.01 | I4: 6.67 | J4: 6.53 | K4: 80.9173 | L4: 1.9891
A5: 45428 | B5: 45433 | C5: 3Y | D5: 2026/H | E5: HU0000406160 | F5: 46316 | G5: 6.71 | H5: 0 | I5: 6.78 | J5: 6.63 | K5: 105.9675 | L5: 5.5287
A6: 45428 | B6: 45433 | C6: 3M | D6: D240821 | E6: HU0000524830 | F6: 45525 | G6: 6.71 | H6: 0.01 | I6: 6.85 | J6: 6.56 | K6: 98.3141 | L6: 0
A7: 45428 | B7: 45433 | C7: 10Y | D7: 2035/A | E7: HU0000406624 | F7: 49606 | G7: 6.59 | H7: -0.04 | I7: 6.67 | J7: 6.52 | K7: 103.1488 | L7: 4.8027
A8: 45428 | B8: 45433 | C8: 6M | D8: D241223 | E8: HU0000525019 | F8: 45649 | G8: 6.75 | H8: 0 | I8: 6.89 | J8: 6.6 | K8: 96.1076 | L8: 0
A9: 45428 | B9: 45433 | C9: 12M | D9: D250430 | E9: HU0000525068 | F9: 45777 | G9: 6.78 | H9: 0.02 | I9: 6.92 | J9: 6.64 | K9: 93.9155 | L9: 0
A10: 45427 | B10: 45429 | C10: 15Y | D10: 2038/A | E10: HU0000403555 | F10: 50705 | G10: 6.64 | H10: -0.09 | I10: 6.71 | J10: 6.56 | K10: 66.8148 | L10: 1.6639
A11: 45427 | B11: 45429 | C11: 20Y | D11: 2041/A | E11: HU0000404165 | F11: 51616 | G11: 6.66 | H11: -0.1 | I11: 6.74 | J11: 6.59 | K11: 63.4757 | L11: 0.1808
A12: 45427 | B12: 45429 | C12: 5Y | D12: 2029/A | E12: HU0000404603 | F12: 47261 | G12: 6.61 | H12: -0.09 | I12: 6.69 | J12: 6.54 | K12: 80.8449 | L12: 1.9672
A13: 45427 | B13: 45429 | C13: 3Y | D13: 2026/H | E13: HU0000406160 | F13: 46316 | G13: 6.71 | H13: -0.1 | I13: 6.78 | J13: 6.63 | K13: 105.9922 | L13: 5.4249
... A4777: 44564 | B4777: 44566 | C4777: 12M | D4777: D221228 | E4777: HU0000523956 | F4777: 44923 | G4777: 3.58 | H4777: 0.01 | I4777: 3.65 | J4777: 3.5 | K4777: 96.5763 | L4777: 0

Sheet zero-coupon-yields_202405171536
A1: Date | B1: Day | C1: Year | D1: Yield (%)
A2: 45404 | B2: 7 | C2: 0.0192 | D2: 7.053
A3: 45404 | B3: 14 | C3: 0.0384 | D3: 7.0549
A4: 45404 | B4: 21 | C4: 0.0575 | D4: 7.0567
A5: 45404 | B5: 28 | C5: 0.0767 | D5: 7.0585
A6: 45404 | B6: 35 | C6: 0.0959 | D6: 7.0603
A7: 45404 | B7: 42 | C7: 0.1151 | D7: 7.0621
A8: 45404 | B8: 49 | C8: 0.1342 | D8: 7.0638
A9: 45404 | B9: 56 | C9: 0.1534 | D9: 7.0656
A10: 45404 | B10: 63 | C10: 0.1726 | D10: 7.0674
A11: 45404 | B11: 70 | C11: 0.1918 | D11: 7.0691
A12: 45404 | B12: 77 | C12: 0.211 | D12: 7.0709
A13: 45404 | B13: 84 | C13: 0.2301 | D13: 7.0726
... A1411: 45404 | B1411: 9867 | C1411: 27.0329 | D1411: 6.9202

Sheet zero-coupon-yields_202405172251
A1: Date | B1: Day | C1: Year | D1: Yield (%)
A2: 44851 | B2: 7 | C2: 0.0192 | D2: 13.2761
A3: 44851 | B3: 14 | C3: 0.0384 | D3: 13.2913
A4: 44851 | B4: 21 | C4: 0.0575 | D4: 13.3064
A5: 44851 | B5: 28 | C5: 0.0767 | D5: 13.3215
A6: 44851 | B6: 35 | C6: 0.0959 | D6: 13.3365
A7: 44851 | B7: 42 | C7: 0.1151 | D7: 13.3514
A8: 44851 | B8: 49 | C8: 0.1342 | D8: 13.3662
A9: 44851 | B9: 56 | C9: 0.1534 | D9: 13.381
A10: 44851 | B10: 63 | C10: 0.1726 | D10: 13.3957
A11: 44851 | B11: 70 | C11: 0.1918 | D11: 13.4103
A12: 44851 | B12: 77 | C12: 0.211 | D12: 13.4248
A13: 44851 | B13: 84 | C13: 0.2301 | D13: 13.4393
... A1490: 44851 | B1490: 10420 | C1490: 28.5479 | D1490: 8.5038
