Workbook

Sheet Individual purchase
C5: 2025 | D5: =+C5+1 -> 2026 | E5: =+D5+1 -> 2027 | F5: =+E5+1 -> 2028 | G5: =+F5+1 -> 2029 | H5: =+G5+1 -> 2030
B6: IC boy | C6: 12000
B7: dIC | C7: 1350 | D7: 1150 | E7: 1100
B8: ROIC=Noplat/IC boy | C8: 0.15
B9: RONIC | D9: 0.17 | E9: 0.165 | F9: 0.16 | G9: 0.15 | H9: 0.15
B10: K=dIC/Noplat | F10: 0.33 | G10: 0.33 | H10: 0.33
B11: Debt/IC boy | C11: 0 | D11: 0.05 | E11: 0.1 | F11: 0.15 | G11: 0.2 | H11: 0.2
B12: rD | D12: 0.07 | E12: 0.07 | F12: 0.07 | G12: 0.07 | H12: 0.07
B13: rA | C13: 0.12 | D13: 0.12 | E13: 0.12 | F13: 0.12 | G13: 0.12 | H13: 0.12
B14: t | C14: 0.2 | D14: 0.2 | E14: 0.2 | F14: 0.2 | G14: 0.2 | H14: 0.2
B15: Moving costs/IC eoy | H15: 0.1
B19: Balance sheet | H19: boy | I19: eoy 2030 | J19: boy 2031
B20: =+B6 -> IC boy | C20: =+C6 -> 12000 | D20: =+C20+C43 -> 13350 | E20: =+D20+D43 -> 14500 | F20: =+E20+E43 -> 15600 | G20: =+F20+F43 -> 16390.432 | H20: =+G20+G43 -> 17219.991 | I20: =+H20+H42*H10 -> 18090.613 | J20: 0
B21: BV D boy | C21: =+C20*C11 -> 0 | D21: =+D20*D11 -> 667.5 | E21: =+E20*E11 -> 1450 | F21: =+F20*F11 -> 2340 | G21: =+G20*G11 -> 3278.0865 | H21: =+H20*H11 -> 3443.9983 | I21: 0 | J21: 0
B22: BV E boy | C22: =+C20-C21 -> 12000 | D22: =+D20-D21 -> 12682.5 | E22: =+E20-E21 -> 13050 | F22: =+F20-F21 -> 13260 | G22: =+G20-G21 -> 13112.346 | H22: =+H20-H21 -> 13775.993 | I22: =+I20-I21 -> 18090.613 | J22: 0
B24: effective tax rate | C24: 0.2 | D24: 0.2 | E24: 0.2 | F24: 0.2 | G24: 0.2 | H24: 0.2
B25: effective tax calculated | C25: =+C34/C33 -> 0.2 | D25: =+D34/D33 -> 0.2 | E25: =+E34/E33 -> 0.2 | F25: =+F34/F33 -> 0.2 | G25: =+G34/G33 -> 0.2 | H25: =+H34/H33 -> 0.2
B27: Sales
B28: Other Income | I28: =+I20*0.9 -> 16281.552
B29: Expenses
B30: Other expense | I30: =+I20 -> 18090.613
B31: EBIT | C31: =+C42/(1-C24) -> 2250 | D31: =+D42/(1-D24) -> 2536.875 | E31: =+E42/(1-E24) -> 2774.0625 | F31: =+F42/(1-F24) -> 2994.0625 | G31: =+G42/(1-G24) -> 3142.2686 | H31: =+H42/(1-H24) -> 3297.8109 | I31: =+I28-I30 -> -1809.0613
B32: Interest paid | C32: =+C21*C12 -> 0 | D32: =+D21*D12 -> 46.725 | E32: =+E21*E12 -> 101.5 | F32: =+F21*F12 -> 163.8 | G32: =+G21*G12 -> 229.46606 | H32: =+H21*H12 -> 241.07988
B33: Profit before tax | C33: =+C31-C32 -> 2250 | D33: =+D31-D32 -> 2490.15 | E33: =+E31-E32 -> 2672.5625 | F33: =+F31-F32 -> 2830.2625 | G33: =+G31-G32 -> 2912.8025 | H33: =+H31-H32+I31 -> 1247.6697
B34: Tax | C34: =+IF(C33<0,0,C33*C14) -> 450 | D34: =+IF(D33<0,0,D33*D14) -> 498.03 | E34: =+IF(E33<0,0,E33*E14) -> 534.5125 | F34: =+IF(F33<0,0,F33*F14) -> 566.0525 | G34: =+IF(G33<0,0,G33*G14) -> 582.56051 | H34: =+IF(H33<0,0,H33*H14) -> 249.53393
B35: Profit after tax | C35: =+C33-C34 -> 1800 | D35: =+D33-D34 -> 1992.12 | E35: =+E33-E34 -> 2138.05 | F35: =+F33-F34 -> 2264.21 | G35: =+G33-G34 -> 2330.242 | H35: =+H33-H34 -> 998.13573
B36: Dividend | C36: =+C35-C37 -> 1117.5 | D36: =+D35-D37 -> 1624.62 | E36: =+E35-E37 -> 1928.05 | F36: =+F35-F37 -> 2264.21 | G36: =+G35-G37 -> 1666.5949 | H36: =+H35-H37 -> 998.13573
B37: Retained earnings | C37: =+IF(C35<0,C35,MAX(0,MIN(C39,C35))) -> 682.5 | D37: =+IF(D35<0,D35,MAX(0,MIN(D39,D35))) -> 367.5 | E37: =+IF(E35<0,E35,MAX(0,MIN(E39,E35))) -> 210 | F37: =+IF(F35<0,F35,MAX(0,MIN(F39,F35))) -> 0 | G37: =+IF(G35<0,G35,MAX(0,MIN(G39,G35))) -> 663.64713 | H37: =+IF(H35<0,H35,MAX(0,MIN(H39,H35))) -> 0
B39: dEquity needed | C39: =+D22-C22 -> 682.5 | D39: =+E22-D22 -> 367.5 | E39: =+F22-E22 -> 210 | F39: =+G22-F22 -> -147.654 | G39: =+H22-G22 -> 663.64713 | H39: =+J22-H22 -> -13775.993
B40: Share issue/buyback | C40: =+C39-C37 -> 0 | D40: =+D39-D37 -> 0 | E40: =+E39-E37 -> 0 | F40: =+F39-F37 -> -147.654 | G40: =+G39-G37 -> 0 | H40: =+H39-H37 -> -13775.993
B42: Noplat=EBIT*(1-t) | C42: =+C20*C8 -> 1800 | D42: =+C42+C43*D9 -> 2029.5 | E42: =+D42+D43*E9 -> 2219.25 | F42: =+E42+E43*F9 -> 2395.25 | G42: =+F42+F43*G9 -> 2513.8149 | H42: =+G42+G43*H9 -> 2638.2487 | I42: =+I31*(1-H24) -> -1447.2491
B43: dIC | C43: =+C7 -> 1350 | D43: =+D7 -> 1150 | E43: =+E7 -> 1100 | F43: =+F42*F10 -> 790.4325 | G43: =+G42*G10 -> 829.55891 | H43: =+J20-H20 -> -17219.991
B44: FCFF | C44: =+C42-C43 -> 450 | D44: =+D42-D43 -> 879.5 | E44: =+E42-E43 -> 1119.25 | F44: =+F42-F43 -> 1604.8175 | G44: =+G42-G43 -> 1684.256 | H44: =+H42-H43+I42 -> 18410.991
B45: =+B32 -> Interest paid | C45: =+C32 -> 0 | D45: =+D32 -> 46.725 | E45: =+E32 -> 101.5 | F45: =+F32 -> 163.8 | G45: =+G32 -> 229.46606 | H45: =+H32 -> 241.07988
B46: Tax shield | C46: =+C45*C24 -> 0 | D46: =+D45*D24 -> 9.345 | E46: =+E45*E24 -> 20.3 | F46: =+F45*F24 -> 32.76 | G46: =+G45*G24 -> 45.893211 | H46: =+H45*H24 -> 48.215976
B47: dDebt | C47: =+D21-C21 -> 667.5 | D47: =+E21-D21 -> 782.5 | E47: =+F21-E21 -> 890 | F47: =+G21-F21 -> 938.0865 | G47: =+H21-G21 -> 165.91178 | H47: =+J21-H21 -> -3443.9983
B48: FCFE | C48: =+C44-C45+C46+C47 -> 1117.5 | D48: =+D44-D45+D46+D47 -> 1624.62 | E48: =+E44-E45+E46+E47 -> 1928.05 | F48: =+F44-F45+F46+F47 -> 2411.864 | G48: =+G44-G45+G46+G47 -> 1666.5949 | H48: =+H44-H45+H46+H47 -> 14774.129
B49: =+B36 -> Dividend | C49: =+C36 -> 1117.5 | D49: =+D36 -> 1624.62 | E49: =+E36 -> 1928.05 | F49: =+F36 -> 2264.21 | G49: =+G36 -> 1666.5949 | H49: =+H36 -> 998.13573
B50: dEquity w/o Retained earnings | C50: =+D22-C22-C37 -> 0 | D50: =+E22-D22-D37 -> 0 | E50: =+F22-E22-E37 -> 0 | F50: =+G22-F22-F37 -> -147.654 | G50: =+H22-G22-G37 -> 0 | H50: =+J22-H22-H37 -> -13775.993
B51: dNon-operative wealth | C51: =+C48-C49+C50 -> 0 | D51: =+D48-D49+D50 -> -2.2737368e-13 | E51: =+E48-E49+E50 -> -2.2737368e-13 | F51: =+F48-F49+F50 -> -4.5474735e-13 | G51: =+G48-G49+G50 -> 4.5474735e-13 | H51: =+H48-H49+H50 -> 0
B54: APV // rA
B55: FCFF+TS | C55: =+C44+C46 -> 450 | D55: =+D44+D46 -> 888.845 | E55: =+E44+E46 -> 1139.55 | F55: =+F44+F46 -> 1637.5775 | G55: =+G44+G46 -> 1730.1492 | H55: =+H44+H46 -> 18459.207
B56: =+B13 -> rA | C56: =+C13 -> 0.12 | D56: =+D13 -> 0.12 | E56: =+E13 -> 0.12 | F56: =+F13 -> 0.12 | G56: =+G13 -> 0.12 | H56: =+H13 -> 0.12 | I56: TV
B57: V boy | C57: =+(C55+D57)/(1+C56) -> 13295.929 | D57: =+(D55+E57)/(1+D56) -> 14441.44 | E57: =+(E55+F57)/(1+E56) -> 15285.568 | F57: =+(F55+G57)/(1+F56) -> 15980.286 | G57: =+(G55+H57)/(1+G56) -> 16260.343 | H57: =+(H55+I57)/(1+H56) -> 16481.435 | I57: 0
B59: FCFF // WACC | J59: D/V+E/V=1
B60: D/V boy assumed | C60: =+C64/C57 -> 0 | D60: =+D64/D57 -> 0.046221152 | E60: =+E64/E57 -> 0.094860722 | F60: =+F64/F57 -> 0.14643042 | G60: =+G64/G57 -> 0.20160008 | H60: =+H64/H57 -> 0.20896228 | J60: rA=D/V*rD+E/V*rE
B61: =+B44 -> FCFF | C61: =+C44 -> 450 | D61: =+D44 -> 879.5 | E61: =+E44 -> 1119.25 | F61: =+F44 -> 1604.8175 | G61: =+G44 -> 1684.256 | H61: =+H44 -> 18410.991 | J61: WACC=D/V*rD*(1-t)+E/V*rE
B62: WACC=rA-D/V*rD*t | C62: =+C56-C60*C12*C24 -> 0.12 | D62: =+D56-D60*D12*D24 -> 0.1193529 | E62: =+E56-E60*E12*E24 -> 0.11867195 | F62: =+F56-F60*F12*F24 -> 0.11794997 | G62: =+G56-G60*G12*G24 -> 0.1171776 | H62: =+H56-H60*H12*H24 -> 0.11707453 | I62: TV
B63: V boy | C63: =+(C61+D63)/(1+C62) -> 13295.929 | D63: =+(D61+E63)/(1+D62) -> 14441.44 | E63: =+(E61+F63)/(1+E62) -> 15285.568 | F63: =+(F61+G63)/(1+F62) -> 15980.286 | G63: =+(G61+H63)/(1+G62) -> 16260.343 | H63: =+(H61+I63)/(1+H62) -> 16481.435 | I63: 0
B64: =+B21 -> BV D boy | C64: =+C21 -> 0 | D64: =+D21 -> 667.5 | E64: =+E21 -> 1450 | F64: =+F21 -> 2340 | G64: =+G21 -> 3278.0865 | H64: =+H21 -> 3443.9983
B65: D/V boy calculated | C65: =+C64/C63 -> 0 | D65: =+D64/D63 -> 0.046221152 | E65: =+E64/E63 -> 0.094860722 | F65: =+F64/F63 -> 0.14643042 | G65: =+G64/G63 -> 0.20160008 | H65: =+H64/H63 -> 0.20896228
B66: diff | C66: =++C60-C65 -> 0 | D66: =++D60-D65 -> 0 | E66: =++E60-E65 -> 0 | F66: =++F60-F65 -> 0 | G66: =++G60-G65 -> 0 | H66: =++H60-H65 -> 0
B69: FCFE//rE
B70: =+B48 -> FCFE | C70: =+C48 -> 1117.5 | D70: =+D48 -> 1624.62 | E70: =+E48 -> 1928.05 | F70: =+F48 -> 2411.864 | G70: =+G48 -> 1666.5949 | H70: =+H48 -> 14774.129
B71: rE=(rA-D/V*rD)/(1-D/V) | C71: =+(C56-C60*C12)/(1-C60) -> 0.12 | D71: =+(D56-D60*D12)/(1-D60) -> 0.12242305 | E71: =+(E56-E60*E12)/(1-E60) -> 0.12524012 | F71: =+(F56-F60*F12)/(1-F60) -> 0.12857753 | G71: =+(G56-G60*G12)/(1-G60) -> 0.13262526 | H71: =+(H56-H60*H12)/(1-H60) -> 0.13320811 | I71: TV
B72: E boy (market value of E) | C72: =+(C70+D72)/(1+C71) -> 13295.929 | D72: =+(D70+E72)/(1+D71) -> 13773.94 | E72: =+(E70+F72)/(1+E71) -> 13835.568 | F72: =+(F70+G72)/(1+F71) -> 13640.286 | G72: =+(G70+H72)/(1+G71) -> 12982.256 | H72: =+(H70+I72)/(1+H71) -> 13037.437 | I72: 0
B73: =+B64 -> BV D boy | C73: =+C64 -> 0 | D73: =+D64 -> 667.5 | E73: =+E64 -> 1450 | F73: =+F64 -> 2340 | G73: =+G64 -> 3278.0865 | H73: =+H64 -> 3443.9983
B74: V boy | C74: =+C72+C73 -> 13295.929 | D74: =+D72+D73 -> 14441.44 | E74: =+E72+E73 -> 15285.568 | F74: =+F72+F73 -> 15980.286 | G74: =+G72+G73 -> 16260.343 | H74: =+H72+H73 -> 16481.435
B77: EVA//WACC
B78: =+B42 -> Noplat=EBIT*(1-t) | C78: =+C42 -> 1800 | D78: =+D42 -> 2029.5 | E78: =+E42 -> 2219.25 | F78: =+F42 -> 2395.25 | G78: =+G42 -> 2513.8149 | H78: =+H42+I42 -> 1190.9996
B79: IC boy * WACC | C79: =+C62*C20 -> 1440 | D79: =+D62*D20 -> 1593.3613 | E79: =+E62*E20 -> 1720.7433 | F79: =+F62*F20 -> 1840.0196 | G79: =+G62*G20 -> 1920.5915 | H79: =+H62*H20 -> 2016.0224
B80: EVA | C80: =+C78-C79 -> 360 | D80: =+D78-D79 -> 436.13873 | E80: =+E78-E79 -> 498.50673 | F80: =+F78-F79 -> 555.2304 | G80: =+G78-G79 -> 593.22335 | H80: =+H78-H79 -> -825.02273 | I80: TV
A81: NPV | B81: PV EVA | C81: =+(C80+D81)/(1+C62) -> 1295.9286 | D81: =+(D80+E81)/(1+D62) -> 1091.4401 | E81: =+(E80+F81)/(1+E62) -> 785.5679 | F81: =+(F80+G81)/(1+F62) -> 380.28604 | G81: =+(G80+H81)/(1+G62) -> -130.08963 | H81: =+(H80+I81)/(1+H62) -> -738.55657 | I81: 0
A82: C0 | B82: =+B20 -> IC boy | C82: =+C20 -> 12000 | D82: =+D20 -> 13350 | E82: =+E20 -> 14500 | F82: =+F20 -> 15600 | G82: =+G20 -> 16390.432 | H82: =+H20 -> 17219.991
A83: PV | B83: V boy | C83: =+C81+C82 -> 13295.929 | D83: =+D81+D82 -> 14441.44 | E83: =+E81+E82 -> 15285.568 | F83: =+F81+F82 -> 15980.286 | G83: =+G81+G82 -> 16260.343 | H83: =+H81+H82 -> 16481.435
B87: RI // rE
B88: =+B35 -> Profit after tax | C88: =+C35 -> 1800 | D88: =+D35 -> 1992.12 | E88: =+E35 -> 2138.05 | F88: =+F35 -> 2264.21 | G88: =+G35 -> 2330.242 | H88: =+H35 -> 998.13573
B89: BV E boy * rE | C89: =+C71*C22 -> 1440 | D89: =+D71*D22 -> 1552.6304 | E89: =+E71*E22 -> 1634.3835 | F89: =+F71*F22 -> 1704.9381 | G89: =+G71*G22 -> 1739.0283 | H89: =+H71*H22 -> 1835.074
B90: Residual Income | C90: =+C88-C89 -> 360 | D90: =+D88-D89 -> 439.48962 | E90: =+E88-E89 -> 503.66647 | F90: =+F88-F89 -> 559.27192 | G90: =+G88-G89 -> 591.21377 | H90: =+H88-H89 -> -836.9383 | I90: TV
B91: PV RI | C91: =+(C90+D91)/(1+C71) -> 1295.9286 | D91: =+(D90+E91)/(1+D71) -> 1091.4401 | E91: =+(E90+F91)/(1+E71) -> 785.5679 | F91: =+(F90+G91)/(1+F71) -> 380.28604 | G91: =+(G90+H91)/(1+G71) -> -130.08963 | H91: =+(H90+I91)/(1+H71) -> -738.55657 | I91: 0
B92: =+B22 -> BV E boy | C92: =+C22 -> 12000 | D92: =+D22 -> 12682.5 | E92: =+E22 -> 13050 | F92: =+F22 -> 13260 | G92: =+G22 -> 13112.346 | H92: =+H22 -> 13775.993
B93: E boy (market value) | C93: =+C91+C92 -> 13295.929 | D93: =+D91+D92 -> 13773.94 | E93: =+E91+E92 -> 13835.568 | F93: =+F91+F92 -> 13640.286 | G93: =+G91+G92 -> 12982.256 | H93: =+H91+H92 -> 13037.437
B94: =+B73 -> BV D boy | C94: =+C73 -> 0 | D94: =+D73 -> 667.5 | E94: =+E73 -> 1450 | F94: =+F73 -> 2340 | G94: =+G73 -> 3278.0865 | H94: =+H73 -> 3443.9983
B95: V boy | C95: =+C93+C94 -> 13295.929 | D95: =+D93+D94 -> 14441.44 | E95: =+E93+E94 -> 15285.568 | F95: =+F93+F94 -> 15980.286 | G95: =+G93+G94 -> 16260.343 | H95: =+H93+H94 -> 16481.435
B98: Max to pay as an individual | C98: =+C93-C92 -> 1295.9286

Sheet Corporate purchase
C5: 2025 | D5: =+C5+1 -> 2026 | E5: =+D5+1 -> 2027 | F5: =+E5+1 -> 2028 | G5: =+F5+1 -> 2029 | H5: =+G5+1 -> 2030
B6: IC boy | C6: 12000
B7: dIC | C7: 1350 | D7: 1150 | E7: 1100
B8: ROIC=Noplat/IC boy | C8: 0.15
B9: RONIC | D9: 0.17 | E9: 0.165 | F9: 0.16 | G9: 0.15 | H9: 0.15
B10: K=dIC/Noplat | F10: 0.33 | G10: 0.33 | H10: 0.33
B11: Debt/IC boy | C11: 0 | D11: 0.05 | E11: 0.1 | F11: 0.15 | G11: 0.2 | H11: 0.2
B12: rD | D12: 0.07 | E12: 0.07 | F12: 0.07 | G12: 0.07 | H12: 0.07
B13: rA | C13: 0.12 | D13: 0.12 | E13: 0.12 | F13: 0.12 | G13: 0.12 | H13: 0.12
B14: t | C14: 0.2 | D14: 0.2 | E14: 0.2 | F14: 0.2 | G14: 0.2 | H14: 0.2
B15: Moving costs/IC eoy | H15: 0.1
B19: Balance sheet | H19: boy | I19: eoy 2030 | J19: boy 2031
B20: Rental right | C20: 1504.8469 | D20: =+C20-$C$20/6 -> 1254.0391 | E20: =+D20-$C$20/6 -> 1003.2313 | F20: =+E20-$C$20/6 -> 752.42346 | G20: =+F20-$C$20/6 -> 501.61564 | H20: =+G20-$C$20/6 -> 250.80782 | I20: =+H20-$C$20/6 -> 0 | J20: 0
B21: =+B6 -> IC boy | C21: =+C6 -> 12000 | D21: =+C21+C45 -> 13350 | E21: =+D21+D45 -> 14500 | F21: =+E21+E45 -> 15600 | G21: =+F21+F45 -> 16390.432 | H21: =+G21+G45 -> 17219.991 | I21: =+H21+H44*H10 -> 18024.4 | J21: 0
B22: BV D boy | C22: =+C21*C11 -> 0 | D22: =+D21*D11 -> 667.5 | E22: =+E21*E11 -> 1450 | F22: =+F21*F11 -> 2340 | G22: =+G21*G11 -> 3278.0865 | H22: =+H21*H11 -> 3443.9983 | I22: 0 | J22: 0
B23: BV E boy | C23: =+C21-C22+C20 -> 13504.847 | D23: =+D21-D22+D20 -> 13936.539 | E23: =+E21-E22+E20 -> 14053.231 | F23: =+F21-F22+F20 -> 14012.423 | G23: =+G21-G22+G20 -> 13613.962 | H23: =+H21-H22+H20 -> 14026.801 | I23: =+I21-I22+I20 -> 18024.4 | J23: =+J21-J22+J20 -> 0
B25: effective tax rate | C25: 0.2 | D25: 0.2 | E25: 0.2 | F25: 0.2 | G25: 0.2 | H25: 0.2
B26: effective tax calculated | C26: =+C36/C35 -> 0.2 | D26: =+D36/D35 -> 0.2 | E26: =+E36/E35 -> 0.2 | F26: =+F36/F35 -> 0.2 | G26: =+G36/G35 -> 0.2 | H26: =+H36/H35 -> 0.2
B28: Sales
B29: Other Income | I29: =+I21*0.9 -> 16221.96
B30: Expenses
B31: Other expense | I31: =+I21 -> 18024.4
B32: D&A rental right | C32: =+$C$20/6 -> 250.80782 | D32: =+$C$20/6 -> 250.80782 | E32: =+$C$20/6 -> 250.80782 | F32: =+$C$20/6 -> 250.80782 | G32: =+$C$20/6 -> 250.80782 | H32: =+$C$20/6 -> 250.80782
B33: EBIT | C33: =+'Individual purchase'!C31-C32 -> 1999.1922 | D33: =+'Individual purchase'!D31-D32 -> 2286.0672 | E33: =+'Individual purchase'!E31-E32 -> 2523.2547 | F33: =+'Individual purchase'!F31-F32 -> 2743.2547 | G33: =+'Individual purchase'!G31-G32 -> 2891.4608 | H33: =+'Individual purchase'!H31-H32 -> 3047.0031 | I33: =+I29-I31 -> -1802.44
B34: Interest paid | C34: =+C22*C12 -> 0 | D34: =+D22*D12 -> 46.725 | E34: =+E22*E12 -> 101.5 | F34: =+F22*F12 -> 163.8 | G34: =+G22*G12 -> 229.46606 | H34: =+H22*H12 -> 241.07988
B35: Profit before tax | C35: =+C33-C34 -> 1999.1922 | D35: =+D33-D34 -> 2239.3422 | E35: =+E33-E34 -> 2421.7547 | F35: =+F33-F34 -> 2579.4547 | G35: =+G33-G34 -> 2661.9947 | H35: =+H33-H34+I33 -> 1003.4832
B36: Tax | C36: =+IF(C35<0,0,C35*C14) -> 399.83844 | D36: =+IF(D35<0,0,D35*D14) -> 447.86844 | E36: =+IF(E35<0,0,E35*E14) -> 484.35094 | F36: =+IF(F35<0,0,F35*F14) -> 515.89094 | G36: =+IF(G35<0,0,G35*G14) -> 532.39894 | H36: =+IF(H35<0,0,H35*H14) -> 200.69663
B37: Profit after tax | C37: =+C35-C36 -> 1599.3537 | D37: =+D35-D36 -> 1791.4737 | E37: =+E35-E36 -> 1937.4037 | F37: =+F35-F36 -> 2063.5637 | G37: =+G35-G36 -> 2129.5958 | H37: =+H35-H36 -> 802.78653
B38: Dividend | C38: =+C37-C39 -> 1167.6616 | D38: =+D37-D39 -> 1674.7816 | E38: =+E37-E39 -> 1937.4037 | F38: =+F37-F39 -> 2063.5637 | G38: =+G37-G39 -> 1716.7565 | H38: =+H37-H39 -> 802.78653
B39: Retained earnings | C39: =+IF(C37<0,C37,MAX(0,MIN(C41,C37))) -> 431.69218 | D39: =+IF(D37<0,D37,MAX(0,MIN(D41,D37))) -> 116.69218 | E39: =+IF(E37<0,E37,MAX(0,MIN(E41,E37))) -> 0 | F39: =+IF(F37<0,F37,MAX(0,MIN(F41,F37))) -> 0 | G39: =+IF(G37<0,G37,MAX(0,MIN(G41,G37))) -> 412.83931 | H39: =+IF(H37<0,H37,MAX(0,MIN(H41,H37))) -> 0
B41: dEquity needed | C41: =+D23-C23 -> 431.69218 | D41: =+E23-D23 -> 116.69218 | E41: =+F23-E23 -> -40.807821 | F41: =+G23-F23 -> -398.46182 | G41: =+H23-G23 -> 412.83931 | H41: =+J23-H23 -> -14026.801
B42: Share issue/buyback | C42: =+C41-C39 -> 0 | D42: =+D41-D39 -> 0 | E42: =+E41-E39 -> -40.807821 | F42: =+F41-F39 -> -398.46182 | G42: =+G41-G39 -> 0 | H42: =+H41-H39 -> -14026.801
B44: Noplat=EBIT*(1-t) | C44: =+C33*(1-C25) -> 1599.3537 | D44: =+D33*(1-D25) -> 1828.8537 | E44: =+E33*(1-E25) -> 2018.6037 | F44: =+F33*(1-F25) -> 2194.6037 | G44: =+G33*(1-G25) -> 2313.1686 | H44: =+H33*(1-H25) -> 2437.6025 | I44: =+I33*(1-H25) -> -1441.952
B45: dIC | C45: =+'Individual purchase'!C43 -> 1350 | D45: =+'Individual purchase'!D43 -> 1150 | E45: =+'Individual purchase'!E43 -> 1100 | F45: =+'Individual purchase'!F43 -> 790.4325 | G45: =+'Individual purchase'!G43 -> 829.55891 | H45: =+J21-H21 -> -17219.991
B46: dRentalright | C46: =+D20-C20 -> -250.80782 | D46: =+E20-D20 -> -250.80782 | E46: =+F20-E20 -> -250.80782 | F46: =+G20-F20 -> -250.80782 | G46: =+H20-G20 -> -250.80782 | H46: =+I20-H20 -> -250.80782
B47: FCFF | C47: =+C44-C45-C46 -> 500.16156 | D47: =+D44-D45-D46 -> 929.66156 | E47: =+E44-E45-E46 -> 1169.4116 | F47: =+F44-F45-F46 -> 1654.9791 | G47: =+G44-G45-G46 -> 1734.4175 | H47: =+H44-H45+I44-H46 -> 18466.45
B48: =+B34 -> Interest paid | C48: =+C34 -> 0 | D48: =+D34 -> 46.725 | E48: =+E34 -> 101.5 | F48: =+F34 -> 163.8 | G48: =+G34 -> 229.46606 | H48: =+H34 -> 241.07988
B49: Tax shield | C49: =+C48*C25 -> 0 | D49: =+D48*D25 -> 9.345 | E49: =+E48*E25 -> 20.3 | F49: =+F48*F25 -> 32.76 | G49: =+G48*G25 -> 45.893211 | H49: =+H48*H25 -> 48.215976
B50: dDebt | C50: =+D22-C22 -> 667.5 | D50: =+E22-D22 -> 782.5 | E50: =+F22-E22 -> 890 | F50: =+G22-F22 -> 938.0865 | G50: =+H22-G22 -> 165.91178 | H50: =+J22-H22 -> -3443.9983
B51: FCFE | C51: =+C47-C48+C49+C50 -> 1167.6616 | D51: =+D47-D48+D49+D50 -> 1674.7816 | E51: =+E47-E48+E49+E50 -> 1978.2116 | F51: =+F47-F48+F49+F50 -> 2462.0256 | G51: =+G47-G48+G49+G50 -> 1716.7565 | H51: =+H47-H48+H49+H50 -> 14829.587
B52: =+B38 -> Dividend | C52: =+C38 -> 1167.6616 | D52: =+D38 -> 1674.7816 | E52: =+E38 -> 1937.4037 | F52: =+F38 -> 2063.5637 | G52: =+G38 -> 1716.7565 | H52: =+H38 -> 802.78653
B53: dEquity w/o Retained earnings | C53: =+D23-C23-C39 -> 0 | D53: =+E23-D23-D39 -> 0 | E53: =+F23-E23-E39 -> -40.807821 | F53: =+G23-F23-F39 -> -398.46182 | G53: =+H23-G23-G39 -> 0 | H53: =+J23-H23-H39 -> -14026.801
B54: dNon-operative wealth | C54: =+C51-C52+C53 -> -1.3642421e-12 | D54: =+D51-D52+D53 -> 6.8212103e-13 | E54: =+E51-E52+E53 -> 4.5474735e-13 | F54: =+F51-F52+F53 -> 4.5474735e-13 | G54: =+G51-G52+G53 -> -9.094947e-13 | H54: =+H51-H52+H53 -> 0
B57: APV // rA
B58: FCFF+TS | C58: =+C47+C49 -> 500.16156 | D58: =+D47+D49 -> 939.00656 | E58: =+E47+E49 -> 1189.7116 | F58: =+F47+F49 -> 1687.7391 | G58: =+G47+G49 -> 1780.3107 | H58: =+H47+H49 -> 18514.666
B59: =+B13 -> rA | C59: =+C13 -> 0.12 | D59: =+D13 -> 0.12 | E59: =+E13 -> 0.12 | F59: =+F13 -> 0.12 | G59: =+G13 -> 0.12 | H59: =+H13 -> 0.12 | I59: TV
B60: V boy | C60: =+(C58+D60)/(1+C59) -> 13504.847 | D60: =+(D58+E60)/(1+D59) -> 14625.267 | E60: =+(E58+F60)/(1+E59) -> 15441.292 | F60: =+(F58+G60)/(1+F59) -> 16104.536 | G60: =+(G58+H60)/(1+G59) -> 16349.341 | H60: =+(H58+I60)/(1+H59) -> 16530.951 | I60: 0
B62: FCFF // WACC | J62: D/V+E/V=1
B63: D/V boy assumed | C63: =+C67/C60 -> 0 | D63: =+D67/D60 -> 0.045640192 | E63: =+E67/E60 -> 0.093904056 | F63: =+F67/F60 -> 0.14530068 | G63: =+G67/G60 -> 0.20050267 | H63: =+H67/H60 -> 0.20833636 | J63: rA=D/V*rD+E/V*rE
B64: =+B47 -> FCFF | C64: =+C47 -> 500.16156 | D64: =+D47 -> 929.66156 | E64: =+E47 -> 1169.4116 | F64: =+F47 -> 1654.9791 | G64: =+G47 -> 1734.4175 | H64: =+H47 -> 18466.45 | J64: WACC=D/V*rD*(1-t)+E/V*rE
B65: WACC=rA-D/V*rD*t | C65: =+C59-C63*C12*C25 -> 0.12 | D65: =+D59-D63*D12*D25 -> 0.11936104 | E65: =+E59-E63*E12*E25 -> 0.11868534 | F65: =+F59-F63*F12*F25 -> 0.11796579 | G65: =+G59-G63*G12*G25 -> 0.11719296 | H65: =+H59-H63*H12*H25 -> 0.11708329 | I65: TV
B66: V boy | C66: =+(C64+D66)/(1+C65) -> 13504.847 | D66: =+(D64+E66)/(1+D65) -> 14625.267 | E66: =+(E64+F66)/(1+E65) -> 15441.292 | F66: =+(F64+G66)/(1+F65) -> 16104.536 | G66: =+(G64+H66)/(1+G65) -> 16349.341 | H66: =+(H64+I66)/(1+H65) -> 16530.951 | I66: 0
B67: =+B22 -> BV D boy | C67: =+C22 -> 0 | D67: =+D22 -> 667.5 | E67: =+E22 -> 1450 | F67: =+F22 -> 2340 | G67: =+G22 -> 3278.0865 | H67: =+H22 -> 3443.9983
B68: D/V boy calculated | C68: =+C67/C66 -> 0 | D68: =+D67/D66 -> 0.045640192 | E68: =+E67/E66 -> 0.093904056 | F68: =+F67/F66 -> 0.14530068 | G68: =+G67/G66 -> 0.20050267 | H68: =+H67/H66 -> 0.20833636
B69: diff | C69: =++C63-C68 -> 0 | D69: =++D63-D68 -> 0 | E69: =++E63-E68 -> 0 | F69: =++F63-F68 -> 0 | G69: =++G63-G68 -> 0 | H69: =++H63-H68 -> 0
B72: FCFE//rE
B73: =+B51 -> FCFE | C73: =+C51 -> 1167.6616 | D73: =+D51 -> 1674.7816 | E73: =+E51 -> 1978.2116 | F73: =+F51 -> 2462.0256 | G73: =+G51 -> 1716.7565 | H73: =+H51 -> 14829.587
B74: rE=(rA-D/V*rD)/(1-D/V) | C74: =+(C59-C63*C12)/(1-C63) -> 0.12 | D74: =+(D59-D63*D12)/(1-D63) -> 0.12239114 | E74: =+(E59-E63*E12)/(1-E63) -> 0.12518179 | F74: =+(F59-F63*F12)/(1-F63) -> 0.1285001 | G74: =+(G59-G63*G12)/(1-G63) -> 0.1325393 | H74: =+(H59-H63*H12)/(1-H63) -> 0.13315814 | I74: TV
B75: E boy (market value of E) | C75: =+(C73+D75)/(1+C74) -> 13504.847 | D75: =+(D73+E75)/(1+D74) -> 13957.767 | E75: =+(E73+F75)/(1+E74) -> 13991.292 | F75: =+(F73+G75)/(1+F74) -> 13764.536 | G75: =+(G73+H75)/(1+G74) -> 13071.255 | H75: =+(H73+I75)/(1+H74) -> 13086.953 | I75: 0
B76: =+B67 -> BV D boy | C76: =+C67 -> 0 | D76: =+D67 -> 667.5 | E76: =+E67 -> 1450 | F76: =+F67 -> 2340 | G76: =+G67 -> 3278.0865 | H76: =+H67 -> 3443.9983
B77: V boy | C77: =+C75+C76 -> 13504.847 | D77: =+D75+D76 -> 14625.267 | E77: =+E75+E76 -> 15441.292 | F77: =+F75+F76 -> 16104.536 | G77: =+G75+G76 -> 16349.341 | H77: =+H75+H76 -> 16530.951
B78: V-IC | C78: =+C77-C20-C21 -> 0
B80: EVA//WACC
B81: =+B44 -> Noplat=EBIT*(1-t) | C81: =+C44 -> 1599.3537 | D81: =+D44 -> 1828.8537 | E81: =+E44 -> 2018.6037 | F81: =+F44 -> 2194.6037 | G81: =+G44 -> 2313.1686 | H81: =+H44+I44 -> 995.65044
B82: (IC+Rental rigtht) boy * WACC | C82: =+C65*(C21+C20) -> 1620.5816 | D82: =+D65*(D21+D20) -> 1743.1533 | E82: =+E65*(E21+E20) -> 1840.0063 | F82: =+F65*(F21+F20) -> 1929.0266 | G82: =+G65*(G21+G20) -> 1979.6292 | H82: =+H65*(H21+H20) -> 2045.5387
B83: EVA | C83: =+C81-C82 -> -21.227888 | D83: =+D81-D82 -> 85.700486 | E83: =+E81-E82 -> 178.59742 | F83: =+F81-F82 -> 265.57718 | G83: =+G81-G82 -> 333.53945 | H83: =+H81-H82 -> -1049.8882 | I83: TV
A84: NPV | B84: PV EVA | C84: =+(C83+D84)/(1+C65) -> 2.747009e-12 | D84: =+(D83+E84)/(1+D65) -> 21.227888 | E84: =+(E83+F84)/(1+E65) -> -61.938815 | F84: =+(F83+G84)/(1+F65) -> -247.88746 | G84: =+(G83+H84)/(1+G65) -> -542.70689 | H84: =+(H83+I84)/(1+H65) -> -939.84776 | I84: 0
A85: C0 | B85: IC+Rental right | C85: =+C21+C20 -> 13504.847 | D85: =+D21+D20 -> 14604.039 | E85: =+E21+E20 -> 15503.231 | F85: =+F21+F20 -> 16352.423 | G85: =+G21+G20 -> 16892.048 | H85: =+H21+H20 -> 17470.799
A86: PV | B86: V boy | C86: =+C84+C85 -> 13504.847 | D86: =+D84+D85 -> 14625.267 | E86: =+E84+E85 -> 15441.292 | F86: =+F84+F85 -> 16104.536 | G86: =+G84+G85 -> 16349.341 | H86: =+H84+H85 -> 16530.951
B90: RI // rE
B91: =+B37 -> Profit after tax | C91: =+C37 -> 1599.3537 | D91: =+D37 -> 1791.4737 | E91: =+E37 -> 1937.4037 | F91: =+F37 -> 2063.5637 | G91: =+G37 -> 2129.5958 | H91: =+H37 -> 802.78653
B92: BV E boy * rE | C92: =+C74*C23 -> 1620.5816 | D92: =+D74*D23 -> 1705.7089 | E92: =+E74*E23 -> 1759.2087 | F92: =+F74*F23 -> 1800.5979 | G92: =+G74*G23 -> 1804.3849 | H92: =+H74*H23 -> 1867.7827
B93: Residual Income | C93: =+C91-C92 -> -21.227888 | D93: =+D91-D92 -> 85.764809 | E93: =+E91-E92 -> 178.19503 | F93: =+F91-F92 -> 262.96586 | G93: =+G91-G92 -> 325.21089 | H93: =+H91-H92 -> -1064.9961 | I93: TV
B94: PV RI | C94: =+(C93+D94)/(1+C74) -> 2.1316282e-12 | D94: =+(D93+E94)/(1+D74) -> 21.227888 | E94: =+(E93+F94)/(1+E74) -> -61.938815 | F94: =+(F93+G94)/(1+F74) -> -247.88746 | G94: =+(G93+H94)/(1+G74) -> -542.70689 | H94: =+(H93+I94)/(1+H74) -> -939.84776 | I94: 0
B95: =+B23 -> BV E boy | C95: =+C23 -> 13504.847 | D95: =+D23 -> 13936.539 | E95: =+E23 -> 14053.231 | F95: =+F23 -> 14012.423 | G95: =+G23 -> 13613.962 | H95: =+H23 -> 14026.801
B96: E boy (market value) | C96: =+C94+C95 -> 13504.847 | D96: =+D94+D95 -> 13957.767 | E96: =+E94+E95 -> 13991.292 | F96: =+F94+F95 -> 13764.536 | G96: =+G94+G95 -> 13071.255 | H96: =+H94+H95 -> 13086.953
B97: =+B76 -> BV D boy | C97: =+C76 -> 0 | D97: =+D76 -> 667.5 | E97: =+E76 -> 1450 | F97: =+F76 -> 2340 | G97: =+G76 -> 3278.0865 | H97: =+H76 -> 3443.9983
B98: V boy | C98: =+C96+C97 -> 13504.847 | D98: =+D96+D97 -> 14625.267 | E98: =+E96+E97 -> 15441.292 | F98: =+F96+F97 -> 16104.536 | G98: =+G96+G97 -> 16349.341 | H98: =+H96+H97 -> 16530.951
B101: Max to pay as an individual | C101: =+C96-C95 -> 0
