Workbook

Sheet Problem5.1
C1: Main message: | E1: There is an inverse relationship between bond price and YTM change
E2: When the yield to maturity is unchanged over the holding period, the rate of return on the bond will equal be that yield.
A3: Par value | B3: coupon | C3: T | D3: YTM (continous)
A4: 100 | B4: 0.1 | C4: 2 | D4: 0.06
A6: T-t | B6: CF | C6: DF | D6: PV(CF)
A7: 1 | B7: 10 | C7: =EXP(-A7*$D$4) -> 0.94176453 | D7: =B7*C7 -> 9.4176453 | F7: First we have to solve a bond pricing problem
A8: 2 | B8: 110 | C8: =EXP(-A8*$D$4) -> 0.88692044 | D8: =B8*C8 -> 97.561248
D10: theoretical price
D11: =SUM(D7:D8) -> 106.97889
B13: yield to maturity after FOMC meeting
A14: a) | B14: 0.04 | C14: =B14-$D$4 -> -0.02 | D14: T-t | E14: CF | F14: DF | G14: PV(CF)
D15: 1 | E15: =B7 -> 10 | F15: =EXP(-B14*D15) -> 0.96078944 | G15: =E15*F15 -> 9.6078944 | I15: theoretical price | K15: Percentage change in bond price
D16: 2 | E16: =B8 -> 110 | F16: =EXP(-B14*D16) -> 0.92311635 | G16: =E16*F16 -> 101.5428 | I16: =SUM(G15:G16) -> 111.15069 | K16: =LN(I16/$D$11) -> 0.038255314
B18: yield to maturity after FOMC meeting
A19: b) | B19: 0.05 | C19: =B19-D4 -> -0.01 | D19: T-t | E19: CF | F19: DF | G19: PV(CF)
D20: 1 | E20: =E15 -> 10 | F20: =EXP(-B19*D20) -> 0.95122942 | G20: =E20*F20 -> 9.5122942 | I20: theoretical price | K20: Percentage change in bond price
D21: 2 | E21: =B8 -> 110 | F21: =EXP(-B19*D21) -> 0.90483742 | G21: =E21*F21 -> 99.532116 | I21: =SUM(G20:G21) -> 109.04441 | K21: =LN(I21/$D$11) -> 0.019123676
B23: yield to maturity after FOMC meeting
A24: c) | B24: 0.07 | C24: =B24-$D$4 -> 0.01 | D24: T-t | E24: CF | F24: DF | G24: PV(CF)
D25: 1 | E25: =E20 -> 10 | F25: =EXP(-B24*D25) -> 0.93239382 | G25: =E25*F25 -> 9.3239382 | I25: theoretical price | K25: Percentage change in bond price
D26: 2 | E26: =B8 -> 110 | F26: =EXP(-B24*D26) -> 0.86935824 | G26: =E26*F26 -> 95.629406 | I26: =SUM(G25:G26) -> 104.95334 | K26: =LN(I26/$D$11) -> -0.019115647 | M26: There is an inverse relationship between bond price and YTM change
B28: yield to maturity after FOMC meeting
A29: d) | B29: 0.08 | C29: =B29-$D$4 -> 0.02 | D29: T-t | E29: CF | F29: DF | G29: PV(CF)
D30: 1 | E30: =E25 -> 10 | F30: =EXP(-B29*D30) -> 0.92311635 | G30: =E30*F30 -> 9.2311635 | I30: theoretical price | K30: Percentage change in bond price
D31: 2 | E31: =E26 -> 110 | F31: =EXP(-B29*D31) -> 0.85214379 | G31: =E31*F31 -> 93.735817 | I31: =SUM(G30:G31) -> 102.96698 | K31: =LN(I31/$D$11) -> -0.0382232

Sheet Problem5.2
C1: Main message: | E1: Longer bonds are more sensitive if the YTM change
A3: Par value | B3: coupon | C3: T | D3: YTM (continous)
A4: 100 | B4: 0.1 | C4: 3 | D4: 0.06
A6: T-t | B6: CF | C6: DF | D6: PV(CF)
A7: 1 | B7: 10 | C7: =EXP(-A7*$D$4) -> 0.94176453 | D7: =B7*C7 -> 9.4176453 | F7: First we have to solve a bond pricing problem
A8: 2 | B8: 10 | C8: =EXP(-A8*$D$4) -> 0.88692044 | D8: =B8*C8 -> 8.8692044
A9: 3 | B9: 110 | C9: =EXP(-A9*$D$4) -> 0.83527021 | D9: =B9*C9 -> 91.879723
D11: theoretical price
D12: =SUM(D7:D9) -> 110.16657
B14: yield to maturity after FOMC meeting
A15: a) | B15: 0.04 | C15: =B15-$D$4 -> -0.02 | D15: T-t | E15: CF | F15: DF | G15: PV(CF)
D16: 1 | E16: =B7 -> 10 | F16: =EXP(-B15*D16) -> 0.96078944 | G16: =E16*F16 -> 9.6078944 | I16: theoretical price | K16: Percentage change in bond price
D17: 2 | E17: =B8 -> 10 | F17: =EXP(-B15*D17) -> 0.92311635 | G17: =E17*F17 -> 9.2311635 | I17: =SUM(G16:G18) -> 116.40031 | K17: =LN(I17/$D$12) -> 0.055041643
D18: 3 | E18: =$B$9 -> 110 | F18: =EXP(-B15*D18) -> 0.88692044 | G18: =E18*F18 -> 97.561248
B20: yield to maturity after FOMC meeting
A21: b) | B21: 0.05 | C21: =B21-D4 -> -0.01 | D21: T-t | E21: CF | F21: DF | G21: PV(CF)
D22: 1 | E22: =E16 -> 10 | F22: =EXP(-B21*D22) -> 0.95122942 | G22: =E22*F22 -> 9.5122942 | I22: theoretical price | K22: Percentage change in bond price
D23: 2 | E23: =B8 -> 10 | F23: =EXP(-B21*D23) -> 0.90483742 | G23: =E23*F23 -> 9.0483742 | I23: =SUM(G22:G24) -> 113.23855 | K23: =LN(I23/$D$12) -> 0.027503099
D24: 3 | E24: =$B$9 -> 110 | F24: =EXP(-B21*D24) -> 0.86070798 | G24: =E24*F24 -> 94.677877
B26: yield to maturity after FOMC meeting
A27: c) | B27: 0.07 | C27: =B27-$D$4 -> 0.01 | D27: T-t | E27: CF | F27: DF | G27: PV(CF)
D28: 1 | E28: =E22 -> 10 | F28: =EXP(-B27*D28) -> 0.93239382 | G28: =E28*F28 -> 9.3239382 | I28: theoretical price | K28: Percentage change in bond price
D29: 2 | E29: =B8 -> 10 | F29: =EXP(-B27*D29) -> 0.86935824 | G29: =E29*F29 -> 8.6935824 | I29: =SUM(G28:G30) -> 107.18179 | K29: =LN(I29/$D$12) -> -0.027467178 | M29: Longer bonds are more sensitive if the YTM change
D30: 3 | E30: =$B$9 -> 110 | F30: =EXP(-B27*D30) -> 0.81058425 | G30: =E30*F30 -> 89.164267
B32: yield to maturity after FOMC meeting
A33: d) | B33: 0.08 | C33: =B33-$D$4 -> 0.02 | D33: T-t | E33: CF | F33: DF | G33: PV(CF)
D34: 1 | E34: =E28 -> 10 | F34: =EXP(-B33*D34) -> 0.92311635 | G34: =E34*F34 -> 9.2311635 | I34: theoretical price | K34: Percentage change in bond price
D35: 2 | E35: =E29 -> 10 | F35: =EXP(-B33*D35) -> 0.85214379 | G35: =E35*F35 -> 8.5214379 | I35: =SUM(G34:G36) -> 104.28167 | K35: =LN(I35/$D$12) -> -0.054897954
D36: 3 | E36: =$B$9 -> 110 | F36: =EXP(-B33*D36) -> 0.78662786 | G36: =E36*F36 -> 86.529065

Sheet Risk management
A1: Risk management
A3: 1.step | C3: measurement | F3: identifying risk factors
F4: measuring risk/calculating risk metrics
A5: 2.step | C5: hedge | F5: selection of hedging instrument
F6: calculate the quantity of hedging instrument
A8: Risk management on bond markets
A9: Fixed income
A10: PV = sum(CF(t)*DF(t)) | F10: DF(t) | H10: risk factors
H11: time to maturity | L11: deterministic
H12: yield curve | L12: stochastic
D14: Main risk factor: the yield curve change/the dynamics of yield curve
D15: The yield curve dynamics is complex
D17: We can relax this easily | J17: new assumption | N17: flat yield curve
N18: parallel shift
B20: How sensitive the bond price if the yield curve shifting parallel?
B21: risk factor | E21: parallel shift of the yield curve
A23: Risk metrics
A24: Duration | C24: D | E24: Modified duration | I24: D* | K24: Convexity | M24: C
A25: Unit of measure | C25: year | I25: % | M25: None
A27: Duration/Modified duration
A28: First-order approximation | F28: D | G28: = | H28: sum(w(t)*t)
F30: w(t) = | G30: = | H30: PV(CF(t))/ P
A32: Modified duration | D32: D* | E32: = | F32: -D/(1+r) | H32: annual compounding
E33: = | F33: -D | H33: continous compounding
A35: Percentage change in bond price | F35: dP/P | G35: = | H35: dr*(D*)
A37: Linear/first order approximation could be inaccurate if the realtionship highly nonlinear
A38: We can underestimate the gain and overestimete the loss
A40: Convexity
A41: Take consideration the second order approximation
D42: C | E42: = | F42: sum(w(t)*t^2)
F44: dP/P | G44: = | H44: dr*(D*) | J44: + | K44: 1/2*(dr^2)*P*C
A46: Portfolio
A47: The duration of a bond portfolio can be defined as a weighted average of the duration of the individual bonds in the portfolio, with the weight being proportional to the bond prices

Sheet Problem5.3
A3: Par value | B3: coupon | C3: T | D3: YTM (continous compounding)
A4: 100 | B4: 0.1 | C4: 2 | D4: 0.06
A6: t | B6: CF | C6: DF | D6: PV(CF) | E6: w | F6: w*t
A7: 1 | B7: 10 | C7: =EXP(-A7*$D$4) -> 0.94176453 | D7: =B7*C7 -> 9.4176453 | E7: =D7/D11 -> 0.088032742 | F7: =A7*E7 -> 0.088032742 | H7: It's related to bond pricing problem
A8: 2 | B8: 110 | C8: =EXP(-A8*$D$4) -> 0.88692044 | D8: =B8*C8 -> 97.561248 | E8: =D8/D11 -> 0.91196726 | F8: =A8*E8 -> 1.8239345
D10: theoretical price | F10: Duration
D11: =SUM(D7:D8) -> 106.97889 | F11: =SUM(F7:F8) -> 1.9119673 | G11: year
F13: Modified duration
F14: =-F11 -> -1.9119673 | G14: %
A18: Par value | B18: coupon | C18: T | D18: YTM (annual compounding)
A19: 100 | B19: 0.1 | C19: 2 | D19: 0.06
A21: t | B21: CF | C21: DF | D21: PV(CF) | E21: w | F21: w*t
A22: 1 | B22: 10 | C22: =1/(1+$D$19)^A22 -> 0.94339623 | D22: =B22*C22 -> 9.4339623 | E22: =D22/D26 -> 0.087893864 | F22: =A22*E22 -> 0.087893864 | H22: It's related to bond pricing problem
A23: 2 | B23: 110 | C23: =1/(1+$D$19)^A23 -> 0.88999644 | D23: =B23*C23 -> 97.899608 | E23: =D23/D26 -> 0.91210614 | F23: =A23*E23 -> 1.8242123
D25: theoretical price | F25: Duration
D26: =SUM(D22:D23) -> 107.33357 | F26: =SUM(F22:F23) -> 1.9121061 | G26: year
F28: Modified duration
F29: =-F26/(1+D19) -> -1.8038737 | G29: %

Sheet Problem5.4
C1: Main message: | E1: For small changes in the bond’s yield to maturity, the duration rule is quite accurate.
E2: However, for larger changes in yield, the duration rule becomes less accurate.
A3: Par value | B3: coupon | C3: T | D3: YTM (continous compounding)
A4: 100 | B4: 0.1 | C4: 2 | D4: 0.06
A6: t | B6: CF | C6: DF | D6: PV(CF) | E6: w | F6: w*t
A7: 1 | B7: 10 | C7: =EXP(-A7*$D$4) -> 0.94176453 | D7: =B7*C7 -> 9.4176453 | E7: =D7/D11 -> 0.088032742 | F7: =A7*E7 -> 0.088032742
A8: 2 | B8: 110 | C8: =EXP(-A8*$D$4) -> 0.88692044 | D8: =B8*C8 -> 97.561248 | E8: =D8/D11 -> 0.91196726 | F8: =A8*E8 -> 1.8239345
D10: theoretical price | F10: Duration
D11: =SUM(D7:D8) -> 106.97889 | F11: =SUM(F7:F8) -> 1.9119673 | G11: year
F13: Modified duration
F14: =-F11 -> -1.9119673 | G14: %
A16: yield to maturity after FOMC meeting
A17: 0.07 | B17: =A17-D4 -> 0.01 | C17: t | D17: CF | E17: DF | F17: PV(CF)
C18: 1 | D18: =B7 -> 10 | E18: =EXP(-A17*C18) -> 0.93239382 | F18: =D18*E18 -> 9.3239382 | G18: theoretical price | I18: Percentage change | K18: Percentage change based on modified duration | M18: Diff | O18: For small changes in the bond’s yield to maturity, the duration rule is quite accurate.
C19: 2 | D19: =B8 -> 110 | E19: =EXP(-A17*C19) -> 0.86935824 | F19: =D19*E19 -> 95.629406 | G19: =SUM(F18:F19) -> 104.95334 | I19: =G19/D11-1 -> -0.018934102 | K19: =B17*F14 -> -0.019119673 | M19: =I19-K19 -> 0.00018557055
A21: yield to maturity after FOMC meeting
A22: 0.1 | B22: =A22-D4 -> 0.04 | C22: t | D22: CF | E22: DF | F22: PV(CF)
C23: 1 | D23: =B7 -> 10 | E23: =EXP(-A22*C23) -> 0.90483742 | F23: =D23*E23 -> 9.0483742 | G23: theoretical price | I23: Percentage change | K23: Percentage change based on modified duration | M23: Diff
C24: 2 | D24: =B8 -> 110 | E24: =EXP(-A22*C24) -> 0.81873075 | F24: =D24*E24 -> 90.060383 | G24: =SUM(F23:F24) -> 99.108757 | I24: =G24/D11-1 -> -0.073567188 | K24: =B22*F14 -> -0.07647869 | M24: =I24-K24 -> 0.0029115024 | O24: However, for larger changes in yield, the duration rule becomes less accurate.

Sheet Problem5.5
A3: Par value | B3: coupon | C3: T | D3: YTM (continous)
A4: 100 | B4: 0.1 | C4: 2 | D4: 0.06
A6: t | B6: CF | C6: DF | D6: PV(CF) | E6: w | F6: w*t | G6: w*t2
A7: 1 | B7: 10 | C7: =EXP(-A7*$D$4) -> 0.94176453 | D7: =B7*C7 -> 9.4176453 | E7: =D7/D11 -> 0.088032742 | F7: =A7*E7 -> 0.088032742 | G7: =E7*A7^2 -> 0.088032742
A8: 2 | B8: 110 | C8: =EXP(-A8*$D$4) -> 0.88692044 | D8: =B8*C8 -> 97.561248 | E8: =D8/D11 -> 0.91196726 | F8: =A8*E8 -> 1.8239345 | G8: =E8*A8^2 -> 3.647869
D10: theoretical price | F10: Duration | H10: Convexity
D11: =SUM(D7:D8) -> 106.97889 | F11: =SUM(F7:F8) -> 1.9119673 | G11: year | H11: =SUM(G7:G8) -> 3.7359018
F13: Modified duration
F14: =-F11 -> -1.9119673 | G14: %
A16: yield to maturity after FOMC meeting
A17: 0.07 | B17: =A17-D4 -> 0.01 | C17: t | D17: CF | E17: DF | F17: PV(CF)
C18: 1 | D18: =B7 -> 10 | E18: =EXP(-A17*C18) -> 0.93239382 | F18: =D18*E18 -> 9.3239382 | G18: theoretical price | I18: Percentage change | K18: Percentage change based on modified duration and convexity | M18: Diff | O18: Without convexity
C19: 2 | D19: =B8 -> 110 | E19: =EXP(-A17*C19) -> 0.86935824 | F19: =D19*E19 -> 95.629406 | G19: =SUM(F18:F19) -> 104.95334 | I19: =G19/D11-1 -> -0.018934102 | K19: =B17*F14+0.5*H11*B17^2 -> -0.018932877 | M19: =I19-K19 -> -1.2245363e-06 | O19: =Problem5.4!M19 -> 0.00018557055
A21: yield to maturity after FOMC meeting
A22: 0.1 | B22: =A22-D4 -> 0.04 | C22: t | D22: CF | E22: DF | F22: PV(CF)
C23: 1 | D23: =B7 -> 10 | E23: =EXP(-A22*C23) -> 0.90483742 | F23: =D23*E23 -> 9.0483742 | G23: theoretical price | I23: Percentage change | K23: Percentage change based on modified duration and convexity | M23: Diff | O23: Without convexity
C24: 2 | D24: =B8 -> 110 | E24: =EXP(-A22*C24) -> 0.81873075 | F24: =D24*E24 -> 90.060383 | G24: =SUM(F23:F24) -> 99.108757 | I24: =G24/D11-1 -> -0.073567188 | K24: =B22*F14+0.5*H11*B17^2 -> -0.076291895 | M24: =I24-K24 -> 0.0027247073 | O24: =Problem5.4!M24 -> 0.0029115024

Sheet Problem5.6
B3: Par value | C3: coupon | D3: T | E3: YTM (continous) | F3: Investment
A4: A | B4: 100 | C4: 0.08 | D4: 3 | E4: 0.1 | F4: 2
A5: B | B5: 100 | C5: - | D5: 2 | E5: 0.08 | F5: 1
A8: A | B8: t | C8: CF | D8: DF | E8: PV(CF) | F8: w | G8: w*t
B9: 1 | C9: =C4*B4 -> 8 | D9: =EXP(-B9*$E$4) -> 0.90483742 | E9: =C9*D9 -> 7.2386993 | F9: =E9/E14 -> 0.077174174 | G9: =B9*F9 -> 0.077174174
B10: 2 | C10: 8 | D10: =EXP(-B10*$E$4) -> 0.81873075 | E10: =C10*D10 -> 6.549846 | F10: =E10/E14 -> 0.069830081 | G10: =B10*F10 -> 0.13966016
B11: 3 | C11: 108 | D11: =EXP(-B11*$E$4) -> 0.74081822 | E11: =C11*D11 -> 80.008368 | F11: =E11/E14 -> 0.85299574 | G11: =B11*F11 -> 2.5589872
E13: theoretical price | G13: Duration
E14: =SUM(E9:E11) -> 93.796913 | G14: =SUM(G9:G11) -> 2.7758216 | H14: year
E16: Investment value | G16: Modified duration
E17: =E14*F4 -> 187.59383 | G17: =-G14 -> -2.7758216 | H17: % | K17: Portfolio duration
K18: =(E17*G14+E24*G24)/(E17+E24) -> 2.5334859 | L18: year
A19: B | B19: t | C19: CF | D19: DF | E19: PV(CF) | F19: w | G19: w*t
B20: 1 | C20: =C15*B15 -> 0 | D20: =EXP(-B20*E5) -> 0.92311635 | E20: =C20*D20 -> 0 | F20: =E20/E24 -> 0 | G20: =B20*F20 -> 0 | K20: Portfolio modified duration
B21: 2 | C21: =B5 -> 100 | D21: =EXP(-B21*E5) -> 0.85214379 | E21: =C21*D21 -> 85.214379 | F21: =E21/E24 -> 1 | G21: =B21*F21 -> 2 | K21: =(E17*G17+E24*G27)/(E17+E24) -> -2.5334859 | L21: %
E23: theoretical price | G23: Duration | I23: The duration of the zero-coupon bond is exactly equal to its time to maturity.
E24: =SUM(E19:E21) -> 85.214379 | G24: =SUM(G19:G21) -> 2 | H24: year
E26: Investment value | G26: Modified duration
E27: =E24*F5 -> 85.214379 | G27: =-G24 -> -2 | H27: %

Sheet Problem5.7
B3: Par value | C3: coupon | D3: T | E3: YTM (continous) | F3: Investment
A4: A | B4: 100 | C4: 0.08 | D4: 3 | E4: 0.1 | F4: 2
A5: B | B5: 100 | C5: - | D5: 2 | E5: 0.08 | F5: 1
A6: C | B6: =B5 -> 100 | C6: - | D6: 1 | E6: 0.06
B8: Investment value | D8: Duration
A9: 2A + B | B9: =Problem5.6!E17+Problem5.6!E27 -> 272.80821 | D9: =Problem5.6!K18 -> 2.5334859
A10: C | B10: -X | D10: =D6 -> 1
A11: cash | B11: X | D11: 0
B13: Portfolio duration
B14: D = (272,81 * 2,533 -X*1 + X*0)/(272,81 - X + X)
B15: 0 = (272,81 * 2,533 -X*1 + X*0)/(272,81 - X + X)
G16: Hedge instrument investment value
B17: X = 272,81*2,533/1 | G17: =B9*D9/D6 -> 691.15575
B19: C bond market value | G19: Hedge instrument face value
B20: =B6*EXP(-E6*D6) -> 94.176453 | G20: =G17/B20*B6 -> 733.89443

Sheet Problem5.8
B3: Par value | C3: coupon | D3: T | E3: YTM (continous) | F3: Investment
A4: A | B4: 100 | C4: 0.08 | D4: 3 | E4: 0.1 | F4: 2
A5: B | B5: 100 | C5: - | D5: 2 | E5: 0.08 | F5: 1
A6: C | B6: =B5 -> 100 | C6: - | D6: 3 | E6: 0.06
B8: Investment value | D8: Duration
A9: 2A + B | B9: =Problem5.6!E17+Problem5.6!E27 -> 272.80821 | D9: =Problem5.6!K18 -> 2.5334859
A10: C | B10: -X | D10: =D6 -> 3
A11: cash | B11: X | D11: 0
B13: Portfolio duration
B14: D = (272,81 * 2,533 -X*1 + X*0)/(272,81 - X + X)
B15: 0 = (272,81 * 2,533 -X*1 + X*0)/(272,81 - X + X)
G16: Hedge instrument investment value
B17: X = 272,81*2,533/3 | G17: =B9*D9/D6 -> 230.38525
B19: C bond market value | G19: Hedge instrument face value
B20: =B6*EXP(-E6*D6) -> 83.527021 | G20: =G17/B20*B6 -> 275.82122

Sheet Problem5.9
A3: Par value | B3: coupon | C3: T | D3: coupon payment | E3: 6-month LIBOR
A4: 100 | B4: LIBOR | C4: 2 | D4: twice per year | E4: 0.04
A6: t | B6: CF | C6: DF
A7: 0.5 | B7: =A4*E4/2 -> 2 | C7: =1/(1+E4)^A7 -> 0.98058068
A8: 1 | B8: LIBOR0,5 | C8: ?
A9: 1.5 | B9: LIBOR1 | C9: ? | E9: theoretical price
A10: 2 | B10: LIBOR1,5 + 100 | C10: ? | E10: =(B7+A4)*C7 -> 100.01923
B13: LIBOR after FOMC meeting | D13: Interest rate change
B14: 0.05 | D14: =B14-E4 -> 0.01
B16: DF | D16: theoretical price
B17: =1/(1+B14)^A7 -> 0.97590007 | D17: =(B7+A4)*B17 -> 99.541807
D19: Percentage change
D20: =D17/E10-1 -> -0.0047732969
D22: Modified duration
D23: =ABS(D20/D14) -> 0.47732969 | E23: %
D25: Duration
D26: =D23*(1+E4) -> 0.49642288

Sheet Problem5.10
A3: Par value | B3: coupon | C3: T | D3: coupon payment | E3: 6-month LIBOR | F3: end of three month interest rate
A4: 100 | B4: LIBOR | C4: 2 | D4: twice per year | E4: 0.04 | F4: 0.02
A6: t | B6: CF | C6: DF
A7: 0.25 | B7: =A4*E4/2 -> 2 | C7: =1/(1+F4)^A7 -> 0.99506158
A8: 0.75 | B8: LIBOR0,5 | C8: ?
A9: 1.25 | B9: LIBOR1 | C9: ? | E9: theoretical price
A10: 1.75 | B10: LIBOR1,5 + 100 | C10: ? | E10: =(B7+A4)*C7 -> 101.49628
B13: LIBOR after FOMC meeting | D13: Interest rate change
B14: 0.01 | D14: =F4-B14 -> 0.01
B16: DF | D16: theoretical price
B17: =1/(1+B14)^A7 -> 0.99751551 | D17: =(B7+A4)*B17 -> 101.74658
D19: Percentage change
D20: =D17/E10-1 -> 0.00246611
D22: Modified duration
D23: =ABS(D20/D14) -> 0.246611 | E23: %
D25: Duration
D26: =D23*(1+F4) -> 0.25154322
