Workbook
Name lista: OFFSET([1]DinamicValidation!$B$4,0,0,COUNTA([1]DinamicValidation!$B$4:$B$1048576),1)

Sheet OpeningPage

Sheet Admin
C9: Applied Business Valuation
C12: Date | D12: 45272
C13: Student name | I13: Master in Finance
C14: Neptun code | I14: Master in Accounting
C16: Study program | D16: Master in Finance
C17: Instructor | D17: Péter Juhász, PhD, CFA
C20: Total points achieved | D20: =+'Task 1'!C9+'Task 4'!C9+'Task 5'!C9+'M&A put in AYA'!C9+'Task 2'!C9+'Bonus Task'!C9 -> 0

Sheet Task 1
B2: =+Admin!C12 -> Date | C2: =+Admin!D12 -> 45272
B3: =+Admin!C13 -> Student name | C3: =+Admin!D13 -> 0
B4: =+Admin!C14 -> Neptun code | C4: =+Admin!D14 -> 0
B6: =+Admin!C16 -> Study program | C6: =+Admin!D16 -> Master in Finance
B7: =+Admin!C17 -> Instructor | C7: =+Admin!D17 -> Péter Juhász, PhD, CFA
B9: Points achived:
D18: =+E18-1 -> 2021 | E18: =+F18-1 -> 2022 | F18: =+YEAR(TODAY())-1 -> 2023
C19: Sales | D19: 19000 | E19: 22000 | F19: 25000
C20: Other income | D20: 0 | E20: 500 | F20: 0
C21: Material expenses | D21: 10000 | E21: 12000 | F21: 13000
C22: Labour expenses | D22: 5000 | E22: 6000 | F22: 7000
C23: D&A | D23: 2000 | E23: 2300 | F23: 2500
C24: EBIT | D24: =+D19+D20-D21-D22-D23 -> 2000 | E24: =+E19+E20-E21-E22-E23 -> 2200 | F24: =+F19+F20-F21-F22-F23 -> 2500
C25: Dividend received | D25: 100 | E25: 60 | F25: 0
C26: Interests received | D26: 0 | E26: 0 | F26: 10
C27: Interests paid on short term loans | D27: 30 | E27: 20 | F27: 10
C28: Interests paid on long term loans | D28: 200 | E28: 250 | F28: 300
C29: Financial profit | D29: =+D25+D26-D27-D28 -> -130 | E29: =+E25+E26-E27-E28 -> -210 | F29: =+F25+F26-F27-F28 -> -300
C30: Profit before tax | D30: =+D29+D24 -> 1870 | E30: =+E29+E24 -> 1990 | F30: =+F29+F24 -> 2200
C31: Corporate tax | D31: 300 | E31: 330 | F31: 370
C32: Profit after tax | D32: =+D30-D31 -> 1570 | E32: =+E30-E31 -> 1660 | F32: =+F30-F31 -> 1830
C33: Dividend | D33: 1000 | E33: 1200 | F33: 1400
C34: Retained earnings | D34: =+D32-D33 -> 570 | E34: =+E32-E33 -> 460 | F34: =+F32-F33 -> 430
C36: Cash | D36: 500 | E36: 600 | F36: 400
C37: of which operational cash | D37: 200 | E37: 220 | F37: 250
C38: Marketable securities | D38: 0 | E38: 50 | F38: 40
C39: Receivables | D39: 600 | E39: 800 | F39: 1000
C40: Inventory | D40: 400 | E40: 500 | F40: 450
C41: Current assets | D41: =+D36+D38+D39+D40 -> 1500 | E41: =+E36+E38+E39+E40 -> 1950 | F41: =+F36+F38+F39+F40 -> 1890
C42: Invested assets | D42: 15000 | E42: 20000 | F42: 19500
C43: Total of assests | D43: =+D42+D41 -> 16500 | E43: =+E42+E41 -> 21950 | F43: =+F42+F41 -> 21390
C44: Short term loans | D44: 300 | E44: 200 | F44: 250
C45: Payables | D45: 300 | E45: 240 | F45: 450
C46: Short term liabilities | D46: =+D44+D45 -> 600 | E46: =+E44+E45 -> 440 | F46: =+F44+F45 -> 700
C47: Long term debt | D47: 5000 | E47: 6000 | F47: 7000
C48: Equity | D48: =+D43-D46-D47 -> 10900 | E48: =+E43-E46-E47 -> 15510 | F48: =+F43-F46-F47 -> 13690
C49: Total of Liabilities and Equity | D49: =+D46+D47+D48 -> 16500 | E49: =+E46+E47+E48 -> 21950 | F49: =+F46+F47+F48 -> 21390
C52: t | D52: =D31/(D30-D25) -> 0.16949153 | E52: =E31/(E30-E25) -> 0.17098446 | F52: =F31/(F30-F25) -> 0.16818182
C55: Cash Flow | D55: =+E55-1 -> 2021 | E55: =+F55-1 -> 2022 | F55: =+YEAR(TODAY())-1 -> 2023
C56: Operational profit (EBIT) | D56: =D24 -> 2000 | E56: =E24 -> 2200 | F56: =F24 -> 2500
C57: NOPLAT (=EBIT-tax = EBIT*(1-t)) | D57: =D56*(1-D52) -> 1661.0169 | E57: =E56*(1-E52) -> 1823.8342 | F57: =F56*(1-F52) -> 2079.5455
C58: D&A | D58: =D23 -> 2000 | E58: =E23 -> 2300 | F58: =F23 -> 2500
C59: Gross CF | D59: =D57+D58 -> 3661.0169 | E59: =E57+E58 -> 4123.8342 | F59: =F57+F58 -> 4579.5455
C60: D Inventory | E60: =-(E40-D40) -> -100 | F60: =-(F40-E40) -> 50
C61: D Receivables | E61: =-(E39-D39) -> -200 | F61: =-(F39-E39) -> -200
C62: D Operational Cash | E62: =-(E37-D37) -> -20 | F62: =-(F37-E37) -> -30
C63: D Payables | E63: =E45-D45 -> -60 | F63: =F45-E45 -> 210
C64: CF from operations | E64: =E59+E60+E61+E62+E63 -> 3743.8342 | F64: =F59+F60+F61+F62+F63 -> 4609.5455
C65: D PPE | E65: =-(E42-D42) -> -5000 | F65: =-(F42-E42) -> 500
C66: D&A | E66: =-E58 -> -2300 | F66: =-F58 -> -2500
C67: CF from investments | E67: =E65+E66 -> -7300 | F67: =F65+F66 -> -2000
C68: FCFF | E68: =E67+E64 -> -3556.1658 | F68: =F67+F64 -> 2609.5455
C69: Interest | E69: =-(E27+E28) -> -270 | F69: =-(F27+F28) -> -310
C70: Tax shield | E70: =-E69*E52 -> 46.165803 | F70: =-F69*F52 -> 52.136364
C71: D Debt | E71: =(E44+E47)-(D44+D47) -> 900 | F71: =(F44+F47)-(E44+E47) -> 1050
C72: FCFD | E72: =E69+E70+E71 -> 676.1658 | F72: =F69+F70+F71 -> 792.13636
C73: FCFE | E73: =E72+E68 -> -2880 | F73: =F72+F68 -> 3401.6818
C74: Dividend | E74: =-E33 -> -1200 | F74: =-F33 -> -1400
C75: Share issue/buyback | E75: =E48-D48-E34 -> 4150 | F75: =F48-E48-F34 -> -2250
C76: CF from financing | E76: =E72+E74+E75 -> 3626.1658 | F76: =F72+F74+F75 -> -2857.8636
C78: Non-operative items change | E78: =E76+E67+E64 -> 70 | F78: =F76+F67+F64 -> -248.31818
C80: Non-operative CF
C81: Dividend received | E81: =E25 -> 60 | F81: =F25 -> 0
C82: Interests received | E82: =E26 -> 0 | F82: =F26 -> 10
C83: TS from Interests received | E83: =-E82*E52 -> 0 | F83: =-F82*F52 -> -1.6818182
C85: Non-operative items change
C86: Marketable securities | E86: =-(E38-D38) -> -50 | F86: =-(F38-E38) -> 10
C87: Non-operative cash | E87: =-((E36-E37)-(D36-D37)) -> -80 | F87: =-((F36-F37)-(E36-E37)) -> 230
C89: check | E89: =SUM(E78:E87) -> 0 | F89: =SUM(F78:F87) -> 0

Sheet Task 2
B2: =+Admin!C12 -> Date | C2: =+Admin!D12 -> 45272
B3: =+Admin!C13 -> Student name | C3: =+Admin!D13 -> 0
B4: =+Admin!C14 -> Neptun code | C4: =+Admin!D14 -> 0
B6: =+Admin!C16 -> Study program | C6: =+Admin!D16 -> Master in Finance
B7: =+Admin!C17 -> Instructor | C7: =+Admin!D17 -> Péter Juhász, PhD, CFA
B9: Points achived:
D24: 2024 | E24: =+D24+1 -> 2025 | F24: =+E24+1 -> 2026 | G24: =+F24+1 -> 2027 | H24: =+G24+1 -> 2028 | I24: TV1 | J24: TV2
C25: rA | D25: 0.12 | E25: 0.12 | F25: 0.12 | G25: 0.12 | H25: 0.12 | I25: 0.12 | J25: 0.12
C26: D/V boy | F26: 0.3 | G26: 0.4 | H26: 0.5 | I26: 0.5 | J26: 0.5
C27: D/IC boy | D27: 0.1 | E27: 0.2
C28: rD | D28: 0.06 | E28: 0.07 | F28: 0.072 | G28: 0.073 | H28: 0.074 | I28: 0.074 | J28: 0.074
C29: ROIC | D29: 0.115
C30: RONIC | E30: 0.16 | F30: 0.15 | G30: 0.14 | H30: 0.13 | I30: =I40 -> 0.11445 | J30: =J40 -> 0.11445
C31: g targeted for the given year | E31: 0.15 | F31: 0.12 | G31: 0.1 | H31: 0.08 | I31: 0.05 | J31: 0.05 | K31: 0.05
C32: t | D32: 0.15 | E32: 0.15 | F32: 0.15 | G32: 0.15 | H32: 0.15 | I32: 0.15 | J32: 0.15
C33: IC boy | D33: 100000
C34: K | D34: =E31/E30 -> 0.9375 | E34: =F31/F30 -> 0.8 | F34: =G31/G30 -> 0.71428571 | G34: =H31/H30 -> 0.61538462 | H34: =I31/I30 -> 0.436872 | I34: =J31/J30 -> 0.436872
C36: D/V boy | D36: =D43/D60 -> 0.092228923 | E36: =E43/E60 -> 0.18367387 | F36: =F26 -> 0.3 | G36: =G26 -> 0.4 | H36: =H26 -> 0.5 | I36: =I26 -> 0.5 | J36: =J26 -> 0.5
C37: D/IC boy | D37: =D27 -> 0.1 | E37: =E27 -> 0.2
C38: IC boy | D38: =D33 -> 100000 | E38: =D38+D48 -> 110781.25 | F38: =E38+E48 -> 121361.25 | G38: =F38+F48 -> 131941.25 | H38: =G38+G48 -> 141967.83 | I38: =H38+H48 -> 149655.32 | J38: =I38+I48 -> 157727.18
C40: WACC | D40: =D25-D36*D28*D32 -> 0.11916994 | E40: =E25-E36*E28*E32 -> 0.11807142 | F40: =F25-F36*F28*F32 -> 0.11676 | G40: =G25-G36*G28*G32 -> 0.11562 | H40: =H25-H36*H28*H32 -> 0.11445 | I40: =I25-I36*I28*I32 -> 0.11445 | J40: =J25-J36*J28*J32 -> 0.11445
C42: IC boy | D42: =D38 -> 100000 | E42: =E38 -> 110781.25 | F42: =F38 -> 121361.25 | G42: =G38 -> 131941.25 | H42: =H38 -> 141967.83
C43: D boy | D43: =D38*D37 -> 10000 | E43: =E38*E37 -> 22156.25 | F43: =F36*F67 -> 39667.786 | G43: =G36*G67 -> 57373.063 | H43: =H36*H67 -> 76874.862 | I43: =I36*I67 -> 80718.606 | J43: =J36*J67 -> 84754.536 | K43: =J43*(1+K31) -> 88992.263
C44: BV of E boy
C46: EBIT | D46: =D47/(1-D32) -> 13529.412 | E46: =E47/(1-E32) -> 15558.824 | F46: =F47/(1-F32) -> 17425.882 | G46: =G47/(1-G32) -> 19168.471 | H46: =H47/(1-H32) -> 20701.948 | I46: =I47/(1-I32) -> 21737.046 | J46: =J47/(1-J32) -> 22823.898
C47: NOPLAT | D47: =D29*D38 -> 11500 | E47: =D47+D48*E30 -> 13225 | F47: =E47+E48*F30 -> 14812 | G47: =F47+F48*G30 -> 16293.2 | H47: =G47+G48*H30 -> 17596.656 | I47: =H47+H48*I30 -> 18476.489 | J47: =I47+I48*J30 -> 19400.313
C48: dIC | D48: =D47*D34 -> 10781.25 | E48: =E47*E34 -> 10580 | F48: =F47*F34 -> 10580 | G48: =G47*G34 -> 10026.585 | H48: =H47*H34 -> 7687.4862 | I48: =I47*I34 -> 8071.8606 | J48: =J47*I34 -> 8475.4536
C49: FCFF | D49: =D47-D48 -> 718.75 | E49: =E47-E48 -> 2645 | F49: =F47-F48 -> 4232 | G49: =G47-G48 -> 6266.6154 | H49: =H47-H48 -> 9909.1698 | I49: =I47-I48 -> 10404.628 | J49: =J47-J48 -> 10924.86
C50: Interest | D50: =D43*D28 -> 600 | E50: =E43*E28 -> 1550.9375 | F50: =F43*F28 -> 2856.0806 | G50: =G43*G28 -> 4188.2336 | H50: =H43*H28 -> 5688.7398 | I50: =I43*I28 -> 5973.1768 | J50: =J43*J28 -> 6271.8356
C51: Tax shield | D51: =D50*D32 -> 90 | E51: =E50*E32 -> 232.64063 | F51: =F50*F32 -> 428.41209 | G51: =G50*G32 -> 628.23504 | H51: =H50*H32 -> 853.31097 | I51: =I50*I32 -> 895.97652 | J51: =J50*J32 -> 940.77535
C52: dD | D52: =E43-D43 -> 12156.25 | E52: =F43-E43 -> 17511.536 | F52: =G43-F43 -> 17705.276 | G52: =H43-G43 -> 19501.8 | H52: =I43-H43 -> 3843.7431 | I52: =J43-I43 -> 4035.9303 | J52: =K43-J43 -> 4237.7268
C53: FCFE | D53: =D49-D50+D51+D52 -> 12365 | E53: =E49-E50+E51+E52 -> 18838.239 | F53: =F49-F50+F51+F52 -> 19509.608 | G53: =G49-G50+G51+G52 -> 22208.417 | H53: =H49-H50+H51+H52 -> 8917.484 | I53: =I49-I50+I51+I52 -> 9363.3582 | J53: =J49-J50+J51+J52 -> 9831.5262
B57: VALUATION
B58: APV | C58: FCFF+TS | D58: =D49+D51 -> 808.75 | E58: =E49+E51 -> 2877.6406 | F58: =F49+F51 -> 4660.4121 | G58: =G49+G51 -> 6894.8504 | H58: =H49+H51 -> 10762.481 | I58: =I49+I51 -> 11300.605 | J58: =J49+J51 -> 11865.635
C59: rA | D59: =D25 -> 0.12 | E59: =E25 -> 0.12 | F59: =F25 -> 0.12 | G59: =G25 -> 0.12 | H59: =H25 -> 0.12 | I59: =I25 -> 0.12 | J59: =J25 -> 0.12
C60: V boy | D60: =(D58+E60)/(1+D59) -> 108425.86 | E60: =(E58+F60)/(1+E59) -> 120628.21 | F60: =(F58+G60)/(1+F59) -> 132225.95 | G60: =(G58+H60)/(1+G59) -> 143432.66 | H60: =(H58+I60)/(1+H59) -> 153749.72 | I60: =(I58+J60)/(1+I59) -> 161437.21 | J60: =J58/(J59-K31) -> 169509.07
B65: FCFF | C65: FCFF | D65: =D49 -> 718.75 | E65: =E49 -> 2645 | F65: =F49 -> 4232 | G65: =G49 -> 6266.6154 | H65: =H49 -> 9909.1698 | I65: =I49 -> 10404.628 | J65: =J49 -> 10924.86
C66: WACC | D66: =D40 -> 0.11916994 | E66: =E40 -> 0.11807142 | F66: =F40 -> 0.11676 | G66: =G40 -> 0.11562 | H66: =H40 -> 0.11445 | I66: =I40 -> 0.11445 | J66: =J40 -> 0.11445
C67: V boy | D67: =(D65+E67)/(1+D66) -> 108425.86 | E67: =(E65+F67)/(1+E66) -> 120628.21 | F67: =(F65+G67)/(1+F66) -> 132225.95 | G67: =(G65+H67)/(1+G66) -> 143432.66 | H67: =(H65+I67)/(1+H66) -> 153749.72 | I67: =(I65+J67)/(1+I66) -> 161437.21 | J67: =J65/(J66-K31) -> 169509.07
B72: FCFE | C72: D/V | D72: =D36 -> 0.092228923 | E72: =E36 -> 0.18367387 | F72: =F36 -> 0.3 | G72: =G36 -> 0.4 | H72: =H36 -> 0.5 | I72: =I36 -> 0.5 | J72: =J36 -> 0.5
C73: rD | D73: =D28 -> 0.06 | E73: =E28 -> 0.07 | F73: =F28 -> 0.072 | G73: =G28 -> 0.073 | H73: =H28 -> 0.074 | I73: =I28 -> 0.074 | J73: =J28 -> 0.074
C74: rA | D74: =D25 -> 0.12 | E74: =E25 -> 0.12 | F74: =F25 -> 0.12 | G74: =G25 -> 0.12 | H74: =H25 -> 0.12 | I74: =I25 -> 0.12 | J74: =J25 -> 0.12
C75: rE | D75: =(D74-D73*D72)/(1-D72) -> 0.12609596 | E75: =(E74-E73*E72)/(1-E72) -> 0.13125003 | F75: =(F74-F73*F72)/(1-F72) -> 0.14057143 | G75: =(G74-G73*G72)/(1-G72) -> 0.15133333 | H75: =(H74-H73*H72)/(1-H72) -> 0.166 | I75: =(I74-I73*I72)/(1-I72) -> 0.166 | J75: =(J74-J73*J72)/(1-J72) -> 0.166
C77: FCFE | D77: =D53 -> 12365 | E77: =E53 -> 18838.239 | F77: =F53 -> 19509.608 | G77: =G53 -> 22208.417 | H77: =H53 -> 8917.484 | I77: =I53 -> 9363.3582 | J77: =J53 -> 9831.5262
C78: E boy | D78: =(D77+E78)/(1+D75) -> 98425.857 | E78: =(E77+F78)/(1+E75) -> 98471.96 | F78: =(F77+G78)/(1+F75) -> 92558.168 | G78: =(G77+H78)/(1+G75) -> 86059.594 | H78: =(H77+I78)/(1+H75) -> 76874.862 | I78: =(I77+J78)/(1+I75) -> 80718.606 | J78: =J77/(J75-K31) -> 84754.536
C79: D boy | D79: =D43 -> 10000 | E79: =E43 -> 22156.25 | F79: =F43 -> 39667.786 | G79: =G43 -> 57373.063 | H79: =H43 -> 76874.862 | I79: =I43 -> 80718.606 | J79: =J43 -> 84754.536
C80: V boy | D80: =D78+D79 -> 108425.86 | E80: =E78+E79 -> 120628.21 | F80: =F78+F79 -> 132225.95 | G80: =G78+G79 -> 143432.66 | H80: =H78+H79 -> 153749.72 | I80: =I78+I79 -> 161437.21 | J80: =J78+J79 -> 169509.07

Sheet M&A put in AYA
B2: =+Admin!C12 -> Date | C2: =+Admin!D12 -> 45272
B3: =+Admin!C13 -> Student name | C3: =+Admin!D13 -> 0
B4: =+Admin!C14 -> Neptun code | C4: =+Admin!D14 -> 0
B6: =+Admin!C16 -> Study program | C6: =+Admin!D16 -> Master in Finance
B7: =+Admin!C17 -> Instructor | C7: =+Admin!D17 -> Péter Juhász, PhD, CFA
B9: Points achived:
C26: transaction fee | D26: 6000000 | E26: 3000000 | F26: HUF
D27: Firm A | E27: Firm B | F27: Together
C28: rA | D28: 0.1 | E28: 0.1 | F28: 0.1
C29: t | D29: 0.15 | E29: 0.15 | F29: 0.15
C30: Noplat | D30: 840 | E30: 100 | F30: 1000 | G30: M HUF?
C31: D/V | D31: 0.4 | E31: 0.25 | F31: 0.4
C32: rD | D32: 0.05 | E32: 0.05 | F32: 0.05
C33: RONIC | D33: 0.101 | E33: 0.12 | F33: 0.102
C34: g | D34: 0.03 | E34: 0.04 | F34: 0.033
C35: Number of shares | D35: 10000000 | E35: 5000000
C37: K | D37: =D34/D33 -> 0.2970297 | E37: =E34/E33 -> 0.33333333 | F37: =F34/F33 -> 0.32352941
C38: FCFF | D38: =D30*(1-D37) -> 590.49505 | E38: =E30*(1-E37) -> 66.666667 | F38: =F30*(1-F37) -> 676.47059
C39: WACC | D39: =D28-D31*D32*D29 -> 0.097 | E39: =E28-E31*E32*E29 -> 0.098125 | F39: =F28-F31*F32*F29 -> 0.097
H40: Without synergy | I40: Synergy
C41: V | D41: =D38/D39-D34 -> 6087.5478 | E41: =E38/E39-E34 -> 679.36552 | F41: =F38/F39-F34 -> 6973.8906 | H41: =D41+E41 -> 6766.9134 | I41: =F41-H41 -> 206.97724
C42: D | D42: =D41*D31 -> 2435.0191 | E42: =E41*E31 -> 169.84138 | F42: =F41*F31 -> 2789.5562 | H42: =D42+E42 -> 2604.8605 | I42: =F42-H42 -> 184.69572
C43: E | D43: =D41-D42 -> 3652.5287 | E43: =E41-E42 -> 509.52414 | F43: =F41-F42 -> 4184.3344 | H43: =D43+E43 -> 4162.0528 | I43: =F43-H43 -> 22.281516
D45: base | E45: transaction cost (M HUF) | F45: Bargaining range
C46: Min | D46: =E43 -> 509.52414 | E46: 3 | F46: =D46-E46 -> 506.52414
C47: Max | D47: =D46+I41 -> 716.50138 | E47: 6 | F47: =D47+E47 -> 722.50138
C51: Price paid | D51: =F46*(1+25%) -> 633.15518
C52: Cash | D52: =D51*50% -> 316.57759
C53: Equity | D53: =D51-D52 -> 316.57759
C55: Share | D55: =D53/F43 -> 0.075657813 | E55: =D55*D57 -> 945722.67
C57: Number of shares | D57: =D35+50%*E35 -> 12500000

Sheet Task 4
B2: =+Admin!C12 -> Date | C2: =+Admin!D12 -> 45272
B3: =+Admin!C13 -> Student name | C3: =+Admin!D13 -> 0
B4: =+Admin!C14 -> Neptun code | C4: =+Admin!D14 -> 0
B6: =+Admin!C16 -> Study program | C6: =+Admin!D16 -> Master in Finance
B7: =+Admin!C17 -> Instructor | C7: =+Admin!D17 -> Péter Juhász, PhD, CFA
B9: Points achived:
B20: Corporate tax rate | C20: 0.15
B21: Required rate of return on renting | C21: 0.09
B22: Capitalisation rate for EBITDA | C22: 0.08
B23: Average inflation during the last 20 years | C23: 0.02
B25: Age of the building | C25: 20 | D25: years
B26: Useful operational years left over | C26: 25 | D26: years
B27: Accounting life time left over | C27: 20 | D27: years
B29: Total net monthly rental income before D&A | C29: 200
B30: Expected g of rental fees | C30: 0.05
B32: Net book value of the building | C32: 28000
B33: Gross book value of the building | C33: 50000
B37: Rental fee | C37: =+C29*12*(1-C20)/(C21-C30)*(1-(1+C30)^C26/(1+C21)^C26) -> 30971.879 | D37: Growing annuity WITHOUT D&A= (c/(r-g) * (1- (1+g)^n / (1+r) ^n))* (1+r)
B39: D&A | C39: =C32/C27 -> 1400
B40: tax shield of D&A | C40: =C39*C20 -> 210
B41: PV of tax shield | C41: =C40/C21*(1-1/(1+C21)^C27) -> 1916.9946 | D41: Non growing annuity (20 yrs)
A43: 1 | B43: Total value | C43: =C37+C41 -> 32888.874
B46: Net income | C46: =C29*12 -> 2400
B47: Capitalization rate | C47: =C22 -> 0.08
A48: 2 | B48: Value | C48: =C46/C47 -> 30000
A51: 3 | B51: Adjusted purchase cost | C51: =+C33*(1+C23)^C25*C32/C33 -> 41606.527

Sheet Task 5
B2: =+Admin!C12 -> Date | C2: =+Admin!D12 -> 45272
B3: =+Admin!C13 -> Student name | C3: =+Admin!D13 -> 0
B4: =+Admin!C14 -> Neptun code | C4: =+Admin!D14 -> 0
B6: =+Admin!C16 -> Study program | C6: =+Admin!D16 -> Master in Finance
B7: =+Admin!C17 -> Instructor | C7: =+Admin!D17 -> Péter Juhász, PhD, CFA
B9: Points achived:

Sheet Bonus Task
B2: =+Admin!C12 -> Date | C2: =+Admin!D12 -> 45272
B3: =+Admin!C13 -> Student name | C3: =+Admin!D13 -> 0
B4: =+Admin!C14 -> Neptun code | C4: =+Admin!D14 -> 0
B6: =+Admin!C16 -> Study program | C6: =+Admin!D16 -> Master in Finance
B7: =+Admin!C17 -> Instructor | C7: =+Admin!D17 -> Péter Juhász, PhD, CFA
B9: Points achived:
B18: rF | C18: 0.03
B19: Market risk premium | C19: 0.06
B21: A
B22: D/V | C22: 0.5
B23: rD | C23: 0.05
C30: P | D30: number of shares | E30: Capitalisation | F30: betaE | G30: rE | H30: Debt | I30: debt risk premium | J30: betaD | K30: rD | L30: D/V
B31: X | C31: 10 | D31: 1000000 | G31: 0.11 | H31: 5000000 | J31: 0.2 | K31: =+J31*C19+C18 -> 0.042
B32: Y | E32: 5000000 | F32: 1.4 | I32: 0.028 | L32: 0.4
B33: Z | F33: 1.2 | J33: 0.15 | L33: 0.2
