Workbook

Sheet WhichIsBetter
G4: NPV | H4: PI
D5: V | E5: E | F5: BV E | G5: SVA | H5: SVA/BV E
C6: ModelAStandard | D6: =+ModelAStandard!C95 -> 33295.68 | E6: =+ModelAStandard!C93 -> 25057.285 | F6: =+ModelAStandard!C52 -> 12000 | G6: =+E6-F6 -> 13057.285 | H6: =+G6/F6 -> 1.0881071
C7: ModelAFairValue | D7: =+ModelAFairValue!C95 -> 33295.68 | E7: =+ModelAFairValue!$C$93 -> 25057.285 | F7: =+ModelAFairValue!$C$52 -> 11761.605 | G7: =+E7-F7 -> 13295.68 | H7: =+G7/F7 -> 1.1304307
C8: ModelBStandard | D8: =+ModelBStandard!C97 -> 33258.012 | E8: =+ModelBFair!C95 -> 24976.854 | F8: =+ModelBStandard!C53 -> 11030 | G8: =+E8-F8 -> 13946.854 | H8: =+G8/F8 -> 1.2644473
C9: ModelBFair | D9: =+ModelBFair!C97 -> 33258.012 | E9: =+ModelBFair!C95 -> 24976.854 | F9: =+ModelBFair!C53 -> 11718.842 | G9: =+E9-F9 -> 13258.012 | H9: =+G9/F9 -> 1.1313416

Sheet ModelAStandard
C26: 2025 | D26: =+C26+1 -> 2026 | E26: =+D26+1 -> 2027 | F26: =+E26+1 -> 2028 | G26: =+F26+1 -> 2029 | H26: =+G26+1 -> 2030 | I26: TV1 | J26: TV2
B27: IC boy | C27: 20000 | I27: RONIC=WACC
B28: ROIC | C28: 0.15
B29: RONIC | D29: 0.14 | E29: 0.13 | F29: 0.12 | G29: 0.11 | H29: 0.1 | I29: =+I38 -> 0.0952 | J29: =+J38 -> 0.0952 | K29: =+K38 -> 0.0952
B30: K | C30: 0.6 | D30: 0.6 | E30: 0.6 | F30: 0.6 | G30: 0.6 | H30: 0.6 | I30: =+J31/J29 -> 0.6302521 | J30: =+K31/K29 -> 0.6302521
B31: g | J31: 0.06 | K31: 0.06
B32: rA | C32: 0.1 | D32: 0.1 | E32: 0.1 | F32: 0.1 | G32: 0.1 | H32: 0.1 | I32: 0.1 | J32: 0.1 | K32: 0.1
B33: t nominal | C33: 0.2 | D33: 0.2 | E33: 0.2 | F33: 0.2 | G33: 0.2 | H33: 0.2 | I33: 0.2 | J33: 0.2 | K33: 0.2
B34: Debt/V boy | C34: =+C46/C86 -> 0.24743135 | D34: =+D46/D86 -> 0.2316068 | E34: =+E46/E86 -> 0.16330579 | F34: =+F46/F86 -> 0.10229263 | G34: =+G46/G86 -> 0.048022381 | H34: 0.4 | I34: 0.4 | J34: 0.4 | K34: 0.4
B35: rD* for WACC | C35: =+C42/C46 -> 0.077685036 | D35: =+D42/D46 -> 0.078286672 | E35: =+E42/E46 -> 0.078593976 | F35: =+F42/F46 -> 0.078917801 | G35: =+G42/G46 -> 0.079259259 | H35: 0.06 | I35: 0.06 | J35: 0.06 | K35: 0.06
B36: t effective assumed | C36: 0.2 | D36: 0.2 | E36: 0.2 | F36: 0.2 | G36: 0.2 | H36: 0.2 | I36: 0.2 | J36: 0.2 | K36: 0.2
B37: t effective calculated | C37: =+C58/C57 -> 0.2 | D37: =+D58/D57 -> 0.2 | E37: =+E58/E57 -> 0.2 | F37: =+F58/F57 -> 0.2 | G37: =+G58/G57 -> 0.2 | H37: =+H58/H57 -> 0.2 | I37: =+I58/I57 -> 0.2 | J37: =+J58/J57 -> 0.2 | K37: =+K58/K57 -> #DIV/0!
B38: WACC | C38: =+C32-C35*C34*C36 -> 0.096155657 | D38: =+D32-D35*D34*D36 -> 0.096373655 | E38: =+E32-E35*E34*E36 -> 0.09743303 | F38: =+F32-F35*F34*F36 -> 0.098385458 | G38: =+G32-G35*G34*G36 -> 0.099238756 | H38: =+H32-H35*H34*H36 -> 0.0952 | I38: =+I32-I35*I34*I36 -> 0.0952 | J38: =+J32-J35*J34*J36 -> 0.0952 | K38: =+K32-K35*K34*K36 -> 0.0952
B40: Principal boy | C40: 8000 | D40: 8000 | E40: 6000 | F40: 4000 | G40: 2000 | H40: 0
B41: interest | C41: 0.08 | D41: 0.08 | E41: 0.08 | F41: 0.08 | G41: 0.08 | H41: 0.08
B42: Interest payment | C42: =+C40*C41 -> 640 | D42: =+D40*D41 -> 640 | E42: =+E40*E41 -> 480 | F42: =+F40*F41 -> 320 | G42: =+G40*G41 -> 160
B43: Principal payment | C43: =+C40-D40 -> 0 | D43: =+D40-E40 -> 2000 | E43: =+E40-F40 -> 2000 | F43: =+F40-G40 -> 2000 | G43: =+G40-H40 -> 2000
B44: Total CF | C44: =+C42+C43 -> 640 | D44: =+D42+D43 -> 2640 | E44: =+E42+E43 -> 2480 | F44: =+F42+F43 -> 2320 | G44: =+G42+G43 -> 2160
B45: rD | C45: 0.07 | D45: 0.07 | E45: 0.07 | F45: 0.07 | G45: 0.07 | H45: =+H35 -> 0.06 | I45: =+I35 -> 0.06 | J45: =+J35 -> 0.06 | K45: =+K35 -> 0.06
B46: D boy | C46: =+(C44+D46)/(1+C45) -> 8238.3949 | D46: =+(D44+E46)/(1+D45) -> 8175.0825 | E46: =+(E44+F46)/(1+E45) -> 6107.3383 | F46: =+(F44+G46)/(1+F45) -> 4054.852 | G46: =+(G44+H46)/(1+G45) -> 2018.6916 | H46: 0
B50: =+B27 -> IC boy | C50: =+C27 -> 20000 | D50: =+C50+C67 -> 21800 | E50: =+D50+D67 -> 23751.2 | F50: =+E50+E67 -> 25854.594 | G50: =+F50+F67 -> 28109.432 | H50: =+G50+G67 -> 30513.089 | I50: =+H50+H67 -> 33060.965 | J50: =+I50+I67 -> 35890.179
B51: BV D boy | C51: =+C40 -> 8000 | D51: =+D40 -> 8000 | E51: =+E40 -> 6000 | F51: =+F40 -> 4000 | G51: =+G40 -> 2000 | H51: =+H34*H80 -> 17842.274 | I51: =+I34*I80 -> 18861.424 | J51: =+J34*J80 -> 19993.11
B52: BV E boy | C52: =+C50-C51 -> 12000 | D52: =+D50-D51 -> 13800 | E52: =+E50-E51 -> 17751.2 | F52: =+F50-F51 -> 21854.594 | G52: =+G50-G51 -> 26109.432 | H52: =+H50-H51 -> 12670.815 | I52: =+I50-I51 -> 14199.541 | J52: =+J50-J51 -> 15897.069
B55: EBIT | C55: =+C66/(1-C36) -> 3750 | D55: =+D66/(1-D36) -> 4065 | E55: =+E66/(1-E36) -> 4382.07 | F55: =+F66/(1-F36) -> 4697.579 | G55: =+G66/(1-G36) -> 5007.6193 | H55: =+H66/(1-H36) -> 5308.0764 | I55: =+I66/(1-I36) -> 5611.2737 | J55: =+J66/(1-J36) -> 5947.9502
B56: Interest payment | C56: =+C42 -> 640 | D56: =+D42 -> 640 | E56: =+E42 -> 480 | F56: =+F42 -> 320 | G56: =+G42 -> 160 | H56: =+H51*H35 -> 1070.5364 | I56: =+I51*I35 -> 1131.6855 | J56: =+J51*J35 -> 1199.5866
B57: PBT | C57: =+C55-C56 -> 3110 | D57: =+D55-D56 -> 3425 | E57: =+E55-E56 -> 3902.07 | F57: =+F55-F56 -> 4377.579 | G57: =+G55-G56 -> 4847.6193 | H57: =+H55-H56 -> 4237.54 | I57: =+I55-I56 -> 4479.5883 | J57: =+J55-J56 -> 4748.3636
B58: Tax | C58: =+IF(C57<0,0,C57*C33) -> 622 | D58: =+IF(D57<0,0,D57*D33) -> 685 | E58: =+IF(E57<0,0,E57*E33) -> 780.414 | F58: =+IF(F57<0,0,F57*F33) -> 875.51581 | G58: =+IF(G57<0,0,G57*G33) -> 969.52385 | H58: =+IF(H57<0,0,H57*H33) -> 847.508 | I58: =+IF(I57<0,0,I57*I33) -> 895.91766 | J58: =+IF(J57<0,0,J57*J33) -> 949.67271
B59: PAT | C59: =+C57-C58 -> 2488 | D59: =+D57-D58 -> 2740 | E59: =+E57-E58 -> 3121.656 | F59: =+F57-F58 -> 3502.0632 | G59: =+G57-G58 -> 3878.0954 | H59: =+H57-H58 -> 3390.032 | I59: =+I57-I58 -> 3583.6706 | J59: =+J57-J58 -> 3798.6909
B60: Dividend | C60: =+C59-C61 -> 688 | D60: =+D59-D61 -> 0 | E60: =+E59-E61 -> 0 | F60: =+F59-F61 -> 0 | G60: =+G59-G61 -> 3878.0954 | H60: =+H59-H61 -> 1861.306 | I60: =+I59-I61 -> 1886.1424 | J60: =+J59-J61 -> 0
B61: Retained Earnings | C61: =+IF(C59<0,C59,MAX(0,MIN(C59,C63))) -> 1800 | D61: =+IF(D59<0,D59,MAX(0,MIN(D59,D63))) -> 2740 | E61: =+IF(E59<0,E59,MAX(0,MIN(E59,E63))) -> 3121.656 | F61: =+IF(F59<0,F59,MAX(0,MIN(F59,F63))) -> 3502.0632 | G61: =+IF(G59<0,G59,MAX(0,MIN(G59,G63))) -> 0 | H61: =+IF(H59<0,H59,MAX(0,MIN(H59,H63))) -> 1528.726 | I61: =+IF(I59<0,I59,MAX(0,MIN(I59,I63))) -> 1697.5282 | J61: =+IF(J59<0,J59,MAX(0,MIN(J59,J63))) -> 3798.6909
B63: dBVEquity needed | C63: =+D52-C52 -> 1800 | D63: =+E52-D52 -> 3951.2 | E63: =+F52-E52 -> 4103.3936 | F63: =+G52-F52 -> 4254.8379 | G63: =+H52-G52 -> -13438.616 | H63: =+I52-H52 -> 1528.726 | I63: =+J52-I52 -> 1697.5282
B64: Share issue/buyback | C64: =+C63-C61 -> 0 | D64: =+D63-D61 -> 1211.2 | E64: =+E63-E61 -> 981.7376 | F64: =+F63-F61 -> 752.77471 | G64: =+G63-G61 -> -13438.616 | H64: =+H63-H61 -> 0 | I64: =+I63-I61 -> 0
B66: Noplat | C66: =+C50*C28 -> 3000 | D66: =+C66+C67*D29 -> 3252 | E66: =+D66+D67*E29 -> 3505.656 | F66: =+E66+E67*F29 -> 3758.0632 | G66: =+F66+F67*G29 -> 4006.0954 | H66: =+G66+G67*H29 -> 4246.4611 | I66: =+H66+H67*I29 -> 4489.019 | J66: =+I66+I67*J29 -> 4758.3601
B67: dIC | C67: =+C66*C30 -> 1800 | D67: =+D66*D30 -> 1951.2 | E67: =+E66*E30 -> 2103.3936 | F67: =+F66*F30 -> 2254.8379 | G67: =+G66*G30 -> 2403.6572 | H67: =+H66*H30 -> 2547.8767 | I67: =+I66*I30 -> 2829.2136 | J67: =+J66*J30 -> 2998.9665
B68: FCFF | C68: =+C66-C67 -> 1200 | D68: =+D66-D67 -> 1300.8 | E68: =+E66-E67 -> 1402.2624 | F68: =+F66-F67 -> 1503.2253 | G68: =+G66-G67 -> 1602.4382 | H68: =+H66-H67 -> 1698.5845 | I68: =+I66-I67 -> 1659.8053 | J68: =+J66-J67 -> 1759.3937
B69: =+B56 -> Interest payment | C69: =+C56 -> 640 | D69: =+D56 -> 640 | E69: =+E56 -> 480 | F69: =+F56 -> 320 | G69: =+G56 -> 160 | H69: =+H56 -> 1070.5364 | I69: =+I56 -> 1131.6855
B70: TS | C70: =+C69*C36 -> 128 | D70: =+D69*D36 -> 128 | E70: =+E69*E36 -> 96 | F70: =+F69*F36 -> 64 | G70: =+G69*G36 -> 32 | H70: =+H69*H36 -> 214.10728 | I70: =+I69*I36 -> 226.33709
B71: dD | C71: =+D51-C51 -> 0 | D71: =+E51-D51 -> -2000 | E71: =+F51-E51 -> -2000 | F71: =+G51-F51 -> -2000 | G71: =+H51-G51 -> 15842.274 | H71: =+I51-H51 -> 1019.1507 | I71: =+J51-I51 -> 1131.6855
B72: FCFE | C72: =+C68-C69+C70+C71 -> 688 | D72: =+D68-D69+D70+D71 -> -1211.2 | E72: =+E68-E69+E70+E71 -> -981.7376 | F72: =+F68-F69+F70+F71 -> -752.77471 | G72: =+G68-G69+G70+G71 -> 17316.712 | H72: =+H68-H69+H70+H71 -> 1861.306 | I72: =+I68-I69+I70+I71 -> 1886.1424
B73: =+B60 -> Dividend | C73: =+C60 -> 688 | D73: =+D60 -> 0 | E73: =+E60 -> 0 | F73: =+F60 -> 0 | G73: =+G60 -> 3878.0954 | H73: =+H60 -> 1861.306 | I73: =+I60 -> 1886.1424
B74: dBV Equity w/oRetained Earnings | C74: =+D52-C52-C61 -> 0 | D74: =+E52-D52-D61 -> 1211.2 | E74: =+F52-E52-E61 -> 981.7376 | F74: =+G52-F52-F61 -> 752.77471 | G74: =+H52-G52-G61 -> -13438.616 | H74: =+I52-H52-H61 -> 0 | I74: =+J52-I52-I61 -> 0
B75: dNOn-op assets | C75: =+C72-C73+C74 -> 0 | D75: =+D72-D73+D74 -> 0 | E75: =+E72-E73+E74 -> 0 | F75: =+F72-F73+F74 -> 0 | G75: =+G72-G73+G74 -> 0 | H75: =+H72-H73+H74 -> -2.5011104e-12 | I75: =+I72-I73+I74 -> -2.9558578e-12
B77: FCFF // WACC
B78: =+B68 -> FCFF | C78: =+C68 -> 1200 | D78: =+D68 -> 1300.8 | E78: =+E68 -> 1402.2624 | F78: =+F68 -> 1503.2253 | G78: =+G68 -> 1602.4382 | H78: =+H68 -> 1698.5845 | I78: =+I68 -> 1659.8053 | J78: =+J68 -> 1759.3937
B79: =+B38 -> WACC | C79: =+C38 -> 0.096155657 | D79: =+D38 -> 0.096373655 | E79: =+E38 -> 0.09743303 | F79: =+F38 -> 0.098385458 | G79: =+G38 -> 0.099238756 | H79: =+H38 -> 0.0952 | I79: =+I38 -> 0.0952 | J79: =+J38 -> 0.0952
B80: V boy | C80: =+(C78+D80)/(1+C79) -> 33295.68 | D80: =+(D78+E80)/(1+D79) -> 35297.248 | E80: =+(E78+F80)/(1+E79) -> 37398.173 | F80: =+(F78+G80)/(1+F79) -> 39639.727 | G80: =+(G78+H80)/(1+G79) -> 42036.475 | H80: =+(H78+I80)/(1+H79) -> 44605.684 | I80: =+(I78+J80)/(1+I79) -> 47153.561 | J80: =+J78/(J79-K31) -> 49982.774
B83: APV // rA
B84: FCFF+TS | C84: =+C68+C70 -> 1328 | D84: =+D68+D70 -> 1428.8 | E84: =+E68+E70 -> 1498.2624 | F84: =+F68+F70 -> 1567.2253 | G84: =+G68+G70 -> 1634.4382 | H84: =+H68+H70 -> 1912.6917 | I84: =+I68+I70 -> 1886.1424
B85: =+B32 -> rA | C85: =+C32 -> 0.1 | D85: =+D32 -> 0.1 | E85: =+E32 -> 0.1 | F85: =+F32 -> 0.1 | G85: =+G32 -> 0.1 | H85: =+H32 -> 0.1 | I85: =+I32 -> 0.1
B86: Vboy | C86: =+(C84+D86)/(1+C85) -> 33295.68 | D86: =+(D84+E86)/(1+D85) -> 35297.248 | E86: =+(E84+F86)/(1+E85) -> 37398.173 | F86: =+(F84+G86)/(1+F85) -> 39639.727 | G86: =+(G84+H86)/(1+G85) -> 42036.475 | H86: =+(H84+I86)/(1+H85) -> 44605.684 | I86: =+I84/(I85-J31) -> 47153.561
B90: FCFE // rE
B91: =+B72 -> FCFE | C91: =+C72 -> 688 | D91: =+D72 -> -1211.2 | E91: =+E72 -> -981.7376 | F91: =+F72 -> -752.77471 | G91: =+G72 -> 17316.712 | H91: =+H72 -> 1861.306 | I91: =+I72 -> 1886.1424
B92: rE | C92: =+(C32-C34*C45)/(1-C34) -> 0.10986347 | D92: =+(D32-D34*D45)/(1-D34) -> 0.10904251 | E92: =+(E32-E34*E45)/(1-E34) -> 0.10585539 | F92: =+(F32-F34*F45)/(1-F34) -> 0.10341846 | G92: =+(G32-G34*G45)/(1-G34) -> 0.10151335 | H92: =+(H32-H34*H45)/(1-H34) -> 0.12666667 | I92: =+(I32-I34*I45)/(1-I34) -> 0.12666667
B93: E boy | C93: =+(C91+D93)/(1+C92) -> 25057.285 | D93: =+(D91+E93)/(1+D92) -> 27122.165 | E93: =+(E91+F93)/(1+E92) -> 31290.834 | F93: =+(F91+G93)/(1+F92) -> 35584.875 | G93: =+(G91+H93)/(1+G92) -> 40017.783 | H93: =+(H91+I93)/(1+H92) -> 26763.41 | I93: =+I91/(I92-J31) -> 28292.136
B94: =+B46 -> D boy | C94: =+C46 -> 8238.3949 | D94: =+D46 -> 8175.0825 | E94: =+E46 -> 6107.3383 | F94: =+F46 -> 4054.852 | G94: =+G46 -> 2018.6916 | H94: =+H51 -> 17842.274 | I94: =+I51 -> 18861.424 | J94: D = BVD
B95: V boy | C95: =+C93+C94 -> 33295.68 | D95: =+D93+D94 -> 35297.248 | E95: =+E93+E94 -> 37398.173 | F95: =+F93+F94 -> 39639.727 | G95: =+G93+G94 -> 42036.475 | H95: =+H93+H94 -> 44605.684 | I95: =+I93+I94 -> 47153.561

Sheet ModelAFairValue
C26: 2025 | D26: =+C26+1 -> 2026 | E26: =+D26+1 -> 2027 | F26: =+E26+1 -> 2028 | G26: =+F26+1 -> 2029 | H26: =+G26+1 -> 2030 | I26: TV1 | J26: TV2
B27: IC boy | C27: 20000 | I27: RONIC=WACC
B28: ROIC | C28: 0.15
B29: RONIC | D29: 0.14 | E29: 0.13 | F29: 0.12 | G29: 0.11 | H29: 0.1 | I29: =+I38 -> 0.0952 | J29: =+J38 -> 0.0952 | K29: =+K38 -> 0.0952
B30: K | C30: 0.6 | D30: 0.6 | E30: 0.6 | F30: 0.6 | G30: 0.6 | H30: 0.6 | I30: =+J31/J29 -> 0.6302521 | J30: =+K31/K29 -> 0.6302521
B31: g | J31: 0.06 | K31: 0.06
B32: rA | C32: 0.1 | D32: 0.1 | E32: 0.1 | F32: 0.1 | G32: 0.1 | H32: 0.1 | I32: 0.1 | J32: 0.1 | K32: 0.1
B33: t nominal | C33: 0.2 | D33: 0.2 | E33: 0.2 | F33: 0.2 | G33: 0.2 | H33: 0.2 | I33: 0.2 | J33: 0.2 | K33: 0.2
B34: Debt/V boy | C34: =+C46/C86 -> 0.24743135 | D34: =+D46/D86 -> 0.2316068 | E34: =+E46/E86 -> 0.16330579 | F34: =+F46/F86 -> 0.10229263 | G34: =+G46/G86 -> 0.048022381 | H34: 0.4 | I34: 0.4 | J34: 0.4 | K34: 0.4
B35: rD* for WACC | C35: =+C42/C46 -> 0.077685036 | D35: =+D42/D46 -> 0.078286672 | E35: =+E42/E46 -> 0.078593976 | F35: =+F42/F46 -> 0.078917801 | G35: =+G42/G46 -> 0.079259259 | H35: 0.06 | I35: 0.06 | J35: 0.06 | K35: 0.06
B36: t effective assumed | C36: 0.2 | D36: 0.2 | E36: 0.2 | F36: 0.2 | G36: 0.2 | H36: 0.2 | I36: 0.2 | J36: 0.2 | K36: 0.2
B37: t effective calculated | C37: =+C58/C57 -> 0.2 | D37: =+D58/D57 -> 0.2 | E37: =+E58/E57 -> 0.2 | F37: =+F58/F57 -> 0.2 | G37: =+G58/G57 -> 0.2 | H37: =+H58/H57 -> 0.2 | I37: =+I58/I57 -> 0.2 | J37: =+J58/J57 -> 0.2 | K37: =+K58/K57 -> #DIV/0!
B38: WACC | C38: =+C32-C35*C34*C36 -> 0.096155657 | D38: =+D32-D35*D34*D36 -> 0.096373655 | E38: =+E32-E35*E34*E36 -> 0.09743303 | F38: =+F32-F35*F34*F36 -> 0.098385458 | G38: =+G32-G35*G34*G36 -> 0.099238756 | H38: =+H32-H35*H34*H36 -> 0.0952 | I38: =+I32-I35*I34*I36 -> 0.0952 | J38: =+J32-J35*J34*J36 -> 0.0952 | K38: =+K32-K35*K34*K36 -> 0.0952
B40: Principal boy | C40: 8000 | D40: 8000 | E40: 6000 | F40: 4000 | G40: 2000 | H40: 0
B41: interest | C41: 0.08 | D41: 0.08 | E41: 0.08 | F41: 0.08 | G41: 0.08 | H41: 0.08
B42: Interest payment | C42: =+C40*C41 -> 640 | D42: =+D40*D41 -> 640 | E42: =+E40*E41 -> 480 | F42: =+F40*F41 -> 320 | G42: =+G40*G41 -> 160
B43: Principal payment | C43: =+C40-D40 -> 0 | D43: =+D40-E40 -> 2000 | E43: =+E40-F40 -> 2000 | F43: =+F40-G40 -> 2000 | G43: =+G40-H40 -> 2000
B44: Total CF | C44: =+C42+C43 -> 640 | D44: =+D42+D43 -> 2640 | E44: =+E42+E43 -> 2480 | F44: =+F42+F43 -> 2320 | G44: =+G42+G43 -> 2160
B45: rD | C45: 0.07 | D45: 0.07 | E45: 0.07 | F45: 0.07 | G45: 0.07 | H45: =+H35 -> 0.06 | I45: =+I35 -> 0.06 | J45: =+J35 -> 0.06 | K45: =+K35 -> 0.06
B46: D boy | C46: =+(C44+D46)/(1+C45) -> 8238.3949 | D46: =+(D44+E46)/(1+D45) -> 8175.0825 | E46: =+(E44+F46)/(1+E45) -> 6107.3383 | F46: =+(F44+G46)/(1+F45) -> 4054.852 | G46: =+(G44+H46)/(1+G45) -> 2018.6916 | H46: 0
B50: =+B27 -> IC boy | C50: =+C27 -> 20000 | D50: =+C50+C67 -> 21800 | E50: =+D50+D67 -> 23751.2 | F50: =+E50+E67 -> 25854.594 | G50: =+F50+F67 -> 28109.432 | H50: =+G50+G67 -> 30513.089 | I50: =+H50+H67 -> 33060.965 | J50: =+I50+I67 -> 35890.179
B51: BV D boy | C51: =+C46 -> 8238.3949 | D51: =+D46 -> 8175.0825 | E51: =+E46 -> 6107.3383 | F51: =+F46 -> 4054.852 | G51: =+G46 -> 2018.6916 | H51: =+H34*H80 -> 17842.274 | I51: =+I34*I80 -> 18861.424 | J51: =+J34*J80 -> 19993.11
B52: BV E boy | C52: =+C50-C51 -> 11761.605 | D52: =+D50-D51 -> 13624.918 | E52: =+E50-E51 -> 17643.862 | F52: =+F50-F51 -> 21799.742 | G52: =+G50-G51 -> 26090.74 | H52: =+H50-H51 -> 12670.815 | I52: =+I50-I51 -> 14199.541 | J52: =+J50-J51 -> 15897.069
B55: EBIT | C55: =+C66/(1-C36) -> 3750 | D55: =+D66/(1-D36) -> 4065 | E55: =+E66/(1-E36) -> 4382.07 | F55: =+F66/(1-F36) -> 4697.579 | G55: =+G66/(1-G36) -> 5007.6193 | H55: =+H66/(1-H36) -> 5308.0764 | I55: =+I66/(1-I36) -> 5611.2737 | J55: =+J66/(1-J36) -> 5947.9502
B56: Interest payment | C56: =+C42 -> 640 | D56: =+D42 -> 640 | E56: =+E42 -> 480 | F56: =+F42 -> 320 | G56: =+G42 -> 160 | H56: =+H51*H35 -> 1070.5364 | I56: =+I51*I35 -> 1131.6855 | J56: =+J51*J35 -> 1199.5866
B57: PBT | C57: =+C55-C56 -> 3110 | D57: =+D55-D56 -> 3425 | E57: =+E55-E56 -> 3902.07 | F57: =+F55-F56 -> 4377.579 | G57: =+G55-G56 -> 4847.6193 | H57: =+H55-H56 -> 4237.54 | I57: =+I55-I56 -> 4479.5883 | J57: =+J55-J56 -> 4748.3636
B58: Tax | C58: =+IF(C57<0,0,C57*C33) -> 622 | D58: =+IF(D57<0,0,D57*D33) -> 685 | E58: =+IF(E57<0,0,E57*E33) -> 780.414 | F58: =+IF(F57<0,0,F57*F33) -> 875.51581 | G58: =+IF(G57<0,0,G57*G33) -> 969.52385 | H58: =+IF(H57<0,0,H57*H33) -> 847.508 | I58: =+IF(I57<0,0,I57*I33) -> 895.91766 | J58: =+IF(J57<0,0,J57*J33) -> 949.67271
B59: PAT | C59: =+C57-C58 -> 2488 | D59: =+D57-D58 -> 2740 | E59: =+E57-E58 -> 3121.656 | F59: =+F57-F58 -> 3502.0632 | G59: =+G57-G58 -> 3878.0954 | H59: =+H57-H58 -> 3390.032 | I59: =+I57-I58 -> 3583.6706 | J59: =+J57-J58 -> 3798.6909
B60: Dividend | C60: =+C59-C61 -> 624.68764 | D60: =+D59-D61 -> 0 | E60: =+E59-E61 -> 0 | F60: =+F59-F61 -> 0 | G60: =+G59-G61 -> 3878.0954 | H60: =+H59-H61 -> 1861.306 | I60: =+I59-I61 -> 1886.1424 | J60: =+J59-J61 -> 0
B61: Retained Earnings | C61: =+IF(C59<0,C59,MAX(0,MIN(C59,C63))) -> 1863.3124 | D61: =+IF(D59<0,D59,MAX(0,MIN(D59,D63))) -> 2740 | E61: =+IF(E59<0,E59,MAX(0,MIN(E59,E63))) -> 3121.656 | F61: =+IF(F59<0,F59,MAX(0,MIN(F59,F63))) -> 3502.0632 | G61: =+IF(G59<0,G59,MAX(0,MIN(G59,G63))) -> 0 | H61: =+IF(H59<0,H59,MAX(0,MIN(H59,H63))) -> 1528.726 | I61: =+IF(I59<0,I59,MAX(0,MIN(I59,I63))) -> 1697.5282 | J61: =+IF(J59<0,J59,MAX(0,MIN(J59,J63))) -> 3798.6909
B63: dBVEquity needed | C63: =+D52-C52 -> 1863.3124 | D63: =+E52-D52 -> 4018.9442 | E63: =+F52-E52 -> 4155.8799 | F63: =+G52-F52 -> 4290.9983 | G63: =+H52-G52 -> -13419.925 | H63: =+I52-H52 -> 1528.726 | I63: =+J52-I52 -> 1697.5282
B64: Share issue/buyback | C64: =+C63-C61 -> 0 | D64: =+D63-D61 -> 1278.9442 | E64: =+E63-E61 -> 1034.2239 | F64: =+F63-F61 -> 788.93507 | G64: =+G63-G61 -> -13419.925 | H64: =+H63-H61 -> 0 | I64: =+I63-I61 -> 0
B66: Noplat | C66: =+C50*C28 -> 3000 | D66: =+C66+C67*D29 -> 3252 | E66: =+D66+D67*E29 -> 3505.656 | F66: =+E66+E67*F29 -> 3758.0632 | G66: =+F66+F67*G29 -> 4006.0954 | H66: =+G66+G67*H29 -> 4246.4611 | I66: =+H66+H67*I29 -> 4489.019 | J66: =+I66+I67*J29 -> 4758.3601
B67: dIC | C67: =+C66*C30 -> 1800 | D67: =+D66*D30 -> 1951.2 | E67: =+E66*E30 -> 2103.3936 | F67: =+F66*F30 -> 2254.8379 | G67: =+G66*G30 -> 2403.6572 | H67: =+H66*H30 -> 2547.8767 | I67: =+I66*I30 -> 2829.2136 | J67: =+J66*J30 -> 2998.9665
B68: FCFF | C68: =+C66-C67 -> 1200 | D68: =+D66-D67 -> 1300.8 | E68: =+E66-E67 -> 1402.2624 | F68: =+F66-F67 -> 1503.2253 | G68: =+G66-G67 -> 1602.4382 | H68: =+H66-H67 -> 1698.5845 | I68: =+I66-I67 -> 1659.8053 | J68: =+J66-J67 -> 1759.3937
B69: =+B56 -> Interest payment | C69: =+C56 -> 640 | D69: =+D56 -> 640 | E69: =+E56 -> 480 | F69: =+F56 -> 320 | G69: =+G56 -> 160 | H69: =+H56 -> 1070.5364 | I69: =+I56 -> 1131.6855
B70: TS | C70: =+C69*C36 -> 128 | D70: =+D69*D36 -> 128 | E70: =+E69*E36 -> 96 | F70: =+F69*F36 -> 64 | G70: =+G69*G36 -> 32 | H70: =+H69*H36 -> 214.10728 | I70: =+I69*I36 -> 226.33709
B71: dD | C71: =+D51-C51 -> -63.31236 | D71: =+E51-D51 -> -2067.7442 | E71: =+F51-E51 -> -2052.4863 | F71: =+G51-F51 -> -2036.1604 | G71: =+H51-G51 -> 15823.582 | H71: =+I51-H51 -> 1019.1507 | I71: =+J51-I51 -> 1131.6855
B72: FCFE | C72: =+C68-C69+C70+C71 -> 624.68764 | D72: =+D68-D69+D70+D71 -> -1278.9442 | E72: =+E68-E69+E70+E71 -> -1034.2239 | F72: =+F68-F69+F70+F71 -> -788.93507 | G72: =+G68-G69+G70+G71 -> 17298.02 | H72: =+H68-H69+H70+H71 -> 1861.306 | I72: =+I68-I69+I70+I71 -> 1886.1424
B73: =+B60 -> Dividend | C73: =+C60 -> 624.68764 | D73: =+D60 -> 0 | E73: =+E60 -> 0 | F73: =+F60 -> 0 | G73: =+G60 -> 3878.0954 | H73: =+H60 -> 1861.306 | I73: =+I60 -> 1886.1424
B74: dBV Equity w/oRetained Earnings | C74: =+D52-C52-C61 -> 0 | D74: =+E52-D52-D61 -> 1278.9442 | E74: =+F52-E52-E61 -> 1034.2239 | F74: =+G52-F52-F61 -> 788.93507 | G74: =+H52-G52-G61 -> -13419.925 | H74: =+I52-H52-H61 -> 0 | I74: =+J52-I52-I61 -> 0
B75: dNOn-op assets | C75: =+C72-C73+C74 -> 0 | D75: =+D72-D73+D74 -> 1.8189894e-12 | E75: =+E72-E73+E74 -> 0 | F75: =+F72-F73+F74 -> -3.4106051e-12 | G75: =+G72-G73+G74 -> 0 | H75: =+H72-H73+H74 -> -2.5011104e-12 | I75: =+I72-I73+I74 -> -2.9558578e-12
B77: FCFF // WACC
B78: =+B68 -> FCFF | C78: =+C68 -> 1200 | D78: =+D68 -> 1300.8 | E78: =+E68 -> 1402.2624 | F78: =+F68 -> 1503.2253 | G78: =+G68 -> 1602.4382 | H78: =+H68 -> 1698.5845 | I78: =+I68 -> 1659.8053 | J78: =+J68 -> 1759.3937
B79: =+B38 -> WACC | C79: =+C38 -> 0.096155657 | D79: =+D38 -> 0.096373655 | E79: =+E38 -> 0.09743303 | F79: =+F38 -> 0.098385458 | G79: =+G38 -> 0.099238756 | H79: =+H38 -> 0.0952 | I79: =+I38 -> 0.0952 | J79: =+J38 -> 0.0952
B80: V boy | C80: =+(C78+D80)/(1+C79) -> 33295.68 | D80: =+(D78+E80)/(1+D79) -> 35297.248 | E80: =+(E78+F80)/(1+E79) -> 37398.173 | F80: =+(F78+G80)/(1+F79) -> 39639.727 | G80: =+(G78+H80)/(1+G79) -> 42036.475 | H80: =+(H78+I80)/(1+H79) -> 44605.684 | I80: =+(I78+J80)/(1+I79) -> 47153.561 | J80: =+J78/(J79-K31) -> 49982.774
B83: APV // rA
B84: FCFF+TS | C84: =+C68+C70 -> 1328 | D84: =+D68+D70 -> 1428.8 | E84: =+E68+E70 -> 1498.2624 | F84: =+F68+F70 -> 1567.2253 | G84: =+G68+G70 -> 1634.4382 | H84: =+H68+H70 -> 1912.6917 | I84: =+I68+I70 -> 1886.1424
B85: =+B32 -> rA | C85: =+C32 -> 0.1 | D85: =+D32 -> 0.1 | E85: =+E32 -> 0.1 | F85: =+F32 -> 0.1 | G85: =+G32 -> 0.1 | H85: =+H32 -> 0.1 | I85: =+I32 -> 0.1
B86: Vboy | C86: =+(C84+D86)/(1+C85) -> 33295.68 | D86: =+(D84+E86)/(1+D85) -> 35297.248 | E86: =+(E84+F86)/(1+E85) -> 37398.173 | F86: =+(F84+G86)/(1+F85) -> 39639.727 | G86: =+(G84+H86)/(1+G85) -> 42036.475 | H86: =+(H84+I86)/(1+H85) -> 44605.684 | I86: =+I84/(I85-J31) -> 47153.561
B90: FCFE // rE
B91: =+B72 -> FCFE | C91: =+C72 -> 624.68764 | D91: =+D72 -> -1278.9442 | E91: =+E72 -> -1034.2239 | F91: =+F72 -> -788.93507 | G91: =+G72 -> 17298.02 | H91: =+H72 -> 1861.306 | I91: =+I72 -> 1886.1424
B92: rE | C92: =+(C32-C34*C35)/(1-C34) -> 0.10733677 | D92: =+(D32-D34*D35)/(1-D34) -> 0.10654477 | E92: =+(E32-E34*E35)/(1-E34) -> 0.10417802 | F92: =+(F32-F34*F35)/(1-F34) -> 0.10240229 | G92: =+(G32-G34*G35)/(1-G34) -> 0.10104626 | H92: =+(H32-H34*H45)/(1-H34) -> 0.12666667 | I92: =+(I32-I34*I45)/(1-I34) -> 0.12666667
B93: E boy | C93: =+(C91+D93)/(1+C92) -> 25057.285 | D93: =+(D91+E93)/(1+D92) -> 27122.165 | E93: =+(E91+F93)/(1+E92) -> 31290.834 | F93: =+(F91+G93)/(1+F92) -> 35584.875 | G93: =+(G91+H93)/(1+G92) -> 40017.783 | H93: =+(H91+I93)/(1+H92) -> 26763.41 | I93: =+I91/(I92-J31) -> 28292.136
B94: =+B46 -> D boy | C94: =+C46 -> 8238.3949 | D94: =+D46 -> 8175.0825 | E94: =+E46 -> 6107.3383 | F94: =+F46 -> 4054.852 | G94: =+G46 -> 2018.6916 | H94: =+H51 -> 17842.274 | I94: =+I51 -> 18861.424 | J94: D = BVD
B95: V boy | C95: =+C93+C94 -> 33295.68 | D95: =+D93+D94 -> 35297.248 | E95: =+E93+E94 -> 37398.173 | F95: =+F93+F94 -> 39639.727 | G95: =+G93+G94 -> 42036.475 | H95: =+H93+H94 -> 44605.684 | I95: =+I93+I94 -> 47153.561

Sheet ModelBStandard
C26: 2025 | D26: =+C26+1 -> 2026 | E26: =+D26+1 -> 2027 | F26: =+E26+1 -> 2028 | G26: =+F26+1 -> 2029 | H26: =+G26+1 -> 2030 | I26: TV1 | J26: TV2
B27: IC boy | C27: 20000 | I27: RONIC=WACC
B28: ROIC | C28: 0.15
B29: RONIC | D29: 0.14 | E29: 0.13 | F29: 0.12 | G29: 0.11 | H29: 0.1 | I29: =+I38 -> 0.0952 | J29: =+J38 -> 0.0952 | K29: =+K38 -> 0.0952
B30: K | C30: 0.6 | D30: 0.6 | E30: 0.6 | F30: 0.6 | G30: 0.6 | H30: 0.6 | I30: =+J31/J29 -> 0.6302521 | J30: =+K31/K29 -> 0.6302521
B31: g | J31: 0.06 | K31: 0.06
B32: rA | C32: 0.1 | D32: 0.1 | E32: 0.1 | F32: 0.1 | G32: 0.1 | H32: 0.1 | I32: 0.1 | J32: 0.1 | K32: 0.1
B33: t nominal | C33: 0.2 | D33: 0.2 | E33: 0.2 | F33: 0.2 | G33: 0.2 | H33: 0.2 | I33: 0.2 | J33: 0.2 | K33: 0.2
B34: Debt/V boy | C34: =+C46/C88 -> 0.63841617 | D34: =+D46/D88 -> 0.63070504 | E34: =+E46/E88 -> 0.62404386 | F34: =+F46/F88 -> 0.61829188 | G34: =+G46/G88 -> 0.50391065 | H34: 0.4 | I34: 0.4 | J34: 0.4 | K34: 0.4
B35: rD* for WACC | C35: =+C42/C47 -> 0.021902204 | D35: =+D42/D47 -> 0.020881826 | E35: =+E42/E47 -> 0.019890313 | F35: =+F42/F47 -> 0.020907367 | G35: =+G42/G47 -> 0.012250959 | H35: 0.06 | I35: 0.06 | J35: 0.06 | K35: 0.06
B36: t effective assumed | C36: 0.2 | D36: 0.2 | E36: 0.2 | F36: 0.2 | G36: 0.2 | H36: 0.2 | I36: 0.2 | J36: 0.2 | K36: 0.2
B37: t effective calculated | C37: =+C59/C58 -> 0.2 | D37: =+D59/D58 -> 0.2 | E37: =+E59/E58 -> 0.2 | F37: =+F59/F58 -> 0.2 | G37: =+G59/G58 -> 0.2 | H37: =+H59/H58 -> 0.2 | I37: =+I59/I58 -> 0.2 | J37: =+J59/J58 -> 0.2 | K37: =+K59/K58 -> #DIV/0!
B38: WACC | C38: =+C32-C35*C48*C36 -> 0.097233749 | D38: =+D32-D35*D48*D36 -> 0.097393163 | E38: =+E32-E35*E48*E36 -> 0.09754196 | F38: =+F32-F35*F48*F36 -> 0.097681262 | G38: =+G32-G35*G48*G36 -> 0.098906043 | H38: =+H32-H35*H34*H36 -> 0.0952 | I38: =+I32-I35*I34*I36 -> 0.0952 | J38: =+J32-J35*J34*J36 -> 0.0952 | K38: =+K32-K35*K34*K36 -> 0.0952
B40: Principal boy | C40: 9200 | D40: 9200 | E40: 9200 | F40: 9200 | G40: =+F40/2 -> 4600 | H40: 0
B41: interest | C41: 0.05 | D41: 0.05 | E41: 0.05 | F41: 0.05 | G41: 0.05
B42: Interest payment | C42: =+C40*C41 -> 460 | D42: =+D40*D41 -> 460 | E42: =+E40*E41 -> 460 | F42: =+F40*F41 -> 460 | G42: =+G40*G41 -> 230
B43: Principal payment | C43: =+C40-D40 -> 0 | D43: =+D40-E40 -> 0 | E43: =+E40-F40 -> 0 | F43: =+F40-G40 -> 4600 | G43: =+G40-H40 -> 4600
B44: Total CF = Debt Service | C44: =+C42+C43 -> 460 | D44: =+D42+D43 -> 460 | E44: =+E42+E43 -> 460 | F44: =+F42+F43 -> 5060 | G44: =+G42+G43 -> 4830
B45: rD | C45: 0.07 | D45: 0.07 | E45: 0.07 | F45: 0.07 | G45: 0.07 | H45: =+H35 -> 0.06 | I45: =+I35 -> 0.06 | J45: =+J35 -> 0.06 | K45: =+K35 -> 0.06
B46: D boy | C46: =+(C44+D46)/(1+C45) -> 21232.453 | D46: =+(D44+E46)/(1+D45) -> 22258.725 | E46: =+(E44+F46)/(1+E45) -> 23356.835 | F46: =+(F44+G46)/(1+F45) -> 24531.814 | G46: =+(G44+H46)/(1+G45) -> 21189.041 | H46: =+H52 -> 17842.274
B47: net D boy | C47: =+C46-C50 -> 21002.453 | D47: =+D46-D50 -> 22028.725 | E47: =+E46-E50 -> 23126.835 | F47: =+F46-F50 -> 22001.814 | G47: =+G46-G50 -> 18774.041
B48: Net D/V | C48: =+C47/C88 -> 0.63150054 | D48: =+D47/D88 -> 0.62418794 | E48: =+E47/E88 -> 0.61789876 | F48: =+F47/F88 -> 0.55452658 | G48: =+G47/G88 -> 0.44647793
B50: DSRA | C50: =+C44/2 -> 230 | D50: =+D44/2 -> 230 | E50: =+E44/2 -> 230 | F50: =+F44/2 -> 2530 | G50: =+G44/2 -> 2415 | H50: 0 | I50: 0 | J50: 0
B51: =+B27 -> IC boy | C51: =+C27 -> 20000 | D51: =+C51+C68 -> 21800 | E51: =+D51+D68 -> 23751.2 | F51: =+E51+E68 -> 25854.594 | G51: =+F51+F68 -> 28109.432 | H51: =+G51+G68 -> 30513.089 | I51: =+H51+H68 -> 33060.965 | J51: =+I51+I68 -> 35890.179
B52: BV D boy | C52: =+C40 -> 9200 | D52: =+D40 -> 9200 | E52: =+E40 -> 9200 | F52: =+F40 -> 9200 | G52: =+G40 -> 4600 | H52: =+H34*H82 -> 17842.274 | I52: =+I34*I82 -> 18861.424 | J52: =+J34*J82 -> 19993.11
B53: BV E boy | C53: =+C50+C51-C52 -> 11030 | D53: =+D50+D51-D52 -> 12830 | E53: =+E50+E51-E52 -> 14781.2 | F53: =+F50+F51-F52 -> 19184.594 | G53: =+G50+G51-G52 -> 25924.432 | H53: =+H50+H51-H52 -> 12670.815 | I53: =+I50+I51-I52 -> 14199.541 | J53: =+J50+J51-J52 -> 15897.069
B56: EBIT | C56: =+C67/(1-C36) -> 3750 | D56: =+D67/(1-D36) -> 4065 | E56: =+E67/(1-E36) -> 4382.07 | F56: =+F67/(1-F36) -> 4697.579 | G56: =+G67/(1-G36) -> 5007.6193 | H56: =+H67/(1-H36) -> 5308.0764 | I56: =+I67/(1-I36) -> 5611.2737 | J56: =+J67/(1-J36) -> 5947.9502
B57: Interest payment | C57: =+C42 -> 460 | D57: =+D42 -> 460 | E57: =+E42 -> 460 | F57: =+F42 -> 460 | G57: =+G42 -> 230 | H57: =+H52*H35 -> 1070.5364 | I57: =+I52*I35 -> 1131.6855 | J57: =+J52*J35 -> 1199.5866
B58: PBT | C58: =+C56-C57 -> 3290 | D58: =+D56-D57 -> 3605 | E58: =+E56-E57 -> 3922.07 | F58: =+F56-F57 -> 4237.579 | G58: =+G56-G57 -> 4777.6193 | H58: =+H56-H57 -> 4237.54 | I58: =+I56-I57 -> 4479.5883 | J58: =+J56-J57 -> 4748.3636
B59: Tax | C59: =+IF(C58<0,0,C58*C33) -> 658 | D59: =+IF(D58<0,0,D58*D33) -> 721 | E59: =+IF(E58<0,0,E58*E33) -> 784.414 | F59: =+IF(F58<0,0,F58*F33) -> 847.51581 | G59: =+IF(G58<0,0,G58*G33) -> 955.52385 | H59: =+IF(H58<0,0,H58*H33) -> 847.508 | I59: =+IF(I58<0,0,I58*I33) -> 895.91766 | J59: =+IF(J58<0,0,J58*J33) -> 949.67271
B60: PAT | C60: =+C58-C59 -> 2632 | D60: =+D58-D59 -> 2884 | E60: =+E58-E59 -> 3137.656 | F60: =+F58-F59 -> 3390.0632 | G60: =+G58-G59 -> 3822.0954 | H60: =+H58-H59 -> 3390.032 | I60: =+I58-I59 -> 3583.6706 | J60: =+J58-J59 -> 3798.6909
B61: Dividend | C61: =+C60-C62 -> 832 | D61: =+D60-D62 -> 932.8 | E61: =+E60-E62 -> 0 | F61: =+F60-F62 -> 0 | G61: =+G60-G62 -> 3822.0954 | H61: =+H60-H62 -> 1861.306 | I61: =+I60-I62 -> 1886.1424 | J61: =+J60-J62 -> 0
B62: Retained Earnings | C62: =+IF(C60<0,C60,MAX(0,MIN(C60,C64))) -> 1800 | D62: =+IF(D60<0,D60,MAX(0,MIN(D60,D64))) -> 1951.2 | E62: =+IF(E60<0,E60,MAX(0,MIN(E60,E64))) -> 3137.656 | F62: =+IF(F60<0,F60,MAX(0,MIN(F60,F64))) -> 3390.0632 | G62: =+IF(G60<0,G60,MAX(0,MIN(G60,G64))) -> 0 | H62: =+IF(H60<0,H60,MAX(0,MIN(H60,H64))) -> 1528.726 | I62: =+IF(I60<0,I60,MAX(0,MIN(I60,I64))) -> 1697.5282 | J62: =+IF(J60<0,J60,MAX(0,MIN(J60,J64))) -> 3798.6909
B64: dBVEquity needed | C64: =+D53-C53 -> 1800 | D64: =+E53-D53 -> 1951.2 | E64: =+F53-E53 -> 4403.3936 | F64: =+G53-F53 -> 6739.8379 | G64: =+H53-G53 -> -13253.616 | H64: =+I53-H53 -> 1528.726 | I64: =+J53-I53 -> 1697.5282
B65: Share issue/buyback | C65: =+C64-C62 -> 0 | D65: =+D64-D62 -> 0 | E65: =+E64-E62 -> 1265.7376 | F65: =+F64-F62 -> 3349.7747 | G65: =+G64-G62 -> -13253.616 | H65: =+H64-H62 -> 0 | I65: =+I64-I62 -> 0
B67: Noplat | C67: =+C51*C28 -> 3000 | D67: =+C67+C68*D29 -> 3252 | E67: =+D67+D68*E29 -> 3505.656 | F67: =+E67+E68*F29 -> 3758.0632 | G67: =+F67+F68*G29 -> 4006.0954 | H67: =+G67+G68*H29 -> 4246.4611 | I67: =+H67+H68*I29 -> 4489.019 | J67: =+I67+I68*J29 -> 4758.3601
B68: dIC | C68: =+C67*C30 -> 1800 | D68: =+D67*D30 -> 1951.2 | E68: =+E67*E30 -> 2103.3936 | F68: =+F67*F30 -> 2254.8379 | G68: =+G67*G30 -> 2403.6572 | H68: =+H67*H30 -> 2547.8767 | I68: =+I67*I30 -> 2829.2136 | J68: =+J67*J30 -> 2998.9665
B69: FCFF | C69: =+C67-C68 -> 1200 | D69: =+D67-D68 -> 1300.8 | E69: =+E67-E68 -> 1402.2624 | F69: =+F67-F68 -> 1503.2253 | G69: =+G67-G68 -> 1602.4382 | H69: =+H67-H68 -> 1698.5845 | I69: =+I67-I68 -> 1659.8053 | J69: =+J67-J68 -> 1759.3937
B70: =+B57 -> Interest payment | C70: =+C57 -> 460 | D70: =+D57 -> 460 | E70: =+E57 -> 460 | F70: =+F57 -> 460 | G70: =+G57 -> 230 | H70: =+H57 -> 1070.5364 | I70: =+I57 -> 1131.6855
B71: TS | C71: =+C70*C36 -> 92 | D71: =+D70*D36 -> 92 | E71: =+E70*E36 -> 92 | F71: =+F70*F36 -> 92 | G71: =+G70*G36 -> 46 | H71: =+H70*H36 -> 214.10728 | I71: =+I70*I36 -> 226.33709
B72: dD | C72: =+D46-C46 -> 1026.2717 | D72: =+E46-D46 -> 1098.1107 | E72: =+F46-E46 -> 1174.9785 | F72: =+G46-F46 -> -3342.773 | G72: =+H46-G46 -> -3346.7671 | H72: =+I52-H52 -> 1019.1507 | I72: =+J52-I52 -> 1131.6855
B73: dDSRA | C73: =+D50-C50 -> 0 | D73: =+E50-D50 -> 0 | E73: =+F50-E50 -> 2300 | F73: =+G50-F50 -> -115 | G73: =+H50-G50 -> -2415 | H73: =+I50-H50 -> 0 | I73: =+J50-I50 -> 0
B74: FCFE | C74: =+C69-C70+C71+C72-C73 -> 1858.2717 | D74: =+D69-D70+D71+D72-D73 -> 2030.9107 | E74: =+E69-E70+E71+E72-E73 -> -90.759125 | F74: =+F69-F70+F71+F72-F73 -> -2092.5477 | G74: =+G69-G70+G71+G72-G73 -> 486.67102 | H74: =+H69-H70+H71+H72-H73 -> 1861.306 | I74: =+I69-I70+I71+I72-I73 -> 1886.1424
B75: =+B61 -> Dividend | C75: =+C61 -> 832 | D75: =+D61 -> 932.8 | E75: =+E61 -> 0 | F75: =+F61 -> 0 | G75: =+G61 -> 3822.0954 | H75: =+H61 -> 1861.306 | I75: =+I61 -> 1886.1424
B76: dBV Equity w/oRetained Earnings | C76: =+D53-C53-C62 -> 0 | D76: =+E53-D53-D62 -> 0 | E76: =+F53-E53-E62 -> 1265.7376 | F76: =+G53-F53-F62 -> 3349.7747 | G76: =+H53-G53-G62 -> -13253.616 | H76: =+I53-H53-H62 -> 0 | I76: =+J53-I53-I62 -> 0
B77: dNOn-op assets | C77: =+C74-C75+C76 -> 1026.2717 | D77: =+D74-D75+D76 -> 1098.1107 | E77: =+E74-E75+E76 -> 1174.9785 | F77: =+F74-F75+F76 -> 1257.227 | G77: =+G74-G75+G76 -> -16589.041 | H77: =+H74-H75+H76 -> -2.5011104e-12 | I77: =+I74-I75+I76 -> -2.9558578e-12
B79: FCFF // WACC
B80: =+B69 -> FCFF | C80: =+C69 -> 1200 | D80: =+D69 -> 1300.8 | E80: =+E69 -> 1402.2624 | F80: =+F69 -> 1503.2253 | G80: =+G69 -> 1602.4382 | H80: =+H69 -> 1698.5845 | I80: =+I69 -> 1659.8053 | J80: =+J69 -> 1759.3937
B81: =+B38 -> WACC | C81: =+C38 -> 0.097233749 | D81: =+D38 -> 0.097393163 | E81: =+E38 -> 0.09754196 | F81: =+F38 -> 0.097681262 | G81: =+G38 -> 0.098906043 | H81: =+H38 -> 0.0952 | I81: =+I38 -> 0.0952 | J81: =+J38 -> 0.0952
B82: V boy | C82: =+(C80+D82)/(1+C81) -> 33258.012 | D82: =+(D80+E82)/(1+D81) -> 35291.814 | E82: =+(E80+F82)/(1+E81) -> 37428.195 | F82: =+(F80+G82)/(1+F81) -> 39676.752 | G82: =+(G80+H82)/(1+G81) -> 42049.202 | H82: =+(H80+I82)/(1+H81) -> 44605.684 | I82: =+(I80+J82)/(1+I81) -> 47153.561 | J82: =+J80/(J81-K31) -> 49982.774
B85: APV // rA
B86: FCFF+TS | C86: =+C69+C71 -> 1292 | D86: =+D69+D71 -> 1392.8 | E86: =+E69+E71 -> 1494.2624 | F86: =+F69+F71 -> 1595.2253 | G86: =+G69+G71 -> 1648.4382 | H86: =+H69+H71 -> 1912.6917 | I86: =+I69+I71 -> 1886.1424
B87: =+B32 -> rA | C87: =+C32 -> 0.1 | D87: =+D32 -> 0.1 | E87: =+E32 -> 0.1 | F87: =+F32 -> 0.1 | G87: =+G32 -> 0.1 | H87: =+H32 -> 0.1 | I87: =+I32 -> 0.1
B88: Vboy | C88: =+(C86+D88)/(1+C87) -> 33258.012 | D88: =+(D86+E88)/(1+D87) -> 35291.814 | E88: =+(E86+F88)/(1+E87) -> 37428.195 | F88: =+(F86+G88)/(1+F87) -> 39676.752 | G88: =+(G86+H88)/(1+G87) -> 42049.202 | H88: =+(H86+I88)/(1+H87) -> 44605.684 | I88: =+I86/(I87-J31) -> 47153.561
B92: FCFE // rE
B93: =+B74 -> FCFE | C93: =+C74 -> 1858.2717 | D93: =+D74 -> 2030.9107 | E93: =+E74 -> -90.759125 | F93: =+F74 -> -2092.5477 | G93: =+G74 -> 486.67102 | H93: =+H74 -> 1861.306 | I93: =+I74 -> 1886.1424
B94: rE | C94: =+(C32-C48*C35)/(1-C48) -> 0.23383683 | D94: =+(D32-D48*D35)/(1-D48) -> 0.23140773 | E94: =+(E32-E48*E35)/(1-E48) -> 0.22954597 | F94: =+(F32-F48*F35)/(1-F48) -> 0.19845474 | G94: =+(G32-G48*G35)/(1-G48) -> 0.17077949 | H94: =+(H32-H34*H45)/(1-H34) -> 0.12666667 | I94: =+(I32-I34*I45)/(1-I34) -> 0.12666667
B95: E boy | C95: =+(C93+D95)/(1+C94) -> 12255.56 | D95: =+(D93+E95)/(1+D94) -> 13263.089 | E95: =+(E93+F95)/(1+E94) -> 14301.36 | F95: =+(F93+G95)/(1+F94) -> 17674.938 | G95: =+(G93+H95)/(1+G94) -> 23275.161 | H95: =+(H93+I95)/(1+H94) -> 26763.41 | I95: =+I93/(I94-J31) -> 28292.136
B96: =+B47 -> net D boy | C96: =+C47 -> 21002.453 | D96: =+D47 -> 22028.725 | E96: =+E47 -> 23126.835 | F96: =+F47 -> 22001.814 | G96: =+G47 -> 18774.041 | H96: =+H52 -> 17842.274 | I96: =+I52 -> 18861.424 | J96: D = BVD
B97: V boy | C97: =+C95+C96 -> 33258.012 | D97: =+D95+D96 -> 35291.814 | E97: =+E95+E96 -> 37428.195 | F97: =+F95+F96 -> 39676.752 | G97: =+G95+G96 -> 42049.202 | H97: =+H95+H96 -> 44605.684 | I97: =+I95+I96 -> 47153.561

Sheet ModelBFair
C26: 2025 | D26: =+C26+1 -> 2026 | E26: =+D26+1 -> 2027 | F26: =+E26+1 -> 2028 | G26: =+F26+1 -> 2029 | H26: =+G26+1 -> 2030 | I26: TV1 | J26: TV2
B27: IC boy | C27: 20000 | I27: RONIC=WACC
B28: ROIC | C28: 0.15
B29: RONIC | D29: 0.14 | E29: 0.13 | F29: 0.12 | G29: 0.11 | H29: 0.1 | I29: =+I38 -> 0.0952 | J29: =+J38 -> 0.0952 | K29: =+K38 -> 0.0952
B30: K | C30: 0.6 | D30: 0.6 | E30: 0.6 | F30: 0.6 | G30: 0.6 | H30: 0.6 | I30: =+J31/J29 -> 0.6302521 | J30: =+K31/K29 -> 0.6302521
B31: g | J31: 0.06 | K31: 0.06
B32: rA | C32: 0.1 | D32: 0.1 | E32: 0.1 | F32: 0.1 | G32: 0.1 | H32: 0.1 | I32: 0.1 | J32: 0.1 | K32: 0.1
B33: t nominal | C33: 0.2 | D33: 0.2 | E33: 0.2 | F33: 0.2 | G33: 0.2 | H33: 0.2 | I33: 0.2 | J33: 0.2 | K33: 0.2
B34: Debt/V boy | C34: =+C46/C88 -> 0.25591302 | D34: =+D46/D88 -> 0.24501261 | E34: =+E46/E88 -> 0.23490914 | F34: =+F46/F88 -> 0.22551445 | G34: =+G46/G88 -> 0.10735088 | H34: 0.4 | I34: 0.4 | J34: 0.4 | K34: 0.4
B35: rD* for WACC | C35: =+C42/C47 -> 0.055547784 | D35: =+D42/D47 -> 0.054651694 | E35: =+E42/E47 -> 0.053724352 | F35: =+F42/F47 -> 0.071676981 | G35: =+G42/G47 -> 0.10957501 | H35: 0.06 | I35: 0.06 | J35: 0.06 | K35: 0.06
B36: t effective assumed | C36: 0.2 | D36: 0.2 | E36: 0.2 | F36: 0.2 | G36: 0.2 | H36: 0.2 | I36: 0.2 | J36: 0.2 | K36: 0.2
B37: t effective calculated | C37: =+C59/C58 -> 0.2 | D37: =+D59/D58 -> 0.2 | E37: =+E59/E58 -> 0.2 | F37: =+F59/F58 -> 0.2 | G37: =+G59/G58 -> 0.2 | H37: =+H59/H58 -> 0.2 | I37: =+I59/I58 -> 0.2 | J37: =+J59/J58 -> 0.2 | K37: =+K59/K58 -> #DIV/0!
B38: WACC | C38: =+C32-C35*C48*C36 -> 0.097233749 | D38: =+D32-D35*D48*D36 -> 0.097393163 | E38: =+E32-E35*E48*E36 -> 0.09754196 | F38: =+F32-F35*F48*F36 -> 0.097681262 | G38: =+G32-G35*G48*G36 -> 0.098906043 | H38: =+H32-H35*H34*H36 -> 0.0952 | I38: =+I32-I35*I34*I36 -> 0.0952 | J38: =+J32-J35*J34*J36 -> 0.0952 | K38: =+K32-K35*K34*K36 -> 0.0952
B40: Principal boy | C40: 9200 | D40: 9200 | E40: 9200 | F40: 9200 | G40: =+F40/2 -> 4600 | H40: 0
B41: interest | C41: 0.05 | D41: 0.05 | E41: 0.05 | F41: 0.05 | G41: 0.05
B42: Interest payment | C42: =+C40*C41 -> 460 | D42: =+D40*D41 -> 460 | E42: =+E40*E41 -> 460 | F42: =+F40*F41 -> 460 | G42: =+G40*G41 -> 230
B43: Principal payment | C43: =+C40-D40 -> 0 | D43: =+D40-E40 -> 0 | E43: =+E40-F40 -> 0 | F43: =+F40-G40 -> 4600 | G43: =+G40-H40 -> 4600
B44: Total CF = Debt Service | C44: =+C42+C43 -> 460 | D44: =+D42+D43 -> 460 | E44: =+E42+E43 -> 460 | F44: =+F42+F43 -> 5060 | G44: =+G42+G43 -> 4830
B45: rD | C45: 0.07 | D45: 0.07 | E45: 0.07 | F45: 0.07 | G45: 0.07 | H45: =+H35 -> 0.06 | I45: =+I35 -> 0.06 | J45: =+J35 -> 0.06 | K45: =+K35 -> 0.06
B46: D boy | C46: =+(C44+D46)/(1+C45) -> 8511.1584 | D46: =+(D44+E46)/(1+D45) -> 8646.9395 | E46: =+(E44+F46)/(1+E45) -> 8792.2253 | F46: =+(F44+G46)/(1+F45) -> 8947.681 | G46: =+(G44+H46)/(1+G45) -> 4514.0187 | H46: 0
B47: net D boy | C47: =+C46-C50 -> 8281.1584 | D47: =+D46-D50 -> 8416.9395 | E47: =+E46-E50 -> 8562.2253 | F47: =+F46-F50 -> 6417.681 | G47: =+G46-G50 -> 2099.0187
B48: Net D/V | C48: =+C47/C88 -> 0.24899739 | D48: =+D47/D88 -> 0.23849552 | E48: =+E47/E88 -> 0.22876404 | F48: =+F47/F88 -> 0.16174915 | G48: =+G47/G88 -> 0.049918157
B50: DSRA | C50: =+C44/2 -> 230 | D50: =+D44/2 -> 230 | E50: =+E44/2 -> 230 | F50: =+F44/2 -> 2530 | G50: =+G44/2 -> 2415 | H50: 0 | I50: 0 | J50: 0
B51: =+B27 -> IC boy | C51: =+C27 -> 20000 | D51: =+C51+C68 -> 21800 | E51: =+D51+D68 -> 23751.2 | F51: =+E51+E68 -> 25854.594 | G51: =+F51+F68 -> 28109.432 | H51: =+G51+G68 -> 30513.089 | I51: =+H51+H68 -> 33060.965 | J51: =+I51+I68 -> 35890.179
B52: BV D boy | C52: =+C46 -> 8511.1584 | D52: =+D46 -> 8646.9395 | E52: =+E46 -> 8792.2253 | F52: =+F46 -> 8947.681 | G52: =+G46 -> 4514.0187 | H52: =+H34*H82 -> 17842.274 | I52: =+I34*I82 -> 18861.424 | J52: =+J34*J82 -> 19993.11
B53: BV E boy | C53: =+C50+C51-C52 -> 11718.842 | D53: =+D50+D51-D52 -> 13383.061 | E53: =+E50+E51-E52 -> 15188.975 | F53: =+F50+F51-F52 -> 19436.913 | G53: =+G50+G51-G52 -> 26010.413 | H53: =+H50+H51-H52 -> 12670.815 | I53: =+I50+I51-I52 -> 14199.541 | J53: =+J50+J51-J52 -> 15897.069
B56: EBIT | C56: =+C67/(1-C36) -> 3750 | D56: =+D67/(1-D36) -> 4065 | E56: =+E67/(1-E36) -> 4382.07 | F56: =+F67/(1-F36) -> 4697.579 | G56: =+G67/(1-G36) -> 5007.6193 | H56: =+H67/(1-H36) -> 5308.0764 | I56: =+I67/(1-I36) -> 5611.2737 | J56: =+J67/(1-J36) -> 5947.9502
B57: Interest payment | C57: =+C42 -> 460 | D57: =+D42 -> 460 | E57: =+E42 -> 460 | F57: =+F42 -> 460 | G57: =+G42 -> 230 | H57: =+H52*H35 -> 1070.5364 | I57: =+I52*I35 -> 1131.6855 | J57: =+J52*J35 -> 1199.5866
B58: PBT | C58: =+C56-C57 -> 3290 | D58: =+D56-D57 -> 3605 | E58: =+E56-E57 -> 3922.07 | F58: =+F56-F57 -> 4237.579 | G58: =+G56-G57 -> 4777.6193 | H58: =+H56-H57 -> 4237.54 | I58: =+I56-I57 -> 4479.5883 | J58: =+J56-J57 -> 4748.3636
B59: Tax | C59: =+IF(C58<0,0,C58*C33) -> 658 | D59: =+IF(D58<0,0,D58*D33) -> 721 | E59: =+IF(E58<0,0,E58*E33) -> 784.414 | F59: =+IF(F58<0,0,F58*F33) -> 847.51581 | G59: =+IF(G58<0,0,G58*G33) -> 955.52385 | H59: =+IF(H58<0,0,H58*H33) -> 847.508 | I59: =+IF(I58<0,0,I58*I33) -> 895.91766 | J59: =+IF(J58<0,0,J58*J33) -> 949.67271
B60: PAT | C60: =+C58-C59 -> 2632 | D60: =+D58-D59 -> 2884 | E60: =+E58-E59 -> 3137.656 | F60: =+F58-F59 -> 3390.0632 | G60: =+G58-G59 -> 3822.0954 | H60: =+H58-H59 -> 3390.032 | I60: =+I58-I59 -> 3583.6706 | J60: =+J58-J59 -> 3798.6909
B61: Dividend | C61: =+C60-C62 -> 967.78109 | D61: =+D60-D62 -> 1078.0858 | E61: =+E60-E62 -> 0 | F61: =+F60-F62 -> 0 | G61: =+G60-G62 -> 3822.0954 | H61: =+H60-H62 -> 1861.306 | I61: =+I60-I62 -> 1886.1424 | J61: =+J60-J62 -> 0
B62: Retained Earnings | C62: =+IF(C60<0,C60,MAX(0,MIN(C60,C64))) -> 1664.2189 | D62: =+IF(D60<0,D60,MAX(0,MIN(D60,D64))) -> 1805.9142 | E62: =+IF(E60<0,E60,MAX(0,MIN(E60,E64))) -> 3137.656 | F62: =+IF(F60<0,F60,MAX(0,MIN(F60,F64))) -> 3390.0632 | G62: =+IF(G60<0,G60,MAX(0,MIN(G60,G64))) -> 0 | H62: =+IF(H60<0,H60,MAX(0,MIN(H60,H64))) -> 1528.726 | I62: =+IF(I60<0,I60,MAX(0,MIN(I60,I64))) -> 1697.5282 | J62: =+IF(J60<0,J60,MAX(0,MIN(J60,J64))) -> 3798.6909
B64: dBVEquity needed | C64: =+D53-C53 -> 1664.2189 | D64: =+E53-D53 -> 1805.9142 | E64: =+F53-E53 -> 4247.9378 | F64: =+G53-F53 -> 6573.5003 | G64: =+H53-G53 -> -13339.598 | H64: =+I53-H53 -> 1528.726 | I64: =+J53-I53 -> 1697.5282
B65: Share issue/buyback | C65: =+C64-C62 -> 0 | D65: =+D64-D62 -> 0 | E65: =+E64-E62 -> 1110.2818 | F65: =+F64-F62 -> 3183.437 | G65: =+G64-G62 -> -13339.598 | H65: =+H64-H62 -> 0 | I65: =+I64-I62 -> 0
B67: Noplat | C67: =+C51*C28 -> 3000 | D67: =+C67+C68*D29 -> 3252 | E67: =+D67+D68*E29 -> 3505.656 | F67: =+E67+E68*F29 -> 3758.0632 | G67: =+F67+F68*G29 -> 4006.0954 | H67: =+G67+G68*H29 -> 4246.4611 | I67: =+H67+H68*I29 -> 4489.019 | J67: =+I67+I68*J29 -> 4758.3601
B68: dIC | C68: =+C67*C30 -> 1800 | D68: =+D67*D30 -> 1951.2 | E68: =+E67*E30 -> 2103.3936 | F68: =+F67*F30 -> 2254.8379 | G68: =+G67*G30 -> 2403.6572 | H68: =+H67*H30 -> 2547.8767 | I68: =+I67*I30 -> 2829.2136 | J68: =+J67*J30 -> 2998.9665
B69: FCFF | C69: =+C67-C68 -> 1200 | D69: =+D67-D68 -> 1300.8 | E69: =+E67-E68 -> 1402.2624 | F69: =+F67-F68 -> 1503.2253 | G69: =+G67-G68 -> 1602.4382 | H69: =+H67-H68 -> 1698.5845 | I69: =+I67-I68 -> 1659.8053 | J69: =+J67-J68 -> 1759.3937
B70: =+B57 -> Interest payment | C70: =+C57 -> 460 | D70: =+D57 -> 460 | E70: =+E57 -> 460 | F70: =+F57 -> 460 | G70: =+G57 -> 230 | H70: =+H57 -> 1070.5364 | I70: =+I57 -> 1131.6855
B71: TS | C71: =+C70*C36 -> 92 | D71: =+D70*D36 -> 92 | E71: =+E70*E36 -> 92 | F71: =+F70*F36 -> 92 | G71: =+G70*G36 -> 46 | H71: =+H70*H36 -> 214.10728 | I71: =+I70*I36 -> 226.33709
B72: dD | C72: =+D52-C52 -> 135.78109 | D72: =+E52-D52 -> 145.28576 | E72: =+F52-E52 -> 155.45577 | F72: =+G52-F52 -> -4433.6623 | G72: =+H52-G52 -> 13328.255 | H72: =+I52-H52 -> 1019.1507 | I72: =+J52-I52 -> 1131.6855
B73: dDSRA | C73: =+D50-C50 -> 0 | D73: =+E50-D50 -> 0 | E73: =+F50-E50 -> 2300 | F73: =+G50-F50 -> -115 | G73: =+H50-G50 -> -2415 | H73: =+I50-H50 -> 0 | I73: =+J50-I50 -> 0
B74: FCFE | C74: =+C69-C70+C71+C72-C73 -> 967.78109 | D74: =+D69-D70+D71+D72-D73 -> 1078.0858 | E74: =+E69-E70+E71+E72-E73 -> -1110.2818 | F74: =+F69-F70+F71+F72-F73 -> -3183.437 | G74: =+G69-G70+G71+G72-G73 -> 17161.693 | H74: =+H69-H70+H71+H72-H73 -> 1861.306 | I74: =+I69-I70+I71+I72-I73 -> 1886.1424
B75: =+B61 -> Dividend | C75: =+C61 -> 967.78109 | D75: =+D61 -> 1078.0858 | E75: =+E61 -> 0 | F75: =+F61 -> 0 | G75: =+G61 -> 3822.0954 | H75: =+H61 -> 1861.306 | I75: =+I61 -> 1886.1424
B76: dBV Equity w/oRetained Earnings | C76: =+D53-C53-C62 -> 0 | D76: =+E53-D53-D62 -> 0 | E76: =+F53-E53-E62 -> 1110.2818 | F76: =+G53-F53-F62 -> 3183.437 | G76: =+H53-G53-G62 -> -13339.598 | H76: =+I53-H53-H62 -> 0 | I76: =+J53-I53-I62 -> 0
B77: dNOn-op assets | C77: =+C74-C75+C76 -> 0 | D77: =+D74-D75+D76 -> 9.094947e-13 | E77: =+E74-E75+E76 -> 0 | F77: =+F74-F75+F76 -> 0 | G77: =+G74-G75+G76 -> 0 | H77: =+H74-H75+H76 -> -2.5011104e-12 | I77: =+I74-I75+I76 -> -2.9558578e-12
B79: FCFF // WACC
B80: =+B69 -> FCFF | C80: =+C69 -> 1200 | D80: =+D69 -> 1300.8 | E80: =+E69 -> 1402.2624 | F80: =+F69 -> 1503.2253 | G80: =+G69 -> 1602.4382 | H80: =+H69 -> 1698.5845 | I80: =+I69 -> 1659.8053 | J80: =+J69 -> 1759.3937
B81: =+B38 -> WACC | C81: =+C38 -> 0.097233749 | D81: =+D38 -> 0.097393163 | E81: =+E38 -> 0.09754196 | F81: =+F38 -> 0.097681262 | G81: =+G38 -> 0.098906043 | H81: =+H38 -> 0.0952 | I81: =+I38 -> 0.0952 | J81: =+J38 -> 0.0952
B82: V boy | C82: =+(C80+D82)/(1+C81) -> 33258.012 | D82: =+(D80+E82)/(1+D81) -> 35291.814 | E82: =+(E80+F82)/(1+E81) -> 37428.195 | F82: =+(F80+G82)/(1+F81) -> 39676.752 | G82: =+(G80+H82)/(1+G81) -> 42049.202 | H82: =+(H80+I82)/(1+H81) -> 44605.684 | I82: =+(I80+J82)/(1+I81) -> 47153.561 | J82: =+J80/(J81-K31) -> 49982.774
B85: APV // rA
B86: FCFF+TS | C86: =+C69+C71 -> 1292 | D86: =+D69+D71 -> 1392.8 | E86: =+E69+E71 -> 1494.2624 | F86: =+F69+F71 -> 1595.2253 | G86: =+G69+G71 -> 1648.4382 | H86: =+H69+H71 -> 1912.6917 | I86: =+I69+I71 -> 1886.1424
B87: =+B32 -> rA | C87: =+C32 -> 0.1 | D87: =+D32 -> 0.1 | E87: =+E32 -> 0.1 | F87: =+F32 -> 0.1 | G87: =+G32 -> 0.1 | H87: =+H32 -> 0.1 | I87: =+I32 -> 0.1
B88: Vboy | C88: =+(C86+D88)/(1+C87) -> 33258.012 | D88: =+(D86+E88)/(1+D87) -> 35291.814 | E88: =+(E86+F88)/(1+E87) -> 37428.195 | F88: =+(F86+G88)/(1+F87) -> 39676.752 | G88: =+(G86+H88)/(1+G87) -> 42049.202 | H88: =+(H86+I88)/(1+H87) -> 44605.684 | I88: =+I86/(I87-J31) -> 47153.561
B92: FCFE // rE
B93: =+B74 -> FCFE | C93: =+C74 -> 967.78109 | D93: =+D74 -> 1078.0858 | E93: =+E74 -> -1110.2818 | F93: =+F74 -> -3183.437 | G93: =+G74 -> 17161.693 | H93: =+H74 -> 1861.306 | I93: =+I74 -> 1886.1424
B94: rE | C94: =+(C32-C48*C35)/(1-C48) -> 0.11473828 | D94: =+(D32-D48*D35)/(1-D48) -> 0.11420263 | E94: =+(E32-E48*E35)/(1-E48) -> 0.11372628 | F94: =+(F32-F48*F35)/(1-F48) -> 0.10546522 | G94: =+(G32-G48*G35)/(1-G48) -> 0.09949692 | H94: =+(H32-H34*H45)/(1-H34) -> 0.12666667 | I94: =+(I32-I34*I45)/(1-I34) -> 0.12666667
B95: E boy | C95: =+(C93+D95)/(1+C94) -> 24976.854 | D95: =+(D93+E95)/(1+D94) -> 26874.874 | E95: =+(E93+F95)/(1+E94) -> 28865.97 | F95: =+(F93+G95)/(1+F94) -> 33259.071 | G95: =+(G93+H95)/(1+G94) -> 39950.183 | H95: =+(H93+I95)/(1+H94) -> 26763.41 | I95: =+I93/(I94-J31) -> 28292.136
B96: =+B47 -> net D boy | C96: =+C47 -> 8281.1584 | D96: =+D47 -> 8416.9395 | E96: =+E47 -> 8562.2253 | F96: =+F47 -> 6417.681 | G96: =+G47 -> 2099.0187 | H96: =+H52 -> 17842.274 | I96: =+I52 -> 18861.424 | J96: D = BVD
B97: V boy | C97: =+C95+C96 -> 33258.012 | D97: =+D95+D96 -> 35291.814 | E97: =+E95+E96 -> 37428.195 | F97: =+F95+F96 -> 39676.752 | G97: =+G95+G96 -> 42049.202 | H97: =+H95+H96 -> 44605.684 | I97: =+I95+I96 -> 47153.561

Sheet ModelBFair (80%)
C26: 2025 | D26: =+C26+1 -> 2026 | E26: =+D26+1 -> 2027 | F26: =+E26+1 -> 2028 | G26: =+F26+1 -> 2029 | H26: =+G26+1 -> 2030 | I26: TV1 | J26: TV2
B27: IC boy | C27: 20000 | I27: RONIC=WACC
B28: ROIC | C28: 0.15
B29: RONIC | D29: 0.14 | E29: 0.13 | F29: 0.12 | G29: 0.11 | H29: 0.1 | I29: =+I38 -> 0.0952 | J29: =+J38 -> 0.0952 | K29: =+K38 -> 0.0952
B30: K | C30: 0.6 | D30: 0.6 | E30: 0.6 | F30: 0.6 | G30: 0.6 | H30: 0.6 | I30: =+J31/J29 -> 0.6302521 | J30: =+K31/K29 -> 0.6302521
B31: g | J31: 0.06 | K31: 0.06
B32: rA | C32: 0.1 | D32: 0.1 | E32: 0.1 | F32: 0.1 | G32: 0.1 | H32: 0.1 | I32: 0.1 | J32: 0.1 | K32: 0.1
B33: t nominal | C33: 0.2 | D33: 0.2 | E33: 0.2 | F33: 0.2 | G33: 0.2 | H33: 0.2 | I33: 0.2 | J33: 0.2 | K33: 0.2
B34: Debt/V boy | C34: =+C47/C91 -> 0.25585502 | D34: =+D47/D91 -> 0.2449729 | E34: =+E47/E91 -> 0.23488438 | F34: =+F47/F91 -> 0.22550205 | G34: =+G47/G91 -> 0.10734985 | H34: 0.4 | I34: 0.4 | J34: 0.4 | K34: 0.4
B35: rD* for WACC | C35: =+C43/C48 -> 0.055547784 | D35: =+D43/D48 -> 0.054651694 | E35: =+E43/E48 -> 0.053724352 | F35: =+F43/F48 -> 0.071676981 | G35: =+G43/G48 -> 0.10957501 | H35: 0.06 | I35: 0.06 | J35: 0.06 | K35: 0.06
B36: t effective assumed | C36: 0.20559271 | D36: 0.20510402 | E36: 0.2046914 | F36: 0.2043421 | G36: 0.20192565 | H36: 0.2 | I36: 0.2 | J36: 0.2 | K36: 0.2
B37: t effective calculated | C37: =+C62/C60 -> 0.20554818 | D37: =+D62/D60 -> 0.20506733 | E37: =+E62/E60 -> 0.20466068 | F37: =+F62/F60 -> 0.20431599 | G37: =+G62/G60 -> 0.20192079 | H37: =+H62/H60 -> 0.2 | I37: =+I62/I60 -> 0.2 | J37: =+J62/J60 -> 0.2 | K37: =+K62/K60 -> #DIV/0!
B38: WACC | C38: =+C32-C35*C49*C36 -> 0.09715704 | D38: =+D32-D35*D49*D36 -> 0.09732707 | E38: =+E32-E35*E49*E36 -> 0.097484567 | F38: =+F32-F35*F49*F36 -> 0.097631051 | G38: =+G32-G35*G49*G36 -> 0.098895521 | H38: =+H32-H35*H34*H36 -> 0.0952 | I38: =+I32-I35*I34*I36 -> 0.0952 | J38: =+J32-J35*J34*J36 -> 0.0952 | K38: =+K32-K35*K34*K36 -> 0.0952
B39: Tax deductible interest % | C39: 0.8 | D39: 0.8 | E39: 0.8 | F39: 0.8 | G39: 0.8 | H39: 1 | I39: 1 | J39: 1 | K39: 1
B41: Principal boy | C41: 9200 | D41: 9200 | E41: 9200 | F41: 9200 | G41: =+F41/2 -> 4600 | H41: 0
B42: interest | C42: 0.05 | D42: 0.05 | E42: 0.05 | F42: 0.05 | G42: 0.05
B43: Interest payment | C43: =+C41*C42 -> 460 | D43: =+D41*D42 -> 460 | E43: =+E41*E42 -> 460 | F43: =+F41*F42 -> 460 | G43: =+G41*G42 -> 230
B44: Principal payment | C44: =+C41-D41 -> 0 | D44: =+D41-E41 -> 0 | E44: =+E41-F41 -> 0 | F44: =+F41-G41 -> 4600 | G44: =+G41-H41 -> 4600
B45: Total CF = Debt Service | C45: =+C43+C44 -> 460 | D45: =+D43+D44 -> 460 | E45: =+E43+E44 -> 460 | F45: =+F43+F44 -> 5060 | G45: =+G43+G44 -> 4830
B46: rD | C46: 0.07 | D46: 0.07 | E46: 0.07 | F46: 0.07 | G46: 0.07 | H46: =+H35 -> 0.06 | I46: =+I35 -> 0.06 | J46: =+J35 -> 0.06 | K46: =+K35 -> 0.06
B47: D boy | C47: =+(C45+D47)/(1+C46) -> 8511.1584 | D47: =+(D45+E47)/(1+D46) -> 8646.9395 | E47: =+(E45+F47)/(1+E46) -> 8792.2253 | F47: =+(F45+G47)/(1+F46) -> 8947.681 | G47: =+(G45+H47)/(1+G46) -> 4514.0187 | H47: 0
B48: net D boy | C48: =+C47-C51 -> 8281.1584 | D48: =+D47-D51 -> 8416.9395 | E48: =+E47-E51 -> 8562.2253 | F48: =+F47-F51 -> 6417.681 | G48: =+G47-G51 -> 2099.0187
B49: Net D/V | C49: =+C48/C91 -> 0.24894096 | D49: =+D48/D91 -> 0.23845687 | E49: =+E48/E91 -> 0.22873993 | F49: =+F48/F91 -> 0.16174026 | G49: =+G48/G91 -> 0.049917679
B51: DSRA | C51: =+C45/2 -> 230 | D51: =+D45/2 -> 230 | E51: =+E45/2 -> 230 | F51: =+F45/2 -> 2530 | G51: =+G45/2 -> 2415 | H51: 0 | I51: 0 | J51: 0
B52: =+B27 -> IC boy | C52: =+C27 -> 20000 | D52: =+C52+C71 -> 21800 | E52: =+D52+D71 -> 23751.2 | F52: =+E52+E71 -> 25854.594 | G52: =+F52+F71 -> 28109.432 | H52: =+G52+G71 -> 30513.089 | I52: =+H52+H71 -> 33060.965 | J52: =+I52+I71 -> 35890.179
B53: BV D boy | C53: =+C47 -> 8511.1584 | D53: =+D47 -> 8646.9395 | E53: =+E47 -> 8792.2253 | F53: =+F47 -> 8947.681 | G53: =+G47 -> 4514.0187 | H53: =+H34*H85 -> 17842.274 | I53: =+I34*I85 -> 18861.424 | J53: =+J34*J85 -> 19993.11
B54: BV E boy | C54: =+C51+C52-C53 -> 11718.842 | D54: =+D51+D52-D53 -> 13383.061 | E54: =+E51+E52-E53 -> 15188.975 | F54: =+F51+F52-F53 -> 19436.913 | G54: =+G51+G52-G53 -> 26010.413 | H54: =+H51+H52-H53 -> 12670.815 | I54: =+I51+I52-I53 -> 14199.541 | J54: =+J51+J52-J53 -> 15897.069
B57: EBIT | C57: =+C70/(1-C36) -> 3776.4004 | D57: =+D70/(1-D36) -> 4091.1013 | E57: =+E70/(1-E36) -> 4407.9191 | F57: =+F70/(1-F36) -> 4723.2149 | G57: =+G70/(1-G36) -> 5019.702 | H57: =+H70/(1-H36) -> 5308.0764 | I57: =+I70/(1-I36) -> 5611.2737 | J57: =+J70/(1-J36) -> 5947.9502
B58: Interest payment | C58: =+C43 -> 460 | D58: =+D43 -> 460 | E58: =+E43 -> 460 | F58: =+F43 -> 460 | G58: =+G43 -> 230 | H58: =+H53*H35 -> 1070.5364 | I58: =+I53*I35 -> 1131.6855 | J58: =+J53*J35 -> 1199.5866
B59: Tax deductible interest | C59: =+C58*C39 -> 368 | D59: =+D58*D39 -> 368 | E59: =+E58*E39 -> 368 | F59: =+F58*F39 -> 368 | G59: =+G58*G39 -> 184 | H59: =+H58*H39 -> 1070.5364 | I59: =+I58*I39 -> 1131.6855 | J59: =+J58*J39 -> 1199.5866
B60: PBT | C60: =+C57-C58 -> 3316.4004 | D60: =+D57-D58 -> 3631.1013 | E60: =+E57-E58 -> 3947.9191 | F60: =+F57-F58 -> 4263.2149 | G60: =+G57-G58 -> 4789.702 | H60: =+H57-H58 -> 4237.54 | I60: =+I57-I58 -> 4479.5883 | J60: =+J57-J58 -> 4748.3636
B61: Tax base | C61: =+C57-C59 -> 3408.4004 | D61: =+D57-D59 -> 3723.1013 | E61: =+E57-E59 -> 4039.9191 | F61: =+F57-F59 -> 4355.2149 | G61: =+G57-G59 -> 4835.702 | H61: =+H57-H59 -> 4237.54 | I61: =+I57-I59 -> 4479.5883 | J61: =+J57-J59 -> 4748.3636
B62: Tax | C62: =+IF(C61<0,0,C61*C33) -> 681.68007 | D62: =+IF(D61<0,0,D61*D33) -> 744.62027 | E62: =+IF(E61<0,0,E61*E33) -> 807.98383 | F62: =+IF(F61<0,0,F61*F33) -> 871.04298 | G62: =+IF(G61<0,0,G61*G33) -> 967.14039 | H62: =+IF(H61<0,0,H61*H33) -> 847.508 | I62: =+IF(I61<0,0,I61*I33) -> 895.91766 | J62: =+IF(J61<0,0,J61*J33) -> 949.67271
B63: PAT | C63: =+C60-C62 -> 2634.7203 | D63: =+D60-D62 -> 2886.4811 | E63: =+E60-E62 -> 3139.9353 | F63: =+F60-F62 -> 3392.1719 | G63: =+G60-G62 -> 3822.5616 | H63: =+H60-H62 -> 3390.032 | I63: =+I60-I62 -> 3583.6706 | J63: =+J60-J62 -> 3798.6909
B64: Dividend | C64: =+C63-C65 -> 970.50138 | D64: =+D63-D65 -> 1080.5668 | E64: =+E63-E65 -> 0 | F64: =+F63-F65 -> 0 | G64: =+G63-G65 -> 3822.5616 | H64: =+H63-H65 -> 1861.306 | I64: =+I63-I65 -> 1886.1424 | J64: =+J63-J65 -> 0
B65: Retained Earnings | C65: =+IF(C63<0,C63,MAX(0,MIN(C63,C67))) -> 1664.2189 | D65: =+IF(D63<0,D63,MAX(0,MIN(D63,D67))) -> 1805.9142 | E65: =+IF(E63<0,E63,MAX(0,MIN(E63,E67))) -> 3139.9353 | F65: =+IF(F63<0,F63,MAX(0,MIN(F63,F67))) -> 3392.1719 | G65: =+IF(G63<0,G63,MAX(0,MIN(G63,G67))) -> 0 | H65: =+IF(H63<0,H63,MAX(0,MIN(H63,H67))) -> 1528.726 | I65: =+IF(I63<0,I63,MAX(0,MIN(I63,I67))) -> 1697.5282 | J65: =+IF(J63<0,J63,MAX(0,MIN(J63,J67))) -> 3798.6909
B67: dBVEquity needed | C67: =+D54-C54 -> 1664.2189 | D67: =+E54-D54 -> 1805.9142 | E67: =+F54-E54 -> 4247.9378 | F67: =+G54-F54 -> 6573.5003 | G67: =+H54-G54 -> -13339.598 | H67: =+I54-H54 -> 1528.726 | I67: =+J54-I54 -> 1697.5282
B68: Share issue/buyback | C68: =+C67-C65 -> 0 | D68: =+D67-D65 -> 0 | E68: =+E67-E65 -> 1108.0025 | F68: =+F67-F65 -> 3181.3284 | G68: =+G67-G65 -> -13339.598 | H68: =+H67-H65 -> 0 | I68: =+I67-I65 -> 0
B70: Noplat | C70: =+C52*C28 -> 3000 | D70: =+C70+C71*D29 -> 3252 | E70: =+D70+D71*E29 -> 3505.656 | F70: =+E70+E71*F29 -> 3758.0632 | G70: =+F70+F71*G29 -> 4006.0954 | H70: =+G70+G71*H29 -> 4246.4611 | I70: =+H70+H71*I29 -> 4489.019 | J70: =+I70+I71*J29 -> 4758.3601
B71: dIC | C71: =+C70*C30 -> 1800 | D71: =+D70*D30 -> 1951.2 | E71: =+E70*E30 -> 2103.3936 | F71: =+F70*F30 -> 2254.8379 | G71: =+G70*G30 -> 2403.6572 | H71: =+H70*H30 -> 2547.8767 | I71: =+I70*I30 -> 2829.2136 | J71: =+J70*J30 -> 2998.9665
B72: FCFF | C72: =+C70-C71 -> 1200 | D72: =+D70-D71 -> 1300.8 | E72: =+E70-E71 -> 1402.2624 | F72: =+F70-F71 -> 1503.2253 | G72: =+G70-G71 -> 1602.4382 | H72: =+H70-H71 -> 1698.5845 | I72: =+I70-I71 -> 1659.8053 | J72: =+J70-J71 -> 1759.3937
B73: =+B58 -> Interest payment | C73: =+C58 -> 460 | D73: =+D58 -> 460 | E73: =+E58 -> 460 | F73: =+F58 -> 460 | G73: =+G58 -> 230 | H73: =+H58 -> 1070.5364 | I73: =+I58 -> 1131.6855
B74: TS | C74: =+C73*C36 -> 94.572644 | D74: =+D73*D36 -> 94.34785 | E74: =+E73*E36 -> 94.158044 | F74: =+F73*F36 -> 93.997367 | G74: =+G73*G36 -> 46.442898 | H74: =+H73*H36 -> 214.10728 | I74: =+I73*I36 -> 226.33709
B75: dD | C75: =+D53-C53 -> 135.78109 | D75: =+E53-D53 -> 145.28576 | E75: =+F53-E53 -> 155.45577 | F75: =+G53-F53 -> -4433.6623 | G75: =+H53-G53 -> 13328.255 | H75: =+I53-H53 -> 1019.1507 | I75: =+J53-I53 -> 1131.6855
B76: dDSRA | C76: =+D51-C51 -> 0 | D76: =+E51-D51 -> 0 | E76: =+F51-E51 -> 2300 | F76: =+G51-F51 -> -115 | G76: =+H51-G51 -> -2415 | H76: =+I51-H51 -> 0 | I76: =+J51-I51 -> 0
B77: FCFE | C77: =+C72-C73+C74+C75-C76 -> 970.35373 | D77: =+D72-D73+D74+D75-D76 -> 1080.4336 | E77: =+E72-E73+E74+E75-E76 -> -1108.1238 | F77: =+F72-F73+F74+F75-F76 -> -3181.4397 | G77: =+G72-G73+G74+G75-G76 -> 17162.136 | H77: =+H72-H73+H74+H75-H76 -> 1861.306 | I77: =+I72-I73+I74+I75-I76 -> 1886.1424
B78: =+B64 -> Dividend | C78: =+C64 -> 970.50138 | D78: =+D64 -> 1080.5668 | E78: =+E64 -> 0 | F78: =+F64 -> 0 | G78: =+G64 -> 3822.5616 | H78: =+H64 -> 1861.306 | I78: =+I64 -> 1886.1424
B79: dBV Equity w/oRetained Earnings | C79: =+D54-C54-C65 -> 0 | D79: =+E54-D54-D65 -> 0 | E79: =+F54-E54-E65 -> 1108.0025 | F79: =+G54-F54-F65 -> 3181.3284 | G79: =+H54-G54-G65 -> -13339.598 | H79: =+I54-H54-H65 -> 0 | I79: =+J54-I54-I65 -> 0
B80: dNOn-op assets | C80: =+C77-C78+C79 -> -0.14764947 | D80: =+D77-D78+D79 -> -0.13322182 | E80: =+E77-E78+E79 -> -0.12126867 | F80: =+F77-F78+F79 -> -0.11131347 | G80: =+G77-G78+G79 -> -0.023267007 | H80: =+H77-H78+H79 -> -2.5011104e-12 | I80: =+I77-I78+I79 -> -2.9558578e-12
B82: FCFF // WACC
B83: =+B72 -> FCFF | C83: =+C72 -> 1200 | D83: =+D72 -> 1300.8 | E83: =+E72 -> 1402.2624 | F83: =+F72 -> 1503.2253 | G83: =+G72 -> 1602.4382 | H83: =+H72 -> 1698.5845 | I83: =+I72 -> 1659.8053 | J83: =+J72 -> 1759.3937
B84: =+B38 -> WACC | C84: =+C38 -> 0.09715704 | D84: =+D38 -> 0.09732707 | E84: =+E38 -> 0.097484567 | F84: =+F38 -> 0.097631051 | G84: =+G38 -> 0.098895521 | H84: =+H38 -> 0.0952 | I84: =+I38 -> 0.0952 | J84: =+J38 -> 0.0952
B85: V boy | C85: =+(C83+D85)/(1+C84) -> 33265.552 | D85: =+(D83+E85)/(1+D84) -> 35297.535 | E85: =+(E83+F85)/(1+E84) -> 37432.14 | F85: =+(F83+G85)/(1+F84) -> 39678.934 | G85: =+(G83+H85)/(1+G84) -> 42049.605 | H85: =+(H83+I85)/(1+H84) -> 44605.684 | I85: =+(I83+J85)/(1+I84) -> 47153.561 | J85: =+J83/(J84-K31) -> 49982.774
B88: APV // rA
B89: FCFF+TS | C89: =+C72+C74 -> 1294.5726 | D89: =+D72+D74 -> 1395.1479 | E89: =+E72+E74 -> 1496.4204 | F89: =+F72+F74 -> 1597.2227 | G89: =+G72+G74 -> 1648.8811 | H89: =+H72+H74 -> 1912.6917 | I89: =+I72+I74 -> 1886.1424
B90: =+B32 -> rA | C90: =+C32 -> 0.1 | D90: =+D32 -> 0.1 | E90: =+E32 -> 0.1 | F90: =+F32 -> 0.1 | G90: =+G32 -> 0.1 | H90: =+H32 -> 0.1 | I90: =+I32 -> 0.1
B91: Vboy | C91: =+(C89+D91)/(1+C90) -> 33265.552 | D91: =+(D89+E91)/(1+D90) -> 35297.535 | E91: =+(E89+F91)/(1+E90) -> 37432.14 | F91: =+(F89+G91)/(1+F90) -> 39678.934 | G91: =+(G89+H91)/(1+G90) -> 42049.605 | H91: =+(H89+I91)/(1+H90) -> 44605.684 | I91: =+I89/(I90-J31) -> 47153.561
B95: FCFE // rE
B96: =+B77 -> FCFE | C96: =+C77 -> 970.35373 | D96: =+D77 -> 1080.4336 | E96: =+E77 -> -1108.1238 | F96: =+F77 -> -3181.4397 | G96: =+G77 -> 17162.136 | H96: =+H77 -> 1861.306 | I96: =+I77 -> 1886.1424
B97: rE | C97: =+(C32-C49*C35)/(1-C49) -> 0.11473383 | D97: =+(D32-D49*D35)/(1-D49) -> 0.11419961 | E97: =+(E32-E49*E35)/(1-E49) -> 0.11372441 | F97: =+(F32-F49*F35)/(1-F49) -> 0.10546486 | G97: =+(G32-G49*G35)/(1-G49) -> 0.099496925 | H97: =+(H32-H34*H46)/(1-H34) -> 0.12666667 | I97: =+(I32-I34*I46)/(1-I34) -> 0.12666667
B98: E boy | C98: =+(C96+D98)/(1+C97) -> 24984.394 | D98: =+(D96+E98)/(1+D97) -> 26880.595 | E98: =+(E96+F98)/(1+E97) -> 28869.915 | F98: =+(F96+G98)/(1+F97) -> 33261.253 | G98: =+(G96+H98)/(1+G97) -> 39950.586 | H98: =+(H96+I98)/(1+H97) -> 26763.41 | I98: =+I96/(I97-J31) -> 28292.136
B99: =+B48 -> net D boy | C99: =+C48 -> 8281.1584 | D99: =+D48 -> 8416.9395 | E99: =+E48 -> 8562.2253 | F99: =+F48 -> 6417.681 | G99: =+G48 -> 2099.0187 | H99: =+H53 -> 17842.274 | I99: =+I53 -> 18861.424 | J99: D = BVD
B100: V boy | C100: =+C98+C99 -> 33265.552 | D100: =+D98+D99 -> 35297.535 | E100: =+E98+E99 -> 37432.14 | F100: =+F98+F99 -> 39678.934 | G100: =+G98+G99 -> 42049.605 | H100: =+H98+H99 -> 44605.684 | I100: =+I98+I99 -> 47153.561
